Workbook

Sheet Lifestyle
A1: Standard Rates
A3: 50sqm Concrete paving | BB3: =50*140 -> 7000 | BD3: Bonus will be reviewed in August 2025 | BH3: Stormy line prices to be the same as sewer. | BM3: Delete bank of draws from vanities
A4: Floor tiles | BB4: 103 | BD4: Up to 24 sq | BE4: 3000 | BH4: Price accordingly in March
A5: Carpets | BB5: 60 | BD5: Above 24 sq | BE5: 4000 | BH5: Keep ordering at the same rate for now
A6: Eaves | BB6: 85 | BH6: Neopower Heat pump 315L as standard
A7: Price rise allowance | BB7: 0
BB9: Shepparton | BC9: Echuca | BO9: Lifestyle
BB10: 6 Months | BC10: 6 Months | BD10: Bonus | BF10: Floor Tiles | BG10: Wastage | BI10: Carpets | BJ10: Wastage | BL10: Eaves | BM10: Total area | BN10: List price | BO10: per m2
AE11: Windows | AO11: Sliding doors | AV11: Built-in robes/linens
A12: Single storey | B12: Dwelling area | C12: Garage area | D12: Porch area | E12: Outdoor living area | F12: Porch concrete footing | G12: Outdoor living footing | H12: Brick pier | I12: 90x90 steel columns | J12: Eaves | K12: Hip length | L12: Valley length | M12: Ridge length | N12: Perimeter walls | O12: Internal walls | P12: Plaster bulkheads | Q12: Kitchen wall bench | R12: Kitchen overhead cupboard | S12: Kitchen island bench | T12: Ens vanity bench | U12: Ens vanity basin | V12: Bath vanity bench | W12: Bath vanity basin | X12: Extra vanity bench | Y12: Extra vanity basin | Z12: Laundry bench | AA12: Internal swing door | AB12: Internal double swing door | AC12: Internal cavity sliders | AD12: Internal double cavity slider | AE12: 1006 | AF12: 1212 | AG12: 1215 | AH12: 1809 | AI12: 1812 | AJ12: 1818 | AK12: 1821 | AL12: 1824 | AM12: External swing door Entry | AN12: External swing door Garage | AO12: 2115 | AP12: 2118 | AQ12: 2121 | AR12: 2124 | AS12: 2127 | AT12: 2136 | AU12: 2155 | AV12: Up to 1800mm wide | AW12: 1800mm to 2500mm wide | AX12: 2500mm to 3000mm wide | AY12: Linen shelving - 4 shelves | AZ12: Robe shelving wth hanging rail | BA12: End panels
B13: m2 | C13: m2 | D13: m2 | E13: m2 | F13: lm | G13: lm | H13: each | I13: each | J13: lm | K13: lm | L13: lm | M13: lm | N13: lm | O13: lm | P13: lm | Q13: lm | R13: lm | S13: lm | T13: lm | U13: each | V13: lm | W13: each | X13: lm | Y13: each | Z13: lm | AA13: each | AB13: each | AC13: each | AD13: each | AE13: each | AF13: each | AG13: each | AH13: each | AI13: each | AJ13: each | AK13: each | AL13: each | AM13: each | AN13: each | AO13: each | AP13: each | AQ13: each | AR13: each | AS13: each | AT13: each | AU13: each | AV13: each | AW13: each | AX13: each | AY13: each | AZ13: each | BA13: each
A14: Adelaide 18 | B14: 120.71 | C14: 38.81 | D14: 5.06 | E14: 9.51 | F14: 3.8 | G14: 6.4 | H14: 1 | I14: 1 | J14: 7.09 | K14: 35.223 | L14: 9.003 | M14: 12.45 | N14: 45.17 | O14: 50.8 | P14: 3.16 | Q14: 1.5 | R14: 1.5 | S14: 2.4 | T14: 0.9 | U14: 1 | V14: 0.9 | W14: 1 | X14: 0 | Y14: 0 | Z14: 1.2 | AA14: 9 | AB14: 0 | AC14: 0 | AD14: 0 | AE14: 1 | AF14: 1 | AG14: 2 | AJ14: 1 | AP14: 1 | BB14: 279204 | BC14: 292541 | BD14: 3000 | BE14: =+BC14-BB14 -> 13337 | BF14: 44.2 | BG14: 1.1 | BH14: =+BG14*BF14 -> 48.62 | BI14: 42.17 | BJ14: 1.1 | BK14: =+BJ14*BI14 -> 46.387 | BL14: 52 | BM14: 174.08 | BN14: =+Shepparton!F4-Shepparton!C4 -> 290005 | BO14: =+ROUND(BN14/BM14,) -> 1666
A15: Adelaide 21 | B15: 142.05 | C15: 38.79 | D15: 5.06 | E15: 10.31 | H15: 1 | J15: 7.09 | K15: 35.226 | L15: 9.003 | M15: 14.97 | N15: 50.21 | O15: 54.65 | P15: 3.16 | Q15: 1.43 | R15: 1.43 | S15: 2.35 | T15: 0.9 | U15: 1 | V15: 0.9 | W15: 1 | X15: 0 | Y15: 0 | Z15: 1.2 | BB15: 293633 | BC15: 306971 | BD15: 3000 | BE15: =+BC15-BB15 -> 13338 | BF15: 45.36 | BG15: 1.1 | BH15: =+BG15*BF15 -> 49.896 | BI15: 62.1 | BJ15: 1.1 | BK15: =+BJ15*BI15 -> 68.31 | BL15: 57 | BM15: 196.26 | BN15: =+Shepparton!F5-Shepparton!C5 -> 305880 | BO15: =+ROUND(BN15/BM15,) -> 1559
A16: Adelaide 22A | B16: 154.9 | C16: 38.57 | D16: 4.18 | E16: 11.61 | H16: 2 | J16: 5.965 | K16: 37.711 | L16: 10.26 | M16: 15.34 | N16: 51.73 | O16: 64.2 | P16: 2.8 | Q16: 3.1 | R16: 1.9 | S16: 2.5 | T16: 1.2 | U16: 1 | V16: 0.9 | W16: 1 | X16: 0 | Y16: 0 | Z16: 1.2 | BB16: 307717 | BC16: 320996 | BD16: 3000 | BE16: =+BC16-BB16 -> 13279 | BF16: 52.38 | BG16: 1.1 | BH16: =+BG16*BF16 -> 57.618 | BI16: 61.84 | BJ16: 1.1 | BK16: =+BJ16*BI16 -> 68.024 | BL16: 60 | BM16: 209.25 | BN16: =+Shepparton!F6-Shepparton!C6 -> 320740 | BO16: =+ROUND(BN16/BM16,) -> 1533
A17: Adelaide 22B | B17: 154.9 | C17: 38.57 | D17: 4.18 | E17: 11.66 | H17: 2 | J17: 5.965 | K17: 37.711 | L17: 10.26 | M17: 15.34 | N17: 51.73 | O17: 68.35 | P17: 2.8 | Q17: 3.1 | R17: 1.9 | S17: 2.5 | T17: 1.2 | U17: 1 | V17: 0.9 | W17: 1 | X17: 0 | Y17: 0 | Z17: 1.2 | BB17: 309383 | BC17: 322640 | BD17: 3000 | BE17: =+BC17-BB17 -> 13257 | BF17: 51.94 | BG17: 1.1 | BH17: =+BG17*BF17 -> 57.134 | BI17: 60.31 | BJ17: 1.1 | BK17: =+BJ17*BI17 -> 66.341 | BL17: 60 | BM17: 209.25 | BN17: =+Shepparton!F7-Shepparton!C7 -> 322260 | BO17: =+ROUND(BN17/BM17,) -> 1540
A18: Adelaide 24 | B18: 170.21 | C18: 38.68 | D18: 5.08 | E18: 11.92 | H18: 1 | J18: 7.09 | K18: 37.32 | L18: 9.002 | M18: 15.66 | N18: 55.29 | O18: 67.25 | P18: 3.9 | Q18: 2.08 | R18: 2.08 | S18: 2.7 | T18: 0.9 | U18: 1 | V18: 0.9 | W18: 1 | X18: 0 | Y18: 0 | Z18: 1.2 | BB18: 316962 | BC18: 330230 | BD18: 3000 | BE18: =+BC18-BB18 -> 13268 | BF18: 56.63 | BG18: 1.1 | BH18: =+BG18*BF18 -> 62.293 | BI18: 75.55 | BJ18: 1.1 | BK18: =+BJ18*BI18 -> 83.105 | BL18: 62 | BM18: 225.88 | BN18: =+Shepparton!F8-Shepparton!C8 -> 331380 | BO18: =+ROUND(BN18/BM18,) -> 1467
A19: Ashfield 24 | B19: 269.78 | C19: 41.25 | D19: 6.32 | E19: 13.24 | H19: 3 | J19: 6.69 | K19: 41.9 | L19: 9.02 | M19: 11.26 | N19: 51.01 | O19: 75.35 | P19: 3.75 | Q19: 2.75 | R19: 2.75 | S19: 2.7 | T19: 0.9 | U19: 1 | V19: 0.9 | W19: 1 | X19: 0 | Y19: 0 | Z19: 1.2 | BB19: 319218 | BC19: 332578 | BD19: 3000 | BE19: =+BC19-BB19 -> 13360 | BF19: 76.52 | BG19: 1.1 | BH19: =+BG19*BF19 -> 84.172 | BI19: 52.6 | BJ19: 1.1 | BK19: =+BJ19*BI19 -> 57.86 | BL19: 58 | BM19: 230.2 | BN19: =+Shepparton!F9-Shepparton!C9 -> 334365 | BO19: =+ROUND(BN19/BM19,) -> 1452
A20: Ashfield 30 | B20: 201.44 | C20: 41.23 | D20: 7.14 | E20: 28.76 | H20: 4 | J20: 6.635 | K20: 45.2 | L20: 22.53 | M20: 20.6 | N20: 55.19 | O20: 92.7 | P20: 6.78 | Q20: 2.75 | R20: 2.75 | S20: 2.7 | T20: 0.9 | U20: 1 | V20: 0.9 | W20: 1 | X20: 1.2 | Y20: 1 | Z20: 1.2 | BB20: 355577 | BC20: 368840 | BD20: 4000 | BE20: =+BC20-BB20 -> 13263 | BF20: 70.06 | BG20: 1.1 | BH20: =+BG20*BF20 -> 77.066 | BI20: 84.94 | BJ20: 1.1 | BK20: =+BJ20*BI20 -> 93.434 | BL20: 60 | BM20: 278.55 | BN20: =+Shepparton!F10-Shepparton!C10 -> 373130 | BO20: =+ROUND(BN20/BM20,) -> 1340
A21: Ashfield 34 | B21: 228.94 | C21: 41.16 | D21: 7.38 | E21: 37.68 | H21: 4 | J21: 6.64 | K21: 47.261 | L21: 25.68 | M21: 24.465 | N21: 60 | O21: 101 | P21: 6.7 | Q21: 2.85 | R21: 2.85 | S21: 2.7 | T21: 0.9 | U21: 1 | V21: 0.9 | W21: 1 | X21: 1.33 | Y21: 1 | Z21: 1.2 | BB21: 382148 | BC21: 395470 | BD21: 4000 | BE21: =+BC21-BB21 -> 13322 | BF21: 74.45 | BG21: 1.1 | BH21: =+BG21*BF21 -> 81.895 | BI21: 101.45 | BJ21: 1.1 | BK21: =+BJ21*BI21 -> 111.595 | BL21: 74 | BM21: 315.15 | BN21: =+Shepparton!F11-Shepparton!C11 -> 401290 | BO21: =+ROUND(BN21/BM21,) -> 1273
A22: Ashley 19 | B22: 126.99 | C22: 38.55 | D22: 5.03 | E22: 9.24 | H22: 2 | J22: 6.08 | K22: 40.75 | L22: 10.6 | M22: 9.32 | N22: 44.06 | O22: 51.35 | P22: 4.06 | Q22: 2.24 | R22: 2.24 | S22: 2.7 | T22: 0.9 | U22: 1 | V22: 0.9 | W22: 1 | X22: 0 | Y22: 0 | Z22: 1.2 | BB22: 277619 | BC22: 290856 | BD22: 3000 | BE22: =+BC22-BB22 -> 13237 | BF22: 51.21 | BG22: 1.1 | BH22: =+BG22*BF22 -> 56.331 | BI22: 42.5 | BJ22: 1.1 | BK22: =+BJ22*BI22 -> 46.75 | BL22: 51 | BM22: 179.82 | BN22: =+Shepparton!F12-Shepparton!C12 -> 289230 | BO22: =+ROUND(BN22/BM22,) -> 1608
A23: Ashley 21 | BB23: 297059 | BC23: 309921 | BD23: 3000 | BE23: =+BC23-BB23 -> 12862 | BF23: 61.52 | BG23: 1.1 | BH23: =+BG23*BF23 -> 67.672 | BI23: 56.58 | BJ23: 1.1 | BK23: =+BJ23*BI23 -> 62.238 | BL23: 59
A24: Ashley 22 | B24: 155.58 | C24: 37.55 | D24: 4.13 | E24: 10.65 | H24: 2 | J24: 6.9 | K24: 41.15 | L24: 11.14 | M24: 11.64 | N24: 48.69 | O24: 66.87 | P24: 2.7 | Q24: 1.8 | R24: 1.8 | S24: 2.7 | T24: 0.9 | U24: 1 | V24: 0.9 | W24: 1 | X24: 0 | Y24: 0 | Z24: 1.2 | BB24: 294577 | BC24: 307545 | BD24: 3000 | BE24: =+BC24-BB24 -> 12968 | BF24: 60.5 | BG24: 1.1 | BH24: =+BG24*BF24 -> 66.55 | BI24: 58.66 | BJ24: 1.1 | BK24: =+BJ24*BI24 -> 64.526 | BL24: 56 | BM24: 207.9 | BN24: =+Shepparton!F14-Shepparton!C14 -> 308310 | BO24: =+ROUND(BN24/BM24,) -> 1483
A25: Ashley 22A | BB25: 300718 | BC25: 313916 | BD25: 3000 | BE25: =+BC25-BB25 -> 13198 | BF25: 65.93 | BG25: 1.1 | BH25: =+BG25*BF25 -> 72.523 | BI25: 54.72 | BJ25: 1.1 | BK25: =+BJ25*BI25 -> 60.192 | BL25: 56
A26: Ashley 24 | B26: 164 | C26: 38.5 | D26: 4.99 | E26: 16.12 | H26: 2 | J26: 6.7 | K26: 41.54 | L26: 10.814 | M26: 13.1 | N26: 52 | O26: 65.9 | P26: 2.8 | Q26: 1.9 | R26: 1.9 | S26: 2.7 | T26: 0.9 | U26: 1 | V26: 0.9 | W26: 1 | X26: 0 | Y26: 0 | Z26: 1.2 | BB26: 312046 | BC26: 325561 | BD26: 3000 | BE26: =+BC26-BB26 -> 13515 | BF26: 57.4 | BG26: 1.1 | BH26: =+BG26*BF26 -> 63.14 | BI26: 70.61 | BJ26: 1.1 | BK26: =+BJ26*BI26 -> 77.671 | BL26: 59 | BM26: 223.46 | BN26: =+Shepparton!F16-Shepparton!C16 -> 326220 | BO26: =+ROUND(BN26/BM26,) -> 1460
A27: Ashley 25 | B27: 170.72 | C27: 38.42 | D27: 4.52 | E27: 21 | H27: 2 | J27: 6.18 | K27: 49.79 | L27: 19.185 | M27: 15.49 | N27: 50.35 | O27: 73.15 | P27: 5.08 | Q27: 4.18 | R27: 4.18 | S27: 3 | T27: 0.9 | U27: 1 | V27: 0.9 | W27: 1 | X27: 0 | Y27: 0 | Z27: 1.2 | BB27: 320081 | BC27: 333403 | BD27: 4000 | BE27: =+BC27-BB27 -> 13322 | BF27: 61.33 | BG27: 1.1 | BH27: =+BG27*BF27 -> 67.463 | BI27: 69.8 | BJ27: 1.1 | BK27: =+BJ27*BI27 -> 76.78 | BL27: 64 | BM27: 234.65 | BN27: =+Shepparton!F17-Shepparton!C17 -> 335650 | BO27: =+ROUND(BN27/BM27,) -> 1430
A28: Ashley 25A | B28: 172.94 | C28: 37.49 | D28: 4.52 | E28: 21 | H28: 3 | J28: 6.18 | K28: 49.79 | L28: 19.185 | M28: 15.49 | N28: 50.35 | O28: 73.15 | P28: 5.08 | Q28: 3.3 | R28: 1.9 | S28: 3.6 | T28: 0.9 | U28: 1 | V28: 0.9 | W28: 1 | X28: 0 | Y28: 0 | Z28: 1.2 | BB28: 330229 | BC28: 343545 | BD28: 4000 | BE28: =+BC28-BB28 -> 13316 | BF28: 62.1 | BG28: 1.1 | BH28: =+BG28*BF28 -> 68.31 | BI28: 70.48 | BJ28: 1.1 | BK28: =+BJ28*BI28 -> 77.528 | BL28: 64 | BM28: 235.95 | BN28: =+Shepparton!F18-Shepparton!C18 -> 345925 | BO28: =+ROUND(BN28/BM28,) -> 1466
A29: Ashley 26 | B29: 175.05 | C29: 38.43 | D29: 7.67 | E29: 20.53 | H29: 2 | J29: 4.44 | K29: 48.14 | L29: 16.61 | M29: 14 | N29: 53.05 | O29: 69.15 | P29: 3.36 | Q29: 2.46 | R29: 2.46 | S29: 3 | T29: 1.2 | U29: 1 | V29: 0.9 | W29: 1 | X29: 0 | Y29: 0 | Z29: 0 | BB29: 326973 | BC29: 340209 | BD29: 4000 | BE29: =+BC29-BB29 -> 13236 | BF29: 62.2 | BG29: 1.1 | BH29: =+BG29*BF29 -> 68.42 | BI29: 74.19 | BJ29: 1.1 | BK29: =+BJ29*BI29 -> 81.609 | BL29: 62 | BM29: 241.67 | BN29: =+Shepparton!F19-Shepparton!C19 -> 342930 | BO29: =+ROUND(BN29/BM29,) -> 1419
A30: Ashley 27 | B30: 195.53 | C30: 38.38 | D30: 4.97 | E30: 15.996 | H30: 2 | J30: 6.18 | K30: 41.138 | L30: 10.814 | M30: 16.47 | N30: 58.28 | O30: 81.85 | P30: 3.22 | Q30: 2.312 | R30: 2.312 | S30: 2.7 | T30: 0.9 | U30: 1 | V30: 0.9 | W30: 1 | X30: 0 | Y30: 0 | Z30: 1.2 | BB30: 338903 | BC30: 352214 | BD30: 4000 | BE30: =+BC30-BB30 -> 13311 | BF30: 70.54 | BG30: 1.1 | BH30: =+BG30*BF30 -> 77.594 | BI30: 92.05 | BJ30: 1.1 | BK30: =+BJ30*BI30 -> 101.255 | BL30: 65 | BM30: 254.89 | BN30: =+Shepparton!F20-Shepparton!C20 -> 356985 | BO30: =+ROUND(BN30/BM30,) -> 1401
A31: Ashley 28 | B31: 193.91 | C31: 38.67 | D31: 7.19 | E31: 19.61 | H31: 2 | J31: 5.26 | K31: 42.66 | L31: 12.891 | M31: 17.025 | N31: 58.25 | O31: 79.65 | P31: 3.27 | Q31: 2.42 | R31: 2.42 | S31: 2.7 | T31: 1.8 | U31: 2 | V31: 0.9 | W31: 1 | X31: 0 | Y31: 0 | Z31: 1.2 | BB31: 343732 | BC31: 356760 | BD31: 4000 | BE31: =+BC31-BB31 -> 13028 | BF31: 78.48 | BG31: 1.1 | BH31: =+BG31*BF31 -> 86.328 | BI31: 66.52 | BJ31: 1.1 | BK31: =+BJ31*BI31 -> 73.172 | BL31: 65 | BM31: 258.33 | BN31: =+Shepparton!F21-Shepparton!C21 -> 361030 | BO31: =+ROUND(BN31/BM31,) -> 1398
A32: Ashley 28A | BB32: 351250 | BC32: 364509 | BD32: 4000 | BE32: =+BC32-BB32 -> 13259 | BF32: 82.36 | BG32: 1.1 | BH32: =+BG32*BF32 -> 90.596 | BI32: 88.36 | BJ32: 1.1 | BK32: =+BJ32*BI32 -> 97.196 | BL32: 65 | BM32: 258.33 | BN32: =+Shepparton!F22-Shepparton!C22 -> 370420 | BO32: =+ROUND(BN32/BM32,) -> 1434
A33: Ballina 24 | B33: 156.97 | C33: 40.42 | D33: 2.83 | E33: 21.22 | H33: 1 | J33: 6.5 | K33: 50.1 | L33: 11.5 | M33: 2 | N33: 47 | O33: 82.6 | P33: 6.9 | Q33: 4.4 | R33: 2.2 | S33: 2.5 | T33: 1.2 | U33: 1 | V33: 0.9 | W33: 1 | X33: 0 | Y33: 0 | Z33: 1.2 | BB33: 312597 | BC33: 325831 | BD33: 3000 | BE33: =+BC33-BB33 -> 13234 | BF33: 70.31 | BG33: 1.1 | BH33: =+BG33*BF33 -> 77.341 | BI33: 45.65 | BJ33: 1.1 | BK33: =+BJ33*BI33 -> 50.215 | BL33: 53 | BM33: 221.43 | BN33: =+Shepparton!F23-Shepparton!C23 -> 326585 | BO33: =+ROUND(BN33/BM33,) -> 1475
A34: Ballina 30 | B34: 209.74 | C34: 37.6 | D34: 2.86 | E34: 23.77 | H34: 3 | J34: 10.3 | K34: 49 | L34: 17.9 | M34: 16.8 | N34: 57.2 | O34: 95 | P34: 11.3 | Q34: 4.4 | R34: 2.5 | S34: 0 | T34: 1.2 | U34: 1 | V34: 0.9 | W34: 1 | X34: 0 | Y34: 0 | Z34: 1.2 | BB34: 360743 | BC34: 373971 | BD34: 4000 | BE34: =+BC34-BB34 -> 13228 | BF34: 85.08 | BG34: 1.1 | BH34: =+BG34*BF34 -> 93.588 | BI34: 80.35 | BJ34: 1.1 | BK34: =+BJ34*BI34 -> 88.385 | BL34: 67 | BM34: 273.96 | BN34: =+Shepparton!F24-Shepparton!C24 -> 379695 | BO34: =+ROUND(BN34/BM34,) -> 1386
A35: Ballina 30A | BB35: 363040 | BC35: 376292 | BD35: 4000 | BE35: =+BC35-BB35 -> 13252 | BF35: 95 | BG35: 1.1 | BH35: =+BG35*BF35 -> 104.5 | BI35: 86 | BJ35: 1.1 | BK35: =+BJ35*BI35 -> 94.6 | BL35: 70 | BM35: 275.39 | BN35: =+Shepparton!F25-Shepparton!C25 -> 383485 | BO35: =+ROUND(BN35/BM35,) -> 1393
A36: Ballina 33 | B36: 240.4 | C36: 38.21 | D36: 2.43 | E36: 30.1 | H36: 1 | J36: 5.6 | K36: 59.1 | L36: 24.1 | M36: 17.8 | N36: 60.9 | O36: 110.8 | P36: 9.6 | Q36: 4.5 | R36: 2.4 | S36: 2.7 | T36: 1.8 | U36: 2 | V36: 0.9 | W36: 1 | X36: 0.9 | Y36: 1 | Z36: 1.2 | BB36: 395086 | BC36: 408310 | BD36: 4000 | BE36: =+BC36-BB36 -> 13224 | BF36: 104.44 | BG36: 1.1 | BH36: =+BG36*BF36 -> 114.884 | BI36: 79.41 | BJ36: 1.1 | BK36: =+BJ36*BI36 -> 87.351 | BL36: 75 | BM36: 311.15 | BN36: =+Shepparton!F26-Shepparton!C26 -> 416170 | BO36: =+ROUND(BN36/BM36,) -> 1338
A37: Ballina 39 | B37: 290 | C37: 39.7 | D37: 2.64 | E37: 31.8 | H37: 3 | J37: 5.7 | K37: 62.8 | L37: 26.2 | M37: 20.3 | N37: 74.5 | O37: 135 | P37: 16.9 | Q37: 4 | R37: 2.5 | S37: 2.7 | T37: 2.3 | U37: 2 | V37: 0.9 | W37: 1 | X37: 0.9 | Y37: 1 | Z37: 1.2 | BB37: 440177 | BC37: 453342 | BD37: 4000 | BE37: =+BC37-BB37 -> 13165 | BF37: 117 | BG37: 1.1 | BH37: =+BG37*BF37 -> 128.7 | BI37: 117 | BJ37: 1.1 | BK37: =+BJ37*BI37 -> 128.7 | BL37: 80 | BM37: 364.15 | BN37: =+Shepparton!F27-Shepparton!C27 -> 465165 | BO37: =+ROUND(BN37/BM37,) -> 1277
A38: Bathurst 25 | BB38: 343405 | BC38: 356677 | BD38: 4000 | BE38: =+BC38-BB38 -> 13272 | BF38: =70.7/1.1 -> 64.272727 | BG38: 1.1 | BH38: =+BG38*BF38 -> 70.7 | BI38: =65.96/1.1 -> 59.963636 | BJ38: 1.1 | BK38: =+BJ38*BI38 -> 65.96 | BL38: 61 | BM38: 231.34 | BN38: =+Shepparton!F28-Shepparton!C28 -> 358655 | BO38: =+ROUND(BN38/BM38,) -> 1550
A39: Bathurst 30 | BB39: 390384 | BC39: 403713 | BD39: 4000 | BE39: =+BC39-BB39 -> 13329 | BF39: =85.22/1.1 -> 77.472727 | BG39: 1.1 | BH39: =+BG39*BF39 -> 85.22 | BI39: =93.9/1.1 -> 85.363636 | BJ39: 1.1 | BK39: =+BJ39*BI39 -> 93.9 | BL39: 70 | BM39: 284.15 | BN39: =+Shepparton!F29-Shepparton!C29 -> 408805 | BO39: =+ROUND(BN39/BM39,) -> 1439
A40: Bathurst 34 | BB40: 411473 | BC40: 422047 | BD40: 4000 | BE40: =+BC40-BB40 -> 10574 | BF40: =93.92/1.1 -> 85.381818 | BG40: 1.1 | BH40: =+BG40*BF40 -> 93.92 | BI40: =105.78/1.1 -> 96.163636 | BJ40: 1.1 | BK40: =+BJ40*BI40 -> 105.78 | BL40: 74 | BM40: 317.69 | BN40: =+Shepparton!F30-Shepparton!C30 -> 431505 | BO40: =+ROUND(BN40/BM40,) -> 1358
A41: Bayview 23 | B41: 154.7 | C41: 38.8 | D41: 5.88 | E41: 13.63 | H41: 1 | J41: 12.72 | K41: 51.381 | L41: 20.817 | M41: 13.47 | N41: 55.16 | O41: 57.7 | P41: 4.2 | Q41: 2.37 | R41: 2.37 | S41: 2.7 | T41: 0.9 | U41: 1 | V41: 0.9 | W41: 1 | X41: 0 | Y41: 0 | Z41: 1.2 | BB41: 313918 | BC41: 327135 | BD41: 3000 | BE41: =+BC41-BB41 -> 13217 | BF41: 71.87 | BG41: 1.1 | BH41: =+BG41*BF41 -> 79.057 | BI41: 45.5 | BJ41: 1.1 | BK41: =+BJ41*BI41 -> 50.05 | BL41: 56 | BM41: 212.95 | BN41: =+Shepparton!F31-Shepparton!C31 -> 328070 | BO41: =+ROUND(BN41/BM41,) -> 1541
A42: Bayview 26 | B42: 181.61 | C42: 38.82 | D42: 5.88 | E42: 17.38 | H42: 1 | J42: 12.77 | K42: 51.267 | L42: 20.239 | M42: 16.46 | N42: 60.98 | O42: 70.1 | P42: 4.2 | Q42: 2.37 | R42: 2.37 | S42: 2.7 | T42: 0.9 | U42: 1 | V42: 0.9 | W42: 1 | X42: 0 | Y42: 0 | Z42: 1.2 | BB42: 335864 | BC42: 349100 | BD42: 4000 | BE42: =+BC42-BB42 -> 13236 | BF42: 62.78 | BG42: 1.1 | BH42: =+BG42*BF42 -> 69.058 | BI42: 76.6 | BJ42: 1.1 | BK42: =+BJ42*BI42 -> 84.26 | BL42: 62 | BM42: 243.4 | BN42: =+Shepparton!F32-Shepparton!C32 -> 352045 | BO42: =+ROUND(BN42/BM42,) -> 1446
A43: Bayview 30 | B43: 224.46 | C43: 38.82 | D43: 5.88 | E43: 17 | H43: 1 | J43: 12.77 | K43: 49.089 | L43: 20.925 | M43: 22.955 | N43: 70.77 | O43: 90.25 | P43: 4 | Q43: 2.17 | R43: 2.17 | S43: 2.7 | T43: 0.9 | U43: 1 | V43: 0.9 | W43: 1 | X43: 0 | Y43: 0 | Z43: 1.2 | BB43: 371790 | BC43: 386547 | BD43: 4000 | BE43: =+BC43-BB43 -> 14757 | BF43: 73.21 | BG43: 1.1 | BH43: =+BG43*BF43 -> 80.531 | BI43: 105.62 | BJ43: 1.1 | BK43: =+BJ43*BI43 -> 116.182 | BL43: 72 | BM43: 286.12 | BN43: =+Shepparton!F33-Shepparton!C33 -> 391060 | BO43: =+ROUND(BN43/BM43,) -> 1367
A44: Bondi 25 | B44: 180.94 | C44: 38.48 | D44: 2.64 | E44: 13.59 | H44: 2 | J44: 6.62 | K44: 39.76 | L44: 10.394 | M44: 15.11 | N44: 55.97 | O44: 69.6 | P44: 4.22 | Q44: 3.32 | R44: 3.32 | S44: 2.7 | T44: 1.3 | U44: 1 | V44: 0.9 | W44: 1 | X44: 0 | Y44: 0 | Z44: 1.2 | BB44: 326725 | BC44: 339954 | BD44: 4000 | BE44: =+BC44-BB44 -> 13229 | BF44: 82.18 | BG44: 1.1 | BH44: =+BG44*BF44 -> 90.398 | BI44: 57.02 | BJ44: 1.1 | BK44: =+BJ44*BI44 -> 62.722 | BL44: 63 | BM44: 235.76 | BN44: =+Shepparton!F34-Shepparton!C34 -> 343810 | BO44: =+ROUND(BN44/BM44,) -> 1458
A45: Bondi 31 | B45: 220.25 | C45: 38.6 | D45: 4.83 | E45: 24.53 | H45: 1 | J45: 7.02 | K45: 45.552 | L45: 12.01 | M45: 15.04 | N45: 62.57 | O45: 88.08 | P45: 4.52 | Q45: 3.62 | R45: 3.62 | S45: 2.7 | T45: 1.87 | U45: 2 | V45: 0.9 | W45: 1 | X45: 0 | Y45: 0 | Z45: 1.2 | BB45: 365164 | BC45: 379707 | BD45: 4000 | BE45: =+BC45-BB45 -> 14543 | BF45: 95.72 | BG45: 1.1 | BH45: =+BG45*BF45 -> 105.292 | BI45: 76.78 | BJ45: 1.1 | BK45: =+BJ45*BI45 -> 84.458 | BL45: 68 | BM45: 288.34 | BN45: =+Shepparton!F35-Shepparton!C35 -> 385090 | BO45: =+ROUND(BN45/BM45,) -> 1336
A46: Bondi 36 | B46: 259.37 | C46: 38.56 | D46: 5.99 | E46: 30.39 | H46: 3 | J46: 9.21 | K46: 57.303 | L46: 18.1 | M46: 13 | N46: 66.3 | O46: 96.65 | P46: 4.2 | Q46: 4.2 | R46: 4.2 | S46: 2.7 | T46: 1.9 | U46: 2 | V46: 0.9 | W46: 1 | X46: 0 | Y46: 0 | Z46: 1.2 | BB46: 395974 | BC46: 409146 | BD46: 4000 | BE46: =+BC46-BB46 -> 13172 | BF46: 108.66 | BG46: 1.1 | BH46: =+BG46*BF46 -> 119.526 | BI46: 97.65 | BJ46: 1.1 | BK46: =+BJ46*BI46 -> 107.415 | BL46: 69 | BM46: 334.42 | BN46: =+Shepparton!F36-Shepparton!C36 -> 418740 | BO46: =+ROUND(BN46/BM46,) -> 1252
A47: Cambridge 22 | B47: 158.04 | C47: 38.46 | D47: 12.31 | E47: 0 | H47: 2 | J47: 6.73 | K47: 54.13 | L47: 21.03 | M47: 11.28 | N47: 55.18 | O47: 64.35 | P47: 2.8 | Q47: 1.9 | R47: 1.9 | S47: 2.7 | T47: 0.9 | U47: 1 | V47: 0.9 | W47: 1 | X47: 0 | Y47: 0 | Z47: 1.2 | BB47: 306745 | BC47: 319820 | BD47: 3000 | BE47: =+BC47-BB47 -> 13075 | BF47: 70.3 | BG47: 1.1 | BH47: =+BG47*BF47 -> 77.33 | BI47: 52.46 | BJ47: 1.1 | BK47: =+BJ47*BI47 -> 57.706 | BL47: 57 | BM47: 208.8 | BN47: =+Shepparton!F37-Shepparton!C37 -> 321180 | BO47: =+ROUND(BN47/BM47,) -> 1538
A48: Cambridge 24 | B48: 177.2 | C48: 38.47 | D48: 12.31 | E48: 0 | H48: 2 | J48: 6.73 | K48: 53.2 | L48: 19.745 | M48: 11.28 | N48: 55.18 | O48: 72.72 | P48: 2.8 | Q48: 1.9 | R48: 1.9 | S48: 2.7 | T48: 0.9 | U48: 1 | V48: 0.9 | W48: 1 | X48: 0 | Y48: 0 | Z48: 1.2 | BB48: 326664 | BC48: 339818 | BD48: 3000 | BE48: =+BC48-BB48 -> 13154 | BF48: 65.87 | BG48: 1.1 | BH48: =+BG48*BF48 -> 72.457 | BI48: 73.37 | BJ48: 1.1 | BK48: =+BJ48*BI48 -> 80.707 | BL48: 57 | BM48: 227.98 | BN48: =+Shepparton!F38-Shepparton!C38 -> 341980 | BO48: =+ROUND(BN48/BM48,) -> 1500
A49: Cambridge 26 | B49: 195.4 | C49: 38.46 | D49: 12.31 | E49: 0 | H49: 2 | J49: 6.724 | K49: 55.85 | L49: 21.45 | M49: 12.6 | N49: 57.82 | O49: 77.15 | P49: 2.8 | Q49: 1.9 | R49: 1.9 | S49: 2.7 | T49: 0.9 | U49: 1 | V49: 0.9 | W49: 1 | X49: 0 | Y49: 0 | Z49: 1.2 | BB49: 342124 | BC49: 355281 | BD49: 4000 | BE49: =+BC49-BB49 -> 13157 | BF49: 77.67 | BG49: 1.1 | BH49: =+BG49*BF49 -> 85.437 | BI49: 80 | BJ49: 1.1 | BK49: =+BJ49*BI49 -> 88 | BL49: 60 | BM49: 246.12 | BN49: =+Shepparton!F39-Shepparton!C39 -> 360215 | BO49: =+ROUND(BN49/BM49,) -> 1464
A50: Cambridge 30 | B50: 231.6 | C50: 38.46 | D50: 12.31 | E50: 0 | H50: 2 | J50: 6.73 | K50: 56.63 | L50: 21.441 | M50: 14.882 | N50: 63.82 | O50: 98.55 | P50: 2.8 | Q50: 1.9 | R50: 1.9 | S50: 2.7 | T50: 0.9 | U50: 1 | V50: 0.9 | W50: 1 | X50: 0 | Y50: 0 | Z50: 1.2 | BB50: 372059 | BC50: 385270 | BD50: 4000 | BE50: =+BC50-BB50 -> 13211 | BF50: 73 | BG50: 1.1 | BH50: =+BG50*BF50 -> 80.3 | BI50: 113.49 | BJ50: 1.1 | BK50: =+BJ50*BI50 -> 124.839 | BL50: 65 | BM50: 282.32 | BN50: =+Shepparton!F40-Shepparton!C40 -> 391830 | BO50: =+ROUND(BN50/BM50,) -> 1388
A51: Duneed 22 | B51: 150 | C51: 38.63 | D51: 1.17 | E51: 17.03 | H51: 0 | J51: 8.56 | K51: 39.36 | L51: 11.43 | M51: 15.7 | N51: 56.58 | O51: 60 | P51: 4.8 | Q51: 2.88 | R51: 2.88 | S51: 2.7 | T51: 0.9 | U51: 1 | V51: 0.9 | W51: 1 | X51: 0.9 | Y51: 1 | Z51: 1.2 | BB51: 312042 | BC51: 325231 | BD51: 3000 | BE51: =+BC51-BB51 -> 13189 | BF51: 59.14 | BG51: 1.1 | BH51: =+BG51*BF51 -> 65.054 | BI51: 48.71 | BJ51: 1.1 | BK51: =+BJ51*BI51 -> 53.581 | BL51: 64 | BM51: 206.75 | BN51: =+Shepparton!F51-Shepparton!C51 -> 324970 | BO51: =+ROUND(BN51/BM51,) -> 1572
A52: Duneed 23 | B52: 154.68 | C52: 38.62 | D52: 1.51 | E52: 17.54 | H52: 0 | J52: 9.32 | K52: 40.24 | L52: 11.52 | M52: 15.37 | N52: 57.14 | O52: 58.6 | P52: 4.8 | Q52: 2.88 | R52: 2.88 | S52: 2.7 | T52: 0.9 | U52: 1 | V52: 0.9 | W52: 1 | X52: 0.95 | Y52: 1 | Z52: 1.2 | BB52: 315108 | BC52: 328247 | BD52: 3000 | BE52: =+BC52-BB52 -> 13139 | BF52: 58.33 | BG52: 1.1 | BH52: =+BG52*BF52 -> 64.163 | BI52: 54.06 | BJ52: 1.1 | BK52: =+BJ52*BI52 -> 59.466 | BL52: 64 | BM52: 212.33 | BN52: =+Shepparton!F52-Shepparton!C52 -> 328290 | BO52: =+ROUND(BN52/BM52,) -> 1546
A53: Duneed 24 | B53: 172.48 | C53: 38.62 | D53: 1.17 | E53: 18.14 | H53: 0 | J53: 8.61 | K53: 36.084 | L53: 8.153 | M53: 15.65 | N53: 56.58 | O53: 70.5 | P53: 4.8 | Q53: 2.88 | R53: 2.88 | S53: 2.7 | T53: 0.9 | U53: 1 | V53: 0.9 | W53: 1 | X53: 0.9 | Y53: 1 | Z53: 1.2 | BB53: 326222 | BC53: 339412 | BD53: 3000 | BE53: =+BC53-BB53 -> 13190 | BF53: 60.91 | BG53: 1.1 | BH53: =+BG53*BF53 -> 67.001 | BI53: 70.39 | BJ53: 1.1 | BK53: =+BJ53*BI53 -> 77.429 | BL53: 64 | BM53: 230.39 | BN53: =+Shepparton!F53-Shepparton!C53 -> 340785 | BO53: =+ROUND(BN53/BM53,) -> 1479
A54: Duneed 25 | B54: 177.88 | C54: 38.62 | D54: 1.51 | E54: 18.68 | H54: 0 | J54: 9.31 | K54: 36.88 | L54: 8.153 | M54: 15.37 | N54: 57.14 | O54: 68.1 | P54: 4.8 | Q54: 2.88 | R54: 2.88 | S54: 2.7 | T54: 0.9 | U54: 1 | V54: 0.9 | W54: 1 | X54: 0.9 | Y54: 1 | Z54: 1.2 | BB54: 329246 | BC54: 342418 | BD54: 4000 | BE54: =+BC54-BB54 -> 13172 | BF54: 60.32 | BG54: 1.1 | BH54: =+BG54*BF54 -> 66.352 | BI54: 76.19 | BJ54: 1.1 | BK54: =+BJ54*BI54 -> 83.809 | BL54: 64 | BM54: 236.67 | BN54: =+Shepparton!F54-Shepparton!C54 -> 345115 | BO54: =+ROUND(BN54/BM54,) -> 1458
A55: Duneed 30 | B55: 209.57 | C55: 39.37 | D55: 1.85 | E55: 24.82 | H55: 0 | J55: 11.56 | K55: 59.18 | L55: 26.5 | M55: 16.75 | N55: 61.63 | O55: 90.4 | P55: 5.05 | Q55: 8.34 | R55: 5.05 | S55: 2.7 | T55: 1.8 | U55: 2 | V55: 0.9 | W55: 1 | X55: 0 | Y55: 0 | Z55: 1.2 | BB55: 372749 | BC55: 385922 | BD55: 4000 | BE55: =+BC55-BB55 -> 13173 | BF55: 79.68 | BG55: 1.1 | BH55: =+BG55*BF55 -> 87.648 | BI55: 81.55 | BJ55: 1.1 | BK55: =+BJ55*BI55 -> 89.705 | BL55: 64 | BM55: 275.59 | BN55: =+Shepparton!F55-Shepparton!C55 -> 391165 | BO55: =+ROUND(BN55/BM55,) -> 1419
A56: Eclipse 23 | B56: 166.76 | C56: 38.79 | D56: 3.12 | E56: 11.81 | H56: 0 | J56: 15.46 | K56: 44.607 | L56: 8.161 | M56: 8.08 | N56: 60.89 | O56: 69.15 | P56: 3.84 | Q56: 2 | R56: 2 | S56: 2.7 | T56: 1.54 | U56: 1 | V56: 0.9 | W56: 1 | X56: 0 | Y56: 0 | Z56: 1.2 | BB56: 323411 | BC56: 336641 | BD56: 4000 | BE56: =+BC56-BB56 -> 13230 | BF56: 54.92 | BG56: 1.1 | BH56: =+BG56*BF56 -> 60.412 | BI56: 69 | BJ56: 1.1 | BK56: =+BJ56*BI56 -> 75.9 | BL56: 55 | BM56: 220.55 | BN56: =+Shepparton!F56-Shepparton!C56 -> 338200 | BO56: =+ROUND(BN56/BM56,) -> 1533
A57: Eclipse 26 | B57: 192.23 | C57: 38.79 | D57: 3.12 | E57: 12.07 | H57: 0 | J57: 15.46 | K57: 49.01 | L57: 11.979 | M57: 12.27 | N57: 69.05 | O57: 83 | P57: 4.62 | Q57: 2.79 | R57: 2.79 | S57: 2.7 | T57: 1.54 | U57: 1 | V57: 0.9 | W57: 1 | X57: 0 | Y57: 0 | Z57: 1.2 | BB57: 351878 | BC57: 365119 | BD57: 4000 | BE57: =+BC57-BB57 -> 13241 | BF57: 60.15 | BG57: 1.1 | BH57: =+BG57*BF57 -> 66.165 | BI57: 84.7 | BJ57: 1.1 | BK57: =+BJ57*BI57 -> 93.17 | BL57: 64 | BM57: 246.2 | BN57: =+Shepparton!F57-Shepparton!C57 -> 368290 | BO57: =+ROUND(BN57/BM57,) -> 1496
A58: Eclipse 28 | B58: 207.4 | C58: 38.79 | D58: 3.12 | E58: 12.07 | H58: 0 | J58: 15.11 | K58: 52.533 | L58: 15.506 | M58: 15.36 | N58: 75.23 | O58: 88.55 | P58: 4.62 | Q58: 2.79 | R58: 2.79 | S58: 2.7 | T58: 1.54 | U58: 1 | V58: 0.9 | W58: 1 | X58: 0 | Y58: 0 | Z58: 1.2 | BB58: 367624 | BC58: 380824 | BD58: 4000 | BE58: =+BC58-BB58 -> 13200 | BF58: 62.67 | BG58: 1.1 | BH58: =+BG58*BF58 -> 68.937 | BI58: 96.15 | BJ58: 1.1 | BK58: =+BJ58*BI58 -> 105.765 | BL58: 70 | BM58: 261.3 | BN58: =+Shepparton!F58-Shepparton!C58 -> 385085 | BO58: =+ROUND(BN58/BM58,) -> 1474
A59: Hamilton 24 | B59: 167.63 | C59: 41.26 | D59: 6.32 | E59: 15 | H59: 3 | J59: 7.54 | K59: 42.112 | L59: 9.131 | M59: 11.26 | N59: 51.01 | O59: 68 | P59: 3.75 | Q59: 2.75 | R59: 2.75 | S59: 2.7 | T59: 0.9 | U59: 1 | V59: 0.9 | W59: 1 | X59: 0 | Y59: 0 | Z59: 1.2 | BB59: 321632 | BC59: 334625 | BD59: 3000 | BE59: =+BC59-BB59 -> 12993 | BF59: 74.57 | BG59: 1.1 | BH59: =+BG59*BF59 -> 82.027 | BI59: 52.4 | BJ59: 1.1 | BK59: =+BJ59*BI59 -> 57.64 | BL59: 57 | BM59: 230.21 | BN59: =+Shepparton!F59-Shepparton!C59 -> 336550 | BO59: =+ROUND(BN59/BM59,) -> 1462
A60: Hamilton 29 | B60: 202.31 | C60: 41.88 | D60: 6.81 | E60: 23.72 | H60: 4 | J60: 6.64 | K60: 44.88 | L60: 20.4 | M60: 20.035 | N60: 55.43 | O60: 84.35 | P60: 3.75 | Q60: 2.734 | R60: 2.734 | S60: 2.7 | T60: 0.9 | U60: 1 | V60: 0.9 | W60: 1 | X60: 0.82 | Y60: 1 | Z60: 1.2 | BB60: 361749 | BC60: 375448 | BD60: 4000 | BE60: =+BC60-BB60 -> 13699 | BF60: 80 | BG60: 1.1 | BH60: =+BG60*BF60 -> 88 | BI60: 76.94 | BJ60: 1.1 | BK60: =+BJ60*BI60 -> 84.634 | BL60: 62 | BM60: 274.7 | BN60: =+Shepparton!F60-Shepparton!C60 -> 379895 | BO60: =+ROUND(BN60/BM60,) -> 1383
A61: Hamilton 34 | B61: 231.68 | C61: 41.97 | D61: 7.2 | E61: 39.44 | H61: 4 | J61: 6.64 | K61: 45.223 | L61: 26.302 | M61: 24.555 | N61: 61.215 | O61: 90.26 | P61: 3.8 | Q61: 2.8 | R61: 2.8 | S61: 2.7 | T61: 1.8 | U61: 2 | V61: 0.9 | W61: 1 | X61: 0.95 | Y61: 1 | Z61: 1.2 | BB61: 393489 | BC61: 407049 | BD61: 4000 | BE61: =+BC61-BB61 -> 13560 | BF61: 83.44 | BG61: 1.1 | BH61: =+BG61*BF61 -> 91.784 | BI61: 100.1 | BJ61: 1.1 | BK61: =+BJ61*BI61 -> 110.11 | BL61: 75 | BM61: 320.29 | BN61: =+Shepparton!F61-Shepparton!C61 -> 413555 | BO61: =+ROUND(BN61/BM61,) -> 1291
A62: Launceston 21 | B62: 150.9 | C62: 24.65 | D62: 4.03 | E62: 12.08 | H62: 2 | J62: 6.83 | K62: 44.065 | L62: 18.295 | M62: 15.895 | N62: 55.14 | O62: 65.71 | P62: 4.14 | Q62: 2.32 | R62: 2.32 | S62: 2.7 | T62: 1.1 | U62: 1 | V62: 0.9 | W62: 1 | X62: 0 | Y62: 0 | Z62: 1.2 | BB62: 301071 | BC62: 314204 | BD62: 3000 | BE62: =+BC62-BB62 -> 13133 | BF62: 57.48 | BG62: 1.1 | BH62: =+BG62*BF62 -> 63.228 | BI62: 56 | BJ62: 1.1 | BK62: =+BJ62*BI62 -> 61.6 | BL62: 58 | BM62: 191.76 | BN62: =+Shepparton!F62-Shepparton!C62 -> 314295 | BO62: =+ROUND(BN62/BM62,) -> 1639
... A83: Santa Barbara 26 | B83: 177.11 | C83: 41.75 | D83: 5.69 | E83: 20.03 | H83: 2 | J83: 7.39 | K83: 52.517 | L83: 19.99 | M83: 13.81 | N83: 57.77 | O83: 73.45 | P83: 2.79 | Q83: 1.86 | R83: 1.86 | S83: 2.7 | T83: 0.9 | U83: 1 | V83: 0.9 | W83: 1 | X83: 0 | Y83: 0 | Z83: 1.2 | BB83: 336030 | BC83: 349264 | BD83: 4000 | BE83: =+BC83-BB83 -> 13234 | BF83: 67.13 | BG83: 1.1 | BH83: =+BG83*BF83 -> 73.843 | BI83: 71.18 | BJ83: 1.1 | BK83: =+BJ83*BI83 -> 78.298 | BL83: 62 | BM83: 244.56 | BN83: =+Shepparton!F83-Shepparton!C83 -> 352340 | BO83: =+ROUND(BN83/BM83,) -> 1441
A85: Homestead | BF85: Floor Tiles | BG85: Wastage | BI85: Carpets | BJ85: Wastage | BL85: Eaves
A86: Inglewood 24 | B86: 164.64 | C86: 38.66 | D86: 3.73 | E86: 15.3 | H86: 3 | J86: 14.4 | K86: 58.8 | L86: 32 | M86: 19.8 | N86: 51.2 | O86: 63.8 | P86: 3.8 | Q86: 2.7 | R86: 2.7 | S86: 0 | T86: 0.9 | U86: 1 | V86: 0.9 | W86: 1 | X86: 0 | Y86: 0 | Z86: 1.2 | BB86: 321256 | BC86: 334465 | BD86: 3000 | BE86: =+BC86-BB86 -> 13209 | BF86: 61.24 | BG86: 1.1 | BH86: =+BG86*BF86 -> 67.364 | BI86: 64.65 | BJ86: 1.1 | BK86: =+BJ86*BI86 -> 71.115 | BL86: 59 | BM86: 222.33 | BN86: =+Shepparton!F95-Shepparton!C95 -> 335470 | BO86: =+ROUND(BN86/BM86,) -> 1509
A87: Inglewood 26 | B87: 185.85 | C87: 38.6 | D87: 3.33 | E87: 15.75 | H87: 2 | J87: 11.7 | K87: 59.6 | L87: 30.9 | M87: 22.7 | N87: 56.1 | O87: 77.1 | P87: 3.8 | Q87: 2.7 | R87: 2.7 | S87: 2.7 | T87: 0.9 | U87: 1 | V87: 0.9 | W87: 1 | X87: 0 | Y87: 0 | Z87: 0 | BB87: 345313 | BC87: 358564 | BD87: 4000 | BE87: =+BC87-BB87 -> 13251 | BF87: 67.2 | BG87: 1.1 | BH87: =+BG87*BF87 -> 73.92 | BI87: 73.9 | BJ87: 1.1 | BK87: =+BJ87*BI87 -> 81.29 | BL87: 68 | BM87: 243.53 | BN87: =+Shepparton!F96-Shepparton!C96 -> 361815 | BO87: =+ROUND(BN87/BM87,) -> 1486
A88: Inglewood 29 | B88: 203.05 | C88: 40.99 | D88: 3.34 | E88: 24.36 | H88: 4 | J88: 12.24 | K88: 63.076 | L88: 33.325 | M88: 23.26 | N88: 60.5 | O88: 82.65 | P88: 3.74 | Q88: 2.74 | R88: 2.74 | S88: 2.7 | T88: 1.6 | U88: 2 | V88: 0.9 | W88: 1 | X88: 0 | Y88: 0 | Z88: 1.2 | BB88: 364949 | BC88: 378282 | BD88: 4000 | BE88: =+BC88-BB88 -> 13333 | BF88: 76.01 | BG88: 1.1 | BH88: =+BG88*BF88 -> 83.611 | BI88: 80.9 | BJ88: 1.1 | BK88: =+BJ88*BI88 -> 88.99 | BL88: 69 | BM88: 271.72 | BN88: =+Shepparton!F97-Shepparton!C97 -> 382905 | BO88: =+ROUND(BN88/BM88,) -> 1409
A89: Inglewood 31 | B89: 215.52 | C89: 39.91 | D89: 3.33 | E89: 32.53 | H89: 4 | J89: 12.2 | K89: 70.7 | L89: 35.5 | M89: 22 | N89: 64.71 | O89: 92.6 | P89: 3.8 | Q89: 2.7 | R89: 2.7 | S89: 2.7 | T89: 1.6 | U89: 2 | V89: 0.9 | W89: 1 | X89: 1.2 | Y89: 1 | Z89: 1.2 | BB89: 383191 | BC89: 396461 | BD89: 4000 | BE89: =+BC89-BB89 -> 13270 | BF89: 75.15 | BG89: 1.1 | BH89: =+BG89*BF89 -> 82.665 | BI89: 91.22 | BJ89: 1.1 | BK89: =+BJ89*BI89 -> 100.342 | BL89: 76 | BM89: 291.29 | BN89: =+Shepparton!F98-Shepparton!C98 -> 401740 | BO89: =+ROUND(BN89/BM89,) -> 1379
A90: Inglewood 34 | B90: 238.31 | C90: 40.98 | D90: 3.34 | E90: 32.45 | H90: 4 | J90: 12.16 | K90: 68.11 | L90: 33.66 | M90: 23.89 | N90: 69.94 | O90: 99.4 | P90: 3.74 | Q90: 2.74 | R90: 2.74 | S90: 2.7 | T90: 1.6 | U90: 2 | V90: 0.9 | W90: 1 | X90: 1.25 | Y90: 1 | Z90: 1.2 | BB90: 402402 | BC90: 415664 | BD90: 4000 | BE90: =+BC90-BB90 -> 13262 | BF90: 79.83 | BG90: 1.1 | BH90: =+BG90*BF90 -> 87.813 | BI90: 110.05 | BJ90: 1.1 | BK90: =+BJ90*BI90 -> 121.055 | BL90: 83 | BM90: 314.9 | BN90: =+Shepparton!F99-Shepparton!C99 -> 422720 | BO90: =+ROUND(BN90/BM90,) -> 1342
A91: Inglewood 35 | B91: 244.73 | C91: 40.46 | D91: 7.7 | E91: 34.04 | H91: 2 | J91: 10.7 | K91: 70.714 | L91: 42.644 | M91: 29.96 | N91: 70.21 | O91: 104.9 | P91: 9.427 | Q91: 6.9 | R91: 5.3 | S91: 2.7 | T91: 2.4 | U91: 2 | V91: 0.9 | W91: 1 | X91: 0.9 | Y91: 1 | Z91: 1.2 | BB91: 421545 | BC91: 434789 | BD91: 4000 | BE91: =+BC91-BB91 -> 13244 | BF91: 79.67 | BG91: 1.1 | BH91: =+BG91*BF91 -> 87.637 | BI91: 106.83 | BJ91: 1.1 | BK91: =+BJ91*BI91 -> 117.513 | BL91: 83 | BM91: 363.81 | BN91: =+Shepparton!F100-Shepparton!C100 -> 441635 | BO91: =+ROUND(BN91/BM91,) -> 1214
A92: Inglewood 38 | B92: 254.84 | C92: 47.61 | D92: 7.7 | E92: 47.94 | H92: 2 | J92: 14.6 | K92: 64 | L92: 46.6 | M92: 36.1 | N92: 73.5 | O92: 100.4 | P92: 11.5 | Q92: 6.4 | R92: 3.4 | S92: 2.7 | T92: 1.8 | U92: 2 | V92: 0.9 | W92: 1 | X92: 1.2 | Y92: 1 | Z92: 1.2 | BB92: 439175 | BC92: 452422 | BD92: 4000 | BE92: =+BC92-BB92 -> 13247 | BF92: 81.05 | BG92: 1.1 | BH92: =+BG92*BF92 -> 89.155 | BI92: 114.65 | BJ92: 1.1 | BK92: =+BJ92*BI92 -> 126.115 | BL92: 83 | BM92: 349.11 | BN92: =+Shepparton!F101-Shepparton!C101 -> 459935 | BO92: =+ROUND(BN92/BM92,) -> 1317
A93: Maldon 23 | BB93: 310120 | BC93: 323347 | BD93: 3000 | BE93: =+BC93-BB93 -> 13227 | BF93: 63.2 | BG93: 1.1 | BH93: =+BG93*BF93 -> 69.52 | BI93: 60 | BJ93: 1.1 | BK93: =+BJ93*BI93 -> 66 | BL93: 53 | BM93: =159.7+37.14 -> 196.84 | BN93: =+Shepparton!F102-Shepparton!C102 -> 324245 | BO93: =+ROUND(BN93/BM93,) -> 1647
A94: Maldon 27 | B94: 193.57 | C94: 38.47 | D94: 6.15 | E94: 13.59 | H94: 1 | J94: 21.63 | K94: 62.1 | L94: 34.6 | M94: 19.85 | N94: 58.76 | O94: 78.97 | P94: 4.78 | Q94: 2.67 | R94: 2.67 | S94: 2.7 | T94: 1.2 | U94: 1 | V94: 1.1 | W94: 1 | X94: 0 | Y94: 0 | Z94: 1.2 | BB94: 348261 | BC94: 361506 | BD94: 4000 | BE94: =+BC94-BB94 -> 13245 | BF94: 75.75 | BG94: 1.1 | BH94: =+BG94*BF94 -> 83.325 | BI94: 69.86 | BJ94: 1.1 | BK94: =+BJ94*BI94 -> 76.846 | BL94: 54 | BM94: 251.33 | BN94: =+Shepparton!F103-Shepparton!C103 -> 365470 | BO94: =+ROUND(BN94/BM94,) -> 1454
A95: Maldon 33 | BB95: 409141 | BC95: 422431 | BD95: 4000 | BE95: =+BC95-BB95 -> 13290 | BF95: =100/1.1 -> 90.909091 | BG95: 1.1 | BH95: =+BG95*BF95 -> 100 | BI95: =99/1.1 -> 90 | BJ95: 1.1 | BK95: =+BJ95*BI95 -> 99 | BL95: 76 | BM95: 349.76
A96: Palmerston 28 | B96: 193.35 | C96: 41.37 | D96: 7.01 | E96: 15.15 | H96: 2 | J96: 11.89 | K96: 55.594 | L96: 22.73 | M96: 17.51 | N96: 61.13 | O96: 81 | P96: 7.13 | Q96: 5.65 | R96: 7.13 | S96: 2.15 | T96: 2.5 | U96: 2 | V96: 0.9 | W96: 1 | X96: 0 | Y96: 0 | Z96: 1.62 | BB96: 355920 | BC96: 369589 | BD96: 4000 | BE96: =+BC96-BB96 -> 13669 | BF96: 70.3 | BG96: 1.1 | BH96: =+BG96*BF96 -> 77.33 | BI96: 77.53 | BJ96: 1.1 | BK96: =+BJ96*BI96 -> 85.283 | BL96: 64 | BM96: 256.87 | BN96: =+Shepparton!F105-Shepparton!C105 -> 373005 | BO96: =+ROUND(BN96/BM96,) -> 1452
A97: Palmerston 35 | B97: 251.05 | C97: 41.39 | D97: 7.01 | E97: 24.13 | H97: 2 | J97: 11.76 | K97: 66.843 | L97: 24.981 | M97: 15.47 | N97: 75.53 | O97: 101.62 | P97: 16.1 | Q97: 5.65 | R97: 5.65 | S97: 2.15 | T97: 2.5 | U97: 2 | V97: 0.9 | W97: 1 | X97: 0 | Y97: 0 | Z97: 1.62 | BB97: 408414 | BC97: 421703 | BD97: 4000 | BE97: =+BC97-BB97 -> 13289 | BF97: 85.2 | BG97: 1.1 | BH97: =+BG97*BF97 -> 93.72 | BI97: 115.55 | BJ97: 1.1 | BK97: =+BJ97*BI97 -> 127.105 | BL97: 73 | BM97: 323.57 | BN97: =+Shepparton!F106-Shepparton!C106 -> 429705 | BO97: =+ROUND(BN97/BM97,) -> 1328
A98: Sandown 23 | B98: 158.33 | C98: 38.99 | D98: 3.79 | E98: 12 | H98: 4 | J98: 11.81 | K98: 62.82 | L98: 37.053 | M98: 20.75 | N98: 50.99 | O98: 67.95 | P98: 3.66 | Q98: 2.76 | R98: 2.76 | S98: 2.76 | T98: 0.9 | U98: 1 | V98: 0.9 | W98: 1 | X98: 0 | Y98: 0 | Z98: 1.2 | BB98: 318048 | BC98: 331300 | BD98: 3000 | BE98: =+BC98-BB98 -> 13252 | BF98: 64.7 | BG98: 1.1 | BH98: =+BG98*BF98 -> 71.17 | BI98: 56.9 | BJ98: 1.1 | BK98: =+BJ98*BI98 -> 62.59 | BL98: 63 | BM98: 213.09 | BN98: =+Shepparton!F107-Shepparton!C107 -> 332145 | BO98: =+ROUND(BN98/BM98,) -> 1559
A99: Sandown 26 | B99: 188.02 | C99: 40.26 | D99: 4.98 | E99: 12 | H99: 4 | J99: 22.6 | K99: 66.9 | L99: 39.1 | M99: 24.4 | N99: 56.32 | O99: 86.8 | P99: 3.7 | Q99: 2.8 | R99: 2.8 | S99: 2.8 | T99: 1.2 | U99: 1 | V99: 0.9 | W99: 1 | X99: 0.9 | Y99: 1 | Z99: 1.2 | BB99: 349713 | BC99: 362956 | BD99: 4000 | BE99: =+BC99-BB99 -> 13243 | BF99: 70.8 | BG99: 1.1 | BH99: =+BG99*BF99 -> 77.88 | BI99: 71.5 | BJ99: 1.1 | BK99: =+BJ99*BI99 -> 78.65 | BL99: 57 | BM99: 245.26 | BN99: =+Shepparton!F108-Shepparton!C108 -> 366465 | BO99: =+ROUND(BN99/BM99,) -> 1494
A100: Sandown 28 (30) | B100: 219.91 | C100: 38.4 | D100: 4.37 | E100: 18 | H100: 4 | J100: 23.02 | K100: 60.8 | L100: 32.2 | M100: 25.6 | N100: 60.19 | O100: 101.7 | P100: 6.7 | Q100: 2.7 | R100: 2.7 | S100: 2.7 | T100: 1.9 | U100: 2 | V100: 0.9 | W100: 1 | X100: 0 | Y100: 0 | Z100: 1.2 | BB100: 372707 | BC100: 385920 | BD100: 4000 | BE100: =+BC100-BB100 -> 13213 | BF100: 79.69 | BG100: 1.1 | BH100: =+BG100*BF100 -> 87.659 | BI100: 94.12 | BJ100: 1.1 | BK100: =+BJ100*BI100 -> 103.532 | BL100: 65 | BM100: 280.68 | BN100: =+Shepparton!F109-Shepparton!C109 -> 391955 | BO100: =+ROUND(BN100/BM100,) -> 1396
A101: Sandown 32 | B101: 221.54 | C101: 38.4 | D101: 5.01 | E101: 29.79 | H101: 5 | J101: 23 | K101: 63.191 | L101: 35.983 | M101: 23.78 | N101: 62.67 | O101: 101 | P101: 8.89 | Q101: 2.7 | R101: 2.7 | S101: 2.7 | T101: 1.8 | U101: 2 | V101: 0.9 | W101: 1 | X101: 0 | Y101: 0 | Z101: 1.2 | BB101: 383246 | BC101: 396488 | BD101: 4000 | BE101: =+BC101-BB101 -> 13242 | BF101: 76 | BG101: 1.1 | BH101: =+BG101*BF101 -> 83.6 | BI101: =13.76+46.81+32.42 -> 92.99 | BJ101: 1.1 | BK101: =+BJ101*BI101 -> 102.289 | BL101: 61 | BM101: 294.73 | BN101: =+Shepparton!F110-Shepparton!C110 -> 402005 | BO101: =+ROUND(BN101/BM101,) -> 1364
A102: Sandown 34 MG | BB102: 418020 | BC102: 431186 | BD102: 4000 | BE102: =+BC102-BB102 -> 13166 | BF102: 84.3 | BG102: 1.1 | BH102: =+BG102*BF102 -> 92.73 | BI102: =39.32+45.71 -> 85.03 | BJ102: 1.1 | BK102: =+BJ102*BI102 -> 93.533 | BL102: =100-20 -> 80 | BM102: =258.72+37.4 -> 296.12 | BN102: =+Shepparton!F111-Shepparton!C111 -> 437190 | BO102: =+ROUND(BN102/BM102,) -> 1476
A103: Sandown 40 MG | BB103: 472601 | BC103: 486075 | BD103: 4000 | BE103: =+BC103-BB103 -> 13474 | BF103: 76.85 | BG103: 1.1 | BH103: =+BG103*BF103 -> 84.535 | BI103: 136 | BJ103: 1.1 | BK103: =+BJ103*BI103 -> 149.6 | BL103: =106-20 -> 86 | BM103: =276.45+37.13+28.04 -> 341.62 | BN103: =+Shepparton!F112-Shepparton!C112 -> 494300 | BO103: =+ROUND(BN103/BM103,) -> 1447
A104: Sandown 41 MG | BB104: 470792 | BC104: 483869 | BD104: 4000 | BE104: =+BC104-BB104 -> 13077 | BF104: 86.76 | BG104: 1.1 | BH104: =+BG104*BF104 -> 95.436 | BI104: 123.56 | BJ104: 1.1 | BK104: =+BJ104*BI104 -> 135.916 | BL104: 85 | BM104: =272.83+36.36+24.23 -> 333.42 | BN104: =+Shepparton!F113-Shepparton!C113 -> 492785 | BO104: =+ROUND(BN104/BM104,) -> 1478
A105: Winton 24 | B105: 164.54 | C105: 41.02 | D105: 7.7 | E105: 15.44 | H105: 3 | J105: 7.13 | K105: 59.1 | L105: 28.1 | M105: 18.29 | N105: 56 | O105: 63.4 | P105: 3.54 | Q105: 3.24 | R105: 3.24 | S105: 2.7 | T105: 0.9 | U105: 1 | V105: 0.9 | W105: 1 | X105: 0 | Y105: 0 | Z105: 1.2 | BB105: 324567 | BC105: 337780 | BD105: 3000 | BE105: =+BC105-BB105 -> 13213 | BF105: 68.71 | BG105: 1.1 | BH105: =+BG105*BF105 -> 75.581 | BI105: 55.88 | BJ105: 1.1 | BK105: =+BJ105*BI105 -> 61.468 | BL105: 64 | BM105: 228.72 | BN105: =+Shepparton!F114-Shepparton!C114 -> 339045 | BO105: =+ROUND(BN105/BM105,) -> 1482
A106: Winton 28 | B106: 200.29 | C106: 41.02 | D106: 7.4 | E106: 15.47 | H106: 3 | J106: 11.08 | K106: 60.808 | L106: 27.699 | M106: 21.43 | N106: 64.41 | O106: 76.2 | P106: 3.54 | Q106: 4.83 | R106: 4.83 | S106: 3 | T106: 0.9 | U106: 1 | V106: 0.9 | W106: 1 | X106: 0 | Y106: 0 | Z106: 1.2 | BB106: 360137 | BC106: 373394 | BD106: 4000 | BE106: =+BC106-BB106 -> 13257 | BF106: 76.63 | BG106: 1.1 | BH106: =+BG106*BF106 -> 84.293 | BI106: 79.18 | BJ106: 1.1 | BK106: =+BJ106*BI106 -> 87.098 | BL106: 68 | BM106: 263.33 | BN106: =+Shepparton!F115-Shepparton!C115 -> 378055 | BO106: =+ROUND(BN106/BM106,) -> 1436
A107: Winton 32 | B107: 240.25 | C107: 41.02 | D107: 8.47 | E107: 16.8 | H107: 3 | J107: 11.6 | K107: 64.863 | L107: 29.508 | M107: 24.42 | N107: 72.22 | O107: 102.2 | P107: 3.54 | Q107: 4.83 | R107: 4.83 | S107: 3 | T107: 1.8 | U107: 2 | V107: 0.9 | W107: 1 | X107: 0 | Y107: 0 | Z107: 1.2 | BB107: 403446 | BC107: 416691 | BD107: 4000 | BE107: =+BC107-BB107 -> 13245 | BF107: 91.44 | BG107: 1.1 | BH107: =+BG107*BF107 -> 100.584 | BI107: 98.11 | BJ107: 1.1 | BK107: =+BJ107*BI107 -> 107.921 | BL107: 75 | BM107: 306.52 | BN107: =+Shepparton!F116-Shepparton!C116 -> 424295 | BO107: =+ROUND(BN107/BM107,) -> 1384
A109: Narrow block | BF109: Floor Tiles | BG109: Wastage | BI109: Carpets | BJ109: Wastage | BL109: Eaves
A110: Albany 17 | B110: 125.75 | C110: 24.37 | D110: 0.54 | E110: 8.95 | H110: 1 | J110: 9.95 | K110: 34.127 | L110: 12.914 | M110: 18.18 | N110: 52.51 | O110: 48.5 | P110: 3.64 | Q110: 1.84 | R110: 1.84 | S110: 2.7 | T110: 0.9 | U110: 1 | V110: 0.8 | W110: 1 | X110: 0 | Y110: 0 | Z110: 1.2 | BB110: 278601 | BC110: 291884 | BD110: 3000 | BE110: =+BC110-BB110 -> 13283 | BF110: 53.12 | BG110: 1.1 | BH110: =+BG110*BF110 -> 58.432 | BI110: 36.65 | BJ110: 1.1 | BK110: =+BJ110*BI110 -> 40.315 | BL110: 58 | BM110: 159.91 | BN110: =+Shepparton!F130-Shepparton!C130 -> 290050 | BO110: =+ROUND(BN110/BM110,) -> 1814
A111: Albany 18 | B111: 125.75 | C111: 38.6 | D111: 0.54 | E111: 8.95 | H111: 1 | J111: 9.25 | K111: 34.127 | L111: 12.941 | M111: 20.38 | N111: 52 | O111: 48.5 | P111: 3.64 | Q111: 1.84 | R111: 1.84 | S111: 2.7 | T111: 0.9 | U111: 1 | V111: 0.8 | W111: 1 | X111: 0 | Y111: 0 | Z111: 1.2 | BB111: 290595 | BC111: 303881 | BD111: 3000 | BE111: =+BC111-BB111 -> 13286 | BF111: 53.12 | BG111: 1.1 | BH111: =+BG111*BF111 -> 58.432 | BI111: 36.65 | BJ111: 1.1 | BK111: =+BJ111*BI111 -> 40.315 | BL111: 62 | BM111: 174.14 | BN111: =+Shepparton!F131-Shepparton!C131 -> 302040 | BO111: =+ROUND(BN111/BM111,) -> 1734
A112: Albany 20 | B112: 134.76 | C112: 38.45 | D112: 0.54 | E112: 12.24 | H112: 1 | J112: 9.25 | K112: 37 | L112: 12.941 | M112: 18.38 | N112: 53.51 | O112: 53.1 | P112: 3.64 | Q112: 1.84 | R112: 1.84 | S112: 2.7 | T112: 0.9 | U112: 1 | V112: 0.8 | W112: 1 | X112: 0 | Y112: 0 | Z112: 1.2 | BB112: 297582 | BC112: 310861 | BD112: 3000 | BE112: =+BC112-BB112 -> 13279 | BF112: 61.62 | BG112: 1.1 | BH112: =+BG112*BF112 -> 67.782 | BI112: 36.58 | BJ112: 1.1 | BK112: =+BJ112*BI112 -> 40.238 | BL112: 62 | BM112: 185.01 | BN112: =+Shepparton!F132-Shepparton!C132 -> 309990 | BO112: =+ROUND(BN112/BM112,) -> 1676
A113: Avoca 16 | B113: 126.2 | C113: 24.56 | D113: 2.61 | E113: 0 | H113: 1 | J113: 5.02 | K113: 34.619 | L113: 11.766 | M113: 13.52 | N113: 45.16 | O113: 54 | P113: 2.31 | Q113: 3.51 | R113: 3.51 | S113: 1.89 | T113: 0.9 | U113: 1 | V113: 0.9 | W113: 1 | X113: 0 | Y113: 0 | Z113: 1.2 | BB113: 274130 | BC113: 287320 | BD113: 3000 | BE113: =+BC113-BB113 -> 13190 | BF113: 51.71 | BG113: 1.1 | BH113: =+BG113*BF113 -> 56.881 | BI113: 38.86 | BJ113: 1.1 | BK113: =+BJ113*BI113 -> 42.746 | BL113: 50 | BM113: 153.78 | BN113: =+Shepparton!F133-Shepparton!C133 -> 285555 | BO113: =+ROUND(BN113/BM113,) -> 1857
A114: Avoca 19 | B114: 143.6 | C114: 24.56 | D114: 3.96 | E114: 10.65 | H114: 2 | J114: 5.02 | K114: 34.618 | L114: 11.766 | M114: 17.21 | N114: 52.56 | O114: 60.2 | P114: 2.31 | Q114: 3.5 | R114: 3.5 | S114: 1.89 | T114: 0.9 | U114: 1 | V114: 0.9 | W114: 1 | X114: 0 | Y114: 0 | Z114: 1.2 | BB114: 294718 | BC114: 308010 | BD114: 3000 | BE114: =+BC114-BB114 -> 13292 | BF114: 56.06 | BG114: 1.1 | BH114: =+BG114*BF114 -> 61.666 | BI114: 48.92 | BJ114: 1.1 | BK114: =+BJ114*BI114 -> 53.812 | BL114: 58 | BM114: 182.98 | BN114: =+Shepparton!F134-Shepparton!C134 -> 307305 | BO114: =+ROUND(BN114/BM114,) -> 1679
A115: Avoca 20 | B115: 149.58 | C115: 24.57 | D115: 3.96 | E115: 10.65 | H115: 3 | J115: 4.62 | K115: 38.051 | L115: 15.157 | M115: 18.77 | N115: 55.68 | O115: 63.5 | P115: 2.31 | Q115: 3.51 | R115: 3.51 | S115: 1.89 | T115: 0.9 | U115: 1 | V115: 0.9 | W115: 1 | X115: 0 | Y115: 0 | Z115: 1.2 | BB115: 298314 | BC115: 311658 | BD115: 3000 | BE115: =+BC115-BB115 -> 13344 | BF115: 52.09 | BG115: 1.1 | BH115: =+BG115*BF115 -> 57.299 | BI115: 58.1 | BJ115: 1.1 | BK115: =+BJ115*BI115 -> 63.91 | BL115: 61 | BM115: 186.97 | BN115: =+Shepparton!F135-Shepparton!C135 -> 311060 | BO115: =+ROUND(BN115/BM115,) -> 1664
A116: Belinda 16 | B116: 120.37 | C116: 25.23 | D116: 4.07 | E116: 0 | H116: 2 | J116: 6.17 | K116: 34.32 | L116: 10.6 | M116: 12.23 | N116: 42.8 | O116: 51.45 | P116: 3.34 | Q116: 1.54 | R116: 1.54 | S116: 2.49 | T116: 0 | U116: 0 | V116: 0.9 | W116: 1 | X116: 0 | Y116: 0 | Z116: 1.2 | BB116: 242920 | BC116: 255631 | BD116: 3000 | BE116: =+BC116-BB116 -> 12711 | BF116: 51.75 | BG116: 1.1 | BH116: =+BG116*BF116 -> 56.925 | BI116: 40.9 | BJ116: 1.1 | BK116: =+BJ116*BI116 -> 44.99 | BL116: 48 | BM116: 149.9 | BN116: =+Shepparton!F136-Shepparton!C136 -> 254485 | BO116: =+ROUND(BN116/BM116,) -> 1698
A117: Belinda 18 | B117: 133.12 | C117: 25.23 | D117: 4.21 | E117: 7.22 | H117: 2 | J117: 6.17 | K117: 34.54 | L117: 10.64 | M117: 14.6 | N117: 47.74 | O117: 53.45 | P117: 3.39 | Q117: 1.57 | R117: 1.57 | S117: 2.58 | T117: 0.9 | U117: 1 | V117: 0.9 | W117: 1 | X117: 0 | Y117: 0 | Z117: 1.2 | BB117: 276599 | BC117: 289769 | BD117: 3000 | BE117: =+BC117-BB117 -> 13170 | BF117: 59.75 | BG117: 1.1 | BH117: =+BG117*BF117 -> 65.725 | BI117: 40.26 | BJ117: 1.1 | BK117: =+BJ117*BI117 -> 44.286 | BL117: 53 | BM117: 169.95 | BN117: =+Shepparton!F137-Shepparton!C137 -> 289030 | BO117: =+ROUND(BN117/BM117,) -> 1701
A118: Belinda 20 | B118: 149.29 | C118: 25.23 | D118: 4.21 | E118: 8.44 | H118: 2 | J118: 6.17 | K118: 34.54 | L118: 10.637 | M118: 16.75 | N118: 52.04 | O118: 58.65 | P118: 3.4 | Q118: 1.57 | R118: 1.57 | S118: 2.58 | T118: 0.9 | U118: 1 | V118: 0.9 | W118: 1 | X118: 0 | Y118: 0 | Z118: 1.2 | BB118: 292091 | BC118: 305240 | BD118: 3000 | BE118: =+BC118-BB118 -> 13149 | BF118: 64.9 | BG118: 1.1 | BH118: =+BG118*BF118 -> 71.39 | BI118: 50.3 | BJ118: 1.1 | BK118: =+BJ118*BI118 -> 55.33 | BL118: 57 | BM118: 187.15 | BN118: =+Shepparton!F138-Shepparton!C138 -> 305775 | BO118: =+ROUND(BN118/BM118,) -> 1634
A119: Fairfield 18 | B119: 134.91 | C119: 24.99 | D119: 3.26 | E119: 8.49 | H119: 2 | J119: 7.33 | K119: 47.12 | L119: 19.171 | M119: 17.1 | N119: 58.02 | O119: 47.8 | P119: 3.64 | Q119: 1.84 | R119: 1.84 | S119: 2.7 | T119: 0.9 | U119: 1 | V119: 0.9 | W119: 1 | X119: 0 | Y119: 0 | Z119: 1.2 | BB119: 288037 | BC119: 301267 | BD119: 3000 | BE119: =+BC119-BB119 -> 13230 | BF119: 59.25 | BG119: 1.1 | BH119: =+BG119*BF119 -> 65.175 | BI119: 41.8 | BJ119: 1.1 | BK119: =+BJ119*BI119 -> 45.98 | BL119: 65 | BM119: 171.83 | BN119: =+Shepparton!F139-Shepparton!C139 -> 300515 | BO119: =+ROUND(BN119/BM119,) -> 1749
A120: Fairfield 19 | B120: 138.24 | C120: 24.99 | D120: 3.68 | E120: 8.05 | H120: 2 | J120: 8.08 | K120: 53.892 | L120: 23.288 | M120: 16.07 | N120: 59.72 | O120: 45.6 | P120: 3.54 | Q120: 1.74 | R120: 1.74 | S120: 2.7 | T120: 0.9 | U120: 1 | V120: 0.9 | W120: 1 | X120: 0 | Y120: 0 | Z120: 1.2 | BB120: 291017 | BC120: 304349 | BD120: 3000 | BE120: =+BC120-BB120 -> 13332 | BF120: 59.89 | BG120: 1.1 | BH120: =+BG120*BF120 -> 65.879 | BI120: 45.6 | BJ120: 1.1 | BK120: =+BJ120*BI120 -> 50.16 | BL120: 66 | BM120: 175.1 | BN120: =+Shepparton!F140-Shepparton!C140 -> 303820 | BO120: =+ROUND(BN120/BM120,) -> 1735
A121: Fairfield 20 | B121: 147.2 | C121: 24.99 | D121: 3.68 | E121: 12.59 | H121: 2 | J121: 8.08 | K121: 55.256 | L121: 23.288 | M121: 16.65 | N121: 62.8 | O121: 52.9 | P121: 3.54 | Q121: 1.74 | R121: 1.74 | S121: 2.7 | T121: 0.9 | U121: 1 | V121: 0.9 | W121: 1 | X121: 0 | Y121: 0 | Z121: 1.2 | BB121: 303815 | BC121: 316965 | BD121: 3000 | BE121: =+BC121-BB121 -> 13150 | BF121: 61.71 | BG121: 1.1 | BH121: =+BG121*BF121 -> 67.881 | BI121: 47.12 | BJ121: 1.1 | BK121: =+BJ121*BI121 -> 51.832 | BL121: 69 | BM121: 188.66 | BN121: =+Shepparton!F141-Shepparton!C141 -> 316925 | BO121: =+ROUND(BN121/BM121,) -> 1680
A122: Launceston 21 | B122: 150.9 | C122: 24.65 | D122: 4.03 | E122: 12.08 | H122: 2 | J122: 6.83 | K122: 44.065 | L122: 18.295 | M122: 15.895 | N122: 55.14 | O122: 65.71 | P122: 4.14 | Q122: 2.32 | R122: 2.32 | S122: 2.7 | T122: 1.1 | U122: 1 | V122: 0.9 | W122: 1 | X122: 0 | Y122: 0 | Z122: 1.2 | BB122: =+BB62 -> 301071 | BC122: =+BC62 -> 314204 | BD122: 3000 | BE122: =+BC122-BB122 -> 13133 | BF122: 57.48 | BG122: 1.1 | BH122: =+BG122*BF122 -> 63.228 | BI122: 56 | BJ122: 1.1 | BK122: =+BJ122*BI122 -> 61.6 | BL122: 58 | BM122: 191.76 | BN122: =+Shepparton!F142-Shepparton!C142 -> 314295 | BO122: =+ROUND(BN122/BM122,) -> 1639
A123: Melrose 19 | B123: 128.99 | C123: 37.56 | D123: 2.45 | E123: 7.44 | H123: 2 | J123: 0.63 | K123: 32.79 | L123: 9.44 | M123: 15.51 | N123: 47.61 | O123: 55.53 | P123: 3.04 | Q123: 1.4 | R123: 1.4 | S123: 3.1 | T123: 0.9 | U123: 1 | V123: 0.9 | W123: 1 | X123: 0 | Y123: 0 | Z123: 0.8 | BB123: 282110 | BC123: 295754 | BD123: 3000 | BE123: =+BC123-BB123 -> 13644 | BF123: 50.94 | BG123: 1.1 | BH123: =+BG123*BF123 -> 56.034 | BI123: 43.52 | BJ123: 1.1 | BK123: =+BJ123*BI123 -> 47.872 | BL123: 55 | BM123: 176.43 | BN123: =+Shepparton!F143-Shepparton!C143 -> 293760 | BO123: =+ROUND(BN123/BM123,) -> 1665
A124: Stratford 16A | B124: 119.67 | C124: 23.62 | D124: 3.02 | E124: 6.15 | H124: 2 | J124: 2.82 | K124: 35.6 | L124: 11.17 | M124: 12.25 | N124: 47.58 | O124: 52.68 | P124: 2.41 | Q124: 1.5 | R124: 1.5 | S124: 3 | T124: 0.9 | U124: 1 | V124: 0.9 | W124: 1 | X124: 0 | Y124: 0 | Z124: 1.1 | BB124: 267755 | BC124: 281000 | BD124: 3000 | BE124: =+BC124-BB124 -> 13245 | BF124: 51.04 | BG124: 1.1 | BH124: =+BG124*BF124 -> 56.144 | BI124: 34.42 | BJ124: 1.1 | BK124: =+BJ124*BI124 -> 37.862 | BL124: 51 | BM124: 152.46 | BN124: =+Shepparton!F144-Shepparton!C144 -> 278820 | BO124: =+ROUND(BN124/BM124,) -> 1829
...

Sheet Landscaping
C5: Seed | D5: Turf | E5: Turf with excavation
B6: 600m2 | C6: 14154.02 | D6: 16686.01 | E6: 18542.01 | H6: =+D6-C6 -> 2531.99 | J6: =+E6-D6 -> 1856
B7: 800m2 | C7: 17723.13 | D7: 21199.93 | E7: 23055.26 | H7: =+D7-C7 -> 3476.8 | J7: =+E7-D7 -> 1855.33
B8: Nature strip | E8: 1918.24
B9: Corner block | E9: 3841.6
B10: External power point | E10: =+Electrical!D11 -> 135
C13: Seed | D13: Turf
B14: 600m2 normal block | C14: =CEILING((C6+J6+E8)*1.36,50)+E10 -> 24535 | D14: =CEILING((E6+E8)*1.36,25)+E10 -> 27985
B15: 600m2 corner block | C15: =+CEILING((C6+J6+E9)*1.36,25)+E10 -> 27135 | D15: =+CEILING((E6+E9)*1.36,25)+E10 -> 30585
B16: 800m2 normal block | C16: =+CEILING((C7+J6+E8)*1.36,25)+E10 -> 29385 | D16: =+CEILING((E7+E8)*1.36,25)+E10 -> 34110
B17: 800m2 corner block | C17: =+CEILING((C7+E9+J6)*1.36,25)+E10 -> 32010 | D17: =+CEILING((E7+E9)*1.36,25)+E10 -> 36735

Sheet Shepparton
A1: SHEPPARTON
A2: LIFESTYLE SINGLE STOREY PRICE LIST VALID UP TO AUG 2025
A3: HOUSE DESIGN | B3: BASE PRICE * | C3: 50sqm NATURAL CONCRETE | D3: LIFESTYLE FLOOR TILES | E3: LIFESTYLE CARPETS | F3: PACKAGE PRICE *50sqm NATURAL CONCRETE *CARPET *TILES | G3: PRICE TO ADD EAVES | I3: List price | J3: Promotional | K3: Bonus | L3: 50sqm natural concrete | M3: Tiles per sqm | N3: Carpet per sqm | O3: Eaves per lm
A4: Adelaide 18 | B4: =+CEILING(I4+J4+K4,10) -> 282210 | C4: =+L4 -> 7000 | D4: =+CEILING(Lifestyle!BH14*Shepparton!M4,5) -> 5010 | E4: =+CEILING(Lifestyle!BK14*Shepparton!N4,5) -> 2785 | F4: =SUM(B4:E4) -> 297005 | G4: =+CEILING(Lifestyle!BL14*Shepparton!O4,5) -> 4420 | I4: =+Lifestyle!BB14 -> 279204 | J4: =+Lifestyle!BB7 -> 0 | K4: =+Lifestyle!BD14 -> 3000 | L4: =+Lifestyle!BB3 -> 7000 | M4: =+Lifestyle!BB4 -> 103 | N4: =+Lifestyle!BB5 -> 60 | O4: =+Lifestyle!BB6 -> 85
A5: Adelaide 21 | B5: =+CEILING(I5+J5+K5,10) -> 296640 | C5: =+L5 -> 7000 | D5: =+CEILING(Lifestyle!BH15*Shepparton!M5,5) -> 5140 | E5: =+CEILING(Lifestyle!BK15*Shepparton!N5,5) -> 4100 | F5: =SUM(B5:E5) -> 312880 | G5: =+CEILING(Lifestyle!BL15*Shepparton!O5,5) -> 4845 | I5: =+Lifestyle!BB15 -> 293633 | J5: =+J4 -> 0 | K5: =+Lifestyle!BD15 -> 3000 | L5: =+L4 -> 7000 | M5: =+M4 -> 103 | N5: =+N4 -> 60 | O5: =+O4 -> 85
A6: Adelaide 22A | B6: =+CEILING(I6+J6+K6,10) -> 310720 | C6: =+L6 -> 7000 | D6: =+CEILING(Lifestyle!BH16*Shepparton!M6,5) -> 5935 | E6: =+CEILING(Lifestyle!BK16*Shepparton!N6,5) -> 4085 | F6: =SUM(B6:E6) -> 327740 | G6: =+CEILING(Lifestyle!BL16*Shepparton!O6,5) -> 5100 | I6: =+Lifestyle!BB16 -> 307717 | J6: =+J5 -> 0 | K6: =+Lifestyle!BD16 -> 3000 | L6: =+L5 -> 7000 | M6: =+M5 -> 103 | N6: =+N5 -> 60 | O6: =+O5 -> 85
A7: Adelaide 22B | B7: =+CEILING(I7+J7+K7,10) -> 312390 | C7: =+L7 -> 7000 | D7: =+CEILING(Lifestyle!BH17*Shepparton!M7,5) -> 5885 | E7: =+CEILING(Lifestyle!BK17*Shepparton!N7,5) -> 3985 | F7: =SUM(B7:E7) -> 329260 | G7: =+CEILING(Lifestyle!BL17*Shepparton!O7,5) -> 5100 | I7: =+Lifestyle!BB17 -> 309383 | J7: =+J6 -> 0 | K7: =+Lifestyle!BD17 -> 3000 | L7: =+L6 -> 7000 | M7: =+M6 -> 103 | N7: =+N6 -> 60 | O7: =+O6 -> 85
A8: Adelaide 24 | B8: =+CEILING(I8+J8+K8,10) -> 319970 | C8: =+L8 -> 7000 | D8: =+CEILING(Lifestyle!BH18*Shepparton!M8,5) -> 6420 | E8: =+CEILING(Lifestyle!BK18*Shepparton!N8,5) -> 4990 | F8: =SUM(B8:E8) -> 338380 | G8: =+CEILING(Lifestyle!BL18*Shepparton!O8,5) -> 5270 | I8: =+Lifestyle!BB18 -> 316962 | J8: =+J7 -> 0 | K8: =+Lifestyle!BD18 -> 3000 | L8: =+L7 -> 7000 | M8: =+M7 -> 103 | N8: =+N7 -> 60 | O8: =+O7 -> 85
A9: Ashfield 24 | B9: =+CEILING(I9+J9+K9,10) -> 322220 | C9: =+L9 -> 7000 | D9: =+CEILING(Lifestyle!BH19*Shepparton!M9,5) -> 8670 | E9: =+CEILING(Lifestyle!BK19*Shepparton!N9,5) -> 3475 | F9: =SUM(B9:E9) -> 341365 | G9: =+CEILING(Lifestyle!BL19*Shepparton!O9,5) -> 4930 | I9: =+Lifestyle!BB19 -> 319218 | J9: =+J8 -> 0 | K9: =+Lifestyle!BD19 -> 3000 | L9: =+L8 -> 7000 | M9: =+M8 -> 103 | N9: =+N8 -> 60 | O9: =+O8 -> 85
A10: Ashfield 30 | B10: =+CEILING(I10+J10+K10,10) -> 359580 | C10: =+L10 -> 7000 | D10: =+CEILING(Lifestyle!BH20*Shepparton!M10,5) -> 7940 | E10: =+CEILING(Lifestyle!BK20*Shepparton!N10,5) -> 5610 | F10: =SUM(B10:E10) -> 380130 | G10: =+CEILING(Lifestyle!BL20*Shepparton!O10,5) -> 5100 | I10: =+Lifestyle!BB20 -> 355577 | J10: =+J9 -> 0 | K10: =+Lifestyle!BD20 -> 4000 | L10: =+L9 -> 7000 | M10: =+M9 -> 103 | N10: =+N9 -> 60 | O10: =+O9 -> 85
A11: Ashfield 34 | B11: =+CEILING(I11+J11+K11,10) -> 386150 | C11: =+L11 -> 7000 | D11: =+CEILING(Lifestyle!BH21*Shepparton!M11,5) -> 8440 | E11: =+CEILING(Lifestyle!BK21*Shepparton!N11,5) -> 6700 | F11: =SUM(B11:E11) -> 408290 | G11: =+CEILING(Lifestyle!BL21*Shepparton!O11,5) -> 6290 | I11: =+Lifestyle!BB21 -> 382148 | J11: =+J10 -> 0 | K11: =+Lifestyle!BD21 -> 4000 | L11: =+L10 -> 7000 | M11: =+M10 -> 103 | N11: =+N10 -> 60 | O11: =+O10 -> 85
A12: Ashley 19 | B12: =+CEILING(I12+J12+K12,10) -> 280620 | C12: =+L12 -> 7000 | D12: =+CEILING(Lifestyle!BH22*Shepparton!M12,5) -> 5805 | E12: =+CEILING(Lifestyle!BK22*Shepparton!N12,5) -> 2805 | F12: =SUM(B12:E12) -> 296230 | G12: =+CEILING(Lifestyle!BL22*Shepparton!O12,5) -> 4335 | I12: =+Lifestyle!BB22 -> 277619 | J12: =+J11 -> 0 | K12: =+Lifestyle!BD22 -> 3000 | L12: =+L11 -> 7000 | M12: =+M11 -> 103 | N12: =+N11 -> 60 | O12: =+O11 -> 85
A13: Ashley 21 | B13: =+CEILING(I13+J13+K13,10) -> 300060 | C13: =+L13 -> 7000 | D13: =+CEILING(Lifestyle!BH23*Shepparton!M13,5) -> 6975 | E13: =+CEILING(Lifestyle!BK23*Shepparton!N13,5) -> 3735 | F13: =SUM(B13:E13) -> 317770 | G13: =+CEILING(Lifestyle!BL23*Shepparton!O13,5) -> 5015 | I13: =+Lifestyle!BB23 -> 297059 | J13: =+J12 -> 0 | K13: =+Lifestyle!BD23 -> 3000 | L13: =+L12 -> 7000 | M13: =+M12 -> 103 | N13: =+N12 -> 60 | O13: =+O12 -> 85
A14: Ashley 22 | B14: =+CEILING(I14+J14+K14,10) -> 297580 | C14: =+L14 -> 7000 | D14: =+CEILING(Lifestyle!BH24*Shepparton!M14,5) -> 6855 | E14: =+CEILING(Lifestyle!BK24*Shepparton!N14,5) -> 3875 | F14: =SUM(B14:E14) -> 315310 | G14: =+CEILING(Lifestyle!BL24*Shepparton!O14,5) -> 4760 | I14: =+Lifestyle!BB24 -> 294577 | J14: =+J13 -> 0 | K14: =+Lifestyle!BD24 -> 3000 | L14: =+L13 -> 7000 | M14: =+M13 -> 103 | N14: =+N13 -> 60 | O14: =+O13 -> 85
A15: Ashley 22A | B15: =+CEILING(I15+J15+K15,10) -> 303720 | C15: =+L15 -> 7000 | D15: =+CEILING(Lifestyle!BH25*Shepparton!M15,5) -> 7470 | E15: =+CEILING(Lifestyle!BK25*Shepparton!N15,5) -> 3615 | F15: =SUM(B15:E15) -> 321805 | G15: =+CEILING(Lifestyle!BL25*Shepparton!O15,5) -> 4760 | I15: =+Lifestyle!BB25 -> 300718 | J15: =+J14 -> 0 | K15: =+Lifestyle!BD25 -> 3000 | L15: =+L14 -> 7000 | M15: =+M14 -> 103 | N15: =+N14 -> 60 | O15: =+O14 -> 85
A16: Ashley 24 | B16: =+CEILING(I16+J16+K16,10) -> 315050 | C16: =+L16 -> 7000 | D16: =+CEILING(Lifestyle!BH26*Shepparton!M16,5) -> 6505 | E16: =+CEILING(Lifestyle!BK26*Shepparton!N16,5) -> 4665 | F16: =SUM(B16:E16) -> 333220 | G16: =+CEILING(Lifestyle!BL26*Shepparton!O16,5) -> 5015 | I16: =+Lifestyle!BB26 -> 312046 | J16: =+J14 -> 0 | K16: =+Lifestyle!BD26 -> 3000 | L16: =+L14 -> 7000 | M16: =+M14 -> 103 | N16: =+N14 -> 60 | O16: =+O14 -> 85
A17: Ashley 25 | B17: =+CEILING(I17+J17+K17,10) -> 324090 | C17: =+L17 -> 7000 | D17: =+CEILING(Lifestyle!BH27*Shepparton!M17,5) -> 6950 | E17: =+CEILING(Lifestyle!BK27*Shepparton!N17,5) -> 4610 | F17: =SUM(B17:E17) -> 342650 | G17: =+CEILING(Lifestyle!BL27*Shepparton!O17,5) -> 5440 | I17: =+Lifestyle!BB27 -> 320081 | J17: =+J16 -> 0 | K17: =+Lifestyle!BD27 -> 4000 | L17: =+L16 -> 7000 | M17: =+M16 -> 103 | N17: =+N16 -> 60 | O17: =+O16 -> 85
A18: Ashley 25A | B18: =+CEILING(I18+J18+K18,10) -> 334230 | C18: =+L18 -> 7000 | D18: =+CEILING(Lifestyle!BH28*Shepparton!M18,5) -> 7040 | E18: =+CEILING(Lifestyle!BK28*Shepparton!N18,5) -> 4655 | F18: =SUM(B18:E18) -> 352925 | G18: =+CEILING(Lifestyle!BL28*Shepparton!O18,5) -> 5440 | I18: =+Lifestyle!BB28 -> 330229 | J18: =+J17 -> 0 | K18: =+Lifestyle!BD28 -> 4000 | L18: =+L17 -> 7000 | M18: =+M17 -> 103 | N18: =+N17 -> 60 | O18: =+O17 -> 85
A19: Ashley 26 | B19: =+CEILING(I19+J19+K19,10) -> 330980 | C19: =+L19 -> 7000 | D19: =+CEILING(Lifestyle!BH29*Shepparton!M19,5) -> 7050 | E19: =+CEILING(Lifestyle!BK29*Shepparton!N19,5) -> 4900 | F19: =SUM(B19:E19) -> 349930 | G19: =+CEILING(Lifestyle!BL29*Shepparton!O19,5) -> 5270 | I19: =+Lifestyle!BB29 -> 326973 | J19: =+J18 -> 0 | K19: =+Lifestyle!BD29 -> 4000 | L19: =+L18 -> 7000 | M19: =+M18 -> 103 | N19: =+N18 -> 60 | O19: =+O18 -> 85
A20: Ashley 27 | B20: =+CEILING(I20+J20+K20,10) -> 342910 | C20: =+L20 -> 7000 | D20: =+CEILING(Lifestyle!BH30*Shepparton!M20,5) -> 7995 | E20: =+CEILING(Lifestyle!BK30*Shepparton!N20,5) -> 6080 | F20: =SUM(B20:E20) -> 363985 | G20: =+CEILING(Lifestyle!BL30*Shepparton!O20,5) -> 5525 | I20: =+Lifestyle!BB30 -> 338903 | J20: =+J19 -> 0 | K20: =+Lifestyle!BD30 -> 4000 | L20: =+L19 -> 7000 | M20: =+M19 -> 103 | N20: =+N19 -> 60 | O20: =+O19 -> 85
A21: Ashley 28 | B21: =+CEILING(I21+J21+K21,10) -> 347740 | C21: =+L21 -> 7000 | D21: =+CEILING(Lifestyle!BH31*Shepparton!M21,5) -> 8895 | E21: =+CEILING(Lifestyle!BK31*Shepparton!N21,5) -> 4395 | F21: =SUM(B21:E21) -> 368030 | G21: =+CEILING(Lifestyle!BL31*Shepparton!O21,5) -> 5525 | I21: =+Lifestyle!BB31 -> 343732 | J21: =+J20 -> 0 | K21: =+Lifestyle!BD31 -> 4000 | L21: =+L20 -> 7000 | M21: =+M20 -> 103 | N21: =+N20 -> 60 | O21: =+O20 -> 85
A22: Ashley 28A | B22: =+CEILING(I22+J22+K22,10) -> 355250 | C22: =+L22 -> 7000 | D22: =+CEILING(Lifestyle!BH32*Shepparton!M22,5) -> 9335 | E22: =+CEILING(Lifestyle!BK32*Shepparton!N22,5) -> 5835 | F22: =SUM(B22:E22) -> 377420 | G22: =+CEILING(Lifestyle!BL32*Shepparton!O22,5) -> 5525 | I22: =+Lifestyle!BB32 -> 351250 | J22: =+J21 -> 0 | K22: =+Lifestyle!BD32 -> 4000 | L22: =+L21 -> 7000 | M22: =+M21 -> 103 | N22: =+N21 -> 60 | O22: =+O21 -> 85
A23: Ballina 24 | B23: =+CEILING(I23+J23+K23,10) -> 315600 | C23: =+L23 -> 7000 | D23: =+CEILING(Lifestyle!BH33*Shepparton!M23,5) -> 7970 | E23: =+CEILING(Lifestyle!BK33*Shepparton!N23,5) -> 3015 | F23: =SUM(B23:E23) -> 333585 | G23: =+CEILING(Lifestyle!BL33*Shepparton!O23,5) -> 4505 | I23: =+Lifestyle!BB33 -> 312597 | J23: =+J22 -> 0 | K23: =+Lifestyle!BD33 -> 3000 | L23: =+L22 -> 7000 | M23: =+M22 -> 103 | N23: =+N22 -> 60 | O23: =+O22 -> 85
A24: Ballina 30 | B24: =+CEILING(I24+J24+K24,10) -> 364750 | C24: =+L24 -> 7000 | D24: =+CEILING(Lifestyle!BH34*Shepparton!M24,5) -> 9640 | E24: =+CEILING(Lifestyle!BK34*Shepparton!N24,5) -> 5305 | F24: =SUM(B24:E24) -> 386695 | G24: =+CEILING(Lifestyle!BL34*Shepparton!O24,5) -> 5695 | I24: =+Lifestyle!BB34 -> 360743 | J24: =+J23 -> 0 | K24: =+Lifestyle!BD34 -> 4000 | L24: =+L23 -> 7000 | M24: =+M23 -> 103 | N24: =+N23 -> 60 | O24: =+O23 -> 85
A25: Ballina 30A | B25: =+CEILING(I25+J25+K25,10) -> 367040 | C25: =+L25 -> 7000 | D25: =+CEILING(Lifestyle!BH35*Shepparton!M25,5) -> 10765 | E25: =+CEILING(Lifestyle!BK35*Shepparton!N25,5) -> 5680 | F25: =SUM(B25:E25) -> 390485 | G25: =+CEILING(Lifestyle!BL35*Shepparton!O25,5) -> 5950 | I25: =+Lifestyle!BB35 -> 363040 | J25: =+J24 -> 0 | K25: =+Lifestyle!BD35 -> 4000 | L25: =+L24 -> 7000 | M25: =+M24 -> 103 | N25: =+N24 -> 60 | O25: =+O24 -> 85
A26: Ballina 33 | B26: =+CEILING(I26+J26+K26,10) -> 399090 | C26: =+L26 -> 7000 | D26: =+CEILING(Lifestyle!BH36*Shepparton!M26,5) -> 11835 | E26: =+CEILING(Lifestyle!BK36*Shepparton!N26,5) -> 5245 | F26: =SUM(B26:E26) -> 423170 | G26: =+CEILING(Lifestyle!BL36*Shepparton!O26,5) -> 6375 | I26: =+Lifestyle!BB36 -> 395086 | J26: =+J25 -> 0 | K26: =+Lifestyle!BD36 -> 4000 | L26: =+L25 -> 7000 | M26: =+M25 -> 103 | N26: =+N25 -> 60 | O26: =+O25 -> 85
A27: Ballina 39 | B27: =+CEILING(I27+J27+K27,10) -> 444180 | C27: =+L27 -> 7000 | D27: =+CEILING(Lifestyle!BH37*Shepparton!M27,5) -> 13260 | E27: =+CEILING(Lifestyle!BK37*Shepparton!N27,5) -> 7725 | F27: =SUM(B27:E27) -> 472165 | G27: =+CEILING(Lifestyle!BL37*Shepparton!O27,5) -> 6800 | I27: =+Lifestyle!BB37 -> 440177 | J27: =+J26 -> 0 | K27: =+Lifestyle!BD37 -> 4000 | L27: =+L26 -> 7000 | M27: =+M26 -> 103 | N27: =+N26 -> 60 | O27: =+O26 -> 85
A28: =+Lifestyle!A38 -> Bathurst 25 | B28: =+CEILING(I28+J28+K28,10) -> 347410 | C28: =+L28 -> 7000 | D28: =+CEILING(Lifestyle!BH38*Shepparton!M28,5) -> 7285 | E28: =+CEILING(Lifestyle!BK38*Shepparton!N28,5) -> 3960 | F28: =SUM(B28:E28) -> 365655 | G28: =+CEILING(Lifestyle!BL38*Shepparton!O28,5) -> 5185 | I28: =+Lifestyle!BB38 -> 343405 | J28: =+J27 -> 0 | K28: =+Lifestyle!BD38 -> 4000 | L28: =+L27 -> 7000 | M28: =+M27 -> 103 | N28: =+N27 -> 60 | O28: =+O27 -> 85
A29: =+Lifestyle!A39 -> Bathurst 30 | B29: =+CEILING(I29+J29+K29,10) -> 394390 | C29: =+L29 -> 7000 | D29: =+CEILING(Lifestyle!BH39*Shepparton!M29,5) -> 8780 | E29: =+CEILING(Lifestyle!BK39*Shepparton!N29,5) -> 5635 | F29: =SUM(B29:E29) -> 415805 | G29: =+CEILING(Lifestyle!BL39*Shepparton!O29,5) -> 5950 | I29: =+Lifestyle!BB39 -> 390384 | J29: =+J28 -> 0 | K29: =+Lifestyle!BD39 -> 4000 | L29: =+L28 -> 7000 | M29: =+M28 -> 103 | N29: =+N28 -> 60 | O29: =+O28 -> 85
A30: =+Lifestyle!A40 -> Bathurst 34 | B30: =+CEILING(I30+J30+K30,10) -> 415480 | C30: =+L30 -> 7000 | D30: =+CEILING(Lifestyle!BH40*Shepparton!M30,5) -> 9675 | E30: =+CEILING(Lifestyle!BK40*Shepparton!N30,5) -> 6350 | F30: =SUM(B30:E30) -> 438505 | G30: =+CEILING(Lifestyle!BL40*Shepparton!O30,5) -> 6290 | I30: =+Lifestyle!BB40 -> 411473 | J30: =+J29 -> 0 | K30: =+Lifestyle!BD40 -> 4000 | L30: =+L29 -> 7000 | M30: =+M29 -> 103 | N30: =+N29 -> 60 | O30: =+O29 -> 85
A31: Bayview 23 | B31: =+CEILING(I31+J31+K31,10) -> 316920 | C31: =+L31 -> 7000 | D31: =+CEILING(Lifestyle!BH41*Shepparton!M31,5) -> 8145 | E31: =+CEILING(Lifestyle!BK41*Shepparton!N31,5) -> 3005 | F31: =SUM(B31:E31) -> 335070 | G31: =+CEILING(Lifestyle!BL41*Shepparton!O31,5) -> 4760 | I31: =+Lifestyle!BB41 -> 313918 | J31: =+J30 -> 0 | K31: =+Lifestyle!BD41 -> 3000 | L31: =+L30 -> 7000 | M31: =+M30 -> 103 | N31: =+N30 -> 60 | O31: =+O30 -> 85
A32: Bayview 26 | B32: =+CEILING(I32+J32+K32,10) -> 339870 | C32: =+L32 -> 7000 | D32: =+CEILING(Lifestyle!BH42*Shepparton!M32,5) -> 7115 | E32: =+CEILING(Lifestyle!BK42*Shepparton!N32,5) -> 5060 | F32: =SUM(B32:E32) -> 359045 | G32: =+CEILING(Lifestyle!BL42*Shepparton!O32,5) -> 5270 | I32: =+Lifestyle!BB42 -> 335864 | J32: =+J31 -> 0 | K32: =+Lifestyle!BD42 -> 4000 | L32: =+L31 -> 7000 | M32: =+M31 -> 103 | N32: =+N31 -> 60 | O32: =+O31 -> 85
A33: Bayview 30 | B33: =+CEILING(I33+J33+K33,10) -> 375790 | C33: =+L33 -> 7000 | D33: =+CEILING(Lifestyle!BH43*Shepparton!M33,5) -> 8295 | E33: =+CEILING(Lifestyle!BK43*Shepparton!N33,5) -> 6975 | F33: =SUM(B33:E33) -> 398060 | G33: =+CEILING(Lifestyle!BL43*Shepparton!O33,5) -> 6120 | I33: =+Lifestyle!BB43 -> 371790 | J33: =+J32 -> 0 | K33: =+Lifestyle!BD43 -> 4000 | L33: =+L32 -> 7000 | M33: =+M32 -> 103 | N33: =+N32 -> 60 | O33: =+O32 -> 85
A34: Bondi 25 | B34: =+CEILING(I34+J34+K34,10) -> 330730 | C34: =+L34 -> 7000 | D34: =+CEILING(Lifestyle!BH44*Shepparton!M34,5) -> 9315 | E34: =+CEILING(Lifestyle!BK44*Shepparton!N34,5) -> 3765 | F34: =SUM(B34:E34) -> 350810 | G34: =+CEILING(Lifestyle!BL44*Shepparton!O34,5) -> 5355 | I34: =+Lifestyle!BB44 -> 326725 | J34: =+J33 -> 0 | K34: =+Lifestyle!BD44 -> 4000 | L34: =+L33 -> 7000 | M34: =+M33 -> 103 | N34: =+N33 -> 60 | O34: =+O33 -> 85
A35: Bondi 31 | B35: =+CEILING(I35+J35+K35,10) -> 369170 | C35: =+L35 -> 7000 | D35: =+CEILING(Lifestyle!BH45*Shepparton!M35,5) -> 10850 | E35: =+CEILING(Lifestyle!BK45*Shepparton!N35,5) -> 5070 | F35: =SUM(B35:E35) -> 392090 | G35: =+CEILING(Lifestyle!BL45*Shepparton!O35,5) -> 5780 | I35: =+Lifestyle!BB45 -> 365164 | J35: =+J34 -> 0 | K35: =+Lifestyle!BD45 -> 4000 | L35: =+L34 -> 7000 | M35: =+M34 -> 103 | N35: =+N34 -> 60 | O35: =+O34 -> 85
A36: Bondi 36 | B36: =+CEILING(I36+J36+K36,10) -> 399980 | C36: =+L36 -> 7000 | D36: =+CEILING(Lifestyle!BH46*Shepparton!M36,5) -> 12315 | E36: =+CEILING(Lifestyle!BK46*Shepparton!N36,5) -> 6445 | F36: =SUM(B36:E36) -> 425740 | G36: =+CEILING(Lifestyle!BL46*Shepparton!O36,5) -> 5865 | I36: =+Lifestyle!BB46 -> 395974 | J36: =+J35 -> 0 | K36: =+Lifestyle!BD46 -> 4000 | L36: =+L35 -> 7000 | M36: =+M35 -> 103 | N36: =+N35 -> 60 | O36: =+O35 -> 85
A37: Cambridge 22 | B37: =+CEILING(I37+J37+K37,10) -> 309750 | C37: =+L37 -> 7000 | D37: =+CEILING(Lifestyle!BH47*Shepparton!M37,5) -> 7965 | E37: =+CEILING(Lifestyle!BK47*Shepparton!N37,5) -> 3465 | F37: =SUM(B37:E37) -> 328180 | G37: =+CEILING(Lifestyle!BL47*Shepparton!O37,5) -> 4845 | I37: =+Lifestyle!BB47 -> 306745 | J37: =+J36 -> 0 | K37: =+Lifestyle!BD47 -> 3000 | L37: =+L36 -> 7000 | M37: =+M36 -> 103 | N37: =+N36 -> 60 | O37: =+O36 -> 85
A38: Cambridge 24 | B38: =+CEILING(I38+J38+K38,10) -> 329670 | C38: =+L38 -> 7000 | D38: =+CEILING(Lifestyle!BH48*Shepparton!M38,5) -> 7465 | E38: =+CEILING(Lifestyle!BK48*Shepparton!N38,5) -> 4845 | F38: =SUM(B38:E38) -> 348980 | G38: =+CEILING(Lifestyle!BL48*Shepparton!O38,5) -> 4845 | I38: =+Lifestyle!BB48 -> 326664 | J38: =+J37 -> 0 | K38: =+Lifestyle!BD48 -> 3000 | L38: =+L37 -> 7000 | M38: =+M37 -> 103 | N38: =+N37 -> 60 | O38: =+O37 -> 85
A39: Cambridge 26 | B39: =+CEILING(I39+J39+K39,10) -> 346130 | C39: =+L39 -> 7000 | D39: =+CEILING(Lifestyle!BH49*Shepparton!M39,5) -> 8805 | E39: =+CEILING(Lifestyle!BK49*Shepparton!N39,5) -> 5280 | F39: =SUM(B39:E39) -> 367215 | G39: =+CEILING(Lifestyle!BL49*Shepparton!O39,5) -> 5100 | I39: =+Lifestyle!BB49 -> 342124 | J39: =+J38 -> 0 | K39: =+Lifestyle!BD49 -> 4000 | L39: =+L38 -> 7000 | M39: =+M38 -> 103 | N39: =+N38 -> 60 | O39: =+O38 -> 85
A40: Cambridge 30 | B40: =+CEILING(I40+J40+K40,10) -> 376060 | C40: =+L40 -> 7000 | D40: =+CEILING(Lifestyle!BH50*Shepparton!M40,5) -> 8275 | E40: =+CEILING(Lifestyle!BK50*Shepparton!N40,5) -> 7495 | F40: =SUM(B40:E40) -> 398830 | G40: =+CEILING(Lifestyle!BL50*Shepparton!O40,5) -> 5525 | I40: =+Lifestyle!BB50 -> 372059 | J40: =+J39 -> 0 | K40: =+Lifestyle!BD50 -> 4000 | L40: =+L39 -> 7000 | M40: =+M39 -> 103 | N40: =+N39 -> 60 | O40: =+O39 -> 85
A42: BASE PRICE INCLUDES: | E42: BASE PRICE DOES NOT INCLUDE:
A43: *SEWER, STORMWATER AND POWER | E43: *SITE PIERING
A44: TO A 700m2 BLOCK | E44: *RAISED PORTICO
A45: *20m TEMP FENCING | E45: *TILES & CARPET
A46: *'MD' CLASS SLAB | E46: *EXTERNAL PAVING
E47: *EAVES
A48: SHEPPARTON
A49: =+A2 -> LIFESTYLE SINGLE STOREY PRICE LIST VALID UP TO AUG 2025
A50: HOUSE DESIGN | B50: BASE PRICE * | C50: 50sqm NATURAL CONCRETE | D50: LIFESTYLE FLOOR TILES | E50: LIFESTYLE CARPETS | F50: PACKAGE PRICE *50sqm NATURAL CONCRETE *CARPET *TILES | G50: PRICE TO ADD EAVES
A51: Duneed 22 | B51: =+CEILING(I51+J51+K51,10) -> 315050 | C51: =+L51 -> 7000 | D51: =+CEILING(Lifestyle!BH51*Shepparton!M51,5) -> 6705 | E51: =+CEILING(Lifestyle!BK51*Shepparton!N51,5) -> 3215 | F51: =SUM(B51:E51) -> 331970 | G51: =+CEILING(Lifestyle!BL51*Shepparton!O51,5) -> 5440 | I51: =+Lifestyle!BB51 -> 312042 | J51: =+J40 -> 0 | K51: =+Lifestyle!BD51 -> 3000 | L51: =+L40 -> 7000 | M51: =+M40 -> 103 | N51: =+N40 -> 60 | O51: =+O40 -> 85
A52: Duneed 23 | B52: =+CEILING(I52+J52+K52,10) -> 318110 | C52: =+L52 -> 7000 | D52: =+CEILING(Lifestyle!BH52*Shepparton!M52,5) -> 6610 | E52: =+CEILING(Lifestyle!BK52*Shepparton!N52,5) -> 3570 | F52: =SUM(B52:E52) -> 335290 | G52: =+CEILING(Lifestyle!BL52*Shepparton!O52,5) -> 5440 | I52: =+Lifestyle!BB52 -> 315108 | J52: =+J51 -> 0 | K52: =+Lifestyle!BD52 -> 3000 | L52: =+L51 -> 7000 | M52: =+M51 -> 103 | N52: =+N51 -> 60 | O52: =+O51 -> 85
A53: Duneed 24 | B53: =+CEILING(I53+J53+K53,10) -> 329230 | C53: =+L53 -> 7000 | D53: =+CEILING(Lifestyle!BH53*Shepparton!M53,5) -> 6905 | E53: =+CEILING(Lifestyle!BK53*Shepparton!N53,5) -> 4650 | F53: =SUM(B53:E53) -> 347785 | G53: =+CEILING(Lifestyle!BL53*Shepparton!O53,5) -> 5440 | I53: =+Lifestyle!BB53 -> 326222 | J53: =+J52 -> 0 | K53: =+Lifestyle!BD53 -> 3000 | L53: =+L52 -> 7000 | M53: =+M52 -> 103 | N53: =+N52 -> 60 | O53: =+O52 -> 85
A54: Duneed 25 | B54: =+CEILING(I54+J54+K54,10) -> 333250 | C54: =+L54 -> 7000 | D54: =+CEILING(Lifestyle!BH54*Shepparton!M54,5) -> 6835 | E54: =+CEILING(Lifestyle!BK54*Shepparton!N54,5) -> 5030 | F54: =SUM(B54:E54) -> 352115 | G54: =+CEILING(Lifestyle!BL54*Shepparton!O54,5) -> 5440 | I54: =+Lifestyle!BB54 -> 329246 | J54: =+J53 -> 0 | K54: =+Lifestyle!BD54 -> 4000 | L54: =+L53 -> 7000 | M54: =+M53 -> 103 | N54: =+N53 -> 60 | O54: =+O53 -> 85
A55: Duneed 30 | B55: =+CEILING(I55+J55+K55,10) -> 376750 | C55: =+L55 -> 7000 | D55: =+CEILING(Lifestyle!BH55*Shepparton!M55,5) -> 9030 | E55: =+CEILING(Lifestyle!BK55*Shepparton!N55,5) -> 5385 | F55: =SUM(B55:E55) -> 398165 | G55: =+CEILING(Lifestyle!BL55*Shepparton!O55,5) -> 5440 | I55: =+Lifestyle!BB55 -> 372749 | J55: =+J54 -> 0 | K55: =+Lifestyle!BD55 -> 4000 | L55: =+L54 -> 7000 | M55: =+M54 -> 103 | N55: =+N54 -> 60 | O55: =+O54 -> 85
A56: Eclipse 23 | B56: =+CEILING(I56+J56+K56,10) -> 327420 | C56: =+L56 -> 7000 | D56: =+CEILING(Lifestyle!BH56*Shepparton!M56,5) -> 6225 | E56: =+CEILING(Lifestyle!BK56*Shepparton!N56,5) -> 4555 | F56: =SUM(B56:E56) -> 345200 | G56: =+CEILING(Lifestyle!BL56*Shepparton!O56,5) -> 4675 | I56: =+Lifestyle!BB56 -> 323411 | J56: =+J55 -> 0 | K56: =+Lifestyle!BD56 -> 4000 | L56: =+L55 -> 7000 | M56: =+M55 -> 103 | N56: =+N55 -> 60 | O56: =+O55 -> 85
A57: Eclipse 26 | B57: =+CEILING(I57+J57+K57,10) -> 355880 | C57: =+L57 -> 7000 | D57: =+CEILING(Lifestyle!BH57*Shepparton!M57,5) -> 6815 | E57: =+CEILING(Lifestyle!BK57*Shepparton!N57,5) -> 5595 | F57: =SUM(B57:E57) -> 375290 | G57: =+CEILING(Lifestyle!BL57*Shepparton!O57,5) -> 5440 | I57: =+Lifestyle!BB57 -> 351878 | J57: =+J56 -> 0 | K57: =+Lifestyle!BD57 -> 4000 | L57: =+L56 -> 7000 | M57: =+M56 -> 103 | N57: =+N56 -> 60 | O57: =+O56 -> 85
A58: Eclipse 28 | B58: =+CEILING(I58+J58+K58,10) -> 371630 | C58: =+L58 -> 7000 | D58: =+CEILING(Lifestyle!BH58*Shepparton!M58,5) -> 7105 | E58: =+CEILING(Lifestyle!BK58*Shepparton!N58,5) -> 6350 | F58: =SUM(B58:E58) -> 392085 | G58: =+CEILING(Lifestyle!BL58*Shepparton!O58,5) -> 5950 | I58: =+Lifestyle!BB58 -> 367624 | J58: =+J57 -> 0 | K58: =+Lifestyle!BD58 -> 4000 | L58: =+L57 -> 7000 | M58: =+M57 -> 103 | N58: =+N57 -> 60 | O58: =+O57 -> 85
A59: Hamilton 24 | B59: =+CEILING(I59+J59+K59,10) -> 324640 | C59: =+L59 -> 7000 | D59: =+CEILING(Lifestyle!BH59*Shepparton!M59,5) -> 8450 | E59: =+CEILING(Lifestyle!BK59*Shepparton!N59,5) -> 3460 | F59: =SUM(B59:E59) -> 343550 | G59: =+CEILING(Lifestyle!BL59*Shepparton!O59,5) -> 4845 | I59: =+Lifestyle!BB59 -> 321632 | J59: =+J58 -> 0 | K59: =+Lifestyle!BD59 -> 3000 | L59: =+L58 -> 7000 | M59: =+M58 -> 103 | N59: =+N58 -> 60 | O59: =+O58 -> 85
A60: Hamilton 29 | B60: =+CEILING(I60+J60+K60,10) -> 365750 | C60: =+L60 -> 7000 | D60: =+CEILING(Lifestyle!BH60*Shepparton!M60,5) -> 9065 | E60: =+CEILING(Lifestyle!BK60*Shepparton!N60,5) -> 5080 | F60: =SUM(B60:E60) -> 386895 | G60: =+CEILING(Lifestyle!BL60*Shepparton!O60,5) -> 5270 | I60: =+Lifestyle!BB60 -> 361749 | J60: =+J59 -> 0 | K60: =+Lifestyle!BD60 -> 4000 | L60: =+L59 -> 7000 | M60: =+M59 -> 103 | N60: =+N59 -> 60 | O60: =+O59 -> 85
A61: Hamilton 34 | B61: =+CEILING(I61+J61+K61,10) -> 397490 | C61: =+L61 -> 7000 | D61: =+CEILING(Lifestyle!BH61*Shepparton!M61,5) -> 9455 | E61: =+CEILING(Lifestyle!BK61*Shepparton!N61,5) -> 6610 | F61: =SUM(B61:E61) -> 420555 | G61: =+CEILING(Lifestyle!BL61*Shepparton!O61,5) -> 6375 | I61: =+Lifestyle!BB61 -> 393489 | J61: =+J60 -> 0 | K61: =+Lifestyle!BD61 -> 4000 | L61: =+L60 -> 7000 | M61: =+M60 -> 103 | N61: =+N60 -> 60 | O61: =+O60 -> 85
A62: Launceston 21 | B62: =+CEILING(I62+J62+K62,10) -> 304080 | C62: =+L62 -> 7000 | D62: =+CEILING(Lifestyle!BH62*Shepparton!M62,5) -> 6515 | E62: =+CEILING(Lifestyle!BK62*Shepparton!N62,5) -> 3700 | F62: =SUM(B62:E62) -> 321295 | G62: =+CEILING(Lifestyle!BL62*Shepparton!O62,5) -> 4930 | I62: =+Lifestyle!BB62 -> 301071 | J62: =+J61 -> 0 | K62: =+Lifestyle!BD62 -> 3000 | L62: =+L61 -> 7000 | M62: =+M61 -> 103 | N62: =+N61 -> 60 | O62: =+O61 -> 85
A63: Launceston 22 | B63: =+CEILING(I63+J63+K63,10) -> 314910 | C63: =+L63 -> 7000 | D63: =+CEILING(Lifestyle!BH63*Shepparton!M63,5) -> 6460 | E63: =+CEILING(Lifestyle!BK63*Shepparton!N63,5) -> 3770 | F63: =SUM(B63:E63) -> 332140 | G63: =+CEILING(Lifestyle!BL63*Shepparton!O63,5) -> 5100 | I63: =+Lifestyle!BB63 -> 311906 | J63: =+J62 -> 0 | K63: =+Lifestyle!BD63 -> 3000 | L63: =+L62 -> 7000 | M63: =+M62 -> 103 | N63: =+N62 -> 60 | O63: =+O62 -> 85
... A82: Santa Barbara 25 | B82: =+CEILING(I82+J82+K82,10) -> 323980 | C82: =+L82 -> 7000 | D82: =+CEILING(Lifestyle!BH82*Shepparton!M82,5) -> 7420 | E82: =+CEILING(Lifestyle!BK82*Shepparton!N82,5) -> 5000 | F82: =SUM(B82:E82) -> 343400 | G82: =+CEILING(Lifestyle!BL82*Shepparton!O82,5) -> 4930 | I82: =+Lifestyle!BB82 -> 319977 | J82: =+J81 -> 0 | K82: =+Lifestyle!BD82 -> 4000 | L82: =+L81 -> 7000 | M82: =+M81 -> 103 | N82: =+N81 -> 60 | O82: =+O81 -> 85
A83: Santa Barbara 26 | B83: =+CEILING(I83+J83+K83,10) -> 340030 | C83: =+L83 -> 7000 | D83: =+CEILING(Lifestyle!BH83*Shepparton!M83,5) -> 7610 | E83: =+CEILING(Lifestyle!BK83*Shepparton!N83,5) -> 4700 | F83: =SUM(B83:E83) -> 359340 | G83: =+CEILING(Lifestyle!BL83*Shepparton!O83,5) -> 5270 | I83: =+Lifestyle!BB83 -> 336030 | J83: =+J81 -> 0 | K83: =+Lifestyle!BD83 -> 4000 | L83: =+L81 -> 7000 | M83: =+M81 -> 103 | N83: =+N81 -> 60 | O83: =+O81 -> 85
A85: BASE PRICE INCLUDES: | E85: BASE PRICE DOES NOT INCLUDE:
A86: *SEWER, STORMWATER AND POWER | E86: *SITE PIERING
A87: TO A 700m2 BLOCK | E87: *RAISED PORTICO
A88: *20m TEMP FENCING | E88: *TILES
A89: *'MD' CLASS SLAB | E89: *CARPET
E90: *EXTERNAL PAVING
E91: *EAVES
A92: SHEPPARTON
A93: LIFESTYLE HOMESTEAD PRICE LIST VALID UP TO AUG 2025
A94: HOUSE DESIGN | B94: BASE PRICE * | C94: 50sqm NATURAL CONCRETE | D94: LIFESTYLE FLOOR TILES | E94: LIFESTYLE CARPETS | F94: PACKAGE PRICE *50sqm NATURAL CONCRETE *CARPET *TILES | G94: PRICE TO ADD EAVES | I94: List price | J94: Promotional | L94: 50sqm natural concrete | M94: Tiles per sqm | N94: Carpet per sqm | O94: Eaves per lm
A95: Inglewood 24 | B95: =+CEILING(I95+J95+K95,10) -> 324260 | C95: =+L95 -> 7000 | D95: =CEILING(Lifestyle!BH86*Shepparton!M95,5) -> 6940 | E95: =CEILING(Lifestyle!BK86*Shepparton!N95,5) -> 4270 | F95: =SUM(B95:E95) -> 342470 | G95: =CEILING(Lifestyle!BL86*Shepparton!O95,5) -> 5015 | I95: =+Lifestyle!BB86 -> 321256 | J95: =+J81 -> 0 | K95: =+Lifestyle!BD86 -> 3000 | L95: =+L81 -> 7000 | M95: =+M81 -> 103 | N95: =+N81 -> 60 | O95: =+O81 -> 85
A96: Inglewood 26 | B96: =+CEILING(I96+J96+K96,10) -> 349320 | C96: =+L96 -> 7000 | D96: =CEILING(Lifestyle!BH87*Shepparton!M96,5) -> 7615 | E96: =CEILING(Lifestyle!BK87*Shepparton!N96,5) -> 4880 | F96: =SUM(B96:E96) -> 368815 | G96: =CEILING(Lifestyle!BL87*Shepparton!O96,5) -> 5780 | I96: =+Lifestyle!BB87 -> 345313 | J96: =+J95 -> 0 | K96: =+Lifestyle!BD87 -> 4000 | L96: =+L95 -> 7000 | M96: =+M95 -> 103 | N96: =+N95 -> 60 | O96: =+O95 -> 85
A97: Inglewood 29 | B97: =+CEILING(I97+J97+K97,10) -> 368950 | C97: =+L97 -> 7000 | D97: =CEILING(Lifestyle!BH88*Shepparton!M97,5) -> 8615 | E97: =CEILING(Lifestyle!BK88*Shepparton!N97,5) -> 5340 | F97: =SUM(B97:E97) -> 389905 | G97: =CEILING(Lifestyle!BL88*Shepparton!O97,5) -> 5865 | I97: =+Lifestyle!BB88 -> 364949 | J97: =+J96 -> 0 | K97: =+Lifestyle!BD88 -> 4000 | L97: =+L96 -> 7000 | M97: =+M96 -> 103 | N97: =+N96 -> 60 | O97: =+O83 -> 85
A98: Inglewood 31 | B98: =+CEILING(I98+J98+K98,10) -> 387200 | C98: =+L98 -> 7000 | D98: =CEILING(Lifestyle!BH89*Shepparton!M98,5) -> 8515 | E98: =CEILING(Lifestyle!BK89*Shepparton!N98,5) -> 6025 | F98: =SUM(B98:E98) -> 408740 | G98: =CEILING(Lifestyle!BL89*Shepparton!O98,5) -> 6460 | I98: =+Lifestyle!BB89 -> 383191 | J98: =+J97 -> 0 | K98: =+Lifestyle!BD89 -> 4000 | L98: =+L97 -> 7000 | M98: =+M97 -> 103 | N98: =+N97 -> 60 | O98: =+O97 -> 85
A99: Inglewood 34 | B99: =+CEILING(I99+J99+K99,10) -> 406410 | C99: =+L99 -> 7000 | D99: =CEILING(Lifestyle!BH90*Shepparton!M99,5) -> 9045 | E99: =CEILING(Lifestyle!BK90*Shepparton!N99,5) -> 7265 | F99: =SUM(B99:E99) -> 429720 | G99: =CEILING(Lifestyle!BL90*Shepparton!O99,5) -> 7055 | I99: =+Lifestyle!BB90 -> 402402 | J99: =+J98 -> 0 | K99: =+Lifestyle!BD90 -> 4000 | L99: =+L98 -> 7000 | M99: =+M98 -> 103 | N99: =+N98 -> 60 | O99: =+O98 -> 85
A100: Inglewood 35 | B100: =+CEILING(I100+J100+K100,10) -> 425550 | C100: =+L100 -> 7000 | D100: =CEILING(Lifestyle!BH91*Shepparton!M100,5) -> 9030 | E100: =CEILING(Lifestyle!BK91*Shepparton!N100,5) -> 7055 | F100: =SUM(B100:E100) -> 448635 | G100: =CEILING(Lifestyle!BL91*Shepparton!O100,5) -> 7055 | I100: =+Lifestyle!BB91 -> 421545 | J100: =+J99 -> 0 | K100: =+Lifestyle!BD91 -> 4000 | L100: =+L99 -> 7000 | M100: =+M99 -> 103 | N100: =+N99 -> 60 | O100: =+O99 -> 85
A101: Inglewood 38 | B101: =+CEILING(I101+J101+K101,10) -> 443180 | C101: =+L101 -> 7000 | D101: =CEILING(Lifestyle!BH92*Shepparton!M101,5) -> 9185 | E101: =CEILING(Lifestyle!BK92*Shepparton!N101,5) -> 7570 | F101: =SUM(B101:E101) -> 466935 | G101: =CEILING(Lifestyle!BL92*Shepparton!O101,5) -> 7055 | I101: =+Lifestyle!BB92 -> 439175 | J101: =+J100 -> 0 | K101: =+Lifestyle!BD92 -> 4000 | L101: =+L100 -> 7000 | M101: =+M100 -> 103 | N101: =+N100 -> 60 | O101: =+O99 -> 85
A102: Maldon 23 | B102: =+CEILING(I102+J102+K102,10) -> 313120 | C102: =+L102 -> 7000 | D102: =CEILING(Lifestyle!BH93*Shepparton!M102,5) -> 7165 | E102: =CEILING(Lifestyle!BK93*Shepparton!N102,5) -> 3960 | F102: =SUM(B102:E102) -> 331245 | G102: =CEILING(Lifestyle!BL93*Shepparton!O102,5) -> 4505 | I102: =+Lifestyle!BB93 -> 310120 | J102: =+J101 -> 0 | K102: =+Lifestyle!BD93 -> 3000 | L102: =+L101 -> 7000 | M102: =+M101 -> 103 | N102: =+N101 -> 60 | O102: =+O100 -> 85
A103: Maldon 27 | B103: =+CEILING(I103+J103+K103,10) -> 352270 | C103: =+L103 -> 7000 | D103: =CEILING(Lifestyle!BH94*Shepparton!M103,5) -> 8585 | E103: =CEILING(Lifestyle!BK94*Shepparton!N103,5) -> 4615 | F103: =SUM(B103:E103) -> 372470 | G103: =CEILING(Lifestyle!BL94*Shepparton!O103,5) -> 4590 | I103: =+Lifestyle!BB94 -> 348261 | J103: =+J102 -> 0 | K103: =+Lifestyle!BD94 -> 4000 | L103: =+L102 -> 7000 | M103: =+M102 -> 103 | N103: =+N102 -> 60 | O103: =+O101 -> 85
A104: Maldon 33 | B104: =+CEILING(I104+J104+K104,10) -> 413150 | C104: =+L104 -> 7000 | D104: =CEILING(Lifestyle!BH95*Shepparton!M104,5) -> 10300 | E104: =CEILING(Lifestyle!BK95*Shepparton!N104,5) -> 5940 | F104: =SUM(B104:E104) -> 436390 | G104: =CEILING(Lifestyle!BL95*Shepparton!O104,5) -> 6460 | I104: =+Lifestyle!BB95 -> 409141 | J104: =+J103 -> 0 | K104: =+Lifestyle!BD95 -> 4000 | L104: =+L103 -> 7000 | M104: =+M103 -> 103 | N104: =+N103 -> 60 | O104: =+O102 -> 85
A105: Palmerston 28 | B105: =+CEILING(I105+J105+K105,10) -> 359920 | C105: =+L105 -> 7000 | D105: =CEILING(Lifestyle!BH96*Shepparton!M105,5) -> 7965 | E105: =CEILING(Lifestyle!BK96*Shepparton!N105,5) -> 5120 | F105: =SUM(B105:E105) -> 380005 | G105: =CEILING(Lifestyle!BL96*Shepparton!O105,5) -> 5440 | I105: =+Lifestyle!BB96 -> 355920 | J105: =+J104 -> 0 | K105: =+Lifestyle!BD96 -> 4000 | L105: =+L104 -> 7000 | M105: =+M104 -> 103 | N105: =+N104 -> 60 | O105: =+O103 -> 85
A106: Palmerston 35 | B106: =+CEILING(I106+J106+K106,10) -> 412420 | C106: =+L106 -> 7000 | D106: =CEILING(Lifestyle!BH97*Shepparton!M106,5) -> 9655 | E106: =CEILING(Lifestyle!BK97*Shepparton!N106,5) -> 7630 | F106: =SUM(B106:E106) -> 436705 | G106: =CEILING(Lifestyle!BL97*Shepparton!O106,5) -> 6205 | I106: =+Lifestyle!BB97 -> 408414 | J106: =+J105 -> 0 | K106: =+Lifestyle!BD97 -> 4000 | L106: =+L105 -> 7000 | M106: =+M105 -> 103 | N106: =+N105 -> 60 | O106: =+O105 -> 85
A107: Sandown 23 | B107: =+CEILING(I107+J107+K107,10) -> 321050 | C107: =+L107 -> 7000 | D107: =CEILING(Lifestyle!BH98*Shepparton!M107,5) -> 7335 | E107: =CEILING(Lifestyle!BK98*Shepparton!N107,5) -> 3760 | F107: =SUM(B107:E107) -> 339145 | G107: =CEILING(Lifestyle!BL98*Shepparton!O107,5) -> 5355 | I107: =+Lifestyle!BB98 -> 318048 | J107: =+J106 -> 0 | K107: =+Lifestyle!BD98 -> 3000 | L107: =+L106 -> 7000 | M107: =+M106 -> 103 | N107: =+N106 -> 60 | O107: =+O106 -> 85
A108: Sandown 26 | B108: =+CEILING(I108+J108+K108,10) -> 353720 | C108: =+L108 -> 7000 | D108: =CEILING(Lifestyle!BH99*Shepparton!M108,5) -> 8025 | E108: =CEILING(Lifestyle!BK99*Shepparton!N108,5) -> 4720 | F108: =SUM(B108:E108) -> 373465 | G108: =CEILING(Lifestyle!BL99*Shepparton!O108,5) -> 4845 | I108: =+Lifestyle!BB99 -> 349713 | J108: =+J107 -> 0 | K108: =+Lifestyle!BD99 -> 4000 | L108: =+L107 -> 7000 | M108: =+M107 -> 103 | N108: =+N107 -> 60 | O108: =+O107 -> 85
A109: Sandown 28 (30) | B109: =+CEILING(I109+J109+K109,10) -> 376710 | C109: =+L109 -> 7000 | D109: =CEILING(Lifestyle!BH100*Shepparton!M109,5) -> 9030 | E109: =CEILING(Lifestyle!BK100*Shepparton!N109,5) -> 6215 | F109: =SUM(B109:E109) -> 398955 | G109: =CEILING(Lifestyle!BL100*Shepparton!O109,5) -> 5525 | I109: =+Lifestyle!BB100 -> 372707 | J109: =+J108 -> 0 | K109: =+Lifestyle!BD100 -> 4000 | L109: =+L108 -> 7000 | M109: =+M108 -> 103 | N109: =+N108 -> 60 | O109: =+O108 -> 85
A110: Sandown 32 | B110: =+CEILING(I110+J110+K110,10) -> 387250 | C110: =+L110 -> 7000 | D110: =CEILING(Lifestyle!BH101*Shepparton!M110,5) -> 8615 | E110: =CEILING(Lifestyle!BK101*Shepparton!N110,5) -> 6140 | F110: =SUM(B110:E110) -> 409005 | G110: =CEILING(Lifestyle!BL101*Shepparton!O110,5) -> 5185 | I110: =+Lifestyle!BB101 -> 383246 | J110: =+J109 -> 0 | K110: =+Lifestyle!BD101 -> 4000 | L110: =+L109 -> 7000 | M110: =+M109 -> 103 | N110: =+N109 -> 60 | O110: =+O109 -> 85
A111: Sandown 34 MG | B111: =+CEILING(I111+J111+K111,10) -> 422020 | C111: =+L111 -> 7000 | D111: =CEILING(Lifestyle!BH102*Shepparton!M111,5) -> 9555 | E111: =CEILING(Lifestyle!BK102*Shepparton!N111,5) -> 5615 | F111: =SUM(B111:E111) -> 444190 | G111: =CEILING(Lifestyle!BL102*Shepparton!O111,5) -> 6800 | I111: =+Lifestyle!BB102 -> 418020 | J111: =+J110 -> 0 | K111: =+Lifestyle!BD102 -> 4000 | L111: =+L110 -> 7000 | M111: =+M110 -> 103 | N111: =+N110 -> 60 | O111: =+O110 -> 85
A112: Sandown 40 MG | B112: =+CEILING(I112+J112+K112,10) -> 476610 | C112: =+L112 -> 7000 | D112: =CEILING(Lifestyle!BH103*Shepparton!M112,5) -> 8710 | E112: =CEILING(Lifestyle!BK103*Shepparton!N112,5) -> 8980 | F112: =SUM(B112:E112) -> 501300 | G112: =CEILING(Lifestyle!BL103*Shepparton!O112,5) -> 7310 | I112: =+Lifestyle!BB103 -> 472601 | J112: =+J111 -> 0 | K112: =+Lifestyle!BD103 -> 4000 | L112: =+L111 -> 7000 | M112: =+M111 -> 103 | N112: =+N111 -> 60 | O112: =+O111 -> 85
A113: Sandown 41 MG | B113: =+CEILING(I113+J113+K113,10) -> 474800 | C113: =+L113 -> 7000 | D113: =CEILING(Lifestyle!BH104*Shepparton!M113,5) -> 9830 | E113: =CEILING(Lifestyle!BK104*Shepparton!N113,5) -> 8155 | F113: =SUM(B113:E113) -> 499785 | G113: =CEILING(Lifestyle!BL104*Shepparton!O113,5) -> 7225 | I113: =+Lifestyle!BB104 -> 470792 | J113: =+J112 -> 0 | K113: =+Lifestyle!BD104 -> 4000 | L113: =+L112 -> 7000 | M113: =+M112 -> 103 | N113: =+N112 -> 60 | O113: =+O112 -> 85
A114: Winton 24 | B114: =+CEILING(I114+J114+K114,10) -> 327570 | C114: =+L114 -> 7000 | D114: =CEILING(Lifestyle!BH105*Shepparton!M114,5) -> 7785 | E114: =CEILING(Lifestyle!BK105*Shepparton!N114,5) -> 3690 | F114: =SUM(B114:E114) -> 346045 | G114: =CEILING(Lifestyle!BL105*Shepparton!O114,5) -> 5440 | I114: =+Lifestyle!BB105 -> 324567 | J114: =+J113 -> 0 | K114: =+Lifestyle!BD105 -> 3000 | L114: =+L113 -> 7000 | M114: =+M113 -> 103 | N114: =+N113 -> 60 | O114: =+O113 -> 85
A115: Winton 28 | B115: =+CEILING(I115+J115+K115,10) -> 364140 | C115: =+L115 -> 7000 | D115: =CEILING(Lifestyle!BH106*Shepparton!M115,5) -> 8685 | E115: =CEILING(Lifestyle!BK106*Shepparton!N115,5) -> 5230 | F115: =SUM(B115:E115) -> 385055 | G115: =CEILING(Lifestyle!BL106*Shepparton!O115,5) -> 5780 | I115: =+Lifestyle!BB106 -> 360137 | J115: =+J114 -> 0 | K115: =+Lifestyle!BD106 -> 4000 | L115: =+L114 -> 7000 | M115: =+M114 -> 103 | N115: =+N114 -> 60 | O115: =+O114 -> 85
A116: Winton 32 | B116: =+CEILING(I116+J116+K116,10) -> 407450 | C116: =+L116 -> 7000 | D116: =CEILING(Lifestyle!BH107*Shepparton!M116,5) -> 10365 | E116: =CEILING(Lifestyle!BK107*Shepparton!N116,5) -> 6480 | F116: =SUM(B116:E116) -> 431295 | G116: =CEILING(Lifestyle!BL107*Shepparton!O116,5) -> 6375 | I116: =+Lifestyle!BB107 -> 403446 | J116: =+J115 -> 0 | K116: =+Lifestyle!BD107 -> 4000 | L116: =+L115 -> 7000 | M116: =+M115 -> 103 | N116: =+N115 -> 60 | O116: =+O115 -> 85
A118: BASE PRICE INCLUDES: | E118: BASE PRICE DOES NOT INCLUDE:
A119: *SEWER, STORMWATER AND POWER | E119: *SITE PIERING
A120: TO A 700m2 BLOCK | E120: *RAISED PORTICO
A121: *20m TEMP FENCING | E121: *TILES
...

Sheet Investor
A1: INVESTOR PRICE LIST VALID UP TO AUGUST 2025
A2: HOUSE DESIGN | B2: BASE PRICE * | C2: 60sqm NATURAL CONCRETE | D2: ASPIRE FLOOR TILES | E2: ASPIRE CARPET | F2: ROLLER BLINDS TO ALL WINDOWS AND SLIDING DOORS | G2: TV ANTENNA | H2: SPLIT SYSTEM TO FAMILY ROOM | I2: WALL MOUNTED CLOTHESLINE | J2: COLORBOND LETTER BOX | K2: PACKAGE PRICE | O2: 60sqm natural concrete | P2: Aspire Tiles per sqm | Q2: Aspire Carpet per sqm
A3: Kiewa 15 | B3: =+CEILING(N3+M3,10) -> 242360 | C3: =+O3 -> 8400 | D3: =+CEILING(Lifestyle!BH139*Investor!P3,5) -> 3015 | E3: =+CEILING(Lifestyle!BK139*Investor!Q3,5) -> 2670 | F3: =9*195 -> 1755 | G3: =+Electrical!D17 -> 590 | H3: INCLUDED | I3: =+'Yard Items'!D33 -> 400 | J3: =+'Yard Items'!D29 -> 150 | K3: =SUM(B3:J3) -> 259340 | M3: 6000 | N3: =+Lifestyle!BB139 -> 236357 | O3: =60*140 -> 8400 | P3: 95 | Q3: 56
A4: Kiewa 17 | B4: =+CEILING(N4+M4,10) -> 260930 | C4: =+O4 -> 8400 | D4: =+CEILING(Lifestyle!BH140*Investor!P4,5) -> 3215 | E4: =+CEILING(Lifestyle!BK140*Investor!Q4,5) -> 3375 | F4: =10*195 -> 1950 | G4: =+G3 -> 590 | H4: INCLUDED | I4: =+I3 -> 400 | J4: =+J3 -> 150 | K4: =SUM(B4:J4) -> 279010 | M4: =+M3 -> 6000 | N4: =+Lifestyle!BB140 -> 254927 | O4: =+O3 -> 8400 | P4: =+P3 -> 95 | Q4: =+Q3 -> 56
A5: Kiewa 18 | B5: =+CEILING(N5+M5,10) -> 279100 | C5: =+O5 -> 8400 | D5: =+CEILING(Lifestyle!BH141*Investor!P5,5) -> 3935 | E5: =+CEILING(Lifestyle!BK141*Investor!Q5,5) -> 4255 | F5: =11*195 -> 2145 | G5: =+G4 -> 590 | H5: INCLUDED | I5: =+I4 -> 400 | J5: =+J4 -> 150 | K5: =SUM(B5:J5) -> 298975 | M5: =+M4 -> 6000 | N5: =+Lifestyle!BB141 -> 273100 | O5: =+O4 -> 8400 | P5: =+P4 -> 95 | Q5: =+Q4 -> 56
A6: Kiewa 21 | B6: =+CEILING(N6+M6,10) -> 288830 | C6: =+O6 -> 8400 | D6: =+CEILING(Lifestyle!BH142*Investor!P6,5) -> 4160 | E6: =+CEILING(Lifestyle!BK142*Investor!Q6,5) -> 4590 | F6: =12*195 -> 2340 | G6: =+G5 -> 590 | H6: 4150 | I6: =+I5 -> 400 | J6: =+J5 -> 150 | K6: =SUM(B6:J6) -> 313610 | M6: =+M5 -> 6000 | N6: =+Lifestyle!BB142 -> 282822 | O6: =+O5 -> 8400 | P6: =+P5 -> 95 | Q6: =+Q5 -> 56
A7: Prices based on a Standard Façade
A9: ## THESE RATES APPLY ONLY FOR INVESTORS, NOT OWNER-OCCUPIERS ##
A10: ## FOR OWNER-OCCUPIERS PLEASE USE THE MAIN PRICE LIST ##
A12: LANDSCAPING PRICES
A13: Size | C13: Seed | D13: Turf
A14: =+Landscaping!B14 -> 600m2 normal block | C14: =+Landscaping!C14 -> 24535 | D14: =+Landscaping!D14 -> 27985 | F14: Includes automated sprinkler sytem
A15: =+Landscaping!B15 -> 600m2 corner block | C15: =+Landscaping!C15 -> 27135 | D15: =+Landscaping!D15 -> 30585 | F15: Credit $600 to go down to a manual system
A16: =+Landscaping!B16 -> 800m2 normal block | C16: =+Landscaping!C16 -> 29385 | D16: =+Landscaping!D16 -> 34110
A17: =+Landscaping!B17 -> 800m2 corner block | C17: =+Landscaping!C17 -> 32010 | D17: =+Landscaping!D17 -> 36735

Sheet Echuca
A1: ECHUCA
A2: LIFESTYLE SINGLE STOREY PRICE LIST VALID UP TO AUG 2025
A3: HOUSE DESIGN | B3: BASE PRICE * | C3: 50sqm NATURAL CONCRETE | D3: LIFESTYLE FLOOR TILES | E3: LIFESTYLE CARPETS | F3: PACKAGE PRICE *50sqm NATURAL CONCRETE *CARPET *TILES | G3: PRICE TO ADD EAVES | I3: List price | J3: Promotional | K3: Bonus | L3: 50sqm natural concrete | M3: Tiles per sqm | N3: Carpet per sqm | O3: Eaves per lm
A4: Adelaide 18 | B4: =+CEILING(I4+J4+K4,10) -> 295550 | C4: =+L4 -> 7000 | D4: =+Shepparton!D4 -> 5010 | E4: =+Shepparton!E4 -> 2785 | F4: =SUM(B4:E4) -> 310345 | G4: =+Shepparton!G4 -> 4420 | I4: =+Lifestyle!BC14 -> 292541 | J4: =+Lifestyle!BB7 -> 0 | K4: =+Lifestyle!BD14 -> 3000 | L4: =50*'2.TRAVEL'!H13 -> 7000 | M4: 103 | N4: 60 | O4: 65
A5: Adelaide 21 | B5: =+CEILING(I5+J5+K5,10) -> 309980 | C5: =+L5 -> 7000 | D5: =+Shepparton!D5 -> 5140 | E5: =+Shepparton!E5 -> 4100 | F5: =SUM(B5:E5) -> 326220 | G5: =+Shepparton!G5 -> 4845 | I5: =+Lifestyle!BC15 -> 306971 | J5: =+J4 -> 0 | K5: =+Lifestyle!BD15 -> 3000 | L5: =+L4 -> 7000 | M5: =+M4 -> 103 | N5: =+N4 -> 60 | O5: =+O4 -> 65
A6: Adelaide 22A | B6: =+CEILING(I6+J6+K6,10) -> 324000 | C6: =+L6 -> 7000 | D6: =+Shepparton!D6 -> 5935 | E6: =+Shepparton!E6 -> 4085 | F6: =SUM(B6:E6) -> 341020 | G6: =+Shepparton!G6 -> 5100 | I6: =+Lifestyle!BC16 -> 320996 | J6: =+J5 -> 0 | K6: =+Lifestyle!BD16 -> 3000 | L6: =+L5 -> 7000 | M6: =+M5 -> 103 | N6: =+N5 -> 60 | O6: =+O5 -> 65
A7: Adelaide 22B | B7: =+CEILING(I7+J7+K7,10) -> 325640 | C7: =+L7 -> 7000 | D7: =+Shepparton!D7 -> 5885 | E7: =+Shepparton!E7 -> 3985 | F7: =SUM(B7:E7) -> 342510 | G7: =+Shepparton!G7 -> 5100 | I7: =+Lifestyle!BC17 -> 322640 | J7: =+J6 -> 0 | K7: =+Lifestyle!BD17 -> 3000 | L7: =+L6 -> 7000 | M7: =+M6 -> 103 | N7: =+N6 -> 60 | O7: =+O6 -> 65
A8: Adelaide 24 | B8: =+CEILING(I8+J8+K8,10) -> 333230 | C8: =+L8 -> 7000 | D8: =+Shepparton!D8 -> 6420 | E8: =+Shepparton!E8 -> 4990 | F8: =SUM(B8:E8) -> 351640 | G8: =+Shepparton!G8 -> 5270 | I8: =+Lifestyle!BC18 -> 330230 | J8: =+J7 -> 0 | K8: =+Lifestyle!BD18 -> 3000 | L8: =+L7 -> 7000 | M8: =+M7 -> 103 | N8: =+N7 -> 60 | O8: =+O7 -> 65
A9: Ashfield 24 | B9: =+CEILING(I9+J9+K9,10) -> 335580 | C9: =+L9 -> 7000 | D9: =+Shepparton!D9 -> 8670 | E9: =+Shepparton!E9 -> 3475 | F9: =SUM(B9:E9) -> 354725 | G9: =+Shepparton!G9 -> 4930 | I9: =+Lifestyle!BC19 -> 332578 | J9: =+J8 -> 0 | K9: =+Lifestyle!BD19 -> 3000 | L9: =+L8 -> 7000 | M9: =+M8 -> 103 | N9: =+N8 -> 60 | O9: =+O8 -> 65
A10: Ashfield 30 | B10: =+CEILING(I10+J10+K10,10) -> 372840 | C10: =+L10 -> 7000 | D10: =+Shepparton!D10 -> 7940 | E10: =+Shepparton!E10 -> 5610 | F10: =SUM(B10:E10) -> 393390 | G10: =+Shepparton!G10 -> 5100 | I10: =+Lifestyle!BC20 -> 368840 | J10: =+J9 -> 0 | K10: =+Lifestyle!BD20 -> 4000 | L10: =+L9 -> 7000 | M10: =+M9 -> 103 | N10: =+N9 -> 60 | O10: =+O9 -> 65
A11: Ashfield 34 | B11: =+CEILING(I11+J11+K11,10) -> 399470 | C11: =+L11 -> 7000 | D11: =+Shepparton!D11 -> 8440 | E11: =+Shepparton!E11 -> 6700 | F11: =SUM(B11:E11) -> 421610 | G11: =+Shepparton!G11 -> 6290 | I11: =+Lifestyle!BC21 -> 395470 | J11: =+J10 -> 0 | K11: =+Lifestyle!BD21 -> 4000 | L11: =+L10 -> 7000 | M11: =+M10 -> 103 | N11: =+N10 -> 60 | O11: =+O10 -> 65
A12: Ashley 19 | B12: =+CEILING(I12+J12+K12,10) -> 293860 | C12: =+L12 -> 7000 | D12: =+Shepparton!D12 -> 5805 | E12: =+Shepparton!E12 -> 2805 | F12: =SUM(B12:E12) -> 309470 | G12: =+Shepparton!G12 -> 4335 | I12: =+Lifestyle!BC22 -> 290856 | J12: =+J11 -> 0 | K12: =+Lifestyle!BD22 -> 3000 | L12: =+L11 -> 7000 | M12: =+M11 -> 103 | N12: =+N11 -> 60 | O12: =+O11 -> 65
A13: Ashley 21 | B13: =+CEILING(I13+J13+K13,10) -> 312930 | C13: =+L13 -> 7000 | D13: =+Shepparton!D13 -> 6975 | E13: =+Shepparton!E13 -> 3735 | F13: =SUM(B13:E13) -> 330640 | G13: =+Shepparton!G13 -> 5015 | I13: =+Lifestyle!BC23 -> 309921 | J13: =+J12 -> 0 | K13: =+Lifestyle!BD23 -> 3000 | L13: =+L12 -> 7000 | M13: =+M12 -> 103 | N13: =+N12 -> 60 | O13: =+O12 -> 65
A14: Ashley 22 | B14: =+CEILING(I14+J14+K14,10) -> 310550 | C14: =+L14 -> 7000 | D14: =+Shepparton!D14 -> 6855 | E14: =+Shepparton!E14 -> 3875 | F14: =SUM(B14:E14) -> 328280 | G14: =+Shepparton!G14 -> 4760 | I14: =+Lifestyle!BC24 -> 307545 | J14: =+J12 -> 0 | K14: =+Lifestyle!BD24 -> 3000 | L14: =+L12 -> 7000 | M14: =+M12 -> 103 | N14: =+N12 -> 60 | O14: =+O12 -> 65
A15: Ashley 22A | B15: =+CEILING(I15+J15+K15,10) -> 316920 | C15: =+L15 -> 7000 | D15: =+Shepparton!D15 -> 7470 | E15: =+Shepparton!E15 -> 3615 | F15: =SUM(B15:E15) -> 335005 | G15: =+Shepparton!G15 -> 4760 | I15: =+Lifestyle!BC25 -> 313916 | J15: =+J13 -> 0 | K15: =+Lifestyle!BD25 -> 3000 | L15: =+L13 -> 7000 | M15: =+M13 -> 103 | N15: =+N13 -> 60 | O15: =+O13 -> 65
A16: Ashley 24 | B16: =+CEILING(I16+J16+K16,10) -> 328570 | C16: =+L16 -> 7000 | D16: =+Shepparton!D16 -> 6505 | E16: =+Shepparton!E16 -> 4665 | F16: =SUM(B16:E16) -> 346740 | G16: =+Shepparton!G16 -> 5015 | I16: =+Lifestyle!BC26 -> 325561 | J16: =+J14 -> 0 | K16: =+Lifestyle!BD26 -> 3000 | L16: =+L14 -> 7000 | M16: =+M14 -> 103 | N16: =+N14 -> 60 | O16: =+O14 -> 65
A17: Ashley 25 | B17: =+CEILING(I17+J17+K17,10) -> 337410 | C17: =+L17 -> 7000 | D17: =+Shepparton!D17 -> 6950 | E17: =+Shepparton!E17 -> 4610 | F17: =SUM(B17:E17) -> 355970 | G17: =+Shepparton!G17 -> 5440 | I17: =+Lifestyle!BC27 -> 333403 | J17: =+J16 -> 0 | K17: =+Lifestyle!BD27 -> 4000 | L17: =+L16 -> 7000 | M17: =+M16 -> 103 | N17: =+N16 -> 60 | O17: =+O16 -> 65
A18: Ashley 25A | B18: =+CEILING(I18+J18+K18,10) -> 347550 | C18: =+L18 -> 7000 | D18: =+Shepparton!D18 -> 7040 | E18: =+Shepparton!E18 -> 4655 | F18: =SUM(B18:E18) -> 366245 | G18: =+Shepparton!G18 -> 5440 | I18: =+Lifestyle!BC28 -> 343545 | J18: =+J17 -> 0 | K18: =+Lifestyle!BD28 -> 4000 | L18: =+L17 -> 7000 | M18: =+M17 -> 103 | N18: =+N17 -> 60 | O18: =+O17 -> 65
A19: Ashley 26 | B19: =+CEILING(I19+J19+K19,10) -> 344210 | C19: =+L19 -> 7000 | D19: =+Shepparton!D19 -> 7050 | E19: =+Shepparton!E19 -> 4900 | F19: =SUM(B19:E19) -> 363160 | G19: =+Shepparton!G19 -> 5270 | I19: =+Lifestyle!BC29 -> 340209 | J19: =+J18 -> 0 | K19: =+Lifestyle!BD29 -> 4000 | L19: =+L18 -> 7000 | M19: =+M18 -> 103 | N19: =+N18 -> 60 | O19: =+O18 -> 65
A20: Ashley 27 | B20: =+CEILING(I20+J20+K20,10) -> 356220 | C20: =+L20 -> 7000 | D20: =+Shepparton!D20 -> 7995 | E20: =+Shepparton!E20 -> 6080 | F20: =SUM(B20:E20) -> 377295 | G20: =+Shepparton!G20 -> 5525 | I20: =+Lifestyle!BC30 -> 352214 | J20: =+J19 -> 0 | K20: =+Lifestyle!BD30 -> 4000 | L20: =+L19 -> 7000 | M20: =+M19 -> 103 | N20: =+N19 -> 60 | O20: =+O19 -> 65
A21: Ashley 28 | B21: =+CEILING(I21+J21+K21,10) -> 360760 | C21: =+L21 -> 7000 | D21: =+Shepparton!D21 -> 8895 | E21: =+Shepparton!E21 -> 4395 | F21: =SUM(B21:E21) -> 381050 | G21: =+Shepparton!G21 -> 5525 | I21: =+Lifestyle!BC31 -> 356760 | J21: =+J20 -> 0 | K21: =+Lifestyle!BD31 -> 4000 | L21: =+L20 -> 7000 | M21: =+M20 -> 103 | N21: =+N20 -> 60 | O21: =+O20 -> 65
A22: Ashley 28A | B22: =+CEILING(I22+J22+K22,10) -> 368510 | C22: =+L22 -> 7000 | D22: =+Shepparton!D22 -> 9335 | E22: =+Shepparton!E22 -> 5835 | F22: =SUM(B22:E22) -> 390680 | G22: =+Shepparton!G22 -> 5525 | I22: =+Lifestyle!BC32 -> 364509 | J22: =+J21 -> 0 | K22: =+Lifestyle!BD32 -> 4000 | L22: =+L21 -> 7000 | M22: =+M21 -> 103 | N22: =+N21 -> 60 | O22: =+O21 -> 65
A23: Ballina 24 | B23: =+CEILING(I23+J23+K23,10) -> 328840 | C23: =+L23 -> 7000 | D23: =+Shepparton!D23 -> 7970 | E23: =+Shepparton!E23 -> 3015 | F23: =SUM(B23:E23) -> 346825 | G23: =+Shepparton!G23 -> 4505 | I23: =+Lifestyle!BC33 -> 325831 | J23: =+J22 -> 0 | K23: =+Lifestyle!BD33 -> 3000 | L23: =+L22 -> 7000 | M23: =+M22 -> 103 | N23: =+N22 -> 60 | O23: =+O22 -> 65
A24: Ballina 30 | B24: =+CEILING(I24+J24+K24,10) -> 377980 | C24: =+L24 -> 7000 | D24: =+Shepparton!D24 -> 9640 | E24: =+Shepparton!E24 -> 5305 | F24: =SUM(B24:E24) -> 399925 | G24: =+Shepparton!G24 -> 5695 | I24: =+Lifestyle!BC34 -> 373971 | J24: =+J23 -> 0 | K24: =+Lifestyle!BD34 -> 4000 | L24: =+L23 -> 7000 | M24: =+M23 -> 103 | N24: =+N23 -> 60 | O24: =+O23 -> 65
A25: Ballina 30A | B25: =+CEILING(I25+J25+K25,10) -> 380300 | C25: =+L25 -> 7000 | D25: =+Shepparton!D25 -> 10765 | E25: =+Shepparton!E25 -> 5680 | F25: =SUM(B25:E25) -> 403745 | G25: =+Shepparton!G25 -> 5950 | I25: =+Lifestyle!BC35 -> 376292 | J25: =+J24 -> 0 | K25: =+Lifestyle!BD35 -> 4000 | L25: =+L24 -> 7000 | M25: =+M24 -> 103 | N25: =+N24 -> 60 | O25: =+O24 -> 65
A26: Ballina 33 | B26: =+CEILING(I26+J26+K26,10) -> 412310 | C26: =+L26 -> 7000 | D26: =+Shepparton!D26 -> 11835 | E26: =+Shepparton!E26 -> 5245 | F26: =SUM(B26:E26) -> 436390 | G26: =+Shepparton!G26 -> 6375 | I26: =+Lifestyle!BC36 -> 408310 | J26: =+J24 -> 0 | K26: =+Lifestyle!BD36 -> 4000 | L26: =+L24 -> 7000 | M26: =+M24 -> 103 | N26: =+N24 -> 60 | O26: =+O24 -> 65
A27: Ballina 39 | B27: =+CEILING(I27+J27+K27,10) -> 457350 | C27: =+L27 -> 7000 | D27: =+Shepparton!D27 -> 13260 | E27: =+Shepparton!E27 -> 7725 | F27: =SUM(B27:E27) -> 485335 | G27: =+Shepparton!G27 -> 6800 | I27: =+Lifestyle!BC37 -> 453342 | J27: =+J26 -> 0 | K27: =+Lifestyle!BD37 -> 4000 | L27: =+L26 -> 7000 | M27: =+M26 -> 103 | N27: =+N26 -> 60 | O27: =+O26 -> 65
A28: =+Lifestyle!A38 -> Bathurst 25 | B28: =+CEILING(I28+J28+K28,10) -> 360680 | C28: =+L28 -> 7000 | D28: =+Shepparton!D28 -> 7285 | E28: =+Shepparton!E28 -> 3960 | F28: =SUM(B28:E28) -> 378925 | G28: =+Shepparton!G28 -> 5185 | I28: =+Lifestyle!BC38 -> 356677 | J28: =+J27 -> 0 | K28: =+Lifestyle!BD38 -> 4000 | L28: =+L27 -> 7000 | M28: =+M27 -> 103 | N28: =+N27 -> 60 | O28: =+O27 -> 65
A29: =+Lifestyle!A39 -> Bathurst 30 | B29: =+CEILING(I29+J29+K29,10) -> 407720 | C29: =+L29 -> 7000 | D29: =+Shepparton!D29 -> 8780 | E29: =+Shepparton!E29 -> 5635 | F29: =SUM(B29:E29) -> 429135 | G29: =+Shepparton!G29 -> 5950 | I29: =+Lifestyle!BC39 -> 403713 | J29: =+J28 -> 0 | K29: =+Lifestyle!BD39 -> 4000 | L29: =+L28 -> 7000 | M29: =+M28 -> 103 | N29: =+N28 -> 60 | O29: =+O28 -> 65
A30: =+Lifestyle!A40 -> Bathurst 34 | B30: =+CEILING(I30+J30+K30,10) -> 426050 | C30: =+L30 -> 7000 | D30: =+Shepparton!D30 -> 9675 | E30: =+Shepparton!E30 -> 6350 | F30: =SUM(B30:E30) -> 449075 | G30: =+Shepparton!G30 -> 6290 | I30: =+Lifestyle!BC40 -> 422047 | J30: =+J29 -> 0 | K30: =+Lifestyle!BD40 -> 4000 | L30: =+L29 -> 7000 | M30: =+M29 -> 103 | N30: =+N29 -> 60 | O30: =+O29 -> 65
A31: Bayview 23 | B31: =+CEILING(I31+J31+K31,10) -> 330140 | C31: =+L31 -> 7000 | D31: =+Shepparton!D31 -> 8145 | E31: =+Shepparton!E31 -> 3005 | F31: =SUM(B31:E31) -> 348290 | G31: =+Shepparton!G31 -> 4760 | I31: =+Lifestyle!BC41 -> 327135 | J31: =+J30 -> 0 | K31: =+Lifestyle!BD41 -> 3000 | L31: =+L30 -> 7000 | M31: =+M30 -> 103 | N31: =+N30 -> 60 | O31: =+O30 -> 65
A32: Bayview 26 | B32: =+CEILING(I32+J32+K32,10) -> 353100 | C32: =+L32 -> 7000 | D32: =+Shepparton!D32 -> 7115 | E32: =+Shepparton!E32 -> 5060 | F32: =SUM(B32:E32) -> 372275 | G32: =+Shepparton!G32 -> 5270 | I32: =+Lifestyle!BC42 -> 349100 | J32: =+J31 -> 0 | K32: =+Lifestyle!BD42 -> 4000 | L32: =+L31 -> 7000 | M32: =+M31 -> 103 | N32: =+N31 -> 60 | O32: =+O31 -> 65
A33: Bayview 30 | B33: =+CEILING(I33+J33+K33,10) -> 390550 | C33: =+L33 -> 7000 | D33: =+Shepparton!D33 -> 8295 | E33: =+Shepparton!E33 -> 6975 | F33: =SUM(B33:E33) -> 412820 | G33: =+Shepparton!G33 -> 6120 | I33: =+Lifestyle!BC43 -> 386547 | J33: =+J32 -> 0 | K33: =+Lifestyle!BD43 -> 4000 | L33: =+L32 -> 7000 | M33: =+M32 -> 103 | N33: =+N32 -> 60 | O33: =+O32 -> 65
A34: Bondi 25 | B34: =+CEILING(I34+J34+K34,10) -> 343960 | C34: =+L34 -> 7000 | D34: =+Shepparton!D34 -> 9315 | E34: =+Shepparton!E34 -> 3765 | F34: =SUM(B34:E34) -> 364040 | G34: =+Shepparton!G34 -> 5355 | I34: =+Lifestyle!BC44 -> 339954 | J34: =+J33 -> 0 | K34: =+Lifestyle!BD44 -> 4000 | L34: =+L33 -> 7000 | M34: =+M33 -> 103 | N34: =+N33 -> 60 | O34: =+O33 -> 65
A35: Bondi 31 | B35: =+CEILING(I35+J35+K35,10) -> 383710 | C35: =+L35 -> 7000 | D35: =+Shepparton!D35 -> 10850 | E35: =+Shepparton!E35 -> 5070 | F35: =SUM(B35:E35) -> 406630 | G35: =+Shepparton!G35 -> 5780 | I35: =+Lifestyle!BC45 -> 379707 | J35: =+J34 -> 0 | K35: =+Lifestyle!BD45 -> 4000 | L35: =+L34 -> 7000 | M35: =+M34 -> 103 | N35: =+N34 -> 60 | O35: =+O34 -> 65
A36: Bondi 36 | B36: =+CEILING(I36+J36+K36,10) -> 413150 | C36: =+L36 -> 7000 | D36: =+Shepparton!D36 -> 12315 | E36: =+Shepparton!E36 -> 6445 | F36: =SUM(B36:E36) -> 438910 | G36: =+Shepparton!G36 -> 5865 | I36: =+Lifestyle!BC46 -> 409146 | J36: =+J35 -> 0 | K36: =+Lifestyle!BD46 -> 4000 | L36: =+L35 -> 7000 | M36: =+M35 -> 103 | N36: =+N35 -> 60 | O36: =+O35 -> 65
A37: Cambridge 22 | B37: =+CEILING(I37+J37+K37,10) -> 322820 | C37: =+L37 -> 7000 | D37: =+Shepparton!D37 -> 7965 | E37: =+Shepparton!E37 -> 3465 | F37: =SUM(B37:E37) -> 341250 | G37: =+Shepparton!G37 -> 4845 | I37: =+Lifestyle!BC47 -> 319820 | J37: =+J36 -> 0 | K37: =+Lifestyle!BD47 -> 3000 | L37: =+L36 -> 7000 | M37: =+M36 -> 103 | N37: =+N36 -> 60 | O37: =+O36 -> 65
A38: Cambridge 24 | B38: =+CEILING(I38+J38+K38,10) -> 342820 | C38: =+L38 -> 7000 | D38: =+Shepparton!D38 -> 7465 | E38: =+Shepparton!E38 -> 4845 | F38: =SUM(B38:E38) -> 362130 | G38: =+Shepparton!G38 -> 4845 | I38: =+Lifestyle!BC48 -> 339818 | J38: =+J37 -> 0 | K38: =+Lifestyle!BD48 -> 3000 | L38: =+L37 -> 7000 | M38: =+M37 -> 103 | N38: =+N37 -> 60 | O38: =+O37 -> 65
A39: Cambridge 26 | B39: =+CEILING(I39+J39+K39,10) -> 359290 | C39: =+L39 -> 7000 | D39: =+Shepparton!D39 -> 8805 | E39: =+Shepparton!E39 -> 5280 | F39: =SUM(B39:E39) -> 380375 | G39: =+Shepparton!G39 -> 5100 | I39: =+Lifestyle!BC49 -> 355281 | J39: =+J38 -> 0 | K39: =+Lifestyle!BD49 -> 4000 | L39: =+L38 -> 7000 | M39: =+M38 -> 103 | N39: =+N38 -> 60 | O39: =+O38 -> 65
A40: Cambridge 30 | B40: =+CEILING(I40+J40+K40,10) -> 389270 | C40: =+L40 -> 7000 | D40: =+Shepparton!D40 -> 8275 | E40: =+Shepparton!E40 -> 7495 | F40: =SUM(B40:E40) -> 412040 | G40: =+Shepparton!G40 -> 5525 | I40: =+Lifestyle!BC50 -> 385270 | J40: =+J39 -> 0 | K40: =+Lifestyle!BD50 -> 4000 | L40: =+L39 -> 7000 | M40: =+M39 -> 103 | N40: =+N39 -> 60 | O40: =+O39 -> 65
A42: BASE PRICE INCLUDES: | E42: BASE PRICE DOES NOT INCLUDE:
A43: *SEWER, STORMWATER AND POWER | E43: *SITE PIERING
A44: TO A 700m2 BLOCK | E44: *RAISED PORTICO
A45: *20m TEMP FENCING | E45: *TILES & CARPET
A46: *'MD' CLASS SLAB | E46: *EXTERNAL PAVING
E47: *EAVES
A48: ECHUCA
A49: =+A2 -> LIFESTYLE SINGLE STOREY PRICE LIST VALID UP TO AUG 2025
A50: HOUSE DESIGN | B50: BASE PRICE * | C50: 50sqm NATURAL CONCRETE | D50: LIFESTYLE FLOOR TILES | E50: LIFESTYLE CARPETS | F50: PACKAGE PRICE *50sqm NATURAL CONCRETE *CARPET *TILES | G50: PRICE TO ADD EAVES
A51: Duneed 22 | B51: =+CEILING(I51+J51+K51,10) -> 328240 | C51: =+L51 -> 7000 | D51: =+Shepparton!D51 -> 6705 | E51: =+Shepparton!E51 -> 3215 | F51: =SUM(B51:E51) -> 345160 | G51: =+Shepparton!G51 -> 5440 | I51: =+Lifestyle!BC51 -> 325231 | J51: =+J40 -> 0 | K51: =+Lifestyle!BD51 -> 3000 | L51: =+L40 -> 7000 | M51: =+M40 -> 103 | N51: =+N40 -> 60 | O51: =+O40 -> 65
A52: Duneed 23 | B52: =+CEILING(I52+J52+K52,10) -> 331250 | C52: =+L52 -> 7000 | D52: =+Shepparton!D52 -> 6610 | E52: =+Shepparton!E52 -> 3570 | F52: =SUM(B52:E52) -> 348430 | G52: =+Shepparton!G52 -> 5440 | I52: =+Lifestyle!BC52 -> 328247 | J52: =+J51 -> 0 | K52: =+Lifestyle!BD52 -> 3000 | L52: =+L51 -> 7000 | M52: =+M51 -> 103 | N52: =+N51 -> 60 | O52: =+O51 -> 65
A53: Duneed 24 | B53: =+CEILING(I53+J53+K53,10) -> 342420 | C53: =+L53 -> 7000 | D53: =+Shepparton!D53 -> 6905 | E53: =+Shepparton!E53 -> 4650 | F53: =SUM(B53:E53) -> 360975 | G53: =+Shepparton!G53 -> 5440 | I53: =+Lifestyle!BC53 -> 339412 | J53: =+J52 -> 0 | K53: =+Lifestyle!BD53 -> 3000 | L53: =+L52 -> 7000 | M53: =+M52 -> 103 | N53: =+N52 -> 60 | O53: =+O52 -> 65
A54: Duneed 25 | B54: =+CEILING(I54+J54+K54,10) -> 346420 | C54: =+L54 -> 7000 | D54: =+Shepparton!D54 -> 6835 | E54: =+Shepparton!E54 -> 5030 | F54: =SUM(B54:E54) -> 365285 | G54: =+Shepparton!G54 -> 5440 | I54: =+Lifestyle!BC54 -> 342418 | J54: =+J53 -> 0 | K54: =+Lifestyle!BD54 -> 4000 | L54: =+L53 -> 7000 | M54: =+M53 -> 103 | N54: =+N53 -> 60 | O54: =+O53 -> 65
A55: Duneed 30 | B55: =+CEILING(I55+J55+K55,10) -> 389930 | C55: =+L55 -> 7000 | D55: =+Shepparton!D55 -> 9030 | E55: =+Shepparton!E55 -> 5385 | F55: =SUM(B55:E55) -> 411345 | G55: =+Shepparton!G55 -> 5440 | I55: =+Lifestyle!BC55 -> 385922 | J55: =+J54 -> 0 | K55: =+Lifestyle!BD55 -> 4000 | L55: =+L54 -> 7000 | M55: =+M54 -> 103 | N55: =+N54 -> 60 | O55: =+O54 -> 65
A56: Eclipse 23 | B56: =+CEILING(I56+J56+K56,10) -> 340650 | C56: =+L56 -> 7000 | D56: =+Shepparton!D56 -> 6225 | E56: =+Shepparton!E56 -> 4555 | F56: =SUM(B56:E56) -> 358430 | G56: =+Shepparton!G56 -> 4675 | I56: =+Lifestyle!BC56 -> 336641 | J56: =+J55 -> 0 | K56: =+Lifestyle!BD56 -> 4000 | L56: =+L55 -> 7000 | M56: =+M55 -> 103 | N56: =+N55 -> 60 | O56: =+O55 -> 65
A57: Eclipse 26 | B57: =+CEILING(I57+J57+K57,10) -> 369120 | C57: =+L57 -> 7000 | D57: =+Shepparton!D57 -> 6815 | E57: =+Shepparton!E57 -> 5595 | F57: =SUM(B57:E57) -> 388530 | G57: =+Shepparton!G57 -> 5440 | I57: =+Lifestyle!BC57 -> 365119 | J57: =+J56 -> 0 | K57: =+Lifestyle!BD57 -> 4000 | L57: =+L56 -> 7000 | M57: =+M56 -> 103 | N57: =+N56 -> 60 | O57: =+O56 -> 65
A58: Eclipse 28 | B58: =+CEILING(I58+J58+K58,10) -> 384830 | C58: =+L58 -> 7000 | D58: =+Shepparton!D58 -> 7105 | E58: =+Shepparton!E58 -> 6350 | F58: =SUM(B58:E58) -> 405285 | G58: =+Shepparton!G58 -> 5950 | I58: =+Lifestyle!BC58 -> 380824 | J58: =+J57 -> 0 | K58: =+Lifestyle!BD58 -> 4000 | L58: =+L57 -> 7000 | M58: =+M57 -> 103 | N58: =+N57 -> 60 | O58: =+O57 -> 65
A59: Hamilton 24 | B59: =+CEILING(I59+J59+K59,10) -> 337630 | C59: =+L59 -> 7000 | D59: =+Shepparton!D59 -> 8450 | E59: =+Shepparton!E59 -> 3460 | F59: =SUM(B59:E59) -> 356540 | G59: =+Shepparton!G59 -> 4845 | I59: =+Lifestyle!BC59 -> 334625 | J59: =+J58 -> 0 | K59: =+Lifestyle!BD59 -> 3000 | L59: =+L58 -> 7000 | M59: =+M58 -> 103 | N59: =+N58 -> 60 | O59: =+O58 -> 65
A60: Hamilton 29 | B60: =+CEILING(I60+J60+K60,10) -> 379450 | C60: =+L60 -> 7000 | D60: =+Shepparton!D60 -> 9065 | E60: =+Shepparton!E60 -> 5080 | F60: =SUM(B60:E60) -> 400595 | G60: =+Shepparton!G60 -> 5270 | I60: =+Lifestyle!BC60 -> 375448 | J60: =+J59 -> 0 | K60: =+Lifestyle!BD60 -> 4000 | L60: =+L59 -> 7000 | M60: =+M59 -> 103 | N60: =+N59 -> 60 | O60: =+O59 -> 65
A61: Hamilton 34 | B61: =+CEILING(I61+J61+K61,10) -> 411050 | C61: =+L61 -> 7000 | D61: =+Shepparton!D61 -> 9455 | E61: =+Shepparton!E61 -> 6610 | F61: =SUM(B61:E61) -> 434115 | G61: =+Shepparton!G61 -> 6375 | I61: =+Lifestyle!BC61 -> 407049 | J61: =+J60 -> 0 | K61: =+Lifestyle!BD61 -> 4000 | L61: =+L60 -> 7000 | M61: =+M60 -> 103 | N61: =+N60 -> 60 | O61: =+O60 -> 65
A62: Launceston 21 | B62: =+CEILING(I62+J62+K62,10) -> 317210 | C62: =+L62 -> 7000 | D62: =+Shepparton!D62 -> 6515 | E62: =+Shepparton!E62 -> 3700 | F62: =SUM(B62:E62) -> 334425 | G62: =+Shepparton!G62 -> 4930 | I62: =+Lifestyle!BC62 -> 314204 | J62: =+J61 -> 0 | K62: =+Lifestyle!BD62 -> 3000 | L62: =+L61 -> 7000 | M62: =+M61 -> 103 | N62: =+N61 -> 60 | O62: =+O61 -> 65
A63: Launceston 22 | B63: =+CEILING(I63+J63+K63,10) -> 328070 | C63: =+L63 -> 7000 | D63: =+Shepparton!D63 -> 6460 | E63: =+Shepparton!E63 -> 3770 | F63: =SUM(B63:E63) -> 345300 | G63: =+Shepparton!G63 -> 5100 | I63: =+Lifestyle!BC63 -> 325064 | J63: =+J62 -> 0 | K63: =+Lifestyle!BD63 -> 3000 | L63: =+L62 -> 7000 | M63: =+M62 -> 103 | N63: =+N62 -> 60 | O63: =+O62 -> 65
... A82: Santa Barbara 25 | B82: =+CEILING(I82+J82+K82,10) -> 337220 | C82: =+L82 -> 7000 | D82: =+Shepparton!D82 -> 7420 | E82: =+Shepparton!E82 -> 5000 | F82: =SUM(B82:E82) -> 356640 | G82: =+Shepparton!G82 -> 4930 | I82: =+Lifestyle!BC82 -> 333212 | J82: =+J81 -> 0 | K82: =+Lifestyle!BD82 -> 4000 | L82: =+L81 -> 7000 | M82: =+M81 -> 103 | N82: =+N81 -> 60 | O82: =+O81 -> 65
A83: Santa Barbara 26 | B83: =+CEILING(I83+J83+K83,10) -> 353270 | C83: =+L83 -> 7000 | D83: =+Shepparton!D83 -> 7610 | E83: =+Shepparton!E83 -> 4700 | F83: =SUM(B83:E83) -> 372580 | G83: =+Shepparton!G83 -> 5270 | I83: =+Lifestyle!BC83 -> 349264 | J83: =+J81 -> 0 | K83: =+Lifestyle!BD83 -> 4000 | L83: =+L81 -> 7000 | M83: =+M81 -> 103 | N83: =+N81 -> 60 | O83: =+O81 -> 65
A85: BASE PRICE INCLUDES: | E85: BASE PRICE DOES NOT INCLUDE:
A86: *SEWER, STORMWATER AND POWER | E86: *SITE PIERING
A87: TO A 700m2 BLOCK | E87: *RAISED PORTICO
A88: *20m TEMP FENCING | E88: *TILES
A89: *'MD' CLASS SLAB | E89: *CARPET
E90: *EXTERNAL PAVING
E91: *EAVES
A92: ECHUCA
A93: LIFESTYLE HOMESTEAD PRICE LIST VALID UP TO AUG 2025
A94: HOUSE DESIGN | B94: BASE PRICE * | C94: 50sqm NATURAL CONCRETE | D94: LIFESTYLE FLOOR TILES | E94: LIFESTYLE CARPETS | F94: PACKAGE PRICE *50sqm NATURAL CONCRETE *CARPET *TILES | G94: PRICE TO ADD EAVES | I94: List price | J94: Promotional | L94: 50sqm natural concrete | M94: Tiles per sqm | N94: Carpet per sqm | O94: Eaves per lm
A95: Inglewood 24 | B95: =+CEILING(I95+J95+K95,10) -> 337470 | C95: =+L95 -> 7000 | D95: =+Shepparton!D95 -> 6940 | E95: =+Shepparton!E95 -> 4270 | F95: =SUM(B95:E95) -> 355680 | G95: =+Shepparton!G95 -> 5015 | I95: =+Lifestyle!BC86 -> 334465 | J95: =+J81 -> 0 | K95: =+Lifestyle!BD86 -> 3000 | L95: =+L81 -> 7000 | M95: =+M81 -> 103 | N95: =+N81 -> 60 | O95: =+O81 -> 65
A96: Inglewood 26 | B96: =+CEILING(I96+J96+K96,10) -> 362570 | C96: =+L96 -> 7000 | D96: =+Shepparton!D96 -> 7615 | E96: =+Shepparton!E96 -> 4880 | F96: =SUM(B96:E96) -> 382065 | G96: =+Shepparton!G96 -> 5780 | I96: =+Lifestyle!BC87 -> 358564 | J96: =+J95 -> 0 | K96: =+Lifestyle!BD87 -> 4000 | L96: =+L95 -> 7000 | M96: =+M95 -> 103 | N96: =+N95 -> 60 | O96: =+O95 -> 65
A97: Inglewood 29 | B97: =+CEILING(I97+J97+K97,10) -> 382290 | C97: =+L97 -> 7000 | D97: =+Shepparton!D97 -> 8615 | E97: =+Shepparton!E97 -> 5340 | F97: =SUM(B97:E97) -> 403245 | G97: =+Shepparton!G97 -> 5865 | I97: =+Lifestyle!BC88 -> 378282 | J97: =+J96 -> 0 | K97: =+Lifestyle!BD88 -> 4000 | L97: =+L96 -> 7000 | M97: =+M96 -> 103 | N97: =+N96 -> 60 | O97: =+O96 -> 65
A98: Inglewood 31 | B98: =+CEILING(I98+J98+K98,10) -> 400470 | C98: =+L98 -> 7000 | D98: =+Shepparton!D98 -> 8515 | E98: =+Shepparton!E98 -> 6025 | F98: =SUM(B98:E98) -> 422010 | G98: =+Shepparton!G98 -> 6460 | I98: =+Lifestyle!BC89 -> 396461 | J98: =+J97 -> 0 | K98: =+Lifestyle!BD89 -> 4000 | L98: =+L97 -> 7000 | M98: =+M97 -> 103 | N98: =+N97 -> 60 | O98: =+O97 -> 65
A99: Inglewood 34 | B99: =+CEILING(I99+J99+K99,10) -> 419670 | C99: =+L99 -> 7000 | D99: =+Shepparton!D99 -> 9045 | E99: =+Shepparton!E99 -> 7265 | F99: =SUM(B99:E99) -> 442980 | G99: =+Shepparton!G99 -> 7055 | I99: =+Lifestyle!BC90 -> 415664 | J99: =+J98 -> 0 | K99: =+Lifestyle!BD90 -> 4000 | L99: =+L98 -> 7000 | M99: =+M98 -> 103 | N99: =+N98 -> 60 | O99: =+O98 -> 65
A100: Inglewood 35 | B100: =+CEILING(I100+J100+K100,10) -> 438790 | C100: =+L100 -> 7000 | D100: =+Shepparton!D100 -> 9030 | E100: =+Shepparton!E100 -> 7055 | F100: =SUM(B100:E100) -> 461875 | G100: =+Shepparton!G100 -> 7055 | I100: =+Lifestyle!BC91 -> 434789 | J100: =+J101 -> 0 | K100: =+Lifestyle!BD91 -> 4000 | L100: =+L101 -> 7000 | M100: =+M101 -> 103 | N100: =+N101 -> 60 | O100: =+O101 -> 65
A101: Inglewood 38 | B101: =+CEILING(I101+J101+K101,10) -> 456430 | C101: =+L101 -> 7000 | D101: =+Shepparton!D101 -> 9185 | E101: =+Shepparton!E101 -> 7570 | F101: =SUM(B101:E101) -> 480185 | G101: =+Shepparton!G101 -> 7055 | I101: =+Lifestyle!BC92 -> 452422 | J101: =+J99 -> 0 | K101: =+Lifestyle!BD92 -> 4000 | L101: =+L99 -> 7000 | M101: =+M99 -> 103 | N101: =+N99 -> 60 | O101: =+O99 -> 65
A102: Maldon 23 | B102: =+CEILING(I102+J102+K102,10) -> 326350 | C102: =+L102 -> 7000 | D102: =+Shepparton!D102 -> 7165 | E102: =+Shepparton!E102 -> 3960 | F102: =SUM(B102:E102) -> 344475 | G102: =+Shepparton!G102 -> 4505 | I102: =+Lifestyle!BC93 -> 323347 | J102: =+J100 -> 0 | K102: =+Lifestyle!BD93 -> 3000 | L102: =+L100 -> 7000 | M102: =+M100 -> 103 | N102: =+N100 -> 60 | O102: =+O100 -> 65
A103: Maldon 27 | B103: =+CEILING(I103+J103+K103,10) -> 365510 | C103: =+L103 -> 7000 | D103: =+Shepparton!D103 -> 8585 | E103: =+Shepparton!E103 -> 4615 | F103: =SUM(B103:E103) -> 385710 | G103: =+Shepparton!G103 -> 4590 | I103: =+Lifestyle!BC94 -> 361506 | J103: =+J100 -> 0 | K103: =+Lifestyle!BD94 -> 4000 | L103: =+L100 -> 7000 | M103: =+M100 -> 103 | N103: =+N100 -> 60 | O103: =+O100 -> 65
A104: Maldon 33 | B104: =+CEILING(I104+J104+K104,10) -> 426440 | C104: =+L104 -> 7000 | D104: =+Shepparton!D104 -> 10300 | E104: =+Shepparton!E104 -> 5940 | F104: =SUM(B104:E104) -> 449680 | G104: =+Shepparton!G104 -> 6460 | I104: =+Lifestyle!BC95 -> 422431 | J104: =+J101 -> 0 | K104: =+Lifestyle!BD95 -> 4000 | L104: =+L101 -> 7000 | M104: =+M101 -> 103 | N104: =+N101 -> 60 | O104: =+O101 -> 65
A105: Palmerston 28 | B105: =+CEILING(I105+J105+K105,10) -> 373590 | C105: =+L105 -> 7000 | D105: =+Shepparton!D105 -> 7965 | E105: =+Shepparton!E105 -> 5120 | F105: =SUM(B105:E105) -> 393675 | G105: =+Shepparton!G105 -> 5440 | I105: =+Lifestyle!BC96 -> 369589 | J105: =+J102 -> 0 | K105: =+Lifestyle!BD96 -> 4000 | L105: =+L102 -> 7000 | M105: =+M102 -> 103 | N105: =+N102 -> 60 | O105: =+O102 -> 65
A106: Palmerston 35 | B106: =+CEILING(I106+J106+K106,10) -> 425710 | C106: =+L106 -> 7000 | D106: =+Shepparton!D106 -> 9655 | E106: =+Shepparton!E106 -> 7630 | F106: =SUM(B106:E106) -> 449995 | G106: =+Shepparton!G106 -> 6205 | I106: =+Lifestyle!BC97 -> 421703 | J106: =+J105 -> 0 | K106: =+Lifestyle!BD97 -> 4000 | L106: =+L105 -> 7000 | M106: =+M105 -> 103 | N106: =+N105 -> 60 | O106: =+O105 -> 65
A107: Sandown 23 | B107: =+CEILING(I107+J107+K107,10) -> 334300 | C107: =+L107 -> 7000 | D107: =+Shepparton!D107 -> 7335 | E107: =+Shepparton!E107 -> 3760 | F107: =SUM(B107:E107) -> 352395 | G107: =+Shepparton!G107 -> 5355 | I107: =+Lifestyle!BC98 -> 331300 | J107: =+J106 -> 0 | K107: =+Lifestyle!BD98 -> 3000 | L107: =+L106 -> 7000 | M107: =+M106 -> 103 | N107: =+N106 -> 60 | O107: =+O106 -> 65
A108: Sandown 26 | B108: =+CEILING(I108+J108+K108,10) -> 366960 | C108: =+L108 -> 7000 | D108: =+Shepparton!D108 -> 8025 | E108: =+Shepparton!E108 -> 4720 | F108: =SUM(B108:E108) -> 386705 | G108: =+Shepparton!G108 -> 4845 | I108: =+Lifestyle!BC99 -> 362956 | J108: =+J107 -> 0 | K108: =+Lifestyle!BD99 -> 4000 | L108: =+L107 -> 7000 | M108: =+M107 -> 103 | N108: =+N107 -> 60 | O108: =+O107 -> 65
A109: Sandown 28 (30) | B109: =+CEILING(I109+J109+K109,10) -> 389920 | C109: =+L109 -> 7000 | D109: =+Shepparton!D109 -> 9030 | E109: =+Shepparton!E109 -> 6215 | F109: =SUM(B109:E109) -> 412165 | G109: =+Shepparton!G109 -> 5525 | I109: =+Lifestyle!BC100 -> 385920 | J109: =+J108 -> 0 | K109: =+Lifestyle!BD100 -> 4000 | L109: =+L108 -> 7000 | M109: =+M108 -> 103 | N109: =+N108 -> 60 | O109: =+O108 -> 65
A110: Sandown 32 | B110: =+CEILING(I110+J110+K110,10) -> 400490 | C110: =+L110 -> 7000 | D110: =+Shepparton!D110 -> 8615 | E110: =+Shepparton!E110 -> 6140 | F110: =SUM(B110:E110) -> 422245 | G110: =+Shepparton!G110 -> 5185 | I110: =+Lifestyle!BC101 -> 396488 | J110: =+J109 -> 0 | K110: =+Lifestyle!BD101 -> 4000 | L110: =+L109 -> 7000 | M110: =+M109 -> 103 | N110: =+N109 -> 60 | O110: =+O109 -> 65
A111: Sandown 34 MG | B111: =+CEILING(I111+J111+K111,10) -> 435190 | C111: =+L111 -> 7000 | D111: =+Shepparton!D111 -> 9555 | E111: =+Shepparton!E111 -> 5615 | F111: =SUM(B111:E111) -> 457360 | G111: =+Shepparton!G111 -> 6800 | I111: =+Lifestyle!BC102 -> 431186 | J111: =+J110 -> 0 | K111: =+Lifestyle!BD102 -> 4000 | L111: =+L110 -> 7000 | M111: =+M110 -> 103 | N111: =+N110 -> 60 | O111: =+O110 -> 65
A112: Sandown 40 MG | B112: =+CEILING(I112+J112+K112,10) -> 490080 | C112: =+L112 -> 7000 | D112: =+Shepparton!D112 -> 8710 | E112: =+Shepparton!E112 -> 8980 | F112: =SUM(B112:E112) -> 514770 | G112: =+Shepparton!G112 -> 7310 | I112: =+Lifestyle!BC103 -> 486075 | J112: =+J111 -> 0 | K112: =+Lifestyle!BD103 -> 4000 | L112: =+L111 -> 7000 | M112: =+M111 -> 103 | N112: =+N111 -> 60 | O112: =+O111 -> 65
A113: Sandown 41 MG | B113: =+CEILING(I113+J113+K113,10) -> 487870 | C113: =+L113 -> 7000 | D113: =+Shepparton!D113 -> 9830 | E113: =+Shepparton!E113 -> 8155 | F113: =SUM(B113:E113) -> 512855 | G113: =+Shepparton!G113 -> 7225 | I113: =+Lifestyle!BC104 -> 483869 | J113: =+J112 -> 0 | K113: =+Lifestyle!BD104 -> 4000 | L113: =+L112 -> 7000 | M113: =+M112 -> 103 | N113: =+N112 -> 60 | O113: =+O112 -> 65
A114: Winton 24 | B114: =+CEILING(I114+J114+K114,10) -> 340780 | C114: =+L114 -> 7000 | D114: =+Shepparton!D114 -> 7785 | E114: =+Shepparton!E114 -> 3690 | F114: =SUM(B114:E114) -> 359255 | G114: =+Shepparton!G114 -> 5440 | I114: =+Lifestyle!BC105 -> 337780 | J114: =+J113 -> 0 | K114: =+Lifestyle!BD105 -> 3000 | L114: =+L113 -> 7000 | M114: =+M113 -> 103 | N114: =+N113 -> 60 | O114: =+O113 -> 65
A115: Winton 28 | B115: =+CEILING(I115+J115+K115,10) -> 377400 | C115: =+L115 -> 7000 | D115: =+Shepparton!D115 -> 8685 | E115: =+Shepparton!E115 -> 5230 | F115: =SUM(B115:E115) -> 398315 | G115: =+Shepparton!G115 -> 5780 | I115: =+Lifestyle!BC106 -> 373394 | J115: =+J114 -> 0 | K115: =+Lifestyle!BD106 -> 4000 | L115: =+L114 -> 7000 | M115: =+M114 -> 103 | N115: =+N114 -> 60 | O115: =+O114 -> 65
A116: Winton 32 | B116: =+CEILING(I116+J116+K116,10) -> 420700 | C116: =+L116 -> 7000 | D116: =+Shepparton!D116 -> 10365 | E116: =+Shepparton!E116 -> 6480 | F116: =SUM(B116:E116) -> 444545 | G116: =+Shepparton!G116 -> 6375 | I116: =+Lifestyle!BC107 -> 416691 | J116: =+J115 -> 0 | K116: =+Lifestyle!BD107 -> 4000 | L116: =+L115 -> 7000 | M116: =+M115 -> 103 | N116: =+N115 -> 60 | O116: =+O115 -> 65
A118: BASE PRICE INCLUDES: | E118: BASE PRICE DOES NOT INCLUDE:
A119: *SEWER, STORMWATER AND POWER | E119: *SITE PIERING
A120: TO A 700m2 BLOCK | E120: *RAISED PORTICO
A121: *20m TEMP FENCING | E121: *TILES
...

Sheet Value Packs
B2: LIFESTYLE VALUE PACKS - NOV 2024
B4: ENTRANCE PACK
B5: 1200mm x 2040mm timber glass front door | C5: 1340
B6: Nexion Trilock handle | C6: 175
B7: Total | C7: =SUM(C5:C6) -> 1515
B9: KITCHEN CABINETRY PACK
B10: 2 Banks of drawers | C10: 660
B11: Twin bin in drawer with drawer below | C11: 250
B12: Fridge overhead cupboard | C12: 960 | E12: 1000mm with one side panel
B13: Total | C13: =SUM(C10:C12) -> 1870
B15: KITCHEN APPLIANCE PACK
B16: 90cm Inbuilt oven & gas cooktop | C16: 1355
B17: 70cm Intergrated rangehood | C17: 165
B18: Water point to fridge | C18: 200
B19: Total | C19: =SUM(C16:C18) -> 1720
B21: KITCHEN BENCHTOP PACK
B22: 20mm Stone benchtop | C22: 3625 | E22: (3.2m wall bench & 2.7m island)
B23: Undermount sink | C23: 355
B24: Total | C24: =SUM(C22:C23) -> 3980
B26: BATHROOM/ENSUITE INDULGENT PACK
B27: 20mm Stone vanity benchtops | C27: 1350 | E27: (up to 1 x 1800mm & 1 x 900mm)
B28: Above counter basins with tower mixers | C28: 450 | E28: x3
B29: Tiled recess shelf to showers | C29: 800
B30: Dual shower head to ensuite | C30: 250
B31: Total | C31: =SUM(C27:C30) -> 2850
B33: LAUNDRY INDULGENT PACK
B34: Extend bench & cabinets up to 2m | C34: 2800
B35: Pull out clothesbasket | C35: 220
B36: Total | C36: =SUM(C34:C35) -> 3020
B38: LIGHTING PACK 1
B39: 30 X LED downlights | C39: 2550 | E39: replaces 15 light points
B40: Total | C40: =SUM(C39:C39) -> 2550
B42: LIGHTING PACK 2
B43: 30 X LED downlights | C43: 2550 | E43: replaces 15 light points
B44: 3 X Pendant lights above island bench | C44: 1155 | E44: 220 per pendant
B45: Total | C45: =SUM(C43:C44) -> 3705
B47: LIGHTING PACK 3
B48: 30 X LED downlights | C48: 2550 | E48: replaces 15 light points
B49: 3 X Pendant lights above island bench | C49: =+C44 -> 1155 | E49: 220 per pendant
B50: 3 X Wall mounted feature lights to the front façade with motion sensor | C50: 1290
B51: Total | C51: =SUM(C48:C50) -> 4995
B53: TV ANTENNA | C53: 590

Sheet Sandown 32 Display
B4: ABN: 50 105 889 745
B5: 7961 Goulburn Valley Hwy | E5: Telephone 5823 1859
B6: P O BOX 922 | E6: Display Home 5832 6082
B7: SHEPPARTON VIC 3632 | E7: DB-U 9856
B9: Dear | C9: =+C48 -> 0
B11: RE: PRELIMINARY PRICING
B13: Thank you for your interest in building a new home with Cavalier Homes Goulburn Valley, we greatly
B14: appreciate the opportunity to work with you designing and building your new home.
B16: Please find attached the preliminary pricing to build a house on your land at
B17: =+C52 -> 0
B19: This preliminary pricing is provided as a guide and is subject to review after 30 days or before this
B20: time if a new price list is released in the interim.
B22: If you are pleased with the preliminary price, we can then provide a firm price once you have paid an
B23: initial preliminary service fee of $2,000 - (this will secure the price as per the terms and conditions
B24: of the Cavalier Homes Goulburn Valley Ground Work document which we will discuss further should
B25: you wish to proceed to the next stage).
B27: Once the initial preliminary service fee is received, we will arrange to have working drawings drafted
B28: which will show you fully detailed plan of the interior and exterior of your home.
B29: We will also engage an independent, qualified engineer to provide a slab design based on your home
B30: design and the results of the soil test inspection carried out on your block.
B32: As discussed, we will provide you with a final fixed price once the following are completed:
B33: The colour selections
... B55: PRE- CONSTRUCTION
B56: Soil test and site inspection of your block | D56: Included
B57: Independent qualified engineer designed slab | D57: Included
B58: Rescode investigation | D58: Included
B59: Building permit and associated fees (does not include planning permit) | D59: Included
B60: Development application for NSW jobs | D60: Included
B61: Builder's insurances | D61: Included
B62: Independent 6 star energy rating | D62: Included
B63: SERVICE CONNECTIONS
B64: Sewer run and connection fees to 700m2 block | D64: Included
B65: Water run and connection fees to 6m front setback | D65: Included
B66: Stormwater connection to 6m front setback | D66: Included
B67: Electricity run to 6m front setback (does not include connection fee) | D67: Included
B68: Gas service is to be supplied by the retailer
B69: FOUNDATIONS
B70: Site fall up to 200mm | D70: Included
B71: MD class concrete slab (floor height at least 250mm - there is no allowance for piers) | D71: Included
B72: Concrete pump | D72: Included
B73: TERMITE PROTECTION
B74: Termite resistant treated timber to all structural framing | D74: Included
B75: ROOFING
B76: Colorbond iron roof with sarking | D76: Included
B77: Colorbond slotted gutter, fascia and downpipes (downpipes 100mm x 50mm) | D77: Included
B78: 22.5 degree roof pitch | D78: Included
B79: FACADE
B80: Standard façade with 450mm eaves to front elevation as per brochure plans | D80: Included
B81: CEILING HEIGHT
B82: 2400mm ceiling height | D82: Included
B83: Plaster ceilings are fixed to a metal batten system, suspended on clips and is laser levelled to the entire home | D83: Included
B84: EXTERNAL FINISH
B85: Lifestyle range of PGH bricks with natural mortar | D85: Included
B86: Bricks over external swing and sliding doors (to openings up to 3.6m wide), windows and garage doors | D86: Included
B87: Outdoor living ceiling to be lined with plaster sheeting (brick piers or duragal steel columns are plan specific) | D87: Included
B88: ENERGY EFFICIENT FEATURES
B89: R3.5 Insulation batts to ceiling (excludes garage ceiling) | D89: Included
B90: R2.0 Insulation batts plus sisalation paper to external walls (excludes garage external walls) | D90: Included
B91: EXTERNAL DOORS
B92: Front door - Hume Newington solid core door with Lockwood Symmetry entry set | D92: Included
B93: External door jambs with perimeter draft seal (Glass sidelights are plan specific) | D93: Included
B94: Flydoors to glass sliding doors (except garage) | D94: Included
B95: WINDOWS
B96: Aluminium sliding windows with key locks | D96: Included
B97: Flyscreens to all opening windows (except garage) | D97: Included
B98: Obscure or clear glass to bathroom, ensuite & WC windows | D98: Included
B99: GARAGE
B100: Choice of external swing door or 2118 glass sliding door | D100: Included
B101: Plaster lined walls & ceiling | D101: Included
B102: Sectional overhead garage door with wall mounted remote control and 2 transmitters | D102: Included
B103: Concrete slab floor | D103: Included
B104: INTERNAL FINISH
B105: 75mm Cove cornice | D105: Included
B106: 67mm x 18mm Bevelled edge architraves | D106: Included
B107: 67mm x 18mm Bevelled edge skirtings | D107: Included
B108: INTERNAL DOORS
B109: Internal doors - 2040mm high flush panel doors | D109: Included
B110: Lockwood velocity door furniture to hinged doors | D110: Included
B111: Privacy locks to bathroom, ensuite and WC hinged doors | D111: Included
B112: Door stops to all hinged doors | D112: Included
B113: KITCHEN
B114: Westinghouse 60cm stainless steel multifunction electric underbench oven | D114: Included
B115: Westinghouse 60cm stainless steel gas cooktop | D115: Included
B116: Westinghouse 60cm stainless steel slideout rangehood | D116: Included
B117: Westinghouse 60cm freestanding dishwasher | D117: Included
B118: Joinery made base cabinet with laminate benchtop and overhead cupboards above cooktop section | D118: Included
B119: Soft close drawers & cupboard doors | D119: Included
B120: Underbench microwave cavity with one pot drawer | D120: Included
B121: 1 & 3/4 bowl stainless steel sink with sink mixer | D121: Included
B122: Bank of four drawers with cutlery insert to top drawer | D122: Included
B123: Four white melamine shelves to pantry | D123: Included
B124: ENSUITE/BATHROOM/WC
B125: Joinery made cabinet with laminate benchtop | D125: Included
B126: Frameless mirror 900mm high x width of vanity | D126: Included
B127: Acrylic bath in white to bathroom | D127: Included
B128: Choice of vanity basins in white | D128: Included
B129: Choice of mixer tapware in chrome | D129: Included
B130: Semi frameless pivot door shower screen in polished silver with clear glass | D130: Included
B131: Tiled shower base | D131: Included
B132: Goulburn glass shower shelf | D132: Included
...

Sheet Travel Working
A1: Draftee travel per km | B1: =+((65+65)/100) -> 1.3
A2: Truck cost per km | B2: 1.65 | F2: 16/10/24 - Add $50 for TV Antenna Instal
A3: Carpenter travel per km | B3: 1.65
A4: Supervisor tavel per km | B4: 1.65
A5: Concrete pump travel | B5: 4
A6: Stone benchtops | B6: 6
B7: Kms | C7: Cost per km return | D7: Bunnings delivery | E7: Drafting inspwction travel | F7: Temp fencing travel | G7: Skip run | H7: site screpe travel | I7: Crusher dust | K7: Concrete supply | M7: Pump travel | P7: Bricks delivery | R7: Brick sand | T7: Stone travel | W7: Supervisor travel
A8: SHEPPARTON | B8: 20 | C8: =+B2*2 -> 3.3 | D8: 45.45 | E8: =+C8*B8 -> 66 | F8: =+C8*B8 -> 66 | G8: =+C8*B8*6 -> 396 | H8: =+C8*B8 -> 66 | I8: 51 | J8: =+I8*35 -> 1785 | K8: 210 | L8: =+K8*60 -> 12600 | M8: =+B5 -> 4 | N8: =+B8-80 -> -60 | O8: =IF((N8>0),(N8*M8*2),) -> 0 | P8: 55 | Q8: =+P8*8 -> 440 | R8: 44 | S8: =+R8*9 -> 396 | T8: =+B6 -> 6 | V8: =+B4 -> 1.65 | W8: =+V8*2*B8*10 -> 660 | AF8: =+A8 -> SHEPPARTON
A9: ALEXANDRA | B9: 120 | C9: =+C8 -> 3.3 | D9: 150 | E9: =+C9*B9 -> 396 | F9: =+C9*B9 -> 396 | G9: =+C9*B9*6 -> 2376 | H9: =+C9*B9 -> 396 | I9: 85 | J9: =+I9*35 -> 2975 | K9: 287 | L9: =+K9*60 -> 17220 | M9: =+M8 -> 4 | N9: =+B9-80 -> 40 | O9: =IF((N9>0),(N9*M9*2),) -> 320 | P9: 65 | Q9: =+P9*8 -> 520 | R9: 80 | S9: =+R9*9 -> 720 | T9: =+T8 -> 6 | U9: =+IF(((B9-80)>0),((B9-80)*T9),0) -> 240 | V9: =+V8 -> 1.65 | W9: =+V9*2*B9*10 -> 3960 | AF9: =+A9 -> ALEXANDRA | AG9: =+C94-B94 -> 29794.75 | AH9: =+CEILING(AG9*1.36,10) -> 40530
A10: AVENEL | B10: 71 | C10: =+C9 -> 3.3 | D10: 110 | E10: =+C10*B10 -> 234.3 | F10: =+C10*B10 -> 234.3 | G10: =+C10*B10*6 -> 1405.8 | H10: =+C10*B10 -> 234.3 | I10: 65 | J10: =+I10*35 -> 2275 | K10: 210 | L10: =+K10*60 -> 12600 | M10: =+M9 -> 4 | N10: =+B10-80 -> -9 | O10: =IF((N10>0),(N10*M10*2),) -> 0 | P10: 55 | Q10: =+P10*8 -> 440 | R10: 56 | S10: =+R10*9 -> 504 | T10: =+T9 -> 6 | U10: =+IF(((B10-80)>0),((B10-80)*T10),0) -> 0 | V10: =+V9 -> 1.65 | W10: =+V10*2*B10*10 -> 2343 | AF10: =+A10 -> AVENEL | AG10: =+D94-B94 -> 10821.05 | AH10: =+CEILING(AG10*1.36,10) -> 14720
A11: BENALLA | B11: 62 | C11: =+C10 -> 3.3 | D11: 70 | E11: =+C11*B11 -> 204.6 | F11: =+C11*B11 -> 204.6 | G11: =+C11*B11*6 -> 1227.6 | H11: =+C11*B11 -> 204.6 | I11: 65 | J11: =+I11*35 -> 2275 | K11: 235 | L11: =+K11*60 -> 14100 | M11: =+M10 -> 4 | N11: =+B11-80 -> -18 | O11: =IF((N11>0),(N11*M11*2),) -> 0 | P11: 55 | Q11: =+P11*8 -> 440 | R11: 54 | S11: =+R11*9 -> 486 | T11: =+T10 -> 6 | U11: =+IF(((B11-80)>0),((B11-80)*T11),0) -> 0 | V11: =+V10 -> 1.65 | W11: =+V11*2*B11*10 -> 2046 | AF11: =+A11 -> BENALLA | AG11: =+E94-B94 -> 10219.35 | AH11: =+CEILING(AG11*1.36,10) -> 13900
A12: COBRAM | B12: 71 | C12: =+C11 -> 3.3 | D12: 70 | E12: =+C12*B12 -> 234.3 | F12: =+C12*B12 -> 234.3 | G12: =+C12*B12*6 -> 1405.8 | H12: =+C12*B12 -> 234.3 | I12: 65 | J12: =+I12*35 -> 2275 | K12: 220 | L12: =+K12*60 -> 13200 | M12: =+M11 -> 4 | N12: =+B12-80 -> -9 | O12: =IF((N12>0),(N12*M12*2),) -> 0 | P12: 70 | Q12: =+P12*8 -> 560 | R12: 54 | S12: =+R12*9 -> 486 | T12: =+T11 -> 6 | U12: =+IF(((B12-80)>0),((B12-80)*T12),0) -> 0 | V12: =+V11 -> 1.65 | W12: =+V12*2*B12*10 -> 2343 | AF12: =+A12 -> COBRAM | AG12: =+F94-B94 -> 10123.05 | AH12: =+CEILING(AG12*1.36,10) -> 13770
A13: COHUNA | B13: 135 | C13: =+C12 -> 3.3 | D13: =+D9 -> 150 | E13: =+C13*B13 -> 445.5 | F13: =+C13*B13 -> 445.5 | G13: =+C13*B13*6 -> 2673 | H13: =+C13*B13 -> 445.5 | I13: 85 | J13: =+I13*35 -> 2975 | K13: 345 | L13: =+K13*60 -> 20700 | M13: =+M12 -> 4 | N13: =+B13-80 -> 55 | O13: =IF((N13>0),(N13*M13*2),) -> 440 | P13: 80 | Q13: =+P13*8 -> 640 | R13: 80 | S13: =+R13*9 -> 720 | T13: =+T12 -> 6 | U13: =+IF(((B13-80)>0),((B13-80)*T13),0) -> 330 | V13: =+V12 -> 1.65 | W13: =+V13*2*B13*10 -> 4455 | AF13: =+A13 -> COHUNA | AG13: =+G94-B94 -> 34192.25 | AH13: =+CEILING(AG13*1.36,10) -> 46510
A14: DENILIQUIN | B14: 137 | C14: =+C13 -> 3.3 | D14: =+D13 -> 150 | E14: =+C14*B14 -> 452.1 | F14: =+C14*B14 -> 452.1 | G14: =+C14*B14*6 -> 2712.6 | H14: =+C14*B14 -> 452.1 | I14: 85 | J14: =+I14*35 -> 2975 | K14: 358 | L14: =+K14*60 -> 21480 | M14: =+M13 -> 4 | N14: =+B14-80 -> 57 | O14: =IF((N14>0),(N14*M14*2),) -> 456 | P14: 80 | Q14: =+P14*8 -> 640 | R14: 80 | S14: =+R14*9 -> 720 | T14: =+T13 -> 6 | U14: =+IF(((B14-80)>0),((B14-80)*T14),0) -> 342 | V14: =+V13 -> 1.65 | W14: =+V14*2*B14*10 -> 4521 | AF14: =+A14 -> DENILIQUIN | AG14: =+H94-B94 -> 35798.85 | AH14: =+CEILING(AG14*1.36,10)+D107 -> 56890
A15: ECHUCA | B15: 71 | C15: =+C14 -> 3.3 | D15: 80 | E15: =+C15*B15 -> 234.3 | F15: =+C15*B15 -> 234.3 | G15: =+C15*B15*6 -> 1405.8 | H15: =+C15*B15 -> 234.3 | I15: 63 | J15: =+I15*35 -> 2205 | K15: 230 | L15: =+K15*60 -> 13800 | M15: =+M14 -> 4 | N15: =+B15-80 -> -9 | O15: =IF((N15>0),(N15*M15*2),) -> 0 | P15: 60 | Q15: =+P15*8 -> 480 | R15: 55 | S15: =+R15*9 -> 495 | T15: =+T14 -> 6 | U15: =+IF(((B15-80)>0),((B15-80)*T15),0) -> 0 | V15: =+V14 -> 1.65 | W15: =+V15*2*B15*10 -> 2343 | AF15: =+A15 -> ECHUCA | AG15: =+I94-B94 -> 9970.05 | AH15: =+CEILING(AG15*1.36,10) -> 13560
A16: EUROA | B16: 49 | C16: =+C15 -> 3.3 | D16: 90 | E16: =+C16*B16 -> 161.7 | F16: =+C16*B16 -> 161.7 | G16: =+C16*B16*6 -> 970.2 | H16: =+C16*B16 -> 161.7 | I16: 63 | J16: =+I16*35 -> 2205 | K16: 257 | L16: =+K16*60 -> 15420 | M16: =+M15 -> 4 | N16: =+B16-80 -> -31 | O16: =IF((N16>0),(N16*M16*2),) -> 0 | P16: 55 | Q16: =+P16*8 -> 440 | R16: 52 | S16: =+R16*9 -> 468 | T16: =+T15 -> 6 | U16: =+IF(((B16-80)>0),((B16-80)*T16),0) -> 0 | V16: =+V15 -> 1.65 | W16: =+V16*2*B16*10 -> 1617 | AF16: =+A16 -> EUROA | AG16: =+J94-B94 -> 7887.45 | AH16: =+CEILING(AG16*1.36,10) -> 10730
A17: FINLEY | B17: 101 | C17: =+C16 -> 3.3 | D17: =+D13 -> 150 | E17: =+C17*B17 -> 333.3 | F17: =+C17*B17 -> 333.3 | G17: =+C17*B17*6 -> 1999.8 | H17: =+C17*B17 -> 333.3 | I17: 85 | J17: =+I17*35 -> 2975 | K17: 247 | L17: =+K17*60 -> 14820 | M17: =+M16 -> 4 | N17: =+B17-80 -> 21 | O17: =IF((N17>0),(N17*M17*2),) -> 168 | P17: 80 | Q17: =+P17*8 -> 640 | R17: 80 | S17: =+R17*9 -> 720 | T17: =+T16 -> 6 | U17: =+IF(((B17-80)>0),((B17-80)*T17),0) -> 126 | V17: =+V16 -> 1.65 | W17: =+V17*2*B17*10 -> 3333 | AF17: =+A17 -> FINLEY | AG17: =+K94-B94 -> 23585.05 | AH17: =+CEILING(AG17*1.36,10)+D107 -> 40280
A18: KATANDRA | B18: 29 | C18: =+C17 -> 3.3 | D18: =+D10 -> 110 | E18: =+C18*B18 -> 95.7 | F18: =+C18*B18 -> 95.7 | G18: =+C18*B18*6 -> 574.2 | H18: =+C18*B18 -> 95.7 | I18: 65 | J18: =+I18*35 -> 2275 | K18: 223 | L18: =+K18*60 -> 13380 | M18: =+M17 -> 4 | N18: =+B18-80 -> -51 | O18: =IF((N18>0),(N18*M18*2),) -> 0 | P18: 65 | Q18: =+P18*8 -> 520 | R18: 60 | S18: =+R18*9 -> 540 | T18: =+T17 -> 6 | U18: =+IF(((B18-80)>0),((B18-80)*T18),0) -> 0 | V18: =+V17 -> 1.65 | W18: =+V18*2*B18*10 -> 957 | AF18: =+A18 -> KATANDRA | AG18: =+L94-B94 -> 5508.45 | AH18: =+CEILING(AG18*1.36,10) -> 7500
A19: KOONDROOK | B19: 158 | C19: =+C18 -> 3.3 | D19: =+D14 -> 150 | E19: =+C19*B19 -> 521.4 | F19: =+C19*B19 -> 521.4 | G19: =+C19*B19*6 -> 3128.4 | H19: =+C19*B19 -> 521.4 | I19: 85 | J19: =+I19*35 -> 2975 | K19: 345 | L19: =+K19*60 -> 20700 | M19: =+M18 -> 4 | N19: =+B19-80 -> 78 | O19: =IF((N19>0),(N19*M19*2),) -> 624 | P19: 80 | Q19: =+P19*8 -> 640 | R19: 80 | S19: =+R19*9 -> 720 | T19: =+T18 -> 6 | U19: =+IF(((B19-80)>0),((B19-80)*T19),0) -> 468 | V19: =+V18 -> 1.65 | W19: =+V19*2*B19*10 -> 5214 | AF19: =+A19 -> KOONDROOK | AG19: =+M94-B94 -> 36608.15 | AH19: =+CEILING(AG19*1.36,10) -> 49790
A20: KYABRAM | B20: 37 | C20: =+C19 -> 3.3 | D20: 50 | E20: =+C20*B20 -> 122.1 | F20: =+C20*B20 -> 122.1 | G20: =+C20*B20*6 -> 732.6 | H20: =+C20*B20 -> 122.1 | I20: 63 | J20: =+I20*35 -> 2205 | K20: 230 | L20: =+K20*60 -> 13800 | M20: =+M19 -> 4 | N20: =+B20-80 -> -43 | O20: =IF((N20>0),(N20*M20*2),) -> 0 | P20: 75 | Q20: =+P20*8 -> 600 | R20: 52 | S20: =+R20*9 -> 468 | T20: =+T19 -> 6 | U20: =+IF(((B20-80)>0),((B20-80)*T20),0) -> 0 | V20: =+V19 -> 1.65 | W20: =+V20*2*B20*10 -> 1221 | AF20: =+A20 -> KYABRAM | AG20: =+N94-B94 -> 4175.85 | AH20: =+CEILING(AG20*1.36,10) -> 5680
A21: MANSFIELD | B21: 125 | C21: =+C20 -> 3.3 | D21: 110 | E21: =+C21*B21 -> 412.5 | F21: =+C21*B21 -> 412.5 | G21: =+C21*B21*6 -> 2475 | H21: =+C21*B21 -> 412.5 | I21: 85 | J21: =+I21*35 -> 2975 | K21: 279 | L21: =+K21*60 -> 16740 | M21: =+M20 -> 4 | N21: =+B21-80 -> 45 | O21: =IF((N21>0),(N21*M21*2),) -> 360 | P21: 70 | Q21: =+P21*8 -> 560 | R21: 80 | S21: =+R21*9 -> 720 | T21: =+T20 -> 6 | U21: =+IF(((B21-80)>0),((B21-80)*T21),0) -> 270 | V21: =+V20 -> 1.65 | W21: =+V21*2*B21*10 -> 4125 | AF21: =+A21 -> MANSFIELD | AG21: =+O94-B94 -> 31259.25 | AH21: =+CEILING(AG21*1.36,10) -> 42520
A22: MATHOURA | B22: 103 | C22: =+C21 -> 3.3 | D22: =+D19 -> 150 | E22: =+C22*B22 -> 339.9 | F22: =+C22*B22 -> 339.9 | G22: =+C22*B22*6 -> 2039.4 | H22: =+C22*B22 -> 339.9 | I22: 85 | J22: =+I22*35 -> 2975 | K22: =+K14 -> 358 | L22: =+K22*60 -> 21480 | M22: =+M21 -> 4 | N22: =+B22-80 -> 23 | O22: =IF((N22>0),(N22*M22*2),) -> 184 | P22: 80 | Q22: =+P22*8 -> 640 | R22: 80 | S22: =+R22*9 -> 720 | T22: =+T21 -> 6 | U22: =+IF(((B22-80)>0),((B22-80)*T22),0) -> 138 | V22: =+V21 -> 1.65 | W22: =+V22*2*B22*10 -> 3399 | AF22: =+A22 -> MATHOURA | AG22: =+P94-B94 -> 31293.65 | AH22: =+CEILING(AG22*1.36,10)+D107 -> 50760
A23: MURCHISON | B23: 43 | C23: =+C22 -> 3.3 | D23: 90 | E23: =+C23*B23 -> 141.9 | F23: =+C23*B23 -> 141.9 | G23: =+C23*B23*6 -> 851.4 | H23: =+C23*B23 -> 141.9 | I23: 65 | J23: =+I23*35 -> 2275 | K23: 218 | L23: =+K23*60 -> 13080 | M23: =+M22 -> 4 | N23: =+B23-80 -> -37 | O23: =IF((N23>0),(N23*M23*2),) -> 0 | P23: 55 | Q23: =+P23*8 -> 440 | R23: 52 | S23: =+R23*9 -> 468 | T23: =+T22 -> 6 | U23: =+IF(((B23-80)>0),((B23-80)*T23),0) -> 0 | V23: =+V22 -> 1.65 | W23: =+V23*2*B23*10 -> 1419 | AF23: =+A23 -> MURCHISON | AG23: =+Q94-B94 -> 4961.65 | AH23: =+CEILING(AG23*1.36,10) -> 6750
A24: NAGAMBIE | B24: 60 | C24: =+C23 -> 3.3 | D24: 70 | E24: =+C24*B24 -> 198 | F24: =+C24*B24 -> 198 | G24: =+C24*B24*6 -> 1188 | H24: =+C24*B24 -> 198 | I24: 65 | J24: =+I24*35 -> 2275 | K24: 210 | L24: =+K24*60 -> 12600 | M24: =+M23 -> 4 | N24: =+B24-80 -> -20 | O24: =IF((N24>0),(N24*M24*2),) -> 0 | P24: 50 | Q24: =+P24*8 -> 400 | R24: 54 | S24: =+R24*9 -> 486 | T24: =+T23 -> 6 | U24: =+IF(((B24-80)>0),((B24-80)*T24),0) -> 0 | V24: =+V23 -> 1.65 | W24: =+V24*2*B24*10 -> 1980 | AF24: =+A24 -> NAGAMBIE | AG24: =+R94-B94 -> 7170.75 | AH24: =+CEILING(AG24*1.36,10) -> 9760
A25: NATHALIA | B25: 40 | C25: =+C24 -> 3.3 | D25: 70 | E25: =+C25*B25 -> 132 | F25: =+C25*B25 -> 132 | G25: =+C25*B25*6 -> 792 | H25: =+C25*B25 -> 132 | I25: 63 | J25: =+I25*35 -> 2205 | K25: 232 | L25: =+K25*60 -> 13920 | M25: =+M24 -> 4 | N25: =+B25-80 -> -40 | O25: =IF((N25>0),(N25*M25*2),) -> 0 | P25: 65 | Q25: =+P25*8 -> 520 | R25: 52 | S25: =+R25*9 -> 468 | T25: =+T24 -> 6 | U25: =+IF(((B25-80)>0),((B25-80)*T25),0) -> 0 | V25: =+V24 -> 1.65 | W25: =+V25*2*B25*10 -> 1320 | AF25: =+A25 -> NATHALIA | AG25: =+S94-B94 -> 5623.75 | AH25: =+CEILING(AG25*1.36,10) -> 7650
A26: NUMURKAH | B26: 35 | C26: =+C25 -> 3.3 | D26: 60 | E26: =+C26*B26 -> 115.5 | F26: =+C26*B26 -> 115.5 | G26: =+C26*B26*6 -> 693 | H26: =+C26*B26 -> 115.5 | I26: 51 | J26: =+I26*35 -> 1785 | K26: 220 | L26: =+K26*60 -> 13200 | M26: =+M25 -> 4 | N26: =+B26-80 -> -45 | O26: =IF((N26>0),(N26*M26*2),) -> 0 | P26: 55 | Q26: =+P26*8 -> 440 | R26: 44 | S26: =+R26*9 -> 396 | T26: =+T25 -> 6 | U26: =+IF(((B26-80)>0),((B26-80)*T26),0) -> 0 | V26: =+V25 -> 1.65 | W26: =+V26*2*B26*10 -> 1155 | AF26: =+A26 -> NUMURKAH | AG26: =+T94-B94 -> 3200.25 | AH26: =+CEILING(AG26*1.36,10) -> 4360
A27: ROCHESTER | B27: 70 | C27: =+C26 -> 3.3 | D27: 90 | E27: =+C27*B27 -> 231 | F27: =+C27*B27 -> 231 | G27: =+C27*B27*6 -> 1386 | H27: =+C27*B27 -> 231 | I27: 65 | J27: =+I27*35 -> 2275 | K27: 256 | L27: =+K27*60 -> 15360 | M27: =+M26 -> 4 | N27: =+B27-80 -> -10 | O27: =IF((N27>0),(N27*M27*2),) -> 0 | P27: 75 | Q27: =+P27*8 -> 600 | R27: 54 | S27: =+R27*9 -> 486 | T27: =+T26 -> 6 | U27: =+IF(((B27-80)>0),((B27-80)*T27),0) -> 0 | V27: =+V26 -> 1.65 | W27: =+V27*2*B27*10 -> 2310 | AF27: =+A27 -> ROCHESTER | AG27: =+U94-B94 -> 11533.75 | AH27: =+CEILING(AG27*1.36,10) -> 15690
A28: RUSHWORTH | B28: 48 | C28: =+C27 -> 3.3 | D28: 90 | E28: =+C28*B28 -> 158.4 | F28: =+C28*B28 -> 158.4 | G28: =+C28*B28*6 -> 950.4 | H28: =+C28*B28 -> 158.4 | I28: 65 | J28: =+I28*35 -> 2275 | K28: 242 | L28: =+K28*60 -> 14520 | M28: =+M27 -> 4 | N28: =+B28-80 -> -32 | O28: =IF((N28>0),(N28*M28*2),) -> 0 | P28: 80 | Q28: =+P28*8 -> 640 | R28: 52 | S28: =+R28*9 -> 468 | T28: =+T27 -> 6 | U28: =+IF(((B28-80)>0),((B28-80)*T28),0) -> 0 | V28: =+V27 -> 1.65 | W28: =+V28*2*B28*10 -> 1584 | AF28: =+A28 -> RUSHWORTH | AG28: =+V94-B94 -> 6488.15 | AH28: =+CEILING(AG28*1.36,10) -> 8830
A29: SEYMOUR | B29: 86 | C29: =+C28 -> 3.3 | D29: 110 | E29: =+C29*B29 -> 283.8 | F29: =+C29*B29 -> 283.8 | G29: =+C29*B29*6 -> 1702.8 | H29: =+C29*B29 -> 283.8 | I29: 65 | J29: =+I29*35 -> 2275 | K29: 220 | L29: =+K29*60 -> 13200 | M29: =+M28 -> 4 | N29: =+B29-80 -> 6 | O29: =IF((N29>0),(N29*M29*2),) -> 48 | P29: 55 | Q29: =+P29*8 -> 440 | R29: 54 | S29: =+R29*9 -> 486 | T29: =+T28 -> 6 | U29: =+IF(((B29-80)>0),((B29-80)*T29),0) -> 36 | V29: =+V28 -> 1.65 | W29: =+V29*2*B29*10 -> 2838 | AF29: =+A29 -> SEYMOUR | AG29: =+W94-B94 -> 11581.55 | AH29: =+CEILING(AG29*1.36,10) -> 15760
A30: STANHOPE | B30: 42 | C30: =+C29 -> 3.3 | D30: 60 | E30: =+C30*B30 -> 138.6 | F30: =+C30*B30 -> 138.6 | G30: =+C30*B30*6 -> 831.6 | H30: =+C30*B30 -> 138.6 | I30: 63 | J30: =+I30*35 -> 2205 | K30: 232 | L30: =+K30*60 -> 13920 | M30: =+M29 -> 4 | N30: =+B30-80 -> -38 | O30: =IF((N30>0),(N30*M30*2),) -> 0 | P30: 80 | Q30: =+P30*8 -> 640 | R30: 52 | S30: =+R30*9 -> 468 | T30: =+T29 -> 6 | U30: =+IF(((B30-80)>0),((B30-80)*T30),0) -> 0 | V30: =+V29 -> 1.65 | W30: =+V30*2*B30*10 -> 1386 | AF30: =+A30 -> STANHOPE | AG30: =+X94-B94 -> 5502.35 | AH30: =+CEILING(AG30*1.36,10) -> 7490
A31: STRATHMERTON | B31: 56 | C31: =+C30 -> 3.3 | D31: 70 | E31: =+C31*B31 -> 184.8 | F31: =+C31*B31 -> 184.8 | G31: =+C31*B31*6 -> 1108.8 | H31: =+C31*B31 -> 184.8 | I31: 65 | J31: =+I31*35 -> 2275 | K31: 216 | L31: =+K31*60 -> 12960 | M31: =+M30 -> 4 | N31: =+B31-80 -> -24 | O31: =IF((N31>0),(N31*M31*2),) -> 0 | P31: 70 | Q31: =+P31*8 -> 560 | R31: 52 | S31: =+R31*9 -> 468 | T31: =+T30 -> 6 | U31: =+IF(((B31-80)>0),((B31-80)*T31),0) -> 0 | V31: =+V30 -> 1.65 | W31: =+V31*2*B31*10 -> 1848 | AF31: =+A31 -> STRATHMERTON | AG31: =+Y94-B94 -> 6853.55 | AH31: =+CEILING(AG31*1.36,10) -> 9330
A32: TATURA | B32: 20 | C32: =+C31 -> 3.3 | D32: =+D8 -> 45.45 | E32: =+C32*B32 -> 66 | F32: =+C32*B32 -> 66 | G32: =+C32*B32*6 -> 396 | H32: =+C32*B32 -> 66 | I32: 51 | J32: =+I32*35 -> 1785 | K32: 210 | L32: =+K32*60 -> 12600 | M32: =+M31 -> 4 | N32: =+B32-80 -> -60 | O32: =IF((N32>0),(N32*M32*2),) -> 0 | P32: 60 | Q32: =+P32*8 -> 480 | R32: 44 | S32: =+R32*9 -> 396 | T32: =+T31 -> 6 | U32: =+IF(((B32-80)>0),((B32-80)*T32),0) -> 0 | V32: =+V31 -> 1.65 | W32: =+V32*2*B32*10 -> 660 | AF32: =+A32 -> TATURA | AG32: =+Z94-B94 -> 890 | AH32: =+CEILING(AG32*1.36,10) -> 1220
A33: TONGALA | B33: 57 | C33: =+C32 -> 3.3 | D33: 80 | E33: =+C33*B33 -> 188.1 | F33: =+C33*B33 -> 188.1 | G33: =+C33*B33*6 -> 1128.6 | H33: =+C33*B33 -> 188.1 | I33: 65 | J33: =+I33*35 -> 2275 | K33: 230 | L33: =+K33*60 -> 13800 | M33: =+M32 -> 4 | N33: =+B33-80 -> -23 | O33: =IF((N33>0),(N33*M33*2),) -> 0 | P33: 85 | Q33: =+P33*8 -> 680 | R33: 52 | S33: =+R33*9 -> 468 | T33: =+T32 -> 6 | U33: =+IF(((B33-80)>0),((B33-80)*T33),0) -> 0 | V33: =+V32 -> 1.65 | W33: =+V33*2*B33*10 -> 1881 | AF33: =+A33 -> TONGALA | AG33: =+AA94-B94 -> 7282.85 | AH33: =+CEILING(AG33*1.36,10) -> 9910
A34: TUNGAMAH | B34: 59 | C34: =+C33 -> 3.3 | D34: =+D10 -> 110 | E34: =+C34*B34 -> 194.7 | F34: =+C34*B34 -> 194.7 | G34: =+C34*B34*6 -> 1168.2 | H34: =+C34*B34 -> 194.7 | I34: 65 | J34: =+I34*35 -> 2275 | K34: 240 | L34: =+K34*60 -> 14400 | M34: =+M33 -> 4 | N34: =+B34-80 -> -21 | O34: =IF((N34>0),(N34*M34*2),) -> 0 | P34: 70 | Q34: =+P34*8 -> 560 | R34: 65 | S34: =+R34*9 -> 585 | T34: =+T33 -> 6 | U34: =+IF(((B34-80)>0),((B34-80)*T34),0) -> 0 | V34: =+V33 -> 1.65 | W34: =+V34*2*B34*10 -> 1947 | AF34: =+A34 -> TUNGAMAH | AG34: =+AB94-B94 -> 10890.45 | AH34: =+CEILING(AG34*1.36,10) -> 14820
A35: YARRAWONGA | B35: 78 | C35: =+C34 -> 3.3 | D35: 80 | E35: =+C35*B35 -> 257.4 | F35: =+C35*B35 -> 257.4 | G35: =+C35*B35*6 -> 1544.4 | H35: =+C35*B35 -> 257.4 | I35: 65 | J35: =+I35*35 -> 2275 | K35: 220 | L35: =+K35*60 -> 13200 | M35: =+M34 -> 4 | N35: =+B35-80 -> -2 | O35: =IF((N35>0),(N35*M35*2),) -> 0 | P35: 65 | Q35: =+P35*8 -> 520 | R35: 54 | S35: =+R35*9 -> 486 | T35: =+T34 -> 6 | U35: =+IF(((B35-80)>0),((B35-80)*T35),0) -> 0 | V35: =+V34 -> 1.65 | W35: =+V35*2*B35*10 -> 2574 | AF35: =+A35 -> YARRAWONGA | AG35: =+AC94-B94 -> 11218.15 | AH35: =+CEILING(AG35*1.36,10) -> 15260
A36: YEA | B36: 119 | C36: =+C35 -> 3.3 | D36: =+D22 -> 150 | E36: =+C36*B36 -> 392.7 | F36: =+C36*B36 -> 392.7 | G36: =(+VALUE(B36))*1.65 -> 196.35 | H36: =+C36*B36 -> 392.7 | I36: 85 | J36: =+I36*35 -> 2975 | K36: 295 | L36: =+K36*60 -> 17700 | M36: =+M35 -> 4 | N36: =+B36-80 -> 39 | O36: =IF((N36>0),(N36*M36*2),) -> 312 | P36: 80 | Q36: =+P36*8 -> 640 | R36: 80 | S36: =+R36*9 -> 720 | T36: =+T35 -> 6 | U36: =+IF(((B36-80)>0),((B36-80)*T36),0) -> 234 | V36: =+V35 -> 1.65 | W36: =+V36*2*B36*10 -> 3927 | AF36: =+A36 -> YEA | AG36: =+AD94-B94 -> 28069.6 | AH36: =+CEILING(AG36*1.36,10) -> 38180
B38: 3630 | C38: 3714 | D38: 3664 | E38: 3671 | F38: 3644 | G38: 3568 | H38: 2710 | I38: 3564 | J38: 3666 | K38: 2713 | L38: 3634 | M38: 3580 | N38: 3620 | O38: 3722 | P38: 2710 | Q38: 3610 | R38: 3608 | S38: 3638 | T38: 3636 | U38: 3561 | V38: 3612 | W38: 3660 | X38: 3623 | Y38: 3641 | Z38: 3616 | AA38: 3621 | AB38: 3728 | AC38: 3730 | AD38: 3717
B39: SHEPPARTON | C39: ALEXANDRA | D39: AVENEL | E39: BENALLA | F39: COBRAM | G39: COHUNA | H39: DENILIQUIN | I39: ECHUCA | J39: EUROA | K39: FINLEY | L39: KATANDRA | M39: KOONDROOK | N39: KYABRAM | O39: MANSFIELD | P39: MATHOURA | Q39: MURCHISON | R39: NAGAMBIE | S39: NATHALIA | T39: NUMURKAH | U39: ROCHESTER | V39: RUSHWORTH | W39: SEYMOUR | X39: STANHOPE | Y39: STRATHMERTON | Z39: TATURA | AA39: TONGALA | AB39: TUNGAMAH | AC39: YARRAWONGA | AD39: YEA
A40: Km | C40: 120km | D40: 71km | E40: 62km | F40: 71km | G40: 135km | H40: 137KM | I40: 71km | J40: 49km | K40: 101km | L40: 29km | M40: 158km | N40: 37km | O40: 125km | P40: 103km | Q40: 43km | R40: 60km | S40: 40km | T40: 35km | U40: 70km | V40: 48km | W40: 86km | X40: 42km | Y40: 56km | Z40: 20km | AA40: 57km | AB40: 59km | AC40: 78km | AD40: 119km
A41: Bunnings delivery - (205, 350, 385, 395) Added extra delivery Load 5 on 545 Fix materials | B41: =+D8*5 -> 227.25 | C41: =+D9*5 -> 750 | D41: =+D10*5 -> 550 | E41: =+D11*5 -> 350 | F41: =+D12*5 -> 350 | G41: =+D13*5 -> 750 | H41: =+D14*5 -> 750 | I41: =+D15*5 -> 400 | J41: =+D16*5 -> 450 | K41: =+D17*5 -> 750 | L41: =+D18*5 -> 550 | M41: =+D19*5 -> 750 | N41: =+D20*5 -> 250 | O41: =+D21*5 -> 550 | P41: =+D22*5 -> 750 | Q41: =+D23*5 -> 450 | R41: =+D24*5 -> 350 | S41: =+D25*5 -> 350 | T41: =+D26*5 -> 300 | U41: =+D27*5 -> 450 | V41: =+D28*5 -> 450 | W41: =+D29*5 -> 550 | X41: =+D30*5 -> 300 | Y41: =+D31*5 -> 350 | Z41: =+D32*5 -> 227.25 | AA41: =+D33*5 -> 400 | AB41: =+D34*5 -> 550 | AC41: =+D35*5 -> 400 | AD41: =+D36*5 -> 750
A42: Bunting & pickets at Benalla | E42: 150
A43: Drafting Inspection travel | B43: =E8 -> 66 | C43: =E9 -> 396 | D43: =E10 -> 234.3 | E43: =E11 -> 204.6 | F43: =E12 -> 234.3 | G43: =E13 -> 445.5 | H43: =E14 -> 452.1 | I43: =E15 -> 234.3 | J43: =E16 -> 161.7 | K43: =E17 -> 333.3 | L43: =E18 -> 95.7 | M43: =E19 -> 521.4 | N43: =E20 -> 122.1 | O43: =E21 -> 412.5 | P43: =E22 -> 339.9 | Q43: =E23 -> 141.9 | R43: =E24 -> 198 | S43: =E25 -> 132 | T43: =E26 -> 115.5 | U43: =E27 -> 231 | V43: =E28 -> 158.4 | W43: =E29 -> 283.8 | X43: =E30 -> 138.6 | Y43: =E31 -> 184.8 | Z43: =E32 -> 66 | AA43: =E33 -> 188.1 | AB43: =E34 -> 194.7 | AC43: =E35 -> 257.4 | AD43: =E36 -> 392.7
A44: Soil test (020) | B44: 0 | C44: 340 | D44: 220 | E44: 220 | F44: 140 | G44: 220 | H44: 220 | I44: 0 | J44: 220 | K44: 220 | L44: 140 | M44: 220 | N44: 115 | O44: 340 | P44: 140 | Q44: 140 | R44: 220 | S44: 140 | T44: 140 | U44: 220 | V44: 140 | W44: 220 | X44: 140 | Y44: 220 | Z44: 140 | AA44: 220 | AB44: 220 | AC44: 0 | AD44: 340
A45: Water connection (050) | O45: 78
A46: Building Surveyour (080) | B46: 0 | C46: 400 | D46: 0 | E46: 0 | F46: 0 | G46: 0 | H46: 400 | I46: 0 | J46: 0 | K46: 400 | L46: 0 | M46: 400 | N46: 0 | O46: 400 | P46: 0 | Q46: 0 | R46: 0 | S46: 0 | T46: 0 | U46: 0 | V46: 0 | W46: 0 | X46: 0 | Y46: 0 | Z46: 0 | AA46: 0 | AB46: 0 | AC46: 0 | AD46: 400
A47: Council charges | D47: 1500 | W47: 1000
A48: Temp fencing travel (100) | B48: =F8 -> 66 | C48: =F9 -> 396 | D48: =+F10 -> 234.3 | E48: =F11 -> 204.6 | F48: =F12 -> 234.3 | G48: =F13 -> 445.5 | H48: =F14 -> 452.1 | I48: =F15 -> 234.3 | J48: =F16 -> 161.7 | K48: =F17 -> 333.3 | L48: =F18 -> 95.7 | M48: =F19 -> 521.4 | N48: =F20 -> 122.1 | O48: =F21 -> 412.5 | P48: =F22 -> 339.9 | Q48: =F23 -> 141.9 | R48: =F24 -> 198 | S48: =F25 -> 132 | T48: =F26 -> 115.5 | U48: =F27 -> 231 | V48: =F28 -> 158.4 | W48: =F29 -> 283.8 | X48: =F30 -> 138.6 | Y48: =F31 -> 184.8 | Z48: =F32 -> 66 | AA48: =F33 -> 188.1 | AB48: =F34 -> 194.7 | AC48: =F35 -> 257.4 | AD48: =F36 -> 392.7
A49: Toilet hire (105) | B49: 0 | C49: 50 | D49: 50 | E49: 50 | F49: 50 | G49: 50 | H49: 50 | I49: 50 | J49: 50 | K49: 50 | L49: 0 | M49: 50 | N49: 0 | O49: 50 | P49: 50 | Q49: 0 | R49: 50 | S49: 0 | T49: 0 | U49: 50 | V49: 50 | W49: 50 | X49: 0 | Y49: 50 | Z49: 0 | AA49: 50 | AB49: 50 | AC49: 50 | AD49: 50
A50: Forklift travel (105) | B50: 0 | C50: 290 | D50: 190 | E50: 190 | F50: 190 | G50: 350 | H50: 350 | I50: 190 | J50: 150 | K50: 290 | L50: 150 | M50: 350 | N50: 150 | O50: 270 | P50: 290 | Q50: 130 | R50: 150 | S50: 150 | T50: 90 | U50: 190 | V50: 150 | W50: 210 | X50: 150 | Y50: 190 | Z50: 90 | AA50: 150 | AB50: 190 | AC50: 190 | AD50: 290
A51: Skip truck travel (115) | B51: =G8 -> 396 | C51: =G9 -> 2376 | D51: =G10 -> 1405.8 | E51: =G11 -> 1227.6 | F51: =G12 -> 1405.8 | G51: =G13 -> 2673 | H51: =G14 -> 2712.6 | I51: =G15 -> 1405.8 | J51: =G16 -> 970.2 | K51: =G17 -> 1999.8 | L51: =G18 -> 574.2 | M51: =G19 -> 3128.4 | N51: =G20 -> 732.6 | O51: =G21 -> 2475 | P51: =G22 -> 2039.4 | Q51: =G23 -> 851.4 | R51: =G24 -> 1188 | S51: =G25 -> 792 | T51: =G26 -> 693 | U51: =G27 -> 1386 | V51: =G28 -> 950.4 | W51: =G29 -> 1702.8 | X51: =G30 -> 831.6 | Y51: =G31 -> 1108.8 | Z51: =G32 -> 396 | AA51: =G33 -> 1128.6 | AB51: =G34 -> 1168.2 | AC51: =G35 -> 1544.4 | AD51: =G36 -> 196.35
A52: Set out travel (125) | B52: =+B61 -> 66 | C52: =+C61 -> 396 | D52: =+D61 -> 234.3 | E52: =+E61 -> 204.6 | F52: =+F61 -> 234.3 | G52: =+G61 -> 445.5 | H52: =+H61 -> 452.1 | I52: =+I61 -> 234.3 | ... AD52: =+AD61 -> 392.7
A53: Drainer travel (135) | C53: 700 | D53: 700 | E53: 780 | F53: 700 | G53: 700 | H53: 700 | I53: 0 | J53: 700 | K53: 700 | L53: 700 | M53: 700 | N53: 700 | O53: 700 | P53: 700 | Q53: 700 | R53: 700 | S53: 700 | T53: 700 | U53: 700 | V53: 700 | W53: 700 | X53: 700 | Y53: 700 | Z53: 700 | AA53: 700 | AB53: 700 | AC53: 760 | AD53: 700
A54: Stormy travel
A55: Post Slab Inspection Travel (135)
A56: Waffle pod delivery (145) | B56: 870 | C56: 800 | D56: 670 | E56: 1030 | F56: 1270 | G56: 1500 | H56: 1500 | I56: 1070 | J56: 770 | K56: 1500 | L56: 1200 | M56: 1500 | N56: 1030 | O56: 1030 | P56: 1500 | Q56: 780 | R56: 680 | S56: 1140 | T56: 1120 | U56: 1000 | V56: 750 | W56: 600 | X56: 950 | Y56: 1230 | Z56: 880 | AA56: 1050 | AB56: 1400 | AC56: 1400 | AD56: 650
A57: Crusher dust (allow 35 M3) | B57: =+J8 -> 1785 | C57: =+J9 -> 2975 | D57: =+J10 -> 2275 | E57: =+J11 -> 2275 | F57: =+J12 -> 2275 | G57: =+J13 -> 2975 | H57: =+J14 -> 2975 | I57: =+J15 -> 2205 | J57: =+J16 -> 2205 | K57: =+J17 -> 2975 | L57: =+J18 -> 2275 | M57: =+J19 -> 2975 | N57: =+J20 -> 2205 | O57: =+J21 -> 2975 | P57: =+J22 -> 2975 | Q57: =+J23 -> 2275 | R57: =+J24 -> 2275 | S57: =+J25 -> 2205 | T57: =+J26 -> 1785 | U57: =+J27 -> 2275 | V57: =+J28 -> 2275 | W57: =+J29 -> 2275 | X57: =+J30 -> 2205 | Y57: =+J31 -> 2275 | Z57: =+J32 -> 1785 | AA57: =+J33 -> 2275 | AB57: =+J34 -> 2275 | AC57: =+J35 -> 2275 | AD57: =+J36 -> 2975
A58: Concreter machine travel (150) | C58: 1800 | D58: 350 | E58: 350 | F58: 350 | G58: 1800 | H58: 1800 | I58: 350 | K58: 350 | M58: 1800 | O58: 1800 | P58: 1800 | U58: 350 | W58: 350 | AB58: 350 | AC58: 350 | AD58: 1800
A59: Concreter labour travel (150) | C59: 650 | D59: 650 | G59: 650 | H59: 650 | I59: 850 | K59: 650 | M59: 650 | O59: 650 | P59: 650 | AD59: 1000
A60: Concreter labour accommodation | C60: 2000 | G60: 2000 | H60: 2000 | K60: 2000 | M60: 2000 | O60: 2000 | P60: 2000 | AD60: 2000
A61: Site scrape travel | B61: =+H8 -> 66 | C61: =+H9 -> 396 | D61: =+H10 -> 234.3 | E61: =+H11 -> 204.6 | F61: =+H12 -> 234.3 | G61: =+H13 -> 445.5 | H61: =+H14 -> 452.1 | I61: =+H15 -> 234.3 | J61: =+H16 -> 161.7 | K61: =+H17 -> 333.3 | L61: =+H18 -> 95.7 | M61: =+H19 -> 521.4 | N61: =+H20 -> 122.1 | O61: =+H21 -> 412.5 | P61: =+H22 -> 339.9 | Q61: =+H23 -> 141.9 | R61: =+H24 -> 198 | S61: =+H25 -> 132 | T61: =+H26 -> 115.5 | U61: =+H27 -> 231 | V61: =+H28 -> 158.4 | W61: =+H29 -> 283.8 | X61: =+H30 -> 138.6 | Y61: =+H31 -> 184.8 | Z61: =+H32 -> 66 | AA61: =+H33 -> 188.1 | AB61: =+H34 -> 194.7 | AC61: =+H35 -> 257.4 | AD61: =+H36 -> 392.7
A62: Concrete supply - allow 60 m3 (155) | B62: =+L8 -> 12600 | C62: =+L9 -> 17220 | D62: =+L10 -> 12600 | E62: =+L11 -> 14100 | F62: =+L12 -> 13200 | G62: =+L13 -> 20700 | H62: =+L14 -> 21480 | I62: =+L15 -> 13800 | J62: =+L16 -> 15420 | K62: =+L17 -> 14820 | L62: =+L17 -> 14820 | M62: =+L19 -> 20700 | N62: =+L20 -> 13800 | O62: =+L21 -> 16740 | P62: =+L22 -> 21480 | Q62: =+L23 -> 13080 | R62: =+L24 -> 12600 | S62: =+L25 -> 13920 | T62: =+L26 -> 13200 | U62: =+L27 -> 15360 | V62: =+L28 -> 14520 | W62: =+L29 -> 13200 | X62: =+L30 -> 13920 | Y62: =+L31 -> 12960 | Z62: =+L32 -> 12600 | AA62: =+L33 -> 13800 | AB62: =+L34 -> 14400 | AC62: =+L35 -> 13200 | AD62: =+L36 -> 17700
A63: Concrete pump travel (160) | B63: =+O8 -> 0 | C63: =+O9 -> 320 | D63: =+O10 -> 0 | E63: =+O11 -> 0 | F63: =+O12 -> 0 | G63: =+O13 -> 440 | H63: =+O14 -> 456 | I63: =+O15 -> 0 | J63: =+O16 -> 0 | K63: =+O17 -> 168 | L63: =+O18 -> 0 | M63: =+O19 -> 624 | N63: =+O20 -> 0 | O63: =+O21 -> 360 | P63: =+O22 -> 184 | Q63: =+O23 -> 0 | R63: =+O24 -> 0 | S63: =+O25 -> 0 | T63: =+O26 -> 0 | U63: =+O27 -> 0 | V63: =+O28 -> 0 | W63: =+O29 -> 48 | X63: =+O30 -> 0 | Y63: =+O31 -> 0 | Z63: =+O32 -> 0 | AA63: =+O33 -> 0 | AB63: =+O34 -> 0 | AC63: =+O35 -> 0 | AD63: =+O36 -> 312
A64: Trusses (200) | B64: 710 | C64: 1030 | D64: 720 | E64: 1020 | F64: 1150 | G64: 730 | H64: 990 | I64: 710 | J64: 800 | K64: 1330 | L64: 880 | M64: 930 | N64: 620 | O64: 1230 | Q64: 620 | R64: 620 | S64: 820 | T64: 930 | U64: 520 | V64: 520 | W64: 620 | X64: 620 | Y64: 1050 | Z64: 620 | AA64: 620 | AB64: 1070 | AC64: 1200 | AD64: 840
A65: Framer travel (210) | C65: 800 | G65: 400 | H65: 400 | K65: 400 | M65: 400 | O65: 400 | P65: 400 | Q65: 400 | AC65: 400 | AD65: 800
A66: Framer accommodation | C66: 2000 | G66: 2000 | H66: 2000 | K66: 2000 | M66: 2000 | O66: 2000 | P66: 2000 | AD66: 2000
A67: Roofing delivery (315) | C67: 1125 | D67: 650 | E67: 650 | F67: 650 | G67: 1125 | H67: 1125 | I67: 650 | J67: 650 | K67: 890 | M67: 1125 | O67: 1125 | P67: 890 | Q67: 650 | R67: 650 | S67: 650 | U67: 650 | V67: 650 | W67: 890 | X67: 650 | Y67: 650 | AA67: 650 | AB67: 650 | AC67: 650 | AD67: 1125
A68: Plumber travel (330) | C68: 400 | G68: 400 | H68: 400 | I68: 400 | K68: 400 | M68: 400 | O68: 400 | P68: 400 | AD68: 400
A69: Electrician travel (335) | C69: 300 | G69: 300 | H69: 300 | I69: 300 | K69: 300 | M69: 300 | O69: 300 | P69: 300 | AD69: 300
A70: Inspection fee | B70: 0 | C70: 200 | D70: 80 | E70: 80 | F70: 80 | G70: 200 | H70: 200 | I70: 80 | J70: 50 | K70: 80 | M70: 200 | N70: 50 | O70: 200 | P70: 200 | Q70: 50 | R70: 80 | S70: 50 | T70: 50 | U70: 80 | V70: 50 | W70: 80 | X70: 50 | Y70: 50 | AA70: 50 | AB70: 50 | AC70: 80 | AD70: 200
A71: Brick delivery for 8000 (340) | B71: =+Q8 -> 440 | C71: =+Q9 -> 520 | D71: =+Q10 -> 440 | E71: =+Q11 -> 440 | F71: =+Q12 -> 560 | G71: =+Q13 -> 640 | H71: =+Q14 -> 640 | I71: =+Q15 -> 480 | J71: =+Q16 -> 440 | K71: =+Q17 -> 640 | L71: =+Q18 -> 520 | M71: =+Q19 -> 640 | N71: =+Q20 -> 600 | O71: =+Q21 -> 560 | P71: =+Q22 -> 640 | Q71: =+Q23 -> 440 | R71: =+Q24 -> 400 | S71: =+Q25 -> 520 | T71: =+Q26 -> 440 | U71: =+Q27 -> 600 | V71: =+Q28 -> 640 | W71: =+Q29 -> 440 | X71: =+Q30 -> 640 | Y71: =+Q31 -> 560 | Z71: =+Q32 -> 480 | AA71: =+Q33 -> 680 | AB71: =+Q34 -> 560 | AC71: =+Q35 -> 520 | AD71: =+Q36 -> 640
A72: Brick sand 9 m3 (345) | B72: =+S8 -> 396 | C72: =+S9 -> 720 | D72: =+S10 -> 504 | E72: =+S11 -> 486 | F72: =+S12 -> 486 | G72: =+S13 -> 720 | H72: =+S14 -> 720 | I72: =+S15 -> 495 | J72: =+S16 -> 468 | K72: =+S17 -> 720 | L72: =+S18 -> 540 | M72: =+S19 -> 720 | N72: =+S20 -> 468 | O72: =+S21 -> 720 | P72: =+S22 -> 720 | Q72: =+S23 -> 468 | R72: =+S24 -> 486 | S72: =+S25 -> 468 | T72: =+S26 -> 396 | U72: =+S27 -> 486 | V72: =+S28 -> 468 | W72: =+S29 -> 486 | X72: =+S30 -> 468 | Y72: =+S31 -> 468 | Z72: =+S32 -> 396 | AA72: =+S33 -> 468 | AB72: =+S34 -> 585 | AC72: =+S35 -> 486 | AD72: =+S36 -> 720
A73: Bricklayer labour extra for 8000 (360) | O73: =8000*0.2 -> 1600
A74: Bricklayer travel (360) | C74: 600 | G74: 600 | H74: 600 | K74: 600 | M74: 600 | O74: 600 | P74: 600 | AD74: 600
A75: Eaves carpenter travel (390) | C75: 200 | G75: 200 | H75: 200 | K75: 200 | M75: 200 | O75: 200 | P75: 200 | AD75: 200
A76: Lock up travel (405) | B76: =+B52 -> 66 | C76: =+C52 -> 396 | D76: =+D52 -> 234.3 | E76: =+E52 -> 204.6 | F76: =+F52 -> 234.3 | G76: =+G52 -> 445.5 | H76: =+H52 -> 452.1 | I76: =+I52 -> 234.3 | ... AD76: =+AD52 -> 392.7
A77: Insulation walls (445) | C77: 85 | D77: 65 | E77: 65 | F77: 65 | G77: 85 | H77: 85 | I77: 65 | K77: 65 | M77: 85 | O77: 85 | P77: 85 | R77: 65 | U77: 65 | W77: 65 | AB77: 65 | AC77: 65 | AD77: 85
A78: Brick cleaner (450) | C78: 110 | D78: 60 | E78: 60 | F78: 60 | G78: 110 | H78: 110 | I78: 60 | J78: 60 | K78: 60 | M78: 110 | O78: 110 | P78: 110 | Q78: 60 | R78: 60 | U78: 60 | V78: 60 | W78: 60 | X78: 60 | Y78: 60 | AA78: 60 | AB78: 60 | AC78: 60 | AD78: 110
A79: Plaster delivery - allow 800 m2 (500) | C79: =0.4*800 -> 320 | D79: =0.4*800 -> 320 | E79: =0.4*800 -> 320 | F79: =0.4*800 -> 320 | G79: =0.4*800 -> 320 | H79: =0.4*800 -> 320 | I79: =0.4*800 -> 320 | J79: =0.4*800 -> 320 | K79: =0.4*800 -> 320 | M79: =0.4*800 -> 320 | O79: =0.4*800 -> 320 | P79: =0.4*800 -> 320 | R79: =0.4*800 -> 320 | U79: =0.4*800 -> 320 | W79: =0.4*800 -> 320 | Y79: =0.4*800 -> 320 | AA79: =0.4*800 -> 320 | AB79: =0.4*800 -> 320 | AC79: =0.4*800 -> 320 | AD79: =0.4*800 -> 320
A80: Plasterer travel (505) | C80: 832 | D80: 832 | E80: 832 | F80: 832 | G80: 832 | H80: 832 | M80: 832 | O80: 832 | P80: 832 | R80: 832 | U80: 832 | W80: 832 | AB80: 832 | AC80: 832 | AD80: 832
A81: Water proofer travel (510) | C81: 230 | D81: 115 | E81: 115 | F81: 115 | G81: 230 | H81: 230 | I81: 115 | J81: 115 | K81: 230 | M81: 230 | O81: 230 | P81: 230 | Q81: 115 | R81: 115 | S81: 115 | U81: 115 | V81: 115 | W81: 230 | X81: 115 | Y81: 115 | AA81: 115 | AB81: 115 | AC81: 115 | AD81: 230
A82: Stone benchtop (530) | C82: =+U9 -> 240 | D82: =+U10 -> 0 | E82: =+U11 -> 0 | F82: =+U12 -> 0 | G82: =+U13 -> 330 | H82: =+U14 -> 342 | I82: =+U15 -> 0 | J82: =+U16 -> 0 | K82: =+U17 -> 126 | L82: =+U18 -> 0 | M82: =+U19 -> 468 | N82: =+U20 -> 0 | O82: =+U21 -> 270 | P82: =+U22 -> 138 | Q82: =+U23 -> 0 | R82: =+U24 -> 0 | S82: =+U25 -> 0 | T82: =+U26 -> 0 | U82: =+U27 -> 0 | V82: =+U28 -> 0 | W82: =+U29 -> 36 | X82: =+U30 -> 0 | Y82: =+U31 -> 0 | Z82: =+U32 -> 0 | AA82: =+U33 -> 0 | AB82: =+U34 -> 0 | AC82: =+U35 -> 0 | AD82: =+U36 -> 234
A83: Fix carpenter travel (555) | C83: 200 | G83: 200 | H83: 200 | K83: 200 | M83: 200 | O83: 200 | P83: 200 | AD83: 200
A84: Fit off travel (565) | C84: 200 | G84: 200 | H84: 200 | K84: 200 | M84: 200 | O84: 200 | P84: 200 | AD84: 200
A85: Tiler travel (605) | C85: 200 | D85: 200 | E85: 200 | F85: 200 | G85: 200 | H85: 200 | I85: 200 | K85: 200 | M85: 200 | O85: 200 | P85: 200 | R85: 200 | U85: 200 | W85: 200 | AB85: 200 | AC85: 200 | AD85: 200
A86: Painter travel (610) | C86: 500 | G86: 500 | H86: 500 | K86: 500 | M86: 500 | O86: 500 | P86: 500 | AD86: 500
A87: Shower screens (615) | C87: 231 | D87: 139 | E87: 139 | F87: 139 | G87: 139 | H87: 139 | I87: 139 | J87: 38 | K87: 231 | L87: 38 | M87: 139 | N87: 38 | O87: 231 | P87: 231 | Q87: 38 | R87: 139 | S87: 38 | T87: 38 | U87: 139 | V87: 38 | W87: 139 | X87: 38 | Y87: 139 | Z87: 0 | AA87: 139 | AB87: 139 | AC87: 139 | AD87: 139
A88: Garage door (625) | B88: 200 | C88: 200 | D88: 200 | E88: 200 | F88: 200 | G88: 300 | H88: 300 | I88: 300 | J88: 200 | K88: 200 | L88: 300 | M88: 200 | N88: 200 | O88: 200 | P88: 300 | Q88: 200 | R88: 200 | S88: 200 | T88: 200 | U88: 200 | V88: 200 | W88: 200 | X88: 200 | Y88: 200 | Z88: 200 | AA88: 200 | AB88: 200 | AC88: 300 | AD88: 200
A89: Paving machine travel (640) | C89: 270 | D89: 270 | E89: 270 | F89: 270 | G89: 270 | H89: 270 | I89: 270 | K89: 270 | M89: 270 | O89: 270 | P89: 270 | R89: 270 | U89: 270 | W89: 270 | AB89: 270 | AC89: 270 | AD89: 270
A90: Insulation ceilings (675) | C90: =+C77 -> 85 | D90: =+D77 -> 65 | E90: =+E77 -> 65 | F90: =+F77 -> 65 | G90: =+G77 -> 85 | H90: =+H77 -> 85 | I90: =+I77 -> 65 | J90: =+J77 -> 0 | ... AD90: =+AD77 -> 85
A91: Site clean travel (included above)
A92: House clean (705) | C92: 200 | D92: 100 | E92: 100 | F92: 100 | G92: 200 | H92: 200 | I92: 100 | K92: 100 | M92: 200 | O92: 200 | P92: 200 | R92: 100 | U92: 100 | W92: 100 | AB92: 100 | AC92: 100 | AD92: 200
A93: Supervisor travel (710) | B93: =+W8 -> 660 | C93: =+W9 -> 3960 | D93: =+W10 -> 2343 | E93: =+W11 -> 2046 | F93: =+W12 -> 2343 | G93: =+W13 -> 4455 | H93: =+W14 -> 4521 | I93: =+W15 -> 2343 | J93: =+W16 -> 1617 | K93: =+W17 -> 3333 | L93: =+W18 -> 957 | M93: =+W19 -> 5214 | N93: =+W20 -> 1221 | O93: =+W21 -> 4125 | P93: =+W22 -> 3399 | Q93: =+W23 -> 1419 | R93: =+W24 -> 1980 | S93: =+W25 -> 1320 | T93: =+W26 -> 1155 | U93: =+W27 -> 2310 | V93: =+W28 -> 1584 | W93: =+W29 -> 2838 | X93: =+W30 -> 1386 | Y93: =+W31 -> 1848 | Z93: =+W32 -> 660 | AA93: =+W33 -> 1881 | AB93: =+W34 -> 1947 | AC93: =+W35 -> 2574 | AD93: =+W36 -> 3927
B94: =SUM(B41:B93) -> 18614.25 | C94: =SUM(C41:C93) -> 48409 | D94: =SUM(D41:D93) -> 29435.3 | E94: =SUM(E41:E93) -> 28833.6 | F94: =SUM(F41:F93) -> 28737.3 | G94: =SUM(G41:G93) -> 52806.5 | H94: =SUM(H41:H93) -> 54413.1 | I94: =SUM(I41:I93) -> 28584.3 | ... AD94: =SUM(AD41:AD93) -> 46683.85
B95: SHEPPARTON | C95: ALEXANDRA | D95: AVENEL | E95: BENALLA | F95: COBRAM | G95: COHUNA | H95: DENILIQUIN | I95: ECHUCA | J95: EUROA | K95: FINLEY | L95: KATANDRA | M95: KOONDROOK | N95: KYABRAM | O95: MANSFIELD | P95: MATHOURA | Q95: MURCHISON | R95: NAGAMBIE | S95: NATHALIA | T95: NUMURKAH | U95: ROCHESTER | V95: RUSHWORTH | W95: SEYMOUR | X95: STANHOPE | Y95: STRATHMERTON | Z95: TATURA | AA95: TONGALA | AB95: TUNGAMAH | AC95: YARRAWONGA | AD95: YEA | AE95: NSW
A98: NSW charges
A99: DA fee | B99: 1500
A100: Insurance | B100: 3200
A101: Floor waste | B101: 350
A102: Hi-impact poly | B102: 20
A103: Whirly bird | B103: 240
...

Sheet Estimator
B2: Base House Plan | C2: Price per sqm | D2: Tiles | E2: Carpets | H2: Pick the closest floor plan and add the items | N2: This sheet is good for adding area, NOT deleting
B3: =+Lifestyle!A14 -> Adelaide 18 | C3: =+Lifestyle!BS14 -> 0 | D3: =+Shepparton!#REF! -> #REF! | E3: =+Shepparton!#REF! -> #REF!
B4: =+Lifestyle!A15 -> Adelaide 21 | C4: =+Lifestyle!BS15 -> 0 | D4: =+Shepparton!#REF! -> #REF! | E4: =+Shepparton!#REF! -> #REF!
B5: =+Lifestyle!A16 -> Adelaide 22A | C5: =+Lifestyle!BS16 -> 0 | D5: =+Shepparton!#REF! -> #REF! | E5: =+Shepparton!#REF! -> #REF!
B6: =+Lifestyle!A17 -> Adelaide 22B | C6: =+Lifestyle!BS17 -> 0 | D6: =+Shepparton!#REF! -> #REF! | E6: =+Shepparton!#REF! -> #REF!
B7: =+Lifestyle!A18 -> Adelaide 24 | C7: =+Lifestyle!BS18 -> 0 | D7: =+Shepparton!#REF! -> #REF! | E7: =+Shepparton!#REF! -> #REF!
B8: =+Lifestyle!A19 -> Ashfield 24 | C8: =+Lifestyle!BS19 -> 0 | D8: =+Shepparton!#REF! -> #REF! | E8: =+Shepparton!#REF! -> #REF!
B9: =+Lifestyle!A20 -> Ashfield 30 | C9: =+Lifestyle!BS20 -> 0 | D9: =+Shepparton!#REF! -> #REF! | E9: =+Shepparton!#REF! -> #REF!
B10: =+Lifestyle!A21 -> Ashfield 34 | C10: =+Lifestyle!BS21 -> 0 | D10: =+Shepparton!#REF! -> #REF! | E10: =+Shepparton!#REF! -> #REF!
B11: =+Lifestyle!A22 -> Ashley 19 | C11: =+Lifestyle!BS22 -> 0 | D11: =+Shepparton!#REF! -> #REF! | E11: =+Shepparton!#REF! -> #REF!
B12: =+Lifestyle!A24 -> Ashley 22 | C12: =+Lifestyle!BS24 -> 0 | D12: =+Shepparton!#REF! -> #REF! | E12: =+Shepparton!#REF! -> #REF!
B13: =+Lifestyle!A26 -> Ashley 24 | C13: =+Lifestyle!BS26 -> 0 | D13: =+Shepparton!#REF! -> #REF! | E13: =+Shepparton!#REF! -> #REF!
B14: =+Lifestyle!A27 -> Ashley 25 | C14: =+Lifestyle!BS27 -> 0 | D14: =+Shepparton!#REF! -> #REF! | E14: =+Shepparton!#REF! -> #REF!
B15: =+Lifestyle!A28 -> Ashley 25A | C15: =+Lifestyle!BS28 -> 0 | D15: =+Shepparton!#REF! -> #REF! | E15: =+Shepparton!#REF! -> #REF!
B16: =+Lifestyle!A29 -> Ashley 26 | C16: =+Lifestyle!BS29 -> 0 | D16: =+Shepparton!#REF! -> #REF! | E16: =+Shepparton!#REF! -> #REF!
B17: =+Lifestyle!A30 -> Ashley 27 | C17: =+Lifestyle!BS30 -> 0 | D17: =+Shepparton!#REF! -> #REF! | E17: =+Shepparton!#REF! -> #REF!
B18: =+Lifestyle!A31 -> Ashley 28 | C18: =+Lifestyle!BS31 -> 0 | D18: =+Shepparton!#REF! -> #REF! | E18: =+Shepparton!#REF! -> #REF!
B19: =+Lifestyle!A34 -> Ballina 30 | C19: =+Lifestyle!BS34 -> 0 | D19: =+Shepparton!#REF! -> #REF! | E19: =+Shepparton!#REF! -> #REF!
B20: =+Lifestyle!A41 -> Bayview 23 | C20: =+Lifestyle!BS41 -> 0 | D20: =+Shepparton!#REF! -> #REF! | E20: =+Shepparton!#REF! -> #REF!
B21: =+Lifestyle!A42 -> Bayview 26 | C21: =+Lifestyle!BS42 -> 0 | D21: =+Shepparton!#REF! -> #REF! | E21: =+Shepparton!#REF! -> #REF!
B22: =+Lifestyle!A43 -> Bayview 30 | C22: =+Lifestyle!BS43 -> 0 | D22: =+Shepparton!#REF! -> #REF! | E22: =+Shepparton!#REF! -> #REF!
B23: =+Lifestyle!A44 -> Bondi 25 | C23: =+Lifestyle!BS44 -> 0 | D23: =+Shepparton!#REF! -> #REF! | E23: =+Shepparton!#REF! -> #REF!
B24: =+Lifestyle!A45 -> Bondi 31 | C24: =+Lifestyle!BS45 -> 0 | D24: =+Shepparton!#REF! -> #REF! | E24: =+Shepparton!#REF! -> #REF!
B25: =+Lifestyle!A46 -> Bondi 36 | C25: =+Lifestyle!BS46 -> 0 | D25: =+Shepparton!#REF! -> #REF! | E25: =+Shepparton!#REF! -> #REF!
B26: =+Lifestyle!A47 -> Cambridge 22 | C26: =+Lifestyle!BS47 -> 0 | D26: =+Shepparton!#REF! -> #REF! | E26: =+Shepparton!#REF! -> #REF!
B27: =+Lifestyle!A48 -> Cambridge 24 | C27: =+Lifestyle!BS48 -> 0 | D27: =+Shepparton!#REF! -> #REF! | E27: =+Shepparton!#REF! -> #REF!
B28: =+Lifestyle!A49 -> Cambridge 26 | C28: =+Lifestyle!BS49 -> 0 | D28: =+Shepparton!#REF! -> #REF! | E28: =+Shepparton!#REF! -> #REF!
B29: =+Lifestyle!A50 -> Cambridge 30 | C29: =+Lifestyle!BS50 -> 0 | D29: =+Shepparton!#REF! -> #REF! | E29: =+Shepparton!#REF! -> #REF!
B30: =+Lifestyle!A51 -> Duneed 22 | C30: =+Lifestyle!BS51 -> 0 | D30: =+Shepparton!#REF! -> #REF! | E30: =+Shepparton!#REF! -> #REF!
B31: =+Lifestyle!A52 -> Duneed 23 | C31: =+Lifestyle!BS52 -> 0 | D31: =+Shepparton!#REF! -> #REF! | E31: =+Shepparton!#REF! -> #REF!
... B62: =+Lifestyle!A83 -> Santa Barbara 26 | C62: =+Lifestyle!BS83 -> 0 | D62: =+Shepparton!#REF! -> #REF! | E62: =+Shepparton!#REF! -> #REF!
B63: =+Lifestyle!A88 -> Inglewood 29 | C63: =+Lifestyle!BS88 -> 0 | D63: =+Shepparton!#REF! -> #REF! | E63: =+Shepparton!#REF! -> #REF!
B64: =+Lifestyle!A89 -> Inglewood 31 | C64: =+Lifestyle!BS89 -> 0 | D64: =+Shepparton!#REF! -> #REF! | E64: =+Shepparton!#REF! -> #REF!
B65: =+Lifestyle!A90 -> Inglewood 34 | C65: =+Lifestyle!BS90 -> 0 | D65: =+Shepparton!#REF! -> #REF! | E65: =+Shepparton!#REF! -> #REF!
B66: =+Lifestyle!A91 -> Inglewood 35 | C66: =+Lifestyle!BS91 -> 0 | D66: =+Shepparton!#REF! -> #REF! | E66: =+Shepparton!#REF! -> #REF!
B67: =+Lifestyle!A92 -> Inglewood 38 | C67: =+Lifestyle!BS92 -> 0 | D67: =+Shepparton!#REF! -> #REF! | E67: =+Shepparton!#REF! -> #REF!
B68: =+Lifestyle!A94 -> Maldon 27 | C68: =+Lifestyle!BS94 -> 0 | D68: =+Shepparton!#REF! -> #REF! | E68: =+Shepparton!#REF! -> #REF!
B69: =+Lifestyle!A96 -> Palmerston 28 | C69: =+Lifestyle!BS96 -> 0 | D69: =+Shepparton!#REF! -> #REF! | E69: =+Shepparton!#REF! -> #REF!
B70: =+Lifestyle!A97 -> Palmerston 35 | C70: =+Lifestyle!BS97 -> 0 | D70: =+Shepparton!#REF! -> #REF! | E70: =+Shepparton!#REF! -> #REF!
B71: =+Lifestyle!A98 -> Sandown 23 | C71: =+Lifestyle!BS98 -> 0 | D71: =+Shepparton!#REF! -> #REF! | E71: =+Shepparton!#REF! -> #REF!
B72: =+Lifestyle!A99 -> Sandown 26 | C72: =+Lifestyle!BS99 -> 0 | D72: =+Shepparton!#REF! -> #REF! | E72: =+Shepparton!#REF! -> #REF!
B73: =+Lifestyle!A100 -> Sandown 28 (30) | C73: =+Lifestyle!BS100 -> 0 | D73: =+Shepparton!#REF! -> #REF! | E73: =+Shepparton!#REF! -> #REF!
B74: =+Lifestyle!A101 -> Sandown 32 | C74: =+Lifestyle!BS101 -> 0 | D74: =+Shepparton!#REF! -> #REF! | E74: =+Shepparton!#REF! -> #REF!
B75: =+Lifestyle!A105 -> Winton 24 | C75: =+Lifestyle!BS105 -> 0 | D75: =+Shepparton!#REF! -> #REF! | E75: =+Shepparton!#REF! -> #REF!
B76: =+Lifestyle!A106 -> Winton 28 | C76: =+Lifestyle!BS106 -> 0 | D76: =+Shepparton!#REF! -> #REF! | E76: =+Shepparton!#REF! -> #REF!
B77: =+Lifestyle!A107 -> Winton 32 | C77: =+Lifestyle!BS107 -> 0 | D77: =+Shepparton!#REF! -> #REF! | E77: =+Shepparton!#REF! -> #REF!
B78: =+Lifestyle!A110 -> Albany 17 | C78: =+Lifestyle!BS110 -> 0 | D78: =+Shepparton!#REF! -> #REF! | E78: =+Shepparton!#REF! -> #REF!
B79: =+Lifestyle!A111 -> Albany 18 | C79: =+Lifestyle!BS111 -> 0 | D79: =+Shepparton!#REF! -> #REF! | E79: =+Shepparton!#REF! -> #REF!
B80: =+Lifestyle!A112 -> Albany 20 | C80: =+Lifestyle!BS112 -> 0 | D80: =+Shepparton!#REF! -> #REF! | E80: =+Shepparton!#REF! -> #REF!
B81: =+Lifestyle!A113 -> Avoca 16 | C81: =+Lifestyle!BS113 -> 0 | D81: =+Shepparton!#REF! -> #REF! | E81: =+Shepparton!#REF! -> #REF!
B82: =+Lifestyle!A114 -> Avoca 19 | C82: =+Lifestyle!BS114 -> 0 | D82: =+Shepparton!#REF! -> #REF! | E82: =+Shepparton!#REF! -> #REF!
B83: =+Lifestyle!A115 -> Avoca 20 | C83: =+Lifestyle!BS115 -> 0 | D83: =+Shepparton!#REF! -> #REF! | E83: =+Shepparton!#REF! -> #REF!
B84: =+Lifestyle!A116 -> Belinda 16 | C84: =+Lifestyle!BS116 -> 0 | D84: =+Shepparton!#REF! -> #REF! | E84: =+Shepparton!#REF! -> #REF!
B85: =+Lifestyle!A117 -> Belinda 18 | C85: =+Lifestyle!BS117 -> 0 | D85: =+Shepparton!#REF! -> #REF! | E85: =+Shepparton!#REF! -> #REF!
B86: =+Lifestyle!A118 -> Belinda 20 | C86: =+Lifestyle!BS118 -> 0 | D86: =+Shepparton!#REF! -> #REF! | E86: =+Shepparton!#REF! -> #REF!
B87: =+Lifestyle!A119 -> Fairfield 18 | C87: =+Lifestyle!BS119 -> 0 | D87: =+Shepparton!#REF! -> #REF! | E87: =+Shepparton!#REF! -> #REF!
B88: =+Lifestyle!A120 -> Fairfield 19 | C88: =+Lifestyle!BS120 -> 0 | D88: =+Shepparton!#REF! -> #REF! | E88: =+Shepparton!#REF! -> #REF!
B89: =+Lifestyle!A121 -> Fairfield 20 | C89: =+Lifestyle!BS121 -> 0 | D89: =+Shepparton!#REF! -> #REF! | E89: =+Shepparton!#REF! -> #REF!
... B93: =+Lifestyle!A125 -> Stratford 16B | C93: =+Lifestyle!BS125 -> 0 | D93: =+Shepparton!#REF! -> #REF! | E93: =+Shepparton!#REF! -> #REF!
B94: =+Lifestyle!A129 -> Belmont 22A | C94: =+Lifestyle!BS129 -> 0 | D94: =+Shepparton!#REF! -> #REF! | E94: =+Shepparton!#REF! -> #REF!
B95: =+Lifestyle!A130 -> Belmont 22B | C95: =+Lifestyle!BS130 -> 0 | D95: =+Shepparton!#REF! -> #REF! | E95: =+Shepparton!#REF! -> #REF!
B96: =+Lifestyle!A131 -> Belmont 24A | C96: =+Lifestyle!BS131 -> 0 | D96: =+Shepparton!#REF! -> #REF! | E96: =+Shepparton!#REF! -> #REF!
B97: =+Lifestyle!A132 -> Belmont 24B | C97: =+Lifestyle!BS132 -> 0 | D97: =+Shepparton!#REF! -> #REF! | E97: =+Shepparton!#REF! -> #REF!
B99: Rate per sqm for the custom plan | D99: 1600 | G99: Tiles | H99: 6105 | I99: Carpets | J99: 4160 | L99: Enter the figures manually
C101: Unit | D101: Base | E101: Custom | G101: =+(D102+D103+D104+D105)*D99+H99+J99 -> 10265
A102: QGEN000_0040_DWELLING | B102: Dwelling area | C102: M2 | F102: =+E102-D102 -> 0 | G102: =+IF(F102>0,(F102*'House extension'!D6),0) -> 0
A103: QGEN000_0060_GARAGE | B103: Garage area | C103: M2 | F103: =+E103-D103 -> 0 | G103: =+IF(F103>0,(F103*'House extension'!D6),0) -> 0
A104: QGEN000_0070_PORCH | B104: Porch area | C104: M2 | F104: =+E104-D104 -> 0 | G104: =+IF(F104>0,(F104*'House extension'!D25),0) -> 0
A105: QGEN000_0080_OUTDOOR_LIVING | B105: Outdoor living area | C105: M2 | F105: =+E105-D105 -> 0 | G105: =+IF(F105>0,(F105*'House extension'!D25),0) -> 0
B106: Porch concrete footing | C106: LM | F106: =+E106-D106 -> 0 | G106: =+IF(F106>0,(F106*('House extension'!D26+'House extension'!D29)),0) -> 0
B107: Outdoor living footing | C107: LM | F107: =+E107-D107 -> 0 | G107: =+IF(F107>0,(F107*('House extension'!D26+'House extension'!D29)),0) -> 0
A108: QGEN340_0510_BRICK_PIER_QUANTITY | B108: Brick pier | C108: Each | F108: =+E108-D108 -> 0 | G108: =+IF(F108>0,(F108*'House extension'!D27),0) -> 0
B109: 90X90 Steel column | C109: Each | F109: =+E109-D109 -> 0 | G109: =+IF(F109>0,(F109*'House extension'!D37),0) -> 0
A111: QGEN385_0030_EAVE_TYPE_450_BRICKWORK | B111: Eaves | C111: LM | F111: =+E111-D111 -> 0 | G111: =+IF(F111>0,(F111*'House extension'!D17),0) -> 0
A112: QGEN200_1030_HIP | B112: Hip length | C112: LM | F112: =+E112-D112 -> 0 | G112: =+IF(F112>0,(F112*'House extension'!D12),0) -> 0
A113: QGEN200_1040_VALLEY_LENGTH | B113: Valley length | C113: LM | F113: =+E113-D113 -> 0 | G113: =+IF(F113>0,(F113*'House extension'!D13),0) -> 0
A114: QGEN200_1050_RIDGE | B114: Ridge length | C114: LM | F114: =+E114-D114 -> 0 | G114: =+IF(F114>0,(F114*'House extension'!D14),0) -> 0
A116: QGEN205_0210_EXT_PERIMETER_WALL_BV | B116: Perimeter walls | C116: LM | F116: =+E116-D116 -> 0 | G116: =+IF(F116>0,(F116*'House extension'!D8),0) -> 0
A117: QGEN205_0250_INT_WALL | B117: Internal walls | C117: LM | F117: =+E117-D117 -> 0 | G117: =+IF(F117>0,(F117*'House extension'!D9),0) -> 0
A118: QGEN500_1050_BULKHEAD_LENGTH | B118: Plaster bulkheads | C118: LM | F118: =+E118-D118 -> 0 | G118: =+IF(F118>0,(F118*'House extension'!D42),0) -> 0
A120: QGEN520_0030_KITCHEN_CABINET_LENGTH | B120: Kitchen wall bench | C120: LM | F120: =+E120-D120 -> 0 | G120: =+IF(F120>0,(F120*Cabinetry!E34*10),(F120*Cabinetry!E34*10*0.8)) -> 0
A121: QGEN520_0070_KITCHEN_OH_LENGTH | B121: Kitchen overhead cupboards | C121: LM | F121: =+E121-D121 -> 0 | G121: =+IF(F121>0,(F121*Cabinetry!E46*10),(F121*Cabinetry!E46*10*0.8)) -> 0
A122: QGEN520_0110_ISLAND_BENCH_WITH_OVERHANG | B122: Kitchen island bench | C122: LM | F122: =+E122-D122 -> 0 | G122: =+IF(F122>0,(F122*Cabinetry!E53*10),(F122*Cabinetry!E53*10*0.8)) -> 0
A124: QGEN520_0230_VANITY_GF_ENSUITE_WIDTH | B124: Ensuite vanity benches | C124: LM | F124: =+E124-D124 -> 0 | G124: =IF(F124>0,(F124*Cabinetry!E6*10),((F124*Cabinetry!E6*10*0.8))) -> 0
A125: QGEN520_0250_VANITY_GF_ENSUITE_BASIN | B125: Ensuite vanity basins | C125: Each | F125: =+E125-D125 -> 0 | G125: =+IF(F125>0,(F125*Cabinetry!E7),((F125*Cabinetry!E7*0.8))) -> 0
A126: QGEN520_0330_VANITY_GF_BATHROOM_WIDTH | B126: Bath vanity benches | C126: LM | F126: =+E126-D126 -> 0 | G126: =IF(F126>0,(F126*Cabinetry!E6*10),((F126*Cabinetry!E6*10*0.8))) -> 0
A127: QGEN520_0350_VANITY_GF_BATHROOM_BASIN | B127: Bath vanity basins | C127: Each | F127: =+E127-D127 -> 0 | G127: =+IF(F127>0,(F127*Cabinetry!E7),((F127*Cabinetry!E7*0.8))) -> 0
A128: QGEN520_0430_VANITY_GF_ADDITIONAL_WIDTH | B128: Extra vanity benches | C128: LM | F128: =+E128-D128 -> 0 | G128: =IF(F128>0,(F128*Cabinetry!E6*10),((F128*Cabinetry!E6*10*0.8))) -> 0
A129: QGEN520_0450_VANITY_GF_ADDITIONAL_BASIN | B129: Extra vanity basins | C129: Each | F129: =+E129-D129 -> 0 | G129: =+IF(F129>0,(F129*Cabinetry!E7),((F129*Cabinetry!E7*0.8))) -> 0
A131: QGEN520_0485_LAUNDRY_BASE_CUPBOARD | B131: Laundry bench | C131: LM | F131: =+E131-D131 -> 0 | G131: =+IF(F131>0,(F131*Cabinetry!E18*10),(F131*Cabinetry!E18*10*0.8)) -> 0
B133: Internal swing doors | C133: Each | F133: =+E133-D133 -> 0 | G133: =+IF(F133>0,(F133*'Swing Doors'!D26),(F133*'Swing Doors'!D26*0.8)) -> 0
B134: Internal double swing doors | C134: Each | F134: =+E134-D134 -> 0 | G134: =+IF(F134>0,(F134*'Swing Doors'!D27),(F134*'Swing Doors'!D27*0.8)) -> 0
B135: Internal cavity sliders | C135: Each | F135: =+E135-D135 -> 0 | G135: =+IF(F135>0,(F135*'Swing Doors'!D30),(F135*'Swing Doors'!D30*0.8)) -> 0
B136: Internal double cavity sliders | C136: Each | F136: =+E136-D136 -> 0 | G136: =+IF(F136>0,(F136*'Swing Doors'!D31),(F136*'Swing Doors'!D31*0.8)) -> 0
B138: Windows
B139: =+'Windows & Sliding Doors'!B9 -> 1006 | C139: Each | D139: 2 | E139: 1 | F139: =+E139-D139 -> -1 | G139: =+IF(F139>0,(F139*'Windows & Sliding Doors'!D9),(F139*'Windows & Sliding Doors'!D9*0.8)) -> -252
B140: =+'Windows & Sliding Doors'!B10 -> 1212 | C140: Each | D140: 2 | E140: 1 | F140: =+E140-D140 -> -1 | G140: =+IF(F140>0,(F140*'Windows & Sliding Doors'!D10),(F140*'Windows & Sliding Doors'!D10*0.8)) -> -352
B141: =+'Windows & Sliding Doors'!B11 -> 1215 | C141: Each | E141: 1 | F141: =+E141-D141 -> 1 | G141: =+IF(F141>0,(F141*'Windows & Sliding Doors'!D11),(F141*'Windows & Sliding Doors'!D11*0.8)) -> 475
B142: =+'Windows & Sliding Doors'!B14 -> 1809 | C142: Each | F142: =+E142-D142 -> 0 | G142: =+IF(F142>0,(F142*'Windows & Sliding Doors'!D14),0) -> 0
B143: =+'Windows & Sliding Doors'!B15 -> 1812 | C143: Each | F143: =+E143-D143 -> 0 | G143: =+IF(F143>0,(F143*'Windows & Sliding Doors'!D15),0) -> 0
...

Sheet Facade Pricing
A2: Facade pricing July 2024
A5: Disclaimer: Façade costings only include porches, windows, cladding, gables etc. Does not include features like lights, upgraded front or garage door, feature or upgraded bricks etc.
A12: FAÇADE 1A (TRADITIONAL)
A13: Awning windows to façade | B13: =ROUNDUP((2*'Windows & Sliding Doors'!J14)-'Windows & Sliding Doors'!D16,10) -> 680
B14: =SUM(B13:B13) -> 680
A16: FAÇADE 1B (TEMPO)
A17: Awning windows to façade | B17: =+B13 -> 680
A18: Stria board gable to porch and bed 1 | B18: 5500
B19: =SUM(B17:B18) -> 6180
A21: FAÇADE 1Ca (TEMPO A)
A22: Full length awning windows to façade | B22: =+ROUNDUP(('Windows & Sliding Doors'!P14*2)-'Windows & Sliding Doors'!D16,10) -> 1200
A23: Stria board gables | B23: =+B18 -> 5500
A24: Perimeter moulding around gable panels with one vent | B24: 1300
A25: Linea board to bed 1 | B25: =+CEILING(((Facades!D13*30)+(Facades!D14*2)+(Facades!D15*2)+(Facades!D16*2)),10) -> 3730
B26: =SUM(B22:B25) -> 11730
A28: FAÇADE 1Cb (TEMPO B)
A29: Overlooking windows to façade | B29: =+'Windows & Sliding Doors'!P16-'Windows & Sliding Doors'!D16 -> 695
A30: Render finish to brick piers | B30: =+Facades!D7 -> 3300
A31: Stria board gable to porch and bed 1 | B31: =+B23 -> 5500
A32: Perimeter moulding around gable panels with one vent | B32: =+B24 -> 1300
A33: Add engaged brick pier | B33: 520
B34: =SUM(B29:B33) -> 11315
A37: =+A2 -> Facade pricing July 2024
A40: FAÇADE 2A (CLASSIC)
A41: Awning windows to façade | B41: =+ROUNDUP(('Windows & Sliding Doors'!J16-'Windows & Sliding Doors'!D16)+'Windows & Sliding Doors'!J14,10) -> 960
A42: Extend porch | B42: =+ROUNDUP((('House extension'!D25*2.5)+2*'House extension'!D26+(2+1.5)*'House extension'!D29),10)+200 -> 1315
B43: =SUM(B41:B42) -> 2275
A45: FAÇADE 2B (RESORT)
A46: Full length awning windows to façade | B46: =+ROUNDUP(('Windows & Sliding Doors'!P14+'Windows & Sliding Doors'!P16-'Windows & Sliding Doors'!D16),10) -> 1545
A47: Raised portico with stria infill or Newtechwood cladding | B47: 6500
A48: Extend porch | B48: =+B42 -> 1315
B49: =SUM(B46:B48) -> 9360
A51: FAÇADE 2C (MODERN)
A52: Overlooking windows to façade | B52: =+B41 -> 960
A53: 590 Brick pier with capped flashing | B53: 1110
A54: RHS pier to be engaged | B54: 530
A55: Raised portico with stria infill or Newtechwood cladding | B55: 6100
A56: Extend porch | B56: =+B48 -> 1315
A57: Linea board to bed 1 | B57: =+ROUNDUP((Facades!D13*30+Facades!D14+Facades!D15+Facades!D15+Facades!D16),10) -> 3280
B58: =SUM(B52:B57) -> 13295
A60: =+A37 -> Facade pricing July 2024
A63: FAÇADE 3A (CLASSIC)
A64: Awning windows to façade | B64: =+B13 -> 680
A65: Extend porch | B65: =+B48 -> 1315
A66: Eaves to porch and bed 1 | B66: Inc
B67: =SUM(B64:B66) -> 1995
A69: FAÇADE 3B (HAMPTONS B)
A70: Full length awning windows to façade | B70: =+B64 -> 680
A71: 115 Square painted timber posts | B71: =+ROUNDUP('House extension'!D36*6-'House extension'!D27-'House extension'!D37,10) -> 1095
A72: Exposed painted timber beam unwrapped | B72: 1040
A73: Stria board Dutch gable | B73: 3700
A74: Linea board to façade | B74: =+B25 -> 3730
A75: Extend porch | B75: =+B65 -> 1315
B76: =SUM(B70:B75) -> 11560
A78: FAÇADE 3C (HAMPTONS A)
A79: Overlooking windows to façade | B79: =+B70 -> 680
A80: 3/4 470 Brick piers with brick capping | B80: 610
A81: 180 Square posts | B81: =+B71 -> 1095
A82: Exposed painted timber beam unwrapped | B82: =+B72 -> 1040
A83: Linea board to façade | B83: =+B74 -> 3730
A84: Stria board Dutch gable with perimeter moulding and vent | B84: =+B73+B32 -> 5000
A85: Render to brick piers and bed 1 | B85: =+Facades!D7 -> 3300
B86: =SUM(B79:B85) -> 15455
A89: =+A60 -> Facade pricing July 2024
A92: FAÇADE 4A (CLASSIC 4A)
A93: Sliding windows throughout | B93: Inc
A94: Eaves to porch and lounge | B94: Inc
B95: =SUM(B94:B94) -> 0
A97: FAÇADE 4B (RESORT 4B)
A98: Awning windows to façade | B98: 1650
A99: Raised prtico with stria bulkhead or Newtechwood cladding | B99: 6500
B100: =SUM(B98:B99) -> 8150
A102: FAÇADE 4Ca (MODERN)
A103: Overlooking windows to façade | B103: 610
A104: 590x470 Brick piers | B104: =470*2 -> 940
A105: Tile finish to RHS brick pier | B105: 1950
A106: Raised prtico with stria bulkhead or Newtechwood cladding | B106: =+B47 -> 6500
A107: Linea board to lounge | B107: =+(Facades!D13*30)+Facades!D14+Facades!D15*2+Facades!D16 -> 3280
A108: Render finish to lounge brick base | B108: 3300
B109: =SUM(B103:B108) -> 16580
A111: FAÇADE 4Cb (GRANGE)
A112: Full length awning windows to façade | B112: 1650
A113: Raised masterwall bulkhead with render | B113: 9500
A114: Newington entrance door | B114: 175
A115: Linea board to lounge | B115: =+B107 -> 3280
B116: =SUM(B112:B115) -> 14605
A118: =+A89 -> Facade pricing July 2024
A121: FAÇADE 5A (CLASSIC)
A122: Awning windows to façade | B122: 1115
B123: =SUM(B122:B122) -> 1115
A125: FAÇADE 5B (RESORT)
A126: Full length awning windows to façade | B126: 2490
A127: 470 brick piers X3 with capped flashing | B127: 1470
A128: Raised porch with stria or newtechwod cladding infill | B128: 8200
A129: Extend porch | B129: 4250
B130: =SUM(B126:B129) -> 16410
A132: FACADE 5C (ASCENT)
A133: Full length awning windows to façade | B133: 2490
A134: Piers - sizes vary | B134: 1980
A135: Linea boards to ensuite | B135: =+B115 -> 3280
...

Sheet Slab
A2: Site Costs Calculations
A4: House area | B4: 255 | C4: M2
A5: Garage area | B5: 50 | C5: M2 | F5: RURAL JOBS
A6: Slab perimeter- enter length when deepened edge beams & for slabs above MD | B6: =35+35+16+16 -> 102 | C6: LM | F6: FOR ALL RURAL JOBS PLEASE ALLOW H1-D (300mm PODS)
F7: BECAUSE MOST OF THEM NEEDS TO BE 300MM ABOVE SURROUNDINGS
A8: Slab upgrade calculations
A9: Number of Concrete Piers up to 1.0m deep | C9: Ea | D9: =+B9*200 -> 0
A10: Number of Concrete Piers from 1.0m deep to 1.5m deep | C10: Ea | D10: =+B10*250 -> 0
A11: Number of Steel Screw pile up to 3.0m deep | C11: Ea | D11: =+B11*340 -> 0
A12: Number of Steel Screw pile up to 4.0m deep | C12: Ea | D12: =+B12*440 -> 0
A13: Number of Piers above 4.0m deep | B13: POA | C13: Ea
A14: H1-D slab with 300mm waffle pod slabs in lieu of standard MD slab with 225mm pods (Area of Dwelling + Garage) | C14: LM | D14: =+((B4+B5)*6*B14)+(11*B6*B14) -> 0
A15: H1-D slab with 375mm waffle pod slabs in lieu of standard MD slab with 225mm pods (Area of Dwelling + Garage) | C15: LM | D15: =+((B4+B5)*12*B15)+(B6*B15*12) -> 0 | F15: RURAL JOBS
A16: H2-D slab with 375mm waffle pod slabs in lieu of standard MD slab with 225mm pods (Area of Dwelling + Garage) | B16: 1 | C16: LM | D16: =+((B5+B4)*43*B16)+(B6*B16*12) -> 14339
A17: Travel for piers
A18: Travel over 20km (Enter one-way distance from Shepparton) | C18: KM | D18: =+IF(B18>60,((B18-60)*4),0) -> 0
A19: Deepned edge beams
A20: Deepened edge beams (per 100mm depth) - enter length | B20: 2 | C20: 1 for YES | D20: =+B6*13.5*B20 -> 2754
A21: Sub-total | D21: =SUM(D9:D20) -> 17093
A23: Power
A24: Extra power run over standard if more than 9m (up to 40m) | B24: 0 | C24: m | D24: =+B24*35 -> 0
A25: Sub-total | D25: =SUM(D24:D24) -> 0
A27: Water
A28: Extra water run if set back is more than 6m | C28: m | D28: =+B28*27 -> 0
A29: Extra if wet tapping and mains more than 150mm dia | C29: m | D29: =+B29*535 -> 0
A30: Sub-total | D30: =SUM(D28:D29) -> 0
A32: Long water tapping
A33: Extra if not tapping and water mains is on other side of road (enter 1) | B33: 0 | C33: m | D33: =+IF(B33=1,930,0) -> 0
A34: Sub-total | D34: =SUM(D33:D33) -> 0
A36: Sewer
A37: Extra sewer run over standard if lot is more than 700m2 | B37: 0 | C37: m | D37: =+B37*64 -> 0
A38: Ground movement if more than 40mm? (enter 1) | B38: 0 | C38: Ea | D38: =+B38*335 -> 0
A39: Sewer tie depth more than 1.5m | C39: Ea | D39: =+B39*400 -> 0
A40: Sub-total | D40: =SUM(D37:D39) -> 0
A42: Stormy
A43: Extra storm water run if set back is more than 6m | C43: m | D43: =31*2*B43 -> 0
A44: Sub-total | D44: =SUM(D43) -> 0
A46: BAL
A47: BAL -Nill | C47: Ea | D47: =+B47*0 -> 0
A48: BAL-12.5 | B48: 0 | C48: Ea | D48: =+B48*1500 -> 0
A49: BAL-19 | B49: 0 | C49: Ea | D49: POA
A50: Sub-total | D50: =SUM(D47:D49) -> 0

Sheet WORKINGS
A1: WORKINGS
B2: Orginal | F2: New
A3: Item | B3: # | D3: $ | E3: Total | F3: # | H3: $ | I3: Total
A5: Façade - Based on the Parkdale Display
A6: Extend Porch | B6: 4.27m2 | E6: 405 | K6: New Porch - 9.35m2 | Standard Porch 5.08m2 = difference 4.27m2 | S6: Carpet Upgrade
A7: Raised porch with infill brick wall | E7: 5200 | K7: Porch Extension - | S7: Bed 1 | T7: 4.2 | U7: 4.2 | V7: =T7*U7 -> 17.64
A8: 2 x 710mm wider piers to porch | E8: 1045 | K8: Extend Roof Area to add Patio | N8: 4.27m2 | O8: 220 | S8: wir 1 | T8: 1.79 | U8: 2.47 | V8: =T8*U8 -> 4.4213
A9: 2 x Engaged brick piers | E9: 2090 | K9: Pation Beam | N9: 3.3lm | O9: 55 | S9: wir 1 | T9: 1.79 | U9: 1.98 | V9: =T9*U9 -> 3.5442
A10: Lightweight clad rendered bulkhead | E10: 15450 | K10: Concrete Footings | N10: 3.3lm | O10: 130 | S10: foyer | T10: 1.79 | U10: 2.3 | V10: =T10*U10 -> 4.117
O11: =SUM(O8:O10) -> 405 | S11: study | T11: 3.3 | U11: 3.3 | V11: =T11*U11 -> 10.89
S12: bed 2 | T12: 3.4 | U12: 3.9 | V12: =T12*U12 -> 13.26
D13: Orginal | E13: =SUM(E6:E12) -> 24190 | H13: New | I13: =SUM(I6:I12) -> 0 | S13: bed 3 | T13: 3.5 | U13: 3.9 | V13: =T13*U13 -> 13.65
H14: COST | I14: =I13-E13 -> -24190 | S14: bed 4 | T14: 3.5 | U14: 3.9 | V14: =T14*U14 -> 13.65
S15: retreat | T15: 5 | U15: 4 | V15: =T15*U15 -> 20
A16: 600mm wide extension from Retreat through to Bed 4 | V16: =SUM(V7:V15) -> 101.1725
A17: Standard floor area incl. roof | B17: =0.6*9.8 -> 5.88 | D17: 555 | E17: =SUM(D17*B17) -> 3263.4 | K17: 9.8m standard x .6m extension
A18: Bricks | B18: 1.2 | D18: 660 | E18: =SUM(D18*B18) -> 792 | S18: Stone Quote | Z18: GV Stone Quote
A19: Carpet (Retreat & Bedrooms) | B19: 4.74 | D19: 60 | E19: =SUM(D19*B19) -> 284.4 | K19: Retreat - 2.4m2 & Bedroom - 2.34m2 | S19: Kitchen
A20: Vinyl (Hallway) | B20: 0.66 | D20: 139 | E20: =SUM(D20*B20) -> 91.74 | T20: 3 | U20: 1.2 | V20: =T20*U20 -> 3.6 | X20: 755 | Y20: =X20*V22 -> 4536.04 | Z20: 11156.2 | AB20: =Z20-Y23 -> 3572.12 | AE20: 3 | AF20: 1.2 | AG20: =AF20*AE20 -> 3.6
A21: Eaves | B21: 1.2 | D21: 85 | E21: =SUM(D21*B21) -> 102 | T21: 3.44 | U21: 0.7 | V21: =T21*U21 -> 2.408 | X21: 755 | Y21: =V21*X21 -> 1818.04 | AB21: =AB20*1.36 -> 4858.0832 | AE21: 3.44 | AF21: 0.7 | AG21: =AF21*AE21 -> 2.408
A22: 2550mm ceiling | B22: 5.88 | D22: 19 | E22: =SUM(D22*B22) -> 111.72 | V22: =SUM(V20:V21) -> 6.008 | X22: waterfall | Y22: 1230 | AG22: =SUM(AG20:AG21) -> 6.008 | AH22: x | AI22: 755
Y23: =SUM(Y20:Y22) -> 7584.08 | AF23: w/falls | AG23: 2 | AH23: x | AI23: 611.55
AI24: =SUM(AI22:AI23) -> 1366.55
K25: Stone 20mm to 40mm (Kitchen) | S25: Pantry | X25: 635 | Y25: =V28*X25 -> 1386.84 | Z25: 4590 | AA25: =Z25-Y25 -> 3203.16 | AB25: =AA25*1.36 -> 4356.2976
T26: 2.74 | U26: 0.6 | V26: =T26*U26 -> 1.644
A27: TOTAL | D27: Orginal | E27: =SUM(E17:E26) -> 4645.26 | H27: New | I27: =SUM(I18:I26) -> 0 | K27: 0.7 | L27: 3.44 | M27: =K27*L27 -> 2.408 | O27: 635 | P27: =M27*O27 -> 1529.08 | T27: 0.9 | U27: 0.6 | V27: =T27*U27 -> 0.54 | AE27: 2.7 | AF27: 0.6 | AG27: =AF27*AE27 -> 1.62
H28: COST | I28: =I27-E27 -> -4645.26 | O28: 755 | P28: =M27*O28 -> 1818.04 | V28: =SUM(V26:V27) -> 2.184 | AE28: 0.9 | AF28: 0.6 | AG28: =AF28*AE28 -> 0.54
AG29: =SUM(AG27:AG28) -> 2.16 | AH29: x | AI29: 635 | AJ29: =AI29*AG29 -> 1371.6
A30: 1300mm wide extension to Garage | S30: Powder room | AJ30: 1730
A31: Standard floor area incl. roof | B31: =7.7*1.3 -> 10.01 | D31: 555 | E31: =SUM(D31*B31) -> 5555.55 | T31: 0.9 | U31: 0.53 | V31: =T31*U31 -> 0.477 | X31: 635 | Y31: =X31*V31 -> 302.895 | AA31: 714 | AB31: =AA31-Y31 -> 411.105 | AC31: =AB31*1.36 -> 559.1028 | AJ31: =AJ30-AJ29 -> 358.4
A32: 2550mm ceiling | B32: 10 | D32: 19 | E32: =SUM(D32*B32) -> 190 | AJ32: =AJ31*1.36 -> 487.424
A33: Brick Wall | B33: 2.6 | D33: 660 | E33: =SUM(D33*B33) -> 1716
A34: Eaves | B34: 2.6 | D34: 85 | E34: =SUM(D34*B34) -> 221 | S34: Bath
A35: Ridge | B35: 1.3 | D35: 40 | E35: =SUM(D35*B35) -> 52 | T35: 0.9 | U35: 0.53 | V35: =T35*U35 -> 0.477 | X35: 635 | Y35: =V35*X35 -> 302.895 | AA35: 468.6 | AB35: =AA35-Y35 -> 165.705 | AC35: =AB35*1.36 -> 225.3588
S37: ens
T38: 1.8 | U38: 0.53 | V38: =T38*U38 -> 0.954 | X38: 635 | Y38: =X38*V38 -> 605.79 | AA38: 937.2 | AB38: =AA38-Y38 -> 331.41 | AC38: =AB38*1.36 -> 450.7176 | AE38: 1.8 | AF38: 0.53 | AG38: =AF38*AE38 -> 0.954 | AH38: x | AI38: 755 | AJ38: =AI38*AG38 -> 720.27
D39: Orginal | E39: =SUM(E31:E38) -> 7734.55 | H39: New | I39: =SUM(I31:I38) -> 0 | AJ39: 937.2
H40: COST | I40: =I39-E39 -> -7734.55 | S40: Laundry | T40: 1.5 | U40: 0.6 | V40: =T40*U40 -> 0.9 | X40: 630 | Y40: =X40*V40 -> 567 | AA40: 745.1 | AB40: =AA40-Y40 -> 178.1 | AC40: =AB40*1.36 -> 242.216 | AJ40: 127.8
AJ41: =SUM(AJ39:AJ40) -> 1065
A42: 550mm wide extension to Butler's Pantry
A43: Standard floor area incl. roof | B43: =0.55*2.4 -> 1.32 | D43: 555 | E43: =SUM(D43*B43) -> 732.6 | K43: .55 x 2.1 | AJ43: =AJ41-AJ38 -> 344.73
A44: Bricks | B44: 0 | D44: 660 | E44: =SUM(D44*B44) -> 0 | AJ44: =AJ43*1.36 -> 468.8328
A45: Tiles | B45: 1.32 | D45: 103 | E45: =SUM(D45*B45) -> 135.96
A46: 2550mm ceiling | B46: 1.32 | D46: 19 | E46: =SUM(D46*B46) -> 25.08 | AE46: 0.9 | AF46: 0.53 | AG46: =AF46*AE46 -> 0.477 | AH46: x | AI46: 755 | AJ46: =AI46*AG46 -> 360.135
A47: Eaves | B47: 0.55 | D47: 85 | E47: =SUM(D47*B47) -> 46.75 | AJ47: 468.6
D48: Orginal | E48: =SUM(E43:E47) -> 940.39 | H48: New | I48: =SUM(I43:I47) -> 0 | K48: Add 1000mm up through centre | P48: Entry | AJ48: =AJ47-AJ46 -> 108.465
H49: COST | I49: =I48-E48 -> -940.39 | K49: 8m - $4440 | L49: Roof | P49: 3m -$1665 | Q49: roof | AJ49: =AJ48*1.36 -> 147.5124
K50: 825 | L50: Tiles | P50: 309 | Q50: tiles
A51: Convert Lounge to Study and resize to 3300mm x 3300mm | K51: 880 | L51: ODL
A52: Internal Wall | B52: -2.27 | D52: 200 | E52: =SUM(D52*B52) -> -454 | K52: 560 | L52: ODL concrete
A53: 1818 | B53: -1 | C53: no | D53: 500 | E53: =SUM(D53*B53) -> -500 | K53: 375 | L53: Porch
K54: 280 | L54: Porch concrete
A56: 1824 | B56: -1 | C56: no | D56: 790 | E56: =SUM(D56*B56) -> -790
A57: 1812 | B57: 2 | C57: no | D57: 450 | E57: =SUM(D57*B57) -> 900 | K57: Add 100mm through hallway only
K58: 1.5m - $835 roof
D59: Orginal | E59: =SUM(E52:E58) -> -844 | H59: New | I59: =SUM(I52:I58) -> 0 | K59: $155 tiles
H60: COST | I60: =I59-E59 -> 844
K61: extra eaves already included in eave price
A62: Delete WIP
A63: Door | B63: -1 | C63: no | D63: 235 | E63: =B63*D63 -> -235
D65: Orginal | E65: =SUM(E63:E64) -> -235 | H65: New | I65: =SUM(I63:I64) -> 0
H66: COST | I66: =I65-E65 -> 235 | J66: =E48+E59+E65 -> -138.61
A68: Remove Rear Verandah
A69: Verandah area | B69: 8.7 | C69: by | D69: 200 | I69: =SUM(B69*D69) -> 1740 | K69: 1.2 | L69: 7.2 | M69: =SUM(K69*L69) -> 8.64 | N69: total area
A70: Strip footing | B70: 7.2 | C70: by | D70: 110 | I70: =SUM(B70*D70) -> 792
A71: Column | B71: 2 | C71: by | D71: 350 | I71: =SUM(B71*D71) -> 700
A72: Extra hip & Valley | B72: -2 | C72: by | D72: 350 | I72: =SUM(B72*D72) -> -700
H73: New | I73: =SUM(I69:I72) -> 2532
H74: COST | I74: =I73-E73 -> 2532
A76: Basin to WC
D82: Orginal | E82: =SUM(E80:E81) -> 0 | H82: New | I82: =SUM(I77:I81) -> 0
H83: COST | I83: =I82-E82 -> 0
A85: Downgrade to Aspire tapware, towel rail and toilet roll holder
D90: Orginal | E90: =SUM(E86:E89) -> 0 | H90: New | I90: =SUM(I86:I89) -> 0
H91: COST | I91: =I90-E90 -> 0
A93: Bathroom Tiles - Upgrade
D97: Orginal | E97: =SUM(E94:E96) -> 0 | H97: New | I97: =SUM(I94:I96) -> 0
H98: COST | I98: =I97-E97 -> 0
A100: Ensuite Tiles - Upgrade
D106: Orginal | E106: =SUM(E101:E105) -> 0 | H106: New | I106: =SUM(I101:I105) -> 0
H107: COST | I107: =I106-E106 -> 0
A109: Extra Tiles - Ensuite
D115: Orginal | E115: =SUM(E110:E114) -> 0 | H115: New | I115: =SUM(I110:I114) -> 0
H116: COST | I116: =I115-E115 -> 0
A118: Bathroom Tiles - Extened
D122: Orginal | E122: =SUM(E119:E121) -> 0 | H122: New | I122: =SUM(I119:I121) -> 0
H123: COST | I123: =I122-E122 -> 0

Sheet 1.HOUSE PRICE
A2: Please pick in the following order. Then go to sheet 2.TRAVEL
A3: 1.Price list
A4: 2.House plan
A7: 2.House design | B7: Base price | C7: 1.Price list | D7: Tiles | E7: Carpets | F7: 7 Star Allowance
A8: =+Lifestyle!A14 -> Adelaide 18 | B8: =+Shepparton!B4 -> 282210 | C8: Shepparton | D8: =+Shepparton!D4 -> 5010 | E8: =+Shepparton!E4 -> 2785 | F8: 5000
A9: =+Lifestyle!A15 -> Adelaide 21 | B9: =+Shepparton!B5 -> 296640 | C9: Shepparton | D9: =+Shepparton!D5 -> 5140 | E9: =+Shepparton!E5 -> 4100 | F9: 5000
A10: =+Lifestyle!A16 -> Adelaide 22A | B10: =+Shepparton!B6 -> 310720 | C10: Shepparton | D10: =+Shepparton!D6 -> 5935 | E10: =+Shepparton!E6 -> 4085 | F10: 5000
A11: =+Lifestyle!A17 -> Adelaide 22B | B11: =+Shepparton!B7 -> 312390 | C11: Shepparton | D11: =+Shepparton!D7 -> 5885 | E11: =+Shepparton!E7 -> 3985 | F11: 5000
A12: =+Lifestyle!A18 -> Adelaide 24 | B12: =+Shepparton!B8 -> 319970 | C12: Shepparton | D12: =+Shepparton!D8 -> 6420 | E12: =+Shepparton!E8 -> 4990 | F12: 5000
A13: =+Lifestyle!A19 -> Ashfield 24 | B13: =+Shepparton!B9 -> 322220 | C13: Shepparton | D13: =+Shepparton!D9 -> 8670 | E13: =+Shepparton!E9 -> 3475 | F13: 5000
A14: =+Lifestyle!A20 -> Ashfield 30 | B14: =+Shepparton!B10 -> 359580 | C14: Shepparton | D14: =+Shepparton!D10 -> 7940 | E14: =+Shepparton!E10 -> 5610 | F14: 5000
A15: =+Lifestyle!A21 -> Ashfield 34 | B15: =+Shepparton!B11 -> 386150 | C15: Shepparton | D15: =+Shepparton!D11 -> 8440 | E15: =+Shepparton!E11 -> 6700 | F15: 5000
A16: =+Lifestyle!A22 -> Ashley 19 | B16: =+Shepparton!B12 -> 280620 | C16: Shepparton | D16: =+Shepparton!D12 -> 5805 | E16: =+Shepparton!E12 -> 2805 | F16: 5000
A17: =+Lifestyle!A24 -> Ashley 22 | B17: =+Shepparton!B14 -> 297580 | C17: Shepparton | D17: =+Shepparton!D14 -> 6855 | E17: =+Shepparton!E14 -> 3875 | F17: 5000
A18: =+Lifestyle!A25 -> Ashley 22A | B18: =+Shepparton!B15 -> 303720 | C18: Shepparton | D18: =+Shepparton!D15 -> 7470 | E18: =+Shepparton!E15 -> 3615 | F18: 5001
A19: =+Lifestyle!A26 -> Ashley 24 | B19: =+Shepparton!B16 -> 315050 | C19: Shepparton | D19: =+Shepparton!D16 -> 6505 | E19: =+Shepparton!E16 -> 4665 | F19: 5002
A20: =+Lifestyle!A27 -> Ashley 25 | B20: =+Shepparton!B17 -> 324090 | C20: Shepparton | D20: =+Shepparton!D17 -> 6950 | E20: =+Shepparton!E17 -> 4610 | F20: 5000
A21: =+Lifestyle!A28 -> Ashley 25A | B21: =+Shepparton!B18 -> 334230 | C21: Shepparton | D21: =+Shepparton!D18 -> 7040 | E21: =+Shepparton!E18 -> 4655 | F21: 5000
A22: =+Lifestyle!A29 -> Ashley 26 | B22: =+Shepparton!B19 -> 330980 | C22: Shepparton | D22: =+Shepparton!D19 -> 7050 | E22: =+Shepparton!E19 -> 4900 | F22: 5000
A23: =+Lifestyle!A30 -> Ashley 27 | B23: =+Shepparton!B20 -> 342910 | C23: Shepparton | D23: =+Shepparton!D20 -> 7995 | E23: =+Shepparton!E20 -> 6080 | F23: 5000
A24: =+Lifestyle!A31 -> Ashley 28 | B24: =+Shepparton!B21 -> 347740 | C24: Shepparton | D24: =+Shepparton!D21 -> 8895 | E24: =+Shepparton!E21 -> 4395 | F24: 5000
A25: =+Lifestyle!A32 -> Ashley 28A | B25: =+Shepparton!B22 -> 355250 | C25: Shepparton | D25: =+Shepparton!D22 -> 9335 | E25: =+Shepparton!E22 -> 5835 | F25: 5000
A26: =+Lifestyle!A33 -> Ballina 24 | B26: =+Shepparton!B23 -> 315600 | C26: Shepparton | D26: =+Shepparton!D23 -> 7970 | E26: =+Shepparton!E23 -> 3015 | F26: 5000
A27: =+Lifestyle!A34 -> Ballina 30 | B27: =+Shepparton!B24 -> 364750 | C27: Shepparton | D27: =+Shepparton!D24 -> 9640 | E27: =+Shepparton!E24 -> 5305 | F27: 5000
A28: =+Lifestyle!A35 -> Ballina 30A | B28: =+Shepparton!B25 -> 367040 | C28: Shepparton | D28: =+Shepparton!D25 -> 10765 | E28: =+Shepparton!E25 -> 5680 | F28: 5000
... A43: =+Lifestyle!A50 -> Cambridge 30 | B43: =+Shepparton!B40 -> 376060 | C43: Shepparton | D43: =+Shepparton!D40 -> 8275 | E43: =+Shepparton!E40 -> 7495 | F43: 5000
A44: Custom | C44: Shepparton | F44: 5000
A45: =+Lifestyle!A51 -> Duneed 22 | B45: =+Shepparton!B51 -> 315050 | C45: Shepparton | D45: =+Shepparton!D51 -> 6705 | E45: =+Shepparton!E51 -> 3215 | F45: 5000
A46: =+Lifestyle!A52 -> Duneed 23 | B46: =+Shepparton!B52 -> 318110 | C46: Shepparton | D46: =+Shepparton!D52 -> 6610 | E46: =+Shepparton!E52 -> 3570 | F46: 5000
A47: =+Lifestyle!A53 -> Duneed 24 | B47: =+Shepparton!B53 -> 329230 | C47: Shepparton | D47: =+Shepparton!D53 -> 6905 | E47: =+Shepparton!E53 -> 4650 | F47: 5000
A48: =+Lifestyle!A54 -> Duneed 25 | B48: =+Shepparton!B54 -> 333250 | C48: Shepparton | D48: =+Shepparton!D54 -> 6835 | E48: =+Shepparton!E54 -> 5030 | F48: 5000
A49: =+Lifestyle!A55 -> Duneed 30 | B49: =+Shepparton!B55 -> 376750 | C49: Shepparton | D49: =+Shepparton!D55 -> 9030 | E49: =+Shepparton!E55 -> 5385 | F49: 5000
A50: =+Lifestyle!A56 -> Eclipse 23 | B50: =+Shepparton!B56 -> 327420 | C50: Shepparton | D50: =+Shepparton!D56 -> 6225 | E50: =+Shepparton!E56 -> 4555 | F50: 5000
A51: =+Lifestyle!A57 -> Eclipse 26 | B51: =+Shepparton!B57 -> 355880 | C51: Shepparton | D51: =+Shepparton!D57 -> 6815 | E51: =+Shepparton!E57 -> 5595 | F51: 5000
A52: =+Lifestyle!A58 -> Eclipse 28 | B52: =+Shepparton!B58 -> 371630 | C52: Shepparton | D52: =+Shepparton!D58 -> 7105 | E52: =+Shepparton!E58 -> 6350 | F52: 5000
A53: =+Lifestyle!A59 -> Hamilton 24 | B53: =+Shepparton!B59 -> 324640 | C53: Shepparton | D53: =+Shepparton!D59 -> 8450 | E53: =+Shepparton!E59 -> 3460 | F53: 5000
A54: =+Lifestyle!A60 -> Hamilton 29 | B54: =+Shepparton!B60 -> 365750 | C54: Shepparton | D54: =+Shepparton!D60 -> 9065 | E54: =+Shepparton!E60 -> 5080 | F54: 5000
A55: =+Lifestyle!A61 -> Hamilton 34 | B55: =+Shepparton!B61 -> 397490 | C55: Shepparton | D55: =+Shepparton!D61 -> 9455 | E55: =+Shepparton!E61 -> 6610 | F55: 5000
A56: =+Lifestyle!A62 -> Launceston 21 | B56: =+Shepparton!B62 -> 304080 | C56: Shepparton | D56: =+Shepparton!D62 -> 6515 | E56: =+Shepparton!E62 -> 3700 | F56: 5000
... A77: =+Lifestyle!A83 -> Santa Barbara 26 | B77: =+Shepparton!B83 -> 340030 | C77: Shepparton | D77: =+Shepparton!D83 -> 7610 | E77: =+Shepparton!E83 -> 4700 | F77: 5000
A78: =+Lifestyle!A86 -> Inglewood 24 | B78: =+Shepparton!B95 -> 324260 | C78: Shepparton | D78: =+Shepparton!D95 -> 6940 | E78: =+Shepparton!E95 -> 4270 | F78: 5000
A79: =+Lifestyle!A87 -> Inglewood 26 | B79: =+Shepparton!B96 -> 349320 | C79: Shepparton | D79: =+Shepparton!D96 -> 7615 | E79: =+Shepparton!E96 -> 4880 | F79: 5000
A80: =+Lifestyle!A88 -> Inglewood 29 | B80: =+Shepparton!B97 -> 368950 | C80: Shepparton | D80: =+Shepparton!D97 -> 8615 | E80: =+Shepparton!E97 -> 5340 | F80: 5000
A81: =+Lifestyle!A89 -> Inglewood 31 | B81: =+Shepparton!B98 -> 387200 | C81: Shepparton | D81: =+Shepparton!D98 -> 8515 | E81: =+Shepparton!E98 -> 6025 | F81: 5000
A82: =+Lifestyle!A90 -> Inglewood 34 | B82: =+Shepparton!B99 -> 406410 | C82: Shepparton | D82: =+Shepparton!D99 -> 9045 | E82: =+Shepparton!E99 -> 7265 | F82: 5000
A83: =+Lifestyle!A91 -> Inglewood 35 | B83: =+Shepparton!B100 -> 425550 | C83: Shepparton | D83: =+Shepparton!D100 -> 9030 | E83: =+Shepparton!E100 -> 7055 | F83: 5000
