Workbook

Sheet Fast Key
A1: Standard Rates
A3: 50sqm Concrete paving | BB3: =50*140 -> 7000 | BD3: Bonus will be reviewed in August 2025 | BI3: Revise price list at end of August
A4: Floor tiles | BB4: 96 | BD4: Up to 24 sq | BE4: 3000 | BI4: Check with Scott for price rise allowance
A5: Carpets | BB5: 55 | BD5: Above 24 sq | BE5: 4000
A6: Price rise allowance | BB6: 0
BB8: Shepparton | BC8: Echuca
BB9: 6 Months | BC9: 6 Months | BD9: Bonus | BF9: Floor Tiles | BG9: Wastage | BI9: Carpets | BJ9: Wastage
AE10: Windows | AO10: Sliding doors | AV10: Built-in robes/linens
A11: Single storey | B11: Dwelling area | C11: Garage area | D11: Porch area | E11: Outdoor living area | F11: Porch concrete footing | G11: Outdoor living footing | H11: Brick pier | I11: 90x90 steel columns | J11: Eaves | K11: Hip length | L11: Valley length | M11: Ridge length | N11: Perimeter walls | O11: Internal walls | P11: Plaster bulkheads | Q11: Kitchen wall bench | R11: Kitchen overhead cupboard | S11: Kitchen island bench | T11: Ens vanity bench | U11: Ens vanity basin | V11: Bath vanity bench | W11: Bath vanity basin | X11: Extra vanity bench | Y11: Extra vanity basin | Z11: Laundry bench | AA11: Internal swing door | AB11: Internal double swing door | AC11: Internal cavity sliders | AD11: Internal double cavity slider | AE11: 1006 | AF11: 1212 | AG11: 1215 | AH11: 1809 | AI11: 1812 | AJ11: 1818 | AK11: 1821 | AL11: 1824 | AM11: External swing door Entry | AN11: External swing door Garage | AO11: 2115 | AP11: 2118 | AQ11: 2121 | AR11: 2124 | AS11: 2127 | AT11: 2136 | AU11: 2155 | AV11: Up to 1800mm wide | AW11: 1800mm to 2500mm wide | AX11: 2500mm to 3000mm wide | AY11: Linen shelving - 4 shelves | AZ11: Robe shelving wth hanging rail | BA11: End panels
B12: m2 | C12: m2 | D12: m2 | E12: m2 | F12: lm | G12: lm | H12: each | I12: each | J12: lm | K12: lm | L12: lm | M12: lm | N12: lm | O12: lm | P12: lm | Q12: lm | R12: lm | S12: lm | T12: lm | U12: each | V12: lm | W12: each | X12: lm | Y12: each | Z12: lm | AA12: each | AB12: each | AC12: each | AD12: each | AE12: each | AF12: each | AG12: each | AH12: each | AI12: each | AJ12: each | AK12: each | AL12: each | AM12: each | AN12: each | AO12: each | AP12: each | AQ12: each | AR12: each | AS12: each | AT12: each | AU12: each | AV12: each | AW12: each | AX12: each | AY12: each | AZ12: each | BA12: each
A13: Byron 19 | B13: 120.71 | C13: 38.81 | D13: 5.06 | E13: 9.51 | F13: 3.8 | G13: 6.4 | H13: 1 | I13: 1 | J13: 7.09 | K13: 35.223 | L13: 9.003 | M13: 12.45 | N13: 45.17 | O13: 50.8 | P13: 3.16 | Q13: 1.5 | R13: 1.5 | S13: 2.4 | T13: 0.9 | U13: 1 | V13: 0.9 | W13: 1 | X13: 0 | Y13: 0 | Z13: 1.2 | AA13: 9 | AB13: 0 | AC13: 0 | AD13: 0 | AE13: 1 | AF13: 1 | AG13: 2 | AJ13: 1 | AP13: 1 | BB13: 270995 | BE13: =+BC13-BB13 -> -270995 | BF13: 55.87 | BG13: 1.1 | BH13: =+BG13*BF13 -> 61.457 | BI13: 49.72 | BJ13: 1.1 | BK13: =+BJ13*BI13 -> 54.692
A14: Byron 22A | B14: 142.05 | C14: 38.79 | D14: 5.06 | E14: 10.31 | H14: 1 | J14: 7.09 | K14: 35.226 | L14: 9.003 | M14: 14.97 | N14: 50.21 | O14: 54.65 | P14: 3.16 | Q14: 1.43 | R14: 1.43 | S14: 2.35 | T14: 0.9 | U14: 1 | V14: 0.9 | W14: 1 | X14: 0 | Y14: 0 | Z14: 1.2 | BB14: 289755 | BE14: =+BC14-BB14 -> -289755 | BF14: 66.31 | BG14: 1.1 | BH14: =+BG14*BF14 -> 72.941 | BI14: 61.4 | BJ14: 1.1 | BK14: =+BJ14*BI14 -> 67.54
A15: Byron 22B | B15: 154.9 | C15: 38.57 | D15: 4.18 | E15: 11.61 | H15: 2 | J15: 5.965 | K15: 37.711 | L15: 10.26 | M15: 15.34 | N15: 51.73 | O15: 64.2 | P15: 2.8 | Q15: 3.1 | R15: 1.9 | S15: 2.5 | T15: 1.2 | U15: 1 | V15: 0.9 | W15: 1 | X15: 0 | Y15: 0 | Z15: 1.2 | BB15: 294955 | BE15: =+BC15-BB15 -> -294955 | BF15: 70.17 | BG15: 1.1 | BH15: =+BG15*BF15 -> 77.187 | BI15: 60.8 | BJ15: 1.1 | BK15: =+BJ15*BI15 -> 66.88
A16: Ashwood 17 | B16: 154.9 | C16: 38.57 | D16: 4.18 | E16: 11.66 | H16: 2 | J16: 5.965 | K16: 37.711 | L16: 10.26 | M16: 15.34 | N16: 51.73 | O16: 68.35 | P16: 2.8 | Q16: 3.1 | R16: 1.9 | S16: 2.5 | T16: 1.2 | U16: 1 | V16: 0.9 | W16: 1 | X16: 0 | Y16: 0 | Z16: 1.2 | BB16: 253005 | BE16: =+BC16-BB16 -> -253005 | BF16: 51.76 | BG16: 1.1 | BH16: =+BG16*BF16 -> 56.936 | BI16: 37.9 | BJ16: 1.1 | BK16: =+BJ16*BI16 -> 41.69
A17: Ashwood 20 | B17: 170.21 | C17: 38.68 | D17: 5.08 | E17: 11.92 | H17: 1 | J17: 7.09 | K17: 37.32 | L17: 9.002 | M17: 15.66 | N17: 55.29 | O17: 67.25 | P17: 3.9 | Q17: 2.08 | R17: 2.08 | S17: 2.7 | T17: 0.9 | U17: 1 | V17: 0.9 | W17: 1 | X17: 0 | Y17: 0 | Z17: 1.2 | BB17: 276490 | BE17: =+BC17-BB17 -> -276490 | BF17: 55.5 | BG17: 1.1 | BH17: =+BG17*BF17 -> 61.05 | BI17: 61.4 | BJ17: 1.1 | BK17: =+BJ17*BI17 -> 67.54
A18: Malvern 20 | B18: 269.78 | C18: 41.25 | D18: 6.32 | E18: 13.24 | H18: 3 | J18: 6.69 | K18: 41.9 | L18: 9.02 | M18: 11.26 | N18: 51.01 | O18: 75.35 | P18: 3.75 | Q18: 2.75 | R18: 2.75 | S18: 2.7 | T18: 0.9 | U18: 1 | V18: 0.9 | W18: 1 | X18: 0 | Y18: 0 | Z18: 1.2 | BB18: 282770 | BE18: =+BC18-BB18 -> -282770 | BF18: 52.9 | BG18: 1.1 | BH18: =+BG18*BF18 -> 58.19 | BI18: 64 | BJ18: 1.1 | BK18: =+BJ18*BI18 -> 70.4
A19: Malvern 23 | B19: 201.44 | C19: 41.23 | D19: 7.14 | E19: 28.76 | H19: 4 | J19: 6.635 | K19: 45.2 | L19: 22.53 | M19: 20.6 | N19: 55.19 | O19: 92.7 | P19: 6.78 | Q19: 2.75 | R19: 2.75 | S19: 2.7 | T19: 0.9 | U19: 1 | V19: 0.9 | W19: 1 | X19: 1.2 | Y19: 1 | Z19: 1.2 | BB19: 304150 | BE19: =+BC19-BB19 -> -304150 | BF19: 69.3 | BG19: 1.1 | BH19: =+BG19*BF19 -> 76.23 | BI19: 73.3 | BJ19: 1.1 | BK19: =+BJ19*BI19 -> 80.63
A20: Malvern 25 | BB20: 332790 | BE20: =+BC20-BB20 -> -332790 | BF20: 68 | BG20: 1.1 | BH20: =+BG20*BF20 -> 74.8 | BI20: 89.1 | BJ20: 1.1 | BK20: =+BJ20*BI20 -> 98.01
B21: 228.94 | C21: 41.16 | D21: 7.38 | E21: 37.68 | H21: 4 | J21: 6.64 | K21: 47.261 | L21: 25.68 | M21: 24.465 | N21: 60 | O21: 101 | P21: 6.7 | Q21: 2.85 | R21: 2.85 | S21: 2.7 | T21: 0.9 | U21: 1 | V21: 0.9 | W21: 1 | X21: 1.33 | Y21: 1 | Z21: 1.2 | BE21: =+BC21-BB21 -> 0 | BG21: 1.1 | BH21: =+BG21*BF21 -> 0 | BJ21: 1.1 | BK21: =+BJ21*BI21 -> 0
B22: 126.99 | C22: 38.55 | D22: 5.03 | E22: 9.24 | H22: 2 | J22: 6.08 | K22: 40.75 | L22: 10.6 | M22: 9.32 | N22: 44.06 | O22: 51.35 | P22: 4.06 | Q22: 2.24 | R22: 2.24 | S22: 2.7 | T22: 0.9 | U22: 1 | V22: 0.9 | W22: 1 | X22: 0 | Y22: 0 | Z22: 1.2 | BE22: =+BC22-BB22 -> 0 | BG22: 1.1 | BH22: =+BG22*BF22 -> 0 | BJ22: 1.1 | BK22: =+BJ22*BI22 -> 0
BE23: =+BC23-BB23 -> 0 | BG23: 1.1 | BH23: =+BG23*BF23 -> 0 | BJ23: 1.1 | BK23: =+BJ23*BI23 -> 0
B24: 155.58 | C24: 37.55 | D24: 4.13 | E24: 10.65 | H24: 2 | J24: 6.9 | K24: 41.15 | L24: 11.14 | M24: 11.64 | N24: 48.69 | O24: 66.87 | P24: 2.7 | Q24: 1.8 | R24: 1.8 | S24: 2.7 | T24: 0.9 | U24: 1 | V24: 0.9 | W24: 1 | X24: 0 | Y24: 0 | Z24: 1.2 | BE24: =+BC24-BB24 -> 0 | BG24: 1.1 | BH24: =+BG24*BF24 -> 0 | BJ24: 1.1 | BK24: =+BJ24*BI24 -> 0
BO162: 375197.45 | BR162: 90 | BS162: =+#REF!*BR162 -> #REF!
BO163: 405966.8 | BR163: =+BR162 -> 90 | BS163: =+#REF!*BR163 -> #REF!
BO164: 422024.06 | BR164: =+BR163 -> 90 | BS164: =+#REF!*BR164 -> #REF!
BO165: 349552.12 | BR165: =+BR164 -> 90 | BS165: =+#REF!*BR165 -> #REF!
BO166: 380005.84 | BR166: =+BR165 -> 90 | BS166: =+#REF!*BR166 -> #REF!
BO167: 393926.2 | BR167: =+BR166 -> 90 | BS167: =+#REF!*BR167 -> #REF!
BO168: 406710.24 | BR168: =+BR167 -> 90 | BS168: =+#REF!*BR168 -> #REF!
BO169: 423263.1 | BR169: =+BR168 -> 90 | BS169: =+#REF!*BR169 -> #REF!
BO170: 472654.46 | BR170: =+BR169 -> 90 | BS170: =+#REF!*BR170 -> #REF!
BO171: 340735.79 | BR171: =+BR170 -> 90 | BS171: =+#REF!*BR171 -> #REF!
BO172: 359987.02 | BR172: =+BR171 -> 90 | BS172: =+#REF!*BR172 -> #REF!
BO173: 404153.49 | BR173: =+BR172 -> 90 | BS173: =+#REF!*BR173 -> #REF!
BO174: 323516.22 | BR174: =+BR173 -> 90 | BS174: =+#REF!*BR174 -> #REF!
... BO176: 384787.17 | BR176: =+BR175 -> 90 | BS176: =+#REF!*BR176 -> #REF!

Sheet Landscaping
C5: Seed | D5: Turf | E5: Turf with excavation
B6: 600m2 | C6: 14154.02 | D6: 16686.01 | E6: 18542.01 | H6: =+D6-C6 -> 2531.99 | J6: =+E6-D6 -> 1856
B7: 800m2 | C7: 17723.13 | D7: 21199.93 | E7: 23055.26 | H7: =+D7-C7 -> 3476.8 | J7: =+E7-D7 -> 1855.33
B8: Nature strip | E8: 1918.24
B9: Corner block | E9: 3841.6
B10: External power point | E10: =+#REF! -> #REF!
C13: Seed | D13: Turf | F13: July 2025 Pricelist - Sijo added 5 %
B14: 600m2 normal block | C14: =CEILING((C6+J6+E8)*1.36*1.05,50)+E10 -> #REF! | D14: =CEILING((E6+E8)*1.36*1.05,25)+E10 -> #REF!
B15: 600m2 corner block | C15: =+CEILING((C6+J6+E9)*1.36*1.05,25)+E10 -> #REF! | D15: =+CEILING((E6+E9)*1.36*1.05,25)+E10 -> #REF!
B16: 800m2 normal block | C16: =+CEILING((C7+J6+E8)*1.36*1.05,25)+E10 -> #REF! | D16: =+CEILING((E7+E8)*1.36*1.05,25)+E10 -> #REF!
B17: 800m2 corner block | C17: =+CEILING((C7+E9+J6)*1.36*1.05,25)+E10 -> #REF! | D17: =+CEILING((E7+E9)*1.36*1.05,25)+E10 -> #REF!

Sheet Shepparton
A1: SHEPPARTON
A2: FAST KEY
A3: HOUSE DESIGN | B3: BASE PRICE * | C3: 50sqm NATURAL CONCRETE | D3: LIFESTYLE FLOOR TILES | E3: LIFESTYLE CARPETS | F3: PACKAGE PRICE *50sqm NATURAL CONCRETE *CARPET *TILES | H3: List price | I3: Promotional | J3: Bonus | K3: 50sqm natural concrete | L3: Tiles per sqm | M3: Carpet per sqm
A4: Byron 19 | B4: =+CEILING(H4+I4+J4,5) -> 270995 | C4: =+K4 -> 7000 | D4: =+CEILING('Fast Key'!BH13*Shepparton!L4,5) -> 5900 | E4: =+CEILING('Fast Key'!BK13*Shepparton!M4,5) -> 3010 | F4: =SUM(B4:E4) -> 286905 | H4: =+'Fast Key'!BB13 -> 270995 | I4: =+'Fast Key'!BB6 -> 0 | J4: =+'Fast Key'!BD13 -> 0 | K4: =+'Fast Key'!BB3 -> 7000 | L4: =+'Fast Key'!BB4 -> 96 | M4: =+'Fast Key'!BB5 -> 55
A5: Byron 22A | B5: =+CEILING(H5+I5+J5,5) -> 289755 | C5: =+K5 -> 7000 | D5: =+CEILING('Fast Key'!BH14*Shepparton!L5,5) -> 7005 | E5: =+CEILING('Fast Key'!BK14*Shepparton!M5,5) -> 3715 | F5: =SUM(B5:E5) -> 307475 | H5: =+'Fast Key'!BB14 -> 289755 | I5: =+I4 -> 0 | J5: =+'Fast Key'!BD14 -> 0 | K5: =+K4 -> 7000 | L5: =+L4 -> 96 | M5: =+M4 -> 55
A6: Byron 22B | B6: =+CEILING(H6+I6+J6,5) -> 294955 | C6: =+K6 -> 7000 | D6: =+CEILING('Fast Key'!BH15*Shepparton!L6,5) -> 7410 | E6: =+CEILING('Fast Key'!BK15*Shepparton!M6,5) -> 3680 | F6: =SUM(B6:E6) -> 313045 | H6: =+'Fast Key'!BB15 -> 294955 | I6: =+I5 -> 0 | J6: =+'Fast Key'!BD15 -> 0 | K6: =+K5 -> 7000 | L6: =+L5 -> 96 | M6: =+M5 -> 55
A7: Ashwood 17 | B7: =+CEILING(H7+I7+J7,5) -> 253005 | C7: =+K7 -> 7000 | D7: =+CEILING('Fast Key'!BH16*Shepparton!L7,5) -> 5470 | E7: =+CEILING('Fast Key'!BK16*Shepparton!M7,5) -> 2295 | F7: =SUM(B7:E7) -> 267770 | H7: =+'Fast Key'!BB16 -> 253005 | I7: =+I6 -> 0 | J7: =+'Fast Key'!BD16 -> 0 | K7: =+K6 -> 7000 | L7: =+L6 -> 96 | M7: =+M6 -> 55
A8: Ashwood 20 | B8: =+CEILING(H8+I8+J8,5) -> 276490 | C8: =+K8 -> 7000 | D8: =+CEILING('Fast Key'!BH17*Shepparton!L8,5) -> 5865 | E8: =+CEILING('Fast Key'!BK17*Shepparton!M8,5) -> 3715 | F8: =SUM(B8:E8) -> 293070 | H8: =+'Fast Key'!BB17 -> 276490 | I8: =+I7 -> 0 | J8: =+'Fast Key'!BD17 -> 0 | K8: =+K7 -> 7000 | L8: =+L7 -> 96 | M8: =+M7 -> 55
A9: Malvern 20 | B9: =+CEILING(H9+I9+J9,5) -> 282770 | C9: =+K9 -> 7000 | D9: =+CEILING('Fast Key'!BH18*Shepparton!L9,5) -> 5590 | E9: =+CEILING('Fast Key'!BK18*Shepparton!M9,5) -> 3875 | F9: =SUM(B9:E9) -> 299235 | H9: =+'Fast Key'!BB18 -> 282770 | I9: =+I8 -> 0 | J9: =+'Fast Key'!BD18 -> 0 | K9: =+K8 -> 7000 | L9: =+L8 -> 96 | M9: =+M8 -> 55
A10: Malvern 23 | B10: =+CEILING(H10+I10+J10,5) -> 304150 | C10: =+K10 -> 7000 | D10: =+CEILING('Fast Key'!BH19*Shepparton!L10,5) -> 7320 | E10: =+CEILING('Fast Key'!BK19*Shepparton!M10,5) -> 4435 | F10: =SUM(B10:E10) -> 322905 | H10: =+'Fast Key'!BB19 -> 304150 | I10: =+I9 -> 0 | J10: =+'Fast Key'!BD19 -> 0 | K10: =+K9 -> 7000 | L10: =+L9 -> 96 | M10: =+M9 -> 55
A11: Malvern 25 | B11: =+CEILING(H11+I11+J11,5) -> 332790 | C11: =+K11 -> 7000 | D11: =+CEILING('Fast Key'!BH20*Shepparton!L11,5) -> 7185 | E11: =+CEILING('Fast Key'!BK20*Shepparton!M11,5) -> 5395 | F11: =SUM(B11:E11) -> 352370 | H11: =+'Fast Key'!BB20 -> 332790 | I11: =+I10 -> 0 | J11: =+'Fast Key'!BD20 -> 0 | K11: =+K10 -> 7000 | L11: =+L10 -> 96 | M11: =+M10 -> 55
B12: =+CEILING(H12+I12+J12,10) -> 0 | C12: =+K12 -> 7000 | D12: =+CEILING('Fast Key'!BH21*Shepparton!L12,5) -> 0 | E12: =+CEILING('Fast Key'!BK21*Shepparton!M12,5) -> 0 | F12: =SUM(B12:E12) -> 7000 | H12: =+'Fast Key'!BB21 -> 0 | I12: =+I11 -> 0 | J12: =+'Fast Key'!BD21 -> 0 | K12: =+K11 -> 7000 | L12: =+L11 -> 96 | M12: =+M11 -> 55
B13: =+CEILING(H13+I13+J13,10) -> 0 | C13: =+K13 -> 7000 | D13: =+CEILING('Fast Key'!BH22*Shepparton!L13,5) -> 0 | E13: =+CEILING('Fast Key'!BK22*Shepparton!M13,5) -> 0 | F13: =SUM(B13:E13) -> 7000 | H13: =+'Fast Key'!BB22 -> 0 | I13: =+I12 -> 0 | J13: =+'Fast Key'!BD22 -> 0 | K13: =+K12 -> 7000 | L13: =+L12 -> 96 | M13: =+M12 -> 55
B14: =+CEILING(H14+I14+J14,10) -> 0 | C14: =+K14 -> 7000 | D14: =+CEILING('Fast Key'!BH23*Shepparton!L14,5) -> 0 | E14: =+CEILING('Fast Key'!BK23*Shepparton!M14,5) -> 0 | F14: =SUM(B14:E14) -> 7000 | H14: =+'Fast Key'!BB23 -> 0 | I14: =+I13 -> 0 | J14: =+'Fast Key'!BD23 -> 0 | K14: =+K13 -> 7000 | L14: =+L13 -> 96 | M14: =+M13 -> 55
B15: =+CEILING(H15+I15+J15,10) -> 0 | C15: =+K15 -> 7000 | D15: =+CEILING('Fast Key'!BH24*Shepparton!L15,5) -> 0 | E15: =+CEILING('Fast Key'!BK24*Shepparton!M15,5) -> 0 | F15: =SUM(B15:E15) -> 7000 | H15: =+'Fast Key'!BB24 -> 0 | I15: =+I14 -> 0 | J15: =+'Fast Key'!BD24 -> 0 | K15: =+K14 -> 7000 | L15: =+L14 -> 96 | M15: =+M14 -> 55
B16: =+CEILING(H16+I16+J16,10) -> 0 | C16: =+K16 -> 7000 | D16: =+CEILING('Fast Key'!BH25*Shepparton!L16,5) -> 0 | E16: =+CEILING('Fast Key'!BK25*Shepparton!M16,5) -> 0 | F16: =SUM(B16:E16) -> 7000 | H16: =+'Fast Key'!BB25 -> 0 | I16: =+I15 -> 0 | J16: =+'Fast Key'!BD25 -> 0 | K16: =+K15 -> 7000 | L16: =+L15 -> 96 | M16: =+M15 -> 55
A18: BASE PRICE INCLUDES: | E18: BASE PRICE DOES NOT INCLUDE:
A19: *SEWER, STORMWATER AND POWER | E19: *SITE PIERING
A20: TO A 700m2 BLOCK | E20: *RAISED PORTICO
A21: *20m TEMP FENCING | E21: *TILES & CARPET
A22: *'MD' CLASS SLAB | E22: *EXTERNAL PAVING
E23: *EAVES

Sheet Investor
A1: INVESTOR PRICE LIST VALID UP TO DECEMBER 2025
A2: HOUSE DESIGN | B2: BASE PRICE * | C2: 60sqm NATURAL CONCRETE | D2: ASPIRE FLOOR TILES | E2: ASPIRE CARPET | F2: ROLLER BLINDS TO ALL WINDOWS AND SLIDING DOORS | G2: TV ANTENNA | H2: SPLIT SYSTEM TO FAMILY ROOM | I2: WALL MOUNTED CLOTHESLINE | J2: COLORBOND LETTER BOX | K2: PACKAGE PRICE | O2: 60sqm natural concrete | P2: Aspire Tiles per sqm | Q2: Aspire Carpet per sqm
A3: Kiewa 15 | B3: =+CEILING(N3+M3,10) -> 6000 | C3: =+O3 -> 8400 | D3: =+CEILING('Fast Key'!BH144*Investor!P3,5) -> 0 | E3: =+CEILING('Fast Key'!BK144*Investor!Q3,5) -> 0 | F3: =9*195 -> 1755 | G3: =+#REF! -> #REF! | H3: INCLUDED | I3: =+#REF! -> #REF! | J3: =+#REF! -> #REF! | K3: =SUM(B3:J3) -> #REF! | M3: 6000 | N3: =+'Fast Key'!BB144 -> 0 | O3: =60*140 -> 8400 | P3: 95 | Q3: 56
A4: Kiewa 17 | B4: =+CEILING(N4+M4,10) -> 6000 | C4: =+O4 -> 8400 | D4: =+CEILING('Fast Key'!BH145*Investor!P4,5) -> 0 | E4: =+CEILING('Fast Key'!BK145*Investor!Q4,5) -> 0 | F4: =10*195 -> 1950 | G4: =+G3 -> #REF! | H4: INCLUDED | I4: =+I3 -> #REF! | J4: =+J3 -> #REF! | K4: =SUM(B4:J4) -> #REF! | M4: =+M3 -> 6000 | N4: =+'Fast Key'!BB145 -> 0 | O4: =+O3 -> 8400 | P4: =+P3 -> 95 | Q4: =+Q3 -> 56
A5: Kiewa 18 | B5: =+CEILING(N5+M5,10) -> 6000 | C5: =+O5 -> 8400 | D5: =+CEILING('Fast Key'!BH146*Investor!P5,5) -> 0 | E5: =+CEILING('Fast Key'!BK146*Investor!Q5,5) -> 0 | F5: =11*195 -> 2145 | G5: =+G4 -> #REF! | H5: INCLUDED | I5: =+I4 -> #REF! | J5: =+J4 -> #REF! | K5: =SUM(B5:J5) -> #REF! | M5: =+M4 -> 6000 | N5: =+'Fast Key'!BB146 -> 0 | O5: =+O4 -> 8400 | P5: =+P4 -> 95 | Q5: =+Q4 -> 56
A6: Kiewa 21 | B6: =+CEILING(N6+M6,10) -> 6000 | C6: =+O6 -> 8400 | D6: =+CEILING('Fast Key'!BH147*Investor!P6,5) -> 0 | E6: =+CEILING('Fast Key'!BK147*Investor!Q6,5) -> 0 | F6: =12*195 -> 2340 | G6: =+G5 -> #REF! | H6: 4150 | I6: =+I5 -> #REF! | J6: =+J5 -> #REF! | K6: =SUM(B6:J6) -> #REF! | M6: =+M5 -> 6000 | N6: =+'Fast Key'!BB147 -> 0 | O6: =+O5 -> 8400 | P6: =+P5 -> 95 | Q6: =+Q5 -> 56
A7: Prices based on a Standard Façade
A9: ## THESE RATES APPLY ONLY FOR INVESTORS, NOT OWNER-OCCUPIERS ##
A10: ## FOR OWNER-OCCUPIERS PLEASE USE THE MAIN PRICE LIST ##
A12: LANDSCAPING PRICES
A13: Size | C13: Seed | D13: Turf
A14: =+Landscaping!B14 -> 600m2 normal block | C14: =+Landscaping!C14 -> #REF! | D14: =+Landscaping!D14 -> #REF! | F14: Includes automated sprinkler sytem
A15: =+Landscaping!B15 -> 600m2 corner block | C15: =+Landscaping!C15 -> #REF! | D15: =+Landscaping!D15 -> #REF! | F15: Credit $600 to go down to a manual system
A16: =+Landscaping!B16 -> 800m2 normal block | C16: =+Landscaping!C16 -> #REF! | D16: =+Landscaping!D16 -> #REF!
A17: =+Landscaping!B17 -> 800m2 corner block | C17: =+Landscaping!C17 -> #REF! | D17: =+Landscaping!D17 -> #REF!

Sheet Echuca
A1: ECHUCA
A2: LIFESTYLE SINGLE STOREY PRICE LIST VALID UP TO DEC 2025
A3: HOUSE DESIGN | B3: BASE PRICE * | C3: 50sqm NATURAL CONCRETE | D3: LIFESTYLE FLOOR TILES | E3: LIFESTYLE CARPETS | F3: PACKAGE PRICE *50sqm NATURAL CONCRETE *CARPET *TILES | G3: PRICE TO ADD EAVES | I3: List price | J3: Promotional | K3: Bonus | L3: 50sqm natural concrete | M3: Tiles per sqm | N3: Carpet per sqm | O3: Eaves per lm
A4: Adelaide 18 | B4: =+CEILING(I4+J4+K4,10) -> 0 | C4: =+L4 -> #REF! | D4: =+Shepparton!D4 -> 5900 | E4: =+Shepparton!E4 -> 3010 | F4: =SUM(B4:E4) -> #REF! | G4: =+Shepparton!#REF! -> #REF! | I4: =+'Fast Key'!BC13 -> 0 | J4: =+'Fast Key'!BB6 -> 0 | K4: =+'Fast Key'!BD13 -> 0 | L4: =50*'2.TRAVEL'!#REF! -> #REF! | M4: 103 | N4: 60 | O4: 65
A5: Adelaide 21 | B5: =+CEILING(I5+J5+K5,10) -> 0 | C5: =+L5 -> #REF! | D5: =+Shepparton!D5 -> 7005 | E5: =+Shepparton!E5 -> 3715 | F5: =SUM(B5:E5) -> #REF! | G5: =+Shepparton!#REF! -> #REF! | I5: =+'Fast Key'!BC14 -> 0 | J5: =+J4 -> 0 | K5: =+'Fast Key'!BD14 -> 0 | L5: =+L4 -> #REF! | M5: =+M4 -> 103 | N5: =+N4 -> 60 | O5: =+O4 -> 65
A6: Adelaide 22A | B6: =+CEILING(I6+J6+K6,10) -> 0 | C6: =+L6 -> #REF! | D6: =+Shepparton!D6 -> 7410 | E6: =+Shepparton!E6 -> 3680 | F6: =SUM(B6:E6) -> #REF! | G6: =+Shepparton!#REF! -> #REF! | I6: =+'Fast Key'!BC15 -> 0 | J6: =+J5 -> 0 | K6: =+'Fast Key'!BD15 -> 0 | L6: =+L5 -> #REF! | M6: =+M5 -> 103 | N6: =+N5 -> 60 | O6: =+O5 -> 65
A7: Adelaide 22B | B7: =+CEILING(I7+J7+K7,10) -> 0 | C7: =+L7 -> #REF! | D7: =+Shepparton!D7 -> 5470 | E7: =+Shepparton!E7 -> 2295 | F7: =SUM(B7:E7) -> #REF! | G7: =+Shepparton!#REF! -> #REF! | I7: =+'Fast Key'!BC16 -> 0 | J7: =+J6 -> 0 | K7: =+'Fast Key'!BD16 -> 0 | L7: =+L6 -> #REF! | M7: =+M6 -> 103 | N7: =+N6 -> 60 | O7: =+O6 -> 65
A8: Adelaide 24 | B8: =+CEILING(I8+J8+K8,10) -> 0 | C8: =+L8 -> #REF! | D8: =+Shepparton!D8 -> 5865 | E8: =+Shepparton!E8 -> 3715 | F8: =SUM(B8:E8) -> #REF! | G8: =+Shepparton!#REF! -> #REF! | I8: =+'Fast Key'!BC17 -> 0 | J8: =+J7 -> 0 | K8: =+'Fast Key'!BD17 -> 0 | L8: =+L7 -> #REF! | M8: =+M7 -> 103 | N8: =+N7 -> 60 | O8: =+O7 -> 65
A9: Ashfield 24 | B9: =+CEILING(I9+J9+K9,10) -> 0 | C9: =+L9 -> #REF! | D9: =+Shepparton!D9 -> 5590 | E9: =+Shepparton!E9 -> 3875 | F9: =SUM(B9:E9) -> #REF! | G9: =+Shepparton!#REF! -> #REF! | I9: =+'Fast Key'!BC18 -> 0 | J9: =+J8 -> 0 | K9: =+'Fast Key'!BD18 -> 0 | L9: =+L8 -> #REF! | M9: =+M8 -> 103 | N9: =+N8 -> 60 | O9: =+O8 -> 65
A10: Ashfield 30 | B10: =+CEILING(I10+J10+K10,10) -> 0 | C10: =+L10 -> #REF! | D10: =+Shepparton!D10 -> 7320 | E10: =+Shepparton!E10 -> 4435 | F10: =SUM(B10:E10) -> #REF! | G10: =+Shepparton!#REF! -> #REF! | I10: =+'Fast Key'!BC19 -> 0 | J10: =+J9 -> 0 | K10: =+'Fast Key'!BD19 -> 0 | L10: =+L9 -> #REF! | M10: =+M9 -> 103 | N10: =+N9 -> 60 | O10: =+O9 -> 65
A11: Ashfield 30A | B11: =+CEILING(I11+J11+K11,10) -> 0 | C11: =+L11 -> #REF! | D11: =+Shepparton!D11 -> 7185 | E11: =+Shepparton!E11 -> 5395 | F11: =SUM(B11:E11) -> #REF! | G11: =+Shepparton!#REF! -> #REF! | I11: =+'Fast Key'!BC20 -> 0 | J11: =+J10 -> 0 | K11: =+'Fast Key'!BD20 -> 0 | L11: =+L10 -> #REF! | M11: =+M10 -> 103 | N11: =+N10 -> 60 | O11: =+O10 -> 65
A12: Ashfield 34 | B12: =+CEILING(I12+J12+K12,10) -> 0 | C12: =+L12 -> #REF! | D12: =+Shepparton!D12 -> 0 | E12: =+Shepparton!E12 -> 0 | F12: =SUM(B12:E12) -> #REF! | G12: =+Shepparton!#REF! -> #REF! | I12: =+'Fast Key'!BC21 -> 0 | J12: =+J11 -> 0 | K12: =+'Fast Key'!BD21 -> 0 | L12: =+L11 -> #REF! | M12: =+M11 -> 103 | N12: =+N11 -> 60 | O12: =+O11 -> 65
A13: Ashley 19 | B13: =+CEILING(I13+J13+K13,10) -> 0 | C13: =+L13 -> #REF! | D13: =+Shepparton!D13 -> 0 | E13: =+Shepparton!E13 -> 0 | F13: =SUM(B13:E13) -> #REF! | G13: =+Shepparton!#REF! -> #REF! | I13: =+'Fast Key'!BC22 -> 0 | J13: =+J12 -> 0 | K13: =+'Fast Key'!BD22 -> 0 | L13: =+L12 -> #REF! | M13: =+M12 -> 103 | N13: =+N12 -> 60 | O13: =+O12 -> 65
A14: Ashley 21 | B14: =+CEILING(I14+J14+K14,10) -> 0 | C14: =+L14 -> #REF! | D14: =+Shepparton!D14 -> 0 | E14: =+Shepparton!E14 -> 0 | F14: =SUM(B14:E14) -> #REF! | G14: =+Shepparton!#REF! -> #REF! | I14: =+'Fast Key'!BC23 -> 0 | J14: =+J13 -> 0 | K14: =+'Fast Key'!BD23 -> 0 | L14: =+L13 -> #REF! | M14: =+M13 -> 103 | N14: =+N13 -> 60 | O14: =+O13 -> 65
A15: Ashley 22 | B15: =+CEILING(I15+J15+K15,10) -> 0 | C15: =+L15 -> #REF! | D15: =+Shepparton!D15 -> 0 | E15: =+Shepparton!E15 -> 0 | F15: =SUM(B15:E15) -> #REF! | G15: =+Shepparton!#REF! -> #REF! | I15: =+'Fast Key'!BC24 -> 0 | J15: =+J13 -> 0 | K15: =+'Fast Key'!BD24 -> 0 | L15: =+L13 -> #REF! | M15: =+M13 -> 103 | N15: =+N13 -> 60 | O15: =+O13 -> 65
A16: Ashley 22A | B16: =+CEILING(I16+J16+K16,10) -> 0 | C16: =+L16 -> #REF! | D16: =+Shepparton!D16 -> 0 | E16: =+Shepparton!E16 -> 0 | F16: =SUM(B16:E16) -> #REF! | G16: =+Shepparton!#REF! -> #REF! | I16: =+'Fast Key'!BC25 -> 0 | J16: =+J14 -> 0 | K16: =+'Fast Key'!BD25 -> 0 | L16: =+L14 -> #REF! | M16: =+M14 -> 103 | N16: =+N14 -> 60 | O16: =+O14 -> 65
A17: Ashley 24 | B17: =+CEILING(I17+J17+K17,10) -> 0 | C17: =+L17 -> #REF! | D17: =+Shepparton!#REF! -> #REF! | E17: =+Shepparton!#REF! -> #REF! | F17: =SUM(B17:E17) -> #REF! | G17: =+Shepparton!#REF! -> #REF! | I17: =+'Fast Key'!BC26 -> 0 | J17: =+J15 -> 0 | K17: =+'Fast Key'!BD26 -> 0 | L17: =+L15 -> #REF! | M17: =+M15 -> 103 | N17: =+N15 -> 60 | O17: =+O15 -> 65
A18: Ashley 25 | B18: =+CEILING(I18+J18+K18,10) -> 0 | C18: =+L18 -> #REF! | D18: =+Shepparton!#REF! -> #REF! | E18: =+Shepparton!#REF! -> #REF! | F18: =SUM(B18:E18) -> #REF! | G18: =+Shepparton!#REF! -> #REF! | I18: =+'Fast Key'!BC27 -> 0 | J18: =+J17 -> 0 | K18: =+'Fast Key'!BD27 -> 0 | L18: =+L17 -> #REF! | M18: =+M17 -> 103 | N18: =+N17 -> 60 | O18: =+O17 -> 65
A19: Ashley 25A | B19: =+CEILING(I19+J19+K19,10) -> 0 | C19: =+L19 -> #REF! | D19: =+Shepparton!#REF! -> #REF! | E19: =+Shepparton!#REF! -> #REF! | F19: =SUM(B19:E19) -> #REF! | G19: =+Shepparton!#REF! -> #REF! | I19: =+'Fast Key'!BC28 -> 0 | J19: =+J18 -> 0 | K19: =+'Fast Key'!BD28 -> 0 | L19: =+L18 -> #REF! | M19: =+M18 -> 103 | N19: =+N18 -> 60 | O19: =+O18 -> 65
A20: Ashley 26 | B20: =+CEILING(I20+J20+K20,10) -> 0 | C20: =+L20 -> #REF! | D20: =+Shepparton!#REF! -> #REF! | E20: =+Shepparton!#REF! -> #REF! | F20: =SUM(B20:E20) -> #REF! | G20: =+Shepparton!#REF! -> #REF! | I20: =+'Fast Key'!BC29 -> 0 | J20: =+J19 -> 0 | K20: =+'Fast Key'!BD29 -> 0 | L20: =+L19 -> #REF! | M20: =+M19 -> 103 | N20: =+N19 -> 60 | O20: =+O19 -> 65
A21: Ashley 27 | B21: =+CEILING(I21+J21+K21,10) -> 0 | C21: =+L21 -> #REF! | D21: =+Shepparton!#REF! -> #REF! | E21: =+Shepparton!#REF! -> #REF! | F21: =SUM(B21:E21) -> #REF! | G21: =+Shepparton!#REF! -> #REF! | I21: =+'Fast Key'!BC30 -> 0 | J21: =+J20 -> 0 | K21: =+'Fast Key'!BD30 -> 0 | L21: =+L20 -> #REF! | M21: =+M20 -> 103 | N21: =+N20 -> 60 | O21: =+O20 -> 65
A22: Ashley 28 | B22: =+CEILING(I22+J22+K22,10) -> 0 | C22: =+L22 -> #REF! | D22: =+Shepparton!#REF! -> #REF! | E22: =+Shepparton!#REF! -> #REF! | F22: =SUM(B22:E22) -> #REF! | G22: =+Shepparton!#REF! -> #REF! | I22: =+'Fast Key'!BC31 -> 0 | J22: =+J21 -> 0 | K22: =+'Fast Key'!BD31 -> 0 | L22: =+L21 -> #REF! | M22: =+M21 -> 103 | N22: =+N21 -> 60 | O22: =+O21 -> 65
A23: Ashley 28A | B23: =+CEILING(I23+J23+K23,10) -> 0 | C23: =+L23 -> #REF! | D23: =+Shepparton!#REF! -> #REF! | E23: =+Shepparton!#REF! -> #REF! | F23: =SUM(B23:E23) -> #REF! | G23: =+Shepparton!#REF! -> #REF! | I23: =+'Fast Key'!BC32 -> 0 | J23: =+J22 -> 0 | K23: =+'Fast Key'!BD32 -> 0 | L23: =+L22 -> #REF! | M23: =+M22 -> 103 | N23: =+N22 -> 60 | O23: =+O22 -> 65
A24: Ballina 24 | B24: =+CEILING(I24+J24+K24,10) -> 0 | C24: =+L24 -> #REF! | D24: =+Shepparton!#REF! -> #REF! | E24: =+Shepparton!#REF! -> #REF! | F24: =SUM(B24:E24) -> #REF! | G24: =+Shepparton!#REF! -> #REF! | I24: =+'Fast Key'!BC33 -> 0 | J24: =+J23 -> 0 | K24: =+'Fast Key'!BD33 -> 0 | L24: =+L23 -> #REF! | M24: =+M23 -> 103 | N24: =+N23 -> 60 | O24: =+O23 -> 65
A25: Ballina 30 | B25: =+CEILING(I25+J25+K25,10) -> 0 | C25: =+L25 -> #REF! | D25: =+Shepparton!#REF! -> #REF! | E25: =+Shepparton!#REF! -> #REF! | F25: =SUM(B25:E25) -> #REF! | G25: =+Shepparton!#REF! -> #REF! | I25: =+'Fast Key'!BC34 -> 0 | J25: =+J24 -> 0 | K25: =+'Fast Key'!BD34 -> 0 | L25: =+L24 -> #REF! | M25: =+M24 -> 103 | N25: =+N24 -> 60 | O25: =+O24 -> 65
A26: Ballina 30A | B26: =+CEILING(I26+J26+K26,10) -> 0 | C26: =+L26 -> #REF! | D26: =+Shepparton!#REF! -> #REF! | E26: =+Shepparton!#REF! -> #REF! | F26: =SUM(B26:E26) -> #REF! | G26: =+Shepparton!#REF! -> #REF! | I26: =+'Fast Key'!BC35 -> 0 | J26: =+J25 -> 0 | K26: =+'Fast Key'!BD35 -> 0 | L26: =+L25 -> #REF! | M26: =+M25 -> 103 | N26: =+N25 -> 60 | O26: =+O25 -> 65
A27: Ballina 33 | B27: =+CEILING(I27+J27+K27,10) -> 0 | C27: =+L27 -> #REF! | D27: =+Shepparton!#REF! -> #REF! | E27: =+Shepparton!#REF! -> #REF! | F27: =SUM(B27:E27) -> #REF! | G27: =+Shepparton!#REF! -> #REF! | I27: =+'Fast Key'!BC36 -> 0 | J27: =+J25 -> 0 | K27: =+'Fast Key'!BD36 -> 0 | L27: =+L25 -> #REF! | M27: =+M25 -> 103 | N27: =+N25 -> 60 | O27: =+O25 -> 65
A28: Ballina 39 | B28: =+CEILING(I28+J28+K28,10) -> 0 | C28: =+L28 -> #REF! | D28: =+Shepparton!#REF! -> #REF! | E28: =+Shepparton!#REF! -> #REF! | F28: =SUM(B28:E28) -> #REF! | G28: =+Shepparton!#REF! -> #REF! | I28: =+'Fast Key'!BC37 -> 0 | J28: =+J27 -> 0 | K28: =+'Fast Key'!BD37 -> 0 | L28: =+L27 -> #REF! | M28: =+M27 -> 103 | N28: =+N27 -> 60 | O28: =+O27 -> 65
A29: =+'Fast Key'!A38 -> 0 | B29: =+CEILING(I29+J29+K29,10) -> 0 | C29: =+L29 -> #REF! | D29: =+Shepparton!#REF! -> #REF! | E29: =+Shepparton!#REF! -> #REF! | F29: =SUM(B29:E29) -> #REF! | G29: =+Shepparton!#REF! -> #REF! | I29: =+'Fast Key'!BC38 -> 0 | J29: =+J28 -> 0 | K29: =+'Fast Key'!BD38 -> 0 | L29: =+L28 -> #REF! | M29: =+M28 -> 103 | N29: =+N28 -> 60 | O29: =+O28 -> 65
A30: =+'Fast Key'!A39 -> 0 | B30: =+CEILING(I30+J30+K30,10) -> 0 | C30: =+L30 -> #REF! | D30: =+Shepparton!#REF! -> #REF! | E30: =+Shepparton!#REF! -> #REF! | F30: =SUM(B30:E30) -> #REF! | G30: =+Shepparton!#REF! -> #REF! | I30: =+'Fast Key'!BC39 -> 0 | J30: =+J29 -> 0 | K30: =+'Fast Key'!BD39 -> 0 | L30: =+L29 -> #REF! | M30: =+M29 -> 103 | N30: =+N29 -> 60 | O30: =+O29 -> 65
A31: =+'Fast Key'!A40 -> 0 | B31: =+CEILING(I31+J31+K31,10) -> 0 | C31: =+L31 -> #REF! | D31: =+Shepparton!#REF! -> #REF! | E31: =+Shepparton!#REF! -> #REF! | F31: =SUM(B31:E31) -> #REF! | G31: =+Shepparton!#REF! -> #REF! | I31: =+'Fast Key'!BC40 -> 0 | J31: =+J30 -> 0 | K31: =+'Fast Key'!BD40 -> 0 | L31: =+L30 -> #REF! | M31: =+M30 -> 103 | N31: =+N30 -> 60 | O31: =+O30 -> 65
A32: Bayview 23 | B32: =+CEILING(I32+J32+K32,10) -> 0 | C32: =+L32 -> #REF! | D32: =+Shepparton!#REF! -> #REF! | E32: =+Shepparton!#REF! -> #REF! | F32: =SUM(B32:E32) -> #REF! | G32: =+Shepparton!#REF! -> #REF! | I32: =+'Fast Key'!BC41 -> 0 | J32: =+J31 -> 0 | K32: =+'Fast Key'!BD41 -> 0 | L32: =+L31 -> #REF! | M32: =+M31 -> 103 | N32: =+N31 -> 60 | O32: =+O31 -> 65
A33: Bayview 26 | B33: =+CEILING(I33+J33+K33,10) -> 0 | C33: =+L33 -> #REF! | D33: =+Shepparton!#REF! -> #REF! | E33: =+Shepparton!#REF! -> #REF! | F33: =SUM(B33:E33) -> #REF! | G33: =+Shepparton!#REF! -> #REF! | I33: =+'Fast Key'!BC42 -> 0 | J33: =+J32 -> 0 | K33: =+'Fast Key'!BD42 -> 0 | L33: =+L32 -> #REF! | M33: =+M32 -> 103 | N33: =+N32 -> 60 | O33: =+O32 -> 65
A34: Bayview 30 | B34: =+CEILING(I34+J34+K34,10) -> 0 | C34: =+L34 -> #REF! | D34: =+Shepparton!#REF! -> #REF! | E34: =+Shepparton!#REF! -> #REF! | F34: =SUM(B34:E34) -> #REF! | G34: =+Shepparton!#REF! -> #REF! | I34: =+'Fast Key'!BC43 -> 0 | J34: =+J33 -> 0 | K34: =+'Fast Key'!BD43 -> 0 | L34: =+L33 -> #REF! | M34: =+M33 -> 103 | N34: =+N33 -> 60 | O34: =+O33 -> 65
A35: Bondi 25 | B35: =+CEILING(I35+J35+K35,10) -> 0 | C35: =+L35 -> #REF! | D35: =+Shepparton!#REF! -> #REF! | E35: =+Shepparton!#REF! -> #REF! | F35: =SUM(B35:E35) -> #REF! | G35: =+Shepparton!#REF! -> #REF! | I35: =+'Fast Key'!BC44 -> 0 | J35: =+J34 -> 0 | K35: =+'Fast Key'!BD44 -> 0 | L35: =+L34 -> #REF! | M35: =+M34 -> 103 | N35: =+N34 -> 60 | O35: =+O34 -> 65
A36: Bondi 31 | B36: =+CEILING(I36+J36+K36,10) -> 0 | C36: =+L36 -> #REF! | D36: =+Shepparton!#REF! -> #REF! | E36: =+Shepparton!#REF! -> #REF! | F36: =SUM(B36:E36) -> #REF! | G36: =+Shepparton!#REF! -> #REF! | I36: =+'Fast Key'!BC45 -> 0 | J36: =+J35 -> 0 | K36: =+'Fast Key'!BD45 -> 0 | L36: =+L35 -> #REF! | M36: =+M35 -> 103 | N36: =+N35 -> 60 | O36: =+O35 -> 65
A37: Bondi 36 | B37: =+CEILING(I37+J37+K37,10) -> 0 | C37: =+L37 -> #REF! | D37: =+Shepparton!#REF! -> #REF! | E37: =+Shepparton!#REF! -> #REF! | F37: =SUM(B37:E37) -> #REF! | G37: =+Shepparton!#REF! -> #REF! | I37: =+'Fast Key'!BC46 -> 0 | J37: =+J36 -> 0 | K37: =+'Fast Key'!BD46 -> 0 | L37: =+L36 -> #REF! | M37: =+M36 -> 103 | N37: =+N36 -> 60 | O37: =+O36 -> 65
A38: Cambridge 22 | B38: =+CEILING(I38+J38+K38,10) -> 0 | C38: =+L38 -> #REF! | D38: =+Shepparton!#REF! -> #REF! | E38: =+Shepparton!#REF! -> #REF! | F38: =SUM(B38:E38) -> #REF! | G38: =+Shepparton!#REF! -> #REF! | I38: =+'Fast Key'!BC47 -> 0 | J38: =+J37 -> 0 | K38: =+'Fast Key'!BD47 -> 0 | L38: =+L37 -> #REF! | M38: =+M37 -> 103 | N38: =+N37 -> 60 | O38: =+O37 -> 65
A39: Cambridge 24 | B39: =+CEILING(I39+J39+K39,10) -> 0 | C39: =+L39 -> #REF! | D39: =+Shepparton!#REF! -> #REF! | E39: =+Shepparton!#REF! -> #REF! | F39: =SUM(B39:E39) -> #REF! | G39: =+Shepparton!#REF! -> #REF! | I39: =+'Fast Key'!BC48 -> 0 | J39: =+J38 -> 0 | K39: =+'Fast Key'!BD48 -> 0 | L39: =+L38 -> #REF! | M39: =+M38 -> 103 | N39: =+N38 -> 60 | O39: =+O38 -> 65
A40: Cambridge 26 | B40: =+CEILING(I40+J40+K40,10) -> 0 | C40: =+L40 -> #REF! | D40: =+Shepparton!#REF! -> #REF! | E40: =+Shepparton!#REF! -> #REF! | F40: =SUM(B40:E40) -> #REF! | G40: =+Shepparton!#REF! -> #REF! | I40: =+'Fast Key'!BC49 -> 0 | J40: =+J39 -> 0 | K40: =+'Fast Key'!BD49 -> 0 | L40: =+L39 -> #REF! | M40: =+M39 -> 103 | N40: =+N39 -> 60 | O40: =+O39 -> 65
A41: Cambridge 30 | B41: =+CEILING(I41+J41+K41,10) -> 0 | C41: =+L41 -> #REF! | D41: =+Shepparton!#REF! -> #REF! | E41: =+Shepparton!#REF! -> #REF! | F41: =SUM(B41:E41) -> #REF! | G41: =+Shepparton!#REF! -> #REF! | I41: =+'Fast Key'!BC50 -> 0 | J41: =+J40 -> 0 | K41: =+'Fast Key'!BD50 -> 0 | L41: =+L40 -> #REF! | M41: =+M40 -> 103 | N41: =+N40 -> 60 | O41: =+O40 -> 65
A43: BASE PRICE INCLUDES: | E43: BASE PRICE DOES NOT INCLUDE:
A44: *SEWER, STORMWATER AND POWER | E44: *SITE PIERING
A45: TO A 700m2 BLOCK | E45: *RAISED PORTICO
A46: *20m TEMP FENCING | E46: *TILES & CARPET
A47: *'MD' CLASS SLAB | E47: *EXTERNAL PAVING
E48: *EAVES
A49: ECHUCA
A50: =+A2 -> LIFESTYLE SINGLE STOREY PRICE LIST VALID UP TO DEC 2025
A51: HOUSE DESIGN | B51: BASE PRICE * | C51: 50sqm NATURAL CONCRETE | D51: LIFESTYLE FLOOR TILES | E51: LIFESTYLE CARPETS | F51: PACKAGE PRICE *50sqm NATURAL CONCRETE *CARPET *TILES | G51: PRICE TO ADD EAVES
A52: Duneed 22 | B52: =+CEILING(I52+J52+K52,10) -> 0 | C52: =+L52 -> #REF! | D52: =+Shepparton!#REF! -> #REF! | E52: =+Shepparton!#REF! -> #REF! | F52: =SUM(B52:E52) -> #REF! | G52: =+Shepparton!#REF! -> #REF! | I52: =+'Fast Key'!BC51 -> 0 | J52: =+J41 -> 0 | K52: =+'Fast Key'!BD51 -> 0 | L52: =+L41 -> #REF! | M52: =+M41 -> 103 | N52: =+N41 -> 60 | O52: =+O41 -> 65
A53: Duneed 23 | B53: =+CEILING(I53+J53+K53,10) -> 0 | C53: =+L53 -> #REF! | D53: =+Shepparton!#REF! -> #REF! | E53: =+Shepparton!#REF! -> #REF! | F53: =SUM(B53:E53) -> #REF! | G53: =+Shepparton!#REF! -> #REF! | I53: =+'Fast Key'!BC52 -> 0 | J53: =+J52 -> 0 | K53: =+'Fast Key'!BD52 -> 0 | L53: =+L52 -> #REF! | M53: =+M52 -> 103 | N53: =+N52 -> 60 | O53: =+O52 -> 65
A54: Duneed 24 | B54: =+CEILING(I54+J54+K54,10) -> 0 | C54: =+L54 -> #REF! | D54: =+Shepparton!#REF! -> #REF! | E54: =+Shepparton!#REF! -> #REF! | F54: =SUM(B54:E54) -> #REF! | G54: =+Shepparton!#REF! -> #REF! | I54: =+'Fast Key'!BC53 -> 0 | J54: =+J53 -> 0 | K54: =+'Fast Key'!BD53 -> 0 | L54: =+L53 -> #REF! | M54: =+M53 -> 103 | N54: =+N53 -> 60 | O54: =+O53 -> 65
A55: Duneed 25 | B55: =+CEILING(I55+J55+K55,10) -> 0 | C55: =+L55 -> #REF! | D55: =+Shepparton!#REF! -> #REF! | E55: =+Shepparton!#REF! -> #REF! | F55: =SUM(B55:E55) -> #REF! | G55: =+Shepparton!#REF! -> #REF! | I55: =+'Fast Key'!BC54 -> 0 | J55: =+J54 -> 0 | K55: =+'Fast Key'!BD54 -> 0 | L55: =+L54 -> #REF! | M55: =+M54 -> 103 | N55: =+N54 -> 60 | O55: =+O54 -> 65
A56: Duneed 30 | B56: =+CEILING(I56+J56+K56,10) -> 0 | C56: =+L56 -> #REF! | D56: =+Shepparton!#REF! -> #REF! | E56: =+Shepparton!#REF! -> #REF! | F56: =SUM(B56:E56) -> #REF! | G56: =+Shepparton!#REF! -> #REF! | I56: =+'Fast Key'!BC55 -> 0 | J56: =+J55 -> 0 | K56: =+'Fast Key'!BD55 -> 0 | L56: =+L55 -> #REF! | M56: =+M55 -> 103 | N56: =+N55 -> 60 | O56: =+O55 -> 65
A57: Eclipse 23 | B57: =+CEILING(I57+J57+K57,10) -> 0 | C57: =+L57 -> #REF! | D57: =+Shepparton!#REF! -> #REF! | E57: =+Shepparton!#REF! -> #REF! | F57: =SUM(B57:E57) -> #REF! | G57: =+Shepparton!#REF! -> #REF! | I57: =+'Fast Key'!BC56 -> 0 | J57: =+J56 -> 0 | K57: =+'Fast Key'!BD56 -> 0 | L57: =+L56 -> #REF! | M57: =+M56 -> 103 | N57: =+N56 -> 60 | O57: =+O56 -> 65
A58: Eclipse 26 | B58: =+CEILING(I58+J58+K58,10) -> 0 | C58: =+L58 -> #REF! | D58: =+Shepparton!#REF! -> #REF! | E58: =+Shepparton!#REF! -> #REF! | F58: =SUM(B58:E58) -> #REF! | G58: =+Shepparton!#REF! -> #REF! | I58: =+'Fast Key'!BC57 -> 0 | J58: =+J57 -> 0 | K58: =+'Fast Key'!BD57 -> 0 | L58: =+L57 -> #REF! | M58: =+M57 -> 103 | N58: =+N57 -> 60 | O58: =+O57 -> 65
A59: Eclipse 28 | B59: =+CEILING(I59+J59+K59,10) -> 0 | C59: =+L59 -> #REF! | D59: =+Shepparton!#REF! -> #REF! | E59: =+Shepparton!#REF! -> #REF! | F59: =SUM(B59:E59) -> #REF! | G59: =+Shepparton!#REF! -> #REF! | I59: =+'Fast Key'!BC58 -> 0 | J59: =+J58 -> 0 | K59: =+'Fast Key'!BD58 -> 0 | L59: =+L58 -> #REF! | M59: =+M58 -> 103 | N59: =+N58 -> 60 | O59: =+O58 -> 65
A60: Hamilton 24 | B60: =+CEILING(I60+J60+K60,10) -> 0 | C60: =+L60 -> #REF! | D60: =+Shepparton!#REF! -> #REF! | E60: =+Shepparton!#REF! -> #REF! | F60: =SUM(B60:E60) -> #REF! | G60: =+Shepparton!#REF! -> #REF! | I60: =+'Fast Key'!BC59 -> 0 | J60: =+J59 -> 0 | K60: =+'Fast Key'!BD59 -> 0 | L60: =+L59 -> #REF! | M60: =+M59 -> 103 | N60: =+N59 -> 60 | O60: =+O59 -> 65
A61: Hamilton 29 | B61: =+CEILING(I61+J61+K61,10) -> 0 | C61: =+L61 -> #REF! | D61: =+Shepparton!#REF! -> #REF! | E61: =+Shepparton!#REF! -> #REF! | F61: =SUM(B61:E61) -> #REF! | G61: =+Shepparton!#REF! -> #REF! | I61: =+'Fast Key'!BC60 -> 0 | J61: =+J60 -> 0 | K61: =+'Fast Key'!BD60 -> 0 | L61: =+L60 -> #REF! | M61: =+M60 -> 103 | N61: =+N60 -> 60 | O61: =+O60 -> 65
A62: Hamilton 34 | B62: =+CEILING(I62+J62+K62,10) -> 0 | C62: =+L62 -> #REF! | D62: =+Shepparton!#REF! -> #REF! | E62: =+Shepparton!#REF! -> #REF! | F62: =SUM(B62:E62) -> #REF! | G62: =+Shepparton!#REF! -> #REF! | I62: =+'Fast Key'!BC61 -> 0 | J62: =+J61 -> 0 | K62: =+'Fast Key'!BD61 -> 0 | L62: =+L61 -> #REF! | M62: =+M61 -> 103 | N62: =+N61 -> 60 | O62: =+O61 -> 65
A63: Launceston 21 | B63: =+CEILING(I63+J63+K63,10) -> 0 | C63: =+L63 -> #REF! | D63: =+Shepparton!#REF! -> #REF! | E63: =+Shepparton!#REF! -> #REF! | F63: =SUM(B63:E63) -> #REF! | G63: =+Shepparton!#REF! -> #REF! | I63: =+'Fast Key'!BC62 -> 0 | J63: =+J62 -> 0 | K63: =+'Fast Key'!BD62 -> 0 | L63: =+L62 -> #REF! | M63: =+M62 -> 103 | N63: =+N62 -> 60 | O63: =+O62 -> 65
A64: Launceston 22 | B64: =+CEILING(I64+J64+K64,10) -> 0 | C64: =+L64 -> #REF! | D64: =+Shepparton!#REF! -> #REF! | E64: =+Shepparton!#REF! -> #REF! | F64: =SUM(B64:E64) -> #REF! | G64: =+Shepparton!#REF! -> #REF! | I64: =+'Fast Key'!BC63 -> 0 | J64: =+J63 -> 0 | K64: =+'Fast Key'!BD63 -> 0 | L64: =+L63 -> #REF! | M64: =+M63 -> 103 | N64: =+N63 -> 60 | O64: =+O63 -> 65
... A88: Santa Barbara 25 | B88: =+CEILING(I88+J88+K88,10) -> 0 | C88: =+L88 -> #REF! | D88: =+Shepparton!#REF! -> #REF! | E88: =+Shepparton!#REF! -> #REF! | F88: =SUM(B88:E88) -> #REF! | G88: =+Shepparton!#REF! -> #REF! | I88: =+'Fast Key'!BC87 -> 0 | J88: =+J87 -> 0 | K88: =+'Fast Key'!BD87 -> 0 | L88: =+L87 -> #REF! | M88: =+M87 -> 103 | N88: =+N87 -> 60 | O88: =+O87 -> 65
A89: Santa Barbara 26 | B89: =+CEILING(I89+J89+K89,10) -> 0 | C89: =+L89 -> #REF! | D89: =+Shepparton!#REF! -> #REF! | E89: =+Shepparton!#REF! -> #REF! | F89: =SUM(B89:E89) -> #REF! | G89: =+Shepparton!#REF! -> #REF! | I89: =+'Fast Key'!BC88 -> 0 | J89: =+J87 -> 0 | K89: =+'Fast Key'!BD88 -> 0 | L89: =+L87 -> #REF! | M89: =+M87 -> 103 | N89: =+N87 -> 60 | O89: =+O87 -> 65
A91: BASE PRICE INCLUDES: | E91: BASE PRICE DOES NOT INCLUDE:
A92: *SEWER, STORMWATER AND POWER | E92: *SITE PIERING
A93: TO A 700m2 BLOCK | E93: *RAISED PORTICO
A94: *20m TEMP FENCING | E94: *TILES
A95: *'MD' CLASS SLAB | E95: *CARPET
E96: *EXTERNAL PAVING
E97: *EAVES
A98: ECHUCA
A99: LIFESTYLE HOMESTEAD PRICE LIST VALID UP TO DEC 2025
A100: HOUSE DESIGN | B100: BASE PRICE * | C100: 50sqm NATURAL CONCRETE | D100: LIFESTYLE FLOOR TILES | E100: LIFESTYLE CARPETS | F100: PACKAGE PRICE *50sqm NATURAL CONCRETE *CARPET *TILES | G100: PRICE TO ADD EAVES | I100: List price | J100: Promotional | L100: 50sqm natural concrete | M100: Tiles per sqm | N100: Carpet per sqm | O100: Eaves per lm
A101: Inglewood 24 | B101: =+CEILING(I101+J101+K101,10) -> 0 | C101: =+L101 -> #REF! | D101: =+Shepparton!#REF! -> #REF! | E101: =+Shepparton!#REF! -> #REF! | F101: =SUM(B101:E101) -> #REF! | G101: =+Shepparton!#REF! -> #REF! | I101: =+'Fast Key'!BC91 -> 0 | J101: =+J87 -> 0 | K101: =+'Fast Key'!BD91 -> 0 | L101: =+L87 -> #REF! | M101: =+M87 -> 103 | N101: =+N87 -> 60 | O101: =+O87 -> 65
A102: Inglewood 26 | B102: =+CEILING(I102+J102+K102,10) -> 0 | C102: =+L102 -> #REF! | D102: =+Shepparton!#REF! -> #REF! | E102: =+Shepparton!#REF! -> #REF! | F102: =SUM(B102:E102) -> #REF! | G102: =+Shepparton!#REF! -> #REF! | I102: =+'Fast Key'!BC92 -> 0 | J102: =+J101 -> 0 | K102: =+'Fast Key'!BD92 -> 0 | L102: =+L101 -> #REF! | M102: =+M101 -> 103 | N102: =+N101 -> 60 | O102: =+O101 -> 65
A103: Inglewood 29 | B103: =+CEILING(I103+J103+K103,10) -> 0 | C103: =+L103 -> #REF! | D103: =+Shepparton!#REF! -> #REF! | E103: =+Shepparton!#REF! -> #REF! | F103: =SUM(B103:E103) -> #REF! | G103: =+Shepparton!#REF! -> #REF! | I103: =+'Fast Key'!BC93 -> 0 | J103: =+J102 -> 0 | K103: =+'Fast Key'!BD93 -> 0 | L103: =+L102 -> #REF! | M103: =+M102 -> 103 | N103: =+N102 -> 60 | O103: =+O102 -> 65
A104: Inglewood 31 | B104: =+CEILING(I104+J104+K104,10) -> 0 | C104: =+L104 -> #REF! | D104: =+Shepparton!#REF! -> #REF! | E104: =+Shepparton!#REF! -> #REF! | F104: =SUM(B104:E104) -> #REF! | G104: =+Shepparton!#REF! -> #REF! | I104: =+'Fast Key'!BC94 -> 0 | J104: =+J103 -> 0 | K104: =+'Fast Key'!BD94 -> 0 | L104: =+L103 -> #REF! | M104: =+M103 -> 103 | N104: =+N103 -> 60 | O104: =+O103 -> 65
A105: Inglewood 34 | B105: =+CEILING(I105+J105+K105,10) -> 0 | C105: =+L105 -> #REF! | D105: =+Shepparton!#REF! -> #REF! | E105: =+Shepparton!#REF! -> #REF! | F105: =SUM(B105:E105) -> #REF! | G105: =+Shepparton!#REF! -> #REF! | I105: =+'Fast Key'!BC95 -> 0 | J105: =+J104 -> 0 | K105: =+'Fast Key'!BD95 -> 0 | L105: =+L104 -> #REF! | M105: =+M104 -> 103 | N105: =+N104 -> 60 | O105: =+O104 -> 65
A106: Inglewood 35 | B106: =+CEILING(I106+J106+K106,10) -> 0 | C106: =+L106 -> #REF! | D106: =+Shepparton!#REF! -> #REF! | E106: =+Shepparton!#REF! -> #REF! | F106: =SUM(B106:E106) -> #REF! | G106: =+Shepparton!#REF! -> #REF! | I106: =+'Fast Key'!BC96 -> 0 | J106: =+J107 -> 0 | K106: =+'Fast Key'!BD96 -> 0 | L106: =+L107 -> #REF! | M106: =+M107 -> 103 | N106: =+N107 -> 60 | O106: =+O107 -> 65
A107: Inglewood 38 | B107: =+CEILING(I107+J107+K107,10) -> 0 | C107: =+L107 -> #REF! | D107: =+Shepparton!#REF! -> #REF! | E107: =+Shepparton!#REF! -> #REF! | F107: =SUM(B107:E107) -> #REF! | G107: =+Shepparton!#REF! -> #REF! | I107: =+'Fast Key'!BC97 -> 0 | J107: =+J105 -> 0 | K107: =+'Fast Key'!BD97 -> 0 | L107: =+L105 -> #REF! | M107: =+M105 -> 103 | N107: =+N105 -> 60 | O107: =+O105 -> 65
A108: Maldon 23 | B108: =+CEILING(I108+J108+K108,10) -> 0 | C108: =+L108 -> #REF! | D108: =+Shepparton!#REF! -> #REF! | E108: =+Shepparton!#REF! -> #REF! | F108: =SUM(B108:E108) -> #REF! | G108: =+Shepparton!#REF! -> #REF! | I108: =+'Fast Key'!BC98 -> 0 | J108: =+J106 -> 0 | K108: =+'Fast Key'!BD98 -> 0 | L108: =+L106 -> #REF! | M108: =+M106 -> 103 | N108: =+N106 -> 60 | O108: =+O106 -> 65
A109: Maldon 27 | B109: =+CEILING(I109+J109+K109,10) -> 0 | C109: =+L109 -> #REF! | D109: =+Shepparton!#REF! -> #REF! | E109: =+Shepparton!#REF! -> #REF! | F109: =SUM(B109:E109) -> #REF! | G109: =+Shepparton!#REF! -> #REF! | I109: =+'Fast Key'!BC99 -> 0 | J109: =+J106 -> 0 | K109: =+'Fast Key'!BD99 -> 0 | L109: =+L106 -> #REF! | M109: =+M106 -> 103 | N109: =+N106 -> 60 | O109: =+O106 -> 65
A110: Maldon 33 | B110: =+CEILING(I110+J110+K110,10) -> 0 | C110: =+L110 -> #REF! | D110: =+Shepparton!#REF! -> #REF! | E110: =+Shepparton!#REF! -> #REF! | F110: =SUM(B110:E110) -> #REF! | G110: =+Shepparton!#REF! -> #REF! | I110: =+'Fast Key'!BC100 -> 0 | J110: =+J107 -> 0 | K110: =+'Fast Key'!BD100 -> 0 | L110: =+L107 -> #REF! | M110: =+M107 -> 103 | N110: =+N107 -> 60 | O110: =+O107 -> 65
A111: Palmerston 28 | B111: =+CEILING(I111+J111+K111,10) -> 0 | C111: =+L111 -> #REF! | D111: =+Shepparton!#REF! -> #REF! | E111: =+Shepparton!#REF! -> #REF! | F111: =SUM(B111:E111) -> #REF! | G111: =+Shepparton!#REF! -> #REF! | I111: =+'Fast Key'!BC101 -> 0 | J111: =+J108 -> 0 | K111: =+'Fast Key'!BD101 -> 0 | L111: =+L108 -> #REF! | M111: =+M108 -> 103 | N111: =+N108 -> 60 | O111: =+O108 -> 65
A112: Palmerston 35 | B112: =+CEILING(I112+J112+K112,10) -> 0 | C112: =+L112 -> #REF! | D112: =+Shepparton!#REF! -> #REF! | E112: =+Shepparton!#REF! -> #REF! | F112: =SUM(B112:E112) -> #REF! | G112: =+Shepparton!#REF! -> #REF! | I112: =+'Fast Key'!BC102 -> 0 | J112: =+J111 -> 0 | K112: =+'Fast Key'!BD102 -> 0 | L112: =+L111 -> #REF! | M112: =+M111 -> 103 | N112: =+N111 -> 60 | O112: =+O111 -> 65
A113: Sandown 23 | B113: =+CEILING(I113+J113+K113,10) -> 0 | C113: =+L113 -> #REF! | D113: =+Shepparton!#REF! -> #REF! | E113: =+Shepparton!#REF! -> #REF! | F113: =SUM(B113:E113) -> #REF! | G113: =+Shepparton!#REF! -> #REF! | I113: =+'Fast Key'!BC103 -> 0 | J113: =+J112 -> 0 | K113: =+'Fast Key'!BD103 -> 0 | L113: =+L112 -> #REF! | M113: =+M112 -> 103 | N113: =+N112 -> 60 | O113: =+O112 -> 65
A114: Sandown 26 | B114: =+CEILING(I114+J114+K114,10) -> 0 | C114: =+L114 -> #REF! | D114: =+Shepparton!#REF! -> #REF! | E114: =+Shepparton!#REF! -> #REF! | F114: =SUM(B114:E114) -> #REF! | G114: =+Shepparton!#REF! -> #REF! | I114: =+'Fast Key'!BC104 -> 0 | J114: =+J113 -> 0 | K114: =+'Fast Key'!BD104 -> 0 | L114: =+L113 -> #REF! | M114: =+M113 -> 103 | N114: =+N113 -> 60 | O114: =+O113 -> 65
A115: Sandown 28 (30) | B115: =+CEILING(I115+J115+K115,10) -> 0 | C115: =+L115 -> #REF! | D115: =+Shepparton!#REF! -> #REF! | E115: =+Shepparton!#REF! -> #REF! | F115: =SUM(B115:E115) -> #REF! | G115: =+Shepparton!#REF! -> #REF! | I115: =+'Fast Key'!BC105 -> 0 | J115: =+J114 -> 0 | K115: =+'Fast Key'!BD105 -> 0 | L115: =+L114 -> #REF! | M115: =+M114 -> 103 | N115: =+N114 -> 60 | O115: =+O114 -> 65
A116: Sandown 32 | B116: =+CEILING(I116+J116+K116,10) -> 0 | C116: =+L116 -> #REF! | D116: =+Shepparton!#REF! -> #REF! | E116: =+Shepparton!#REF! -> #REF! | F116: =SUM(B116:E116) -> #REF! | G116: =+Shepparton!#REF! -> #REF! | I116: =+'Fast Key'!BC106 -> 0 | J116: =+J115 -> 0 | K116: =+'Fast Key'!BD106 -> 0 | L116: =+L115 -> #REF! | M116: =+M115 -> 103 | N116: =+N115 -> 60 | O116: =+O115 -> 65
A117: Sandown 34 MG | B117: =+CEILING(I117+J117+K117,10) -> 0 | C117: =+L117 -> #REF! | D117: =+Shepparton!#REF! -> #REF! | E117: =+Shepparton!#REF! -> #REF! | F117: =SUM(B117:E117) -> #REF! | G117: =+Shepparton!#REF! -> #REF! | I117: =+'Fast Key'!BC107 -> 0 | J117: =+J116 -> 0 | K117: =+'Fast Key'!BD107 -> 0 | L117: =+L116 -> #REF! | M117: =+M116 -> 103 | N117: =+N116 -> 60 | O117: =+O116 -> 65
A118: Sandown 40 MG | B118: =+CEILING(I118+J118+K118,10) -> 0 | C118: =+L118 -> #REF! | D118: =+Shepparton!#REF! -> #REF! | E118: =+Shepparton!#REF! -> #REF! | F118: =SUM(B118:E118) -> #REF! | G118: =+Shepparton!#REF! -> #REF! | I118: =+'Fast Key'!BC108 -> 0 | J118: =+J117 -> 0 | K118: =+'Fast Key'!BD108 -> 0 | L118: =+L117 -> #REF! | M118: =+M117 -> 103 | N118: =+N117 -> 60 | O118: =+O117 -> 65
A119: Sandown 41 MG | B119: =+CEILING(I119+J119+K119,10) -> 0 | C119: =+L119 -> #REF! | D119: =+Shepparton!#REF! -> #REF! | E119: =+Shepparton!#REF! -> #REF! | F119: =SUM(B119:E119) -> #REF! | G119: =+Shepparton!#REF! -> #REF! | I119: =+'Fast Key'!BC109 -> 0 | J119: =+J118 -> 0 | K119: =+'Fast Key'!BD109 -> 0 | L119: =+L118 -> #REF! | M119: =+M118 -> 103 | N119: =+N118 -> 60 | O119: =+O118 -> 65
A120: Winton 24 | B120: =+CEILING(I120+J120+K120,10) -> 0 | C120: =+L120 -> #REF! | D120: =+Shepparton!#REF! -> #REF! | E120: =+Shepparton!#REF! -> #REF! | F120: =SUM(B120:E120) -> #REF! | G120: =+Shepparton!#REF! -> #REF! | I120: =+'Fast Key'!BC110 -> 0 | J120: =+J119 -> 0 | K120: =+'Fast Key'!BD110 -> 0 | L120: =+L119 -> #REF! | M120: =+M119 -> 103 | N120: =+N119 -> 60 | O120: =+O119 -> 65
A121: Winton 28 | B121: =+CEILING(I121+J121+K121,10) -> 0 | C121: =+L121 -> #REF! | D121: =+Shepparton!#REF! -> #REF! | E121: =+Shepparton!#REF! -> #REF! | F121: =SUM(B121:E121) -> #REF! | G121: =+Shepparton!#REF! -> #REF! | I121: =+'Fast Key'!BC111 -> 0 | J121: =+J120 -> 0 | K121: =+'Fast Key'!BD111 -> 0 | L121: =+L120 -> #REF! | M121: =+M120 -> 103 | N121: =+N120 -> 60 | O121: =+O120 -> 65
A122: Winton 32 | B122: =+CEILING(I122+J122+K122,10) -> 0 | C122: =+L122 -> #REF! | D122: =+Shepparton!#REF! -> #REF! | E122: =+Shepparton!#REF! -> #REF! | F122: =SUM(B122:E122) -> #REF! | G122: =+Shepparton!#REF! -> #REF! | I122: =+'Fast Key'!BC112 -> 0 | J122: =+J121 -> 0 | K122: =+'Fast Key'!BD112 -> 0 | L122: =+L121 -> #REF! | M122: =+M121 -> 103 | N122: =+N121 -> 60 | O122: =+O121 -> 65
A124: BASE PRICE INCLUDES: | E124: BASE PRICE DOES NOT INCLUDE:
A125: *SEWER, STORMWATER AND POWER | E125: *SITE PIERING
A126: TO A 700m2 BLOCK | E126: *RAISED PORTICO
...

Sheet Value Packs
B2: LIFESTYLE VALUE PACKS - NOV 2024
B4: ENTRANCE PACK
B5: 1200mm x 2040mm timber glass front door | C5: 1340
B6: Nexion Trilock handle | C6: 175
B7: Total | C7: =SUM(C5:C6) -> 1515
B9: KITCHEN CABINETRY PACK
B10: 2 Banks of drawers | C10: 660
B11: Twin bin in drawer with drawer below | C11: 250
B12: Fridge overhead cupboard | C12: 960 | E12: 1000mm with one side panel
B13: Total | C13: =SUM(C10:C12) -> 1870
B15: KITCHEN APPLIANCE PACK
B16: 90cm Inbuilt oven & gas cooktop | C16: 1355
B17: 70cm Intergrated rangehood | C17: 165
B18: Water point to fridge | C18: 200
B19: Total | C19: =SUM(C16:C18) -> 1720
B21: KITCHEN BENCHTOP PACK
B22: 20mm Stone benchtop | C22: 3625 | E22: (3.2m wall bench & 2.7m island)
B23: Undermount sink | C23: 355
B24: Total | C24: =SUM(C22:C23) -> 3980
B26: BATHROOM/ENSUITE INDULGENT PACK
B27: 20mm Stone vanity benchtops | C27: 1350 | E27: (up to 1 x 1800mm & 1 x 900mm)
B28: Above counter basins with tower mixers | C28: 450 | E28: x3
B29: Tiled recess shelf to showers | C29: 800
B30: Dual shower head to ensuite | C30: 250
B31: Total | C31: =SUM(C27:C30) -> 2850
B33: LAUNDRY INDULGENT PACK
B34: Extend bench & cabinets up to 2m | C34: 2800
B35: Pull out clothesbasket | C35: 220
B36: Total | C36: =SUM(C34:C35) -> 3020
B38: LIGHTING PACK 1
B39: 30 X LED downlights | C39: 2550 | E39: replaces 15 light points
B40: Total | C40: =SUM(C39:C39) -> 2550
B42: LIGHTING PACK 2
B43: 30 X LED downlights | C43: 2550 | E43: replaces 15 light points
B44: 3 X Pendant lights above island bench | C44: 1155 | E44: 220 per pendant
B45: Total | C45: =SUM(C43:C44) -> 3705
B47: LIGHTING PACK 3
B48: 30 X LED downlights | C48: 2550 | E48: replaces 15 light points
B49: 3 X Pendant lights above island bench | C49: =+C44 -> 1155 | E49: 220 per pendant
B50: 3 X Wall mounted feature lights to the front façade with motion sensor | C50: 1290
B51: Total | C51: =SUM(C48:C50) -> 4995
B53: TV ANTENNA | C53: 590

Sheet Sandown 32 Display
B4: ABN: 50 105 889 745
B5: 7961 Goulburn Valley Hwy | E5: Telephone 5823 1859
B6: P O BOX 922 | E6: Display Home 5832 6082
B7: SHEPPARTON VIC 3632 | E7: DB-U 9856
B9: Dear | C9: =+C48 -> 0
B11: RE: PRELIMINARY PRICING
B13: Thank you for your interest in building a new home with Cavalier Homes Goulburn Valley, we greatly
B14: appreciate the opportunity to work with you designing and building your new home.
B16: Please find attached the preliminary pricing to build a house on your land at
B17: =+C52 -> 0
B19: This preliminary pricing is provided as a guide and is subject to review after 30 days or before this
B20: time if a new price list is released in the interim.
B22: If you are pleased with the preliminary price, we can then provide a firm price once you have paid an
B23: initial preliminary service fee of $2,000 - (this will secure the price as per the terms and conditions
B24: of the Cavalier Homes Goulburn Valley Ground Work document which we will discuss further should
B25: you wish to proceed to the next stage).
B27: Once the initial preliminary service fee is received, we will arrange to have working drawings drafted
B28: which will show you fully detailed plan of the interior and exterior of your home.
B29: We will also engage an independent, qualified engineer to provide a slab design based on your home
B30: design and the results of the soil test inspection carried out on your block.
B32: As discussed, we will provide you with a final fixed price once the following are completed:
B33: The colour selections
... B55: PRE- CONSTRUCTION
B56: Soil test and site inspection of your block | D56: Included
B57: Independent qualified engineer designed slab | D57: Included
B58: Rescode investigation | D58: Included
B59: Building permit and associated fees (does not include planning permit) | D59: Included
B60: Development application for NSW jobs | D60: Included
B61: Builder's insurances | D61: Included
B62: Independent 6 star energy rating | D62: Included
B63: SERVICE CONNECTIONS
B64: Sewer run and connection fees to 700m2 block | D64: Included
B65: Water run and connection fees to 6m front setback | D65: Included
B66: Stormwater connection to 6m front setback | D66: Included
B67: Electricity run to 6m front setback (does not include connection fee) | D67: Included
B68: Gas service is to be supplied by the retailer
B69: FOUNDATIONS
B70: Site fall up to 200mm | D70: Included
B71: MD class concrete slab (floor height at least 250mm - there is no allowance for piers) | D71: Included
B72: Concrete pump | D72: Included
B73: TERMITE PROTECTION
B74: Termite resistant treated timber to all structural framing | D74: Included
B75: ROOFING
B76: Colorbond iron roof with sarking | D76: Included
B77: Colorbond slotted gutter, fascia and downpipes (downpipes 100mm x 50mm) | D77: Included
B78: 22.5 degree roof pitch | D78: Included
B79: FACADE
B80: Standard façade with 450mm eaves to front elevation as per brochure plans | D80: Included
B81: CEILING HEIGHT
B82: 2400mm ceiling height | D82: Included
B83: Plaster ceilings are fixed to a metal batten system, suspended on clips and is laser levelled to the entire home | D83: Included
B84: EXTERNAL FINISH
B85: Lifestyle range of PGH bricks with natural mortar | D85: Included
B86: Bricks over external swing and sliding doors (to openings up to 3.6m wide), windows and garage doors | D86: Included
B87: Outdoor living ceiling to be lined with plaster sheeting (brick piers or duragal steel columns are plan specific) | D87: Included
B88: ENERGY EFFICIENT FEATURES
B89: R3.5 Insulation batts to ceiling (excludes garage ceiling) | D89: Included
B90: R2.0 Insulation batts plus sisalation paper to external walls (excludes garage external walls) | D90: Included
B91: EXTERNAL DOORS
B92: Front door - Hume Newington solid core door with Lockwood Symmetry entry set | D92: Included
B93: External door jambs with perimeter draft seal (Glass sidelights are plan specific) | D93: Included
B94: Flydoors to glass sliding doors (except garage) | D94: Included
B95: WINDOWS
B96: Aluminium sliding windows with key locks | D96: Included
B97: Flyscreens to all opening windows (except garage) | D97: Included
B98: Obscure or clear glass to bathroom, ensuite & WC windows | D98: Included
B99: GARAGE
B100: Choice of external swing door or 2118 glass sliding door | D100: Included
B101: Plaster lined walls & ceiling | D101: Included
B102: Sectional overhead garage door with wall mounted remote control and 2 transmitters | D102: Included
B103: Concrete slab floor | D103: Included
B104: INTERNAL FINISH
B105: 75mm Cove cornice | D105: Included
B106: 67mm x 18mm Bevelled edge architraves | D106: Included
B107: 67mm x 18mm Bevelled edge skirtings | D107: Included
B108: INTERNAL DOORS
B109: Internal doors - 2040mm high flush panel doors | D109: Included
B110: Lockwood velocity door furniture to hinged doors | D110: Included
B111: Privacy locks to bathroom, ensuite and WC hinged doors | D111: Included
B112: Door stops to all hinged doors | D112: Included
B113: KITCHEN
B114: Westinghouse 60cm stainless steel multifunction electric underbench oven | D114: Included
B115: Westinghouse 60cm stainless steel gas cooktop | D115: Included
B116: Westinghouse 60cm stainless steel slideout rangehood | D116: Included
B117: Westinghouse 60cm freestanding dishwasher | D117: Included
B118: Joinery made base cabinet with laminate benchtop and overhead cupboards above cooktop section | D118: Included
B119: Soft close drawers & cupboard doors | D119: Included
B120: Underbench microwave cavity with one pot drawer | D120: Included
B121: 1 & 3/4 bowl stainless steel sink with sink mixer | D121: Included
B122: Bank of four drawers with cutlery insert to top drawer | D122: Included
B123: Four white melamine shelves to pantry | D123: Included
B124: ENSUITE/BATHROOM/WC
B125: Joinery made cabinet with laminate benchtop | D125: Included
B126: Frameless mirror 900mm high x width of vanity | D126: Included
B127: Acrylic bath in white to bathroom | D127: Included
B128: Choice of vanity basins in white | D128: Included
B129: Choice of mixer tapware in chrome | D129: Included
B130: Semi frameless pivot door shower screen in polished silver with clear glass | D130: Included
B131: Tiled shower base | D131: Included
B132: Goulburn glass shower shelf | D132: Included
...

Sheet Travel Working
A1: Draftee travel per km | B1: =+((65+65)/100) -> 1.3
A2: Truck cost per km | B2: 1.65 | F2: 23/06/25 - Add $50 for TV Antenna Install
A3: Carpenter travel per km | B3: 1.65
A4: Supervisor tavel per km | B4: 1.65
A5: Concrete pump travel | B5: 4
A6: Stone benchtops | B6: 6
B7: Kms | C7: Cost per km return | D7: Bunnings delivery | E7: Drafting inspwction travel | F7: Temp fencing travel | G7: Skip run | H7: site screpe travel | I7: Crusher dust | K7: Concrete supply | M7: Pump travel | P7: Bricks delivery | R7: Brick sand | T7: Stone travel | W7: Supervisor travel | X7: Solar pnel travel
A8: SHEPPARTON | B8: 20 | C8: =+B2*2 -> 3.3 | D8: 45.45 | E8: =+C8*B8 -> 66 | F8: =+C8*B8 -> 66 | G8: =+C8*B8*6 -> 396 | H8: =+C8*B8 -> 66 | I8: 51 | J8: =+I8*35 -> 1785 | K8: 210 | L8: =+K8*60 -> 12600 | M8: =+B5 -> 4 | N8: =+B8-80 -> -60 | O8: =IF((N8>0),(N8*M8*2),) -> 0 | P8: 55 | Q8: =+P8*8 -> 440 | R8: 44 | S8: =+R8*9 -> 396 | T8: =+B6 -> 6 | V8: =+B4 -> 1.65 | W8: =+V8*2*B8*10 -> 660 | AF8: =+A8 -> SHEPPARTON
A9: ALEXANDRA | B9: 120 | C9: =+C8 -> 3.3 | D9: 150 | E9: =+C9*B9 -> 396 | F9: =+C9*B9 -> 396 | G9: =+C9*B9*6 -> 2376 | H9: =+C9*B9 -> 396 | I9: 85 | J9: =+I9*35 -> 2975 | K9: 287 | L9: =+K9*60 -> 17220 | M9: =+M8 -> 4 | N9: =+B9-80 -> 40 | O9: =IF((N9>0),(N9*M9*2),) -> 320 | P9: 65 | Q9: =+P9*8 -> 520 | R9: 80 | S9: =+R9*9 -> 720 | T9: =+T8 -> 6 | U9: =+IF(((B9-80)>0),((B9-80)*T9),0) -> 240 | V9: =+V8 -> 1.65 | W9: =+V9*2*B9*10 -> 3960 | X9: 2 | Y9: =+X9*B9 -> 240 | AF9: =+A9 -> ALEXANDRA | AG9: =+C95-B95 -> 30199.75 | AH9: =+CEILING(AG9*1.36,10) -> 41080
A10: AVENEL | B10: 71 | C10: =+C9 -> 3.3 | D10: 110 | E10: =+C10*B10 -> 234.3 | F10: =+C10*B10 -> 234.3 | G10: =+C10*B10*6 -> 1405.8 | H10: =+C10*B10 -> 234.3 | I10: 65 | J10: =+I10*35 -> 2275 | K10: 210 | L10: =+K10*60 -> 12600 | M10: =+M9 -> 4 | N10: =+B10-80 -> -9 | O10: =IF((N10>0),(N10*M10*2),) -> 0 | P10: 55 | Q10: =+P10*8 -> 440 | R10: 56 | S10: =+R10*9 -> 504 | T10: =+T9 -> 6 | U10: =+IF(((B10-80)>0),((B10-80)*T10),0) -> 0 | V10: =+V9 -> 1.65 | W10: =+V10*2*B10*10 -> 2343 | X10: 2 | Y10: =+X10*B10 -> 142 | AF10: =+A10 -> AVENEL | AG10: =+D95-B95 -> 11128.05 | AH10: =+CEILING(AG10*1.36,10) -> 15140
A11: BENALLA | B11: 62 | C11: =+C10 -> 3.3 | D11: 70 | E11: =+C11*B11 -> 204.6 | F11: =+C11*B11 -> 204.6 | G11: =+C11*B11*6 -> 1227.6 | H11: =+C11*B11 -> 204.6 | I11: 65 | J11: =+I11*35 -> 2275 | K11: 235 | L11: =+K11*60 -> 14100 | M11: =+M10 -> 4 | N11: =+B11-80 -> -18 | O11: =IF((N11>0),(N11*M11*2),) -> 0 | P11: 55 | Q11: =+P11*8 -> 440 | R11: 54 | S11: =+R11*9 -> 486 | T11: =+T10 -> 6 | U11: =+IF(((B11-80)>0),((B11-80)*T11),0) -> 0 | V11: =+V10 -> 1.65 | W11: =+V11*2*B11*10 -> 2046 | X11: 2 | Y11: =+X11*B11 -> 124 | AF11: =+A11 -> BENALLA | AG11: =+E95-B95 -> 10508.35 | AH11: =+CEILING(AG11*1.36,10) -> 14300
A12: COBRAM | B12: 71 | C12: =+C11 -> 3.3 | D12: 70 | E12: =+C12*B12 -> 234.3 | F12: =+C12*B12 -> 234.3 | G12: =+C12*B12*6 -> 1405.8 | H12: =+C12*B12 -> 234.3 | I12: 65 | J12: =+I12*35 -> 2275 | K12: 220 | L12: =+K12*60 -> 13200 | M12: =+M11 -> 4 | N12: =+B12-80 -> -9 | O12: =IF((N12>0),(N12*M12*2),) -> 0 | P12: 70 | Q12: =+P12*8 -> 560 | R12: 54 | S12: =+R12*9 -> 486 | T12: =+T11 -> 6 | U12: =+IF(((B12-80)>0),((B12-80)*T12),0) -> 0 | V12: =+V11 -> 1.65 | W12: =+V12*2*B12*10 -> 2343 | X12: 2 | Y12: =+X12*B12 -> 142 | AF12: =+A12 -> COBRAM | AG12: =+F95-B95 -> 10430.05 | AH12: =+CEILING(AG12*1.36,10) -> 14190
A13: COHUNA | B13: 135 | C13: =+C12 -> 3.3 | D13: =+D9 -> 150 | E13: =+C13*B13 -> 445.5 | F13: =+C13*B13 -> 445.5 | G13: =+C13*B13*6 -> 2673 | H13: =+C13*B13 -> 445.5 | I13: 85 | J13: =+I13*35 -> 2975 | K13: 345 | L13: =+K13*60 -> 20700 | M13: =+M12 -> 4 | N13: =+B13-80 -> 55 | O13: =IF((N13>0),(N13*M13*2),) -> 440 | P13: 80 | Q13: =+P13*8 -> 640 | R13: 80 | S13: =+R13*9 -> 720 | T13: =+T12 -> 6 | U13: =+IF(((B13-80)>0),((B13-80)*T13),0) -> 330 | V13: =+V12 -> 1.65 | W13: =+V13*2*B13*10 -> 4455 | X13: 2 | Y13: =+X13*B13 -> 270 | AF13: =+A13 -> COHUNA | AG13: =+G95-B95 -> 34627.25 | AH13: =+CEILING(AG13*1.36,10) -> 47100
A14: DENILIQUIN | B14: 137 | C14: =+C13 -> 3.3 | D14: =+D13 -> 150 | E14: =+C14*B14 -> 452.1 | F14: =+C14*B14 -> 452.1 | G14: =+C14*B14*6 -> 2712.6 | H14: =+C14*B14 -> 452.1 | I14: 85 | J14: =+I14*35 -> 2975 | K14: 358 | L14: =+K14*60 -> 21480 | M14: =+M13 -> 4 | N14: =+B14-80 -> 57 | O14: =IF((N14>0),(N14*M14*2),) -> 456 | P14: 80 | Q14: =+P14*8 -> 640 | R14: 80 | S14: =+R14*9 -> 720 | T14: =+T13 -> 6 | U14: =+IF(((B14-80)>0),((B14-80)*T14),0) -> 342 | V14: =+V13 -> 1.65 | W14: =+V14*2*B14*10 -> 4521 | X14: 2 | Y14: =+X14*B14 -> 274 | AF14: =+A14 -> DENILIQUIN | AG14: =+H95-B95 -> 36237.85 | AH14: =+CEILING(AG14*1.36,10)+D108 -> 57490
A15: ECHUCA | B15: 71 | C15: =+C14 -> 3.3 | D15: 80 | E15: =+C15*B15 -> 234.3 | F15: =+C15*B15 -> 234.3 | G15: =+C15*B15*6 -> 1405.8 | H15: =+C15*B15 -> 234.3 | I15: 63 | J15: =+I15*35 -> 2205 | K15: 230 | L15: =+K15*60 -> 13800 | M15: =+M14 -> 4 | N15: =+B15-80 -> -9 | O15: =IF((N15>0),(N15*M15*2),) -> 0 | P15: 60 | Q15: =+P15*8 -> 480 | R15: 55 | S15: =+R15*9 -> 495 | T15: =+T14 -> 6 | U15: =+IF(((B15-80)>0),((B15-80)*T15),0) -> 0 | V15: =+V14 -> 1.65 | W15: =+V15*2*B15*10 -> 2343 | X15: 2 | Y15: =+X15*B15 -> 142 | AF15: =+A15 -> ECHUCA | AG15: =+I95-B95 -> 10112.05 | AH15: =+CEILING(AG15*1.36,10) -> 13760
A16: EUROA | B16: 49 | C16: =+C15 -> 3.3 | D16: 90 | E16: =+C16*B16 -> 161.7 | F16: =+C16*B16 -> 161.7 | G16: =+C16*B16*6 -> 970.2 | H16: =+C16*B16 -> 161.7 | I16: 63 | J16: =+I16*35 -> 2205 | K16: 257 | L16: =+K16*60 -> 15420 | M16: =+M15 -> 4 | N16: =+B16-80 -> -31 | O16: =IF((N16>0),(N16*M16*2),) -> 0 | P16: 55 | Q16: =+P16*8 -> 440 | R16: 52 | S16: =+R16*9 -> 468 | T16: =+T15 -> 6 | U16: =+IF(((B16-80)>0),((B16-80)*T16),0) -> 0 | V16: =+V15 -> 1.65 | W16: =+V16*2*B16*10 -> 1617 | X16: 2 | Y16: =+X16*B16 -> 98 | AF16: =+A16 -> EUROA | AG16: =+J95-B95 -> 8150.45 | AH16: =+CEILING(AG16*1.36,10) -> 11090
A17: FINLEY | B17: 101 | C17: =+C16 -> 3.3 | D17: =+D13 -> 150 | E17: =+C17*B17 -> 333.3 | F17: =+C17*B17 -> 333.3 | G17: =+C17*B17*6 -> 1999.8 | H17: =+C17*B17 -> 333.3 | I17: 85 | J17: =+I17*35 -> 2975 | K17: 247 | L17: =+K17*60 -> 14820 | M17: =+M16 -> 4 | N17: =+B17-80 -> 21 | O17: =IF((N17>0),(N17*M17*2),) -> 168 | P17: 80 | Q17: =+P17*8 -> 640 | R17: 80 | S17: =+R17*9 -> 720 | T17: =+T16 -> 6 | U17: =+IF(((B17-80)>0),((B17-80)*T17),0) -> 126 | V17: =+V16 -> 1.65 | W17: =+V17*2*B17*10 -> 3333 | X17: 2 | Y17: =+X17*B17 -> 202 | AF17: =+A17 -> FINLEY | AG17: =+K95-B95 -> 23952.05 | AH17: =+CEILING(AG17*1.36,10)+D108 -> 40780
A18: KATANDRA | B18: 29 | C18: =+C17 -> 3.3 | D18: =+D10 -> 110 | E18: =+C18*B18 -> 95.7 | F18: =+C18*B18 -> 95.7 | G18: =+C18*B18*6 -> 574.2 | H18: =+C18*B18 -> 95.7 | I18: 65 | J18: =+I18*35 -> 2275 | K18: 223 | L18: =+K18*60 -> 13380 | M18: =+M17 -> 4 | N18: =+B18-80 -> -51 | O18: =IF((N18>0),(N18*M18*2),) -> 0 | P18: 65 | Q18: =+P18*8 -> 520 | R18: 60 | S18: =+R18*9 -> 540 | T18: =+T17 -> 6 | U18: =+IF(((B18-80)>0),((B18-80)*T18),0) -> 0 | V18: =+V17 -> 1.65 | W18: =+V18*2*B18*10 -> 957 | X18: 2 | Y18: =+X18*B18 -> 58 | AF18: =+A18 -> KATANDRA | AG18: =+L95-B95 -> 5731.45 | AH18: =+CEILING(AG18*1.36,10) -> 7800
A19: KOONDROOK | B19: 158 | C19: =+C18 -> 3.3 | D19: =+D14 -> 150 | E19: =+C19*B19 -> 521.4 | F19: =+C19*B19 -> 521.4 | G19: =+C19*B19*6 -> 3128.4 | H19: =+C19*B19 -> 521.4 | I19: 85 | J19: =+I19*35 -> 2975 | K19: 345 | L19: =+K19*60 -> 20700 | M19: =+M18 -> 4 | N19: =+B19-80 -> 78 | O19: =IF((N19>0),(N19*M19*2),) -> 624 | P19: 80 | Q19: =+P19*8 -> 640 | R19: 80 | S19: =+R19*9 -> 720 | T19: =+T18 -> 6 | U19: =+IF(((B19-80)>0),((B19-80)*T19),0) -> 468 | V19: =+V18 -> 1.65 | W19: =+V19*2*B19*10 -> 5214 | X19: 2 | Y19: =+X19*B19 -> 316 | AF19: =+A19 -> KOONDROOK | AG19: =+M95-B95 -> 37089.15 | AH19: =+CEILING(AG19*1.36,10) -> 50450
A20: KYABRAM | B20: 37 | C20: =+C19 -> 3.3 | D20: 50 | E20: =+C20*B20 -> 122.1 | F20: =+C20*B20 -> 122.1 | G20: =+C20*B20*6 -> 732.6 | H20: =+C20*B20 -> 122.1 | I20: 63 | J20: =+I20*35 -> 2205 | K20: 230 | L20: =+K20*60 -> 13800 | M20: =+M19 -> 4 | N20: =+B20-80 -> -43 | O20: =IF((N20>0),(N20*M20*2),) -> 0 | P20: 75 | Q20: =+P20*8 -> 600 | R20: 52 | S20: =+R20*9 -> 468 | T20: =+T19 -> 6 | U20: =+IF(((B20-80)>0),((B20-80)*T20),0) -> 0 | V20: =+V19 -> 1.65 | W20: =+V20*2*B20*10 -> 1221 | X20: 2 | Y20: =+X20*B20 -> 74 | AF20: =+A20 -> KYABRAM | AG20: =+N95-B95 -> 4414.85 | AH20: =+CEILING(AG20*1.36,10) -> 6010
A21: MANSFIELD | B21: 125 | C21: =+C20 -> 3.3 | D21: 110 | E21: =+C21*B21 -> 412.5 | F21: =+C21*B21 -> 412.5 | G21: =+C21*B21*6 -> 2475 | H21: =+C21*B21 -> 412.5 | I21: 85 | J21: =+I21*35 -> 2975 | K21: 279 | L21: =+K21*60 -> 16740 | M21: =+M20 -> 4 | N21: =+B21-80 -> 45 | O21: =IF((N21>0),(N21*M21*2),) -> 360 | P21: 70 | Q21: =+P21*8 -> 560 | R21: 80 | S21: =+R21*9 -> 720 | T21: =+T20 -> 6 | U21: =+IF(((B21-80)>0),((B21-80)*T21),0) -> 270 | V21: =+V20 -> 1.65 | W21: =+V21*2*B21*10 -> 4125 | X21: 2 | Y21: =+X21*B21 -> 250 | AF21: =+A21 -> MANSFIELD | AG21: =+O95-B95 -> 31674.25 | AH21: =+CEILING(AG21*1.36,10) -> 43080
A22: MATHOURA | B22: 103 | C22: =+C21 -> 3.3 | D22: =+D19 -> 150 | E22: =+C22*B22 -> 339.9 | F22: =+C22*B22 -> 339.9 | G22: =+C22*B22*6 -> 2039.4 | H22: =+C22*B22 -> 339.9 | I22: 85 | J22: =+I22*35 -> 2975 | K22: =+K14 -> 358 | L22: =+K22*60 -> 21480 | M22: =+M21 -> 4 | N22: =+B22-80 -> 23 | O22: =IF((N22>0),(N22*M22*2),) -> 184 | P22: 80 | Q22: =+P22*8 -> 640 | R22: 80 | S22: =+R22*9 -> 720 | T22: =+T21 -> 6 | U22: =+IF(((B22-80)>0),((B22-80)*T22),0) -> 138 | V22: =+V21 -> 1.65 | W22: =+V22*2*B22*10 -> 3399 | X22: 2 | Y22: =+X22*B22 -> 206 | AF22: =+A22 -> MATHOURA | AG22: =+P95-B95 -> 31664.65 | AH22: =+CEILING(AG22*1.36,10)+D108 -> 51270
A23: MURCHISON | B23: 43 | C23: =+C22 -> 3.3 | D23: 90 | E23: =+C23*B23 -> 141.9 | F23: =+C23*B23 -> 141.9 | G23: =+C23*B23*6 -> 851.4 | H23: =+C23*B23 -> 141.9 | I23: 65 | J23: =+I23*35 -> 2275 | K23: 218 | L23: =+K23*60 -> 13080 | M23: =+M22 -> 4 | N23: =+B23-80 -> -37 | O23: =IF((N23>0),(N23*M23*2),) -> 0 | P23: 55 | Q23: =+P23*8 -> 440 | R23: 52 | S23: =+R23*9 -> 468 | T23: =+T22 -> 6 | U23: =+IF(((B23-80)>0),((B23-80)*T23),0) -> 0 | V23: =+V22 -> 1.65 | W23: =+V23*2*B23*10 -> 1419 | X23: 2 | Y23: =+X23*B23 -> 86 | AF23: =+A23 -> MURCHISON | AG23: =+Q95-B95 -> 5212.65 | AH23: =+CEILING(AG23*1.36,10) -> 7090
A24: NAGAMBIE | B24: 60 | C24: =+C23 -> 3.3 | D24: 70 | E24: =+C24*B24 -> 198 | F24: =+C24*B24 -> 198 | G24: =+C24*B24*6 -> 1188 | H24: =+C24*B24 -> 198 | I24: 65 | J24: =+I24*35 -> 2275 | K24: 210 | L24: =+K24*60 -> 12600 | M24: =+M23 -> 4 | N24: =+B24-80 -> -20 | O24: =IF((N24>0),(N24*M24*2),) -> 0 | P24: 50 | Q24: =+P24*8 -> 400 | R24: 54 | S24: =+R24*9 -> 486 | T24: =+T23 -> 6 | U24: =+IF(((B24-80)>0),((B24-80)*T24),0) -> 0 | V24: =+V23 -> 1.65 | W24: =+V24*2*B24*10 -> 1980 | X24: 2 | Y24: =+X24*B24 -> 120 | AF24: =+A24 -> NAGAMBIE | AG24: =+R95-B95 -> 7455.75 | AH24: =+CEILING(AG24*1.36,10) -> 10140
A25: NATHALIA | B25: 40 | C25: =+C24 -> 3.3 | D25: 70 | E25: =+C25*B25 -> 132 | F25: =+C25*B25 -> 132 | G25: =+C25*B25*6 -> 792 | H25: =+C25*B25 -> 132 | I25: 63 | J25: =+I25*35 -> 2205 | K25: 232 | L25: =+K25*60 -> 13920 | M25: =+M24 -> 4 | N25: =+B25-80 -> -40 | O25: =IF((N25>0),(N25*M25*2),) -> 0 | P25: 65 | Q25: =+P25*8 -> 520 | R25: 52 | S25: =+R25*9 -> 468 | T25: =+T24 -> 6 | U25: =+IF(((B25-80)>0),((B25-80)*T25),0) -> 0 | V25: =+V24 -> 1.65 | W25: =+V25*2*B25*10 -> 1320 | X25: 2 | Y25: =+X25*B25 -> 80 | AF25: =+A25 -> NATHALIA | AG25: =+S95-B95 -> 5868.75 | AH25: =+CEILING(AG25*1.36,10) -> 7990
A26: NUMURKAH | B26: 35 | C26: =+C25 -> 3.3 | D26: 60 | E26: =+C26*B26 -> 115.5 | F26: =+C26*B26 -> 115.5 | G26: =+C26*B26*6 -> 693 | H26: =+C26*B26 -> 115.5 | I26: 51 | J26: =+I26*35 -> 1785 | K26: 220 | L26: =+K26*60 -> 13200 | M26: =+M25 -> 4 | N26: =+B26-80 -> -45 | O26: =IF((N26>0),(N26*M26*2),) -> 0 | P26: 55 | Q26: =+P26*8 -> 440 | R26: 44 | S26: =+R26*9 -> 396 | T26: =+T25 -> 6 | U26: =+IF(((B26-80)>0),((B26-80)*T26),0) -> 0 | V26: =+V25 -> 1.65 | W26: =+V26*2*B26*10 -> 1155 | X26: 2 | Y26: =+X26*B26 -> 70 | AF26: =+A26 -> NUMURKAH | AG26: =+T95-B95 -> 3435.25 | AH26: =+CEILING(AG26*1.36,10) -> 4680
A27: ROCHESTER | B27: 70 | C27: =+C26 -> 3.3 | D27: 90 | E27: =+C27*B27 -> 231 | F27: =+C27*B27 -> 231 | G27: =+C27*B27*6 -> 1386 | H27: =+C27*B27 -> 231 | I27: 65 | J27: =+I27*35 -> 2275 | K27: 256 | L27: =+K27*60 -> 15360 | M27: =+M26 -> 4 | N27: =+B27-80 -> -10 | O27: =IF((N27>0),(N27*M27*2),) -> 0 | P27: 75 | Q27: =+P27*8 -> 600 | R27: 54 | S27: =+R27*9 -> 486 | T27: =+T26 -> 6 | U27: =+IF(((B27-80)>0),((B27-80)*T27),0) -> 0 | V27: =+V26 -> 1.65 | W27: =+V27*2*B27*10 -> 2310 | X27: 2 | Y27: =+X27*B27 -> 140 | AF27: =+A27 -> ROCHESTER | AG27: =+U95-B95 -> 11838.75 | AH27: =+CEILING(AG27*1.36,10) -> 16110
A28: RUSHWORTH | B28: 48 | C28: =+C27 -> 3.3 | D28: 90 | E28: =+C28*B28 -> 158.4 | F28: =+C28*B28 -> 158.4 | G28: =+C28*B28*6 -> 950.4 | H28: =+C28*B28 -> 158.4 | I28: 65 | J28: =+I28*35 -> 2275 | K28: 242 | L28: =+K28*60 -> 14520 | M28: =+M27 -> 4 | N28: =+B28-80 -> -32 | O28: =IF((N28>0),(N28*M28*2),) -> 0 | P28: 80 | Q28: =+P28*8 -> 640 | R28: 52 | S28: =+R28*9 -> 468 | T28: =+T27 -> 6 | U28: =+IF(((B28-80)>0),((B28-80)*T28),0) -> 0 | V28: =+V27 -> 1.65 | W28: =+V28*2*B28*10 -> 1584 | X28: 2 | Y28: =+X28*B28 -> 96 | AF28: =+A28 -> RUSHWORTH | AG28: =+V95-B95 -> 6749.15 | AH28: =+CEILING(AG28*1.36,10) -> 9180
A29: SEYMOUR | B29: 86 | C29: =+C28 -> 3.3 | D29: 110 | E29: =+C29*B29 -> 283.8 | F29: =+C29*B29 -> 283.8 | G29: =+C29*B29*6 -> 1702.8 | H29: =+C29*B29 -> 283.8 | I29: 65 | J29: =+I29*35 -> 2275 | K29: 220 | L29: =+K29*60 -> 13200 | M29: =+M28 -> 4 | N29: =+B29-80 -> 6 | O29: =IF((N29>0),(N29*M29*2),) -> 48 | P29: 55 | Q29: =+P29*8 -> 440 | R29: 54 | S29: =+R29*9 -> 486 | T29: =+T28 -> 6 | U29: =+IF(((B29-80)>0),((B29-80)*T29),0) -> 36 | V29: =+V28 -> 1.65 | W29: =+V29*2*B29*10 -> 2838 | X29: 2 | Y29: =+X29*B29 -> 172 | AF29: =+A29 -> SEYMOUR | AG29: =+W95-B95 -> 11918.55 | AH29: =+CEILING(AG29*1.36,10) -> 16210
A30: STANHOPE | B30: 42 | C30: =+C29 -> 3.3 | D30: 60 | E30: =+C30*B30 -> 138.6 | F30: =+C30*B30 -> 138.6 | G30: =+C30*B30*6 -> 831.6 | H30: =+C30*B30 -> 138.6 | I30: 63 | J30: =+I30*35 -> 2205 | K30: 232 | L30: =+K30*60 -> 13920 | M30: =+M29 -> 4 | N30: =+B30-80 -> -38 | O30: =IF((N30>0),(N30*M30*2),) -> 0 | P30: 80 | Q30: =+P30*8 -> 640 | R30: 52 | S30: =+R30*9 -> 468 | T30: =+T29 -> 6 | U30: =+IF(((B30-80)>0),((B30-80)*T30),0) -> 0 | V30: =+V29 -> 1.65 | W30: =+V30*2*B30*10 -> 1386 | X30: 2 | Y30: =+X30*B30 -> 84 | AF30: =+A30 -> STANHOPE | AG30: =+X95-B95 -> 5751.35 | AH30: =+CEILING(AG30*1.36,10) -> 7830
A31: STRATHMERTON | B31: 56 | C31: =+C30 -> 3.3 | D31: 70 | E31: =+C31*B31 -> 184.8 | F31: =+C31*B31 -> 184.8 | G31: =+C31*B31*6 -> 1108.8 | H31: =+C31*B31 -> 184.8 | I31: 65 | J31: =+I31*35 -> 2275 | K31: 216 | L31: =+K31*60 -> 12960 | M31: =+M30 -> 4 | N31: =+B31-80 -> -24 | O31: =IF((N31>0),(N31*M31*2),) -> 0 | P31: 70 | Q31: =+P31*8 -> 560 | R31: 52 | S31: =+R31*9 -> 468 | T31: =+T30 -> 6 | U31: =+IF(((B31-80)>0),((B31-80)*T31),0) -> 0 | V31: =+V30 -> 1.65 | W31: =+V31*2*B31*10 -> 1848 | X31: 2 | Y31: =+X31*B31 -> 112 | AF31: =+A31 -> STRATHMERTON | AG31: =+Y95-B95 -> 7130.55 | AH31: =+CEILING(AG31*1.36,10) -> 9700
A32: TATURA | B32: 20 | C32: =+C31 -> 3.3 | D32: =+D8 -> 45.45 | E32: =+C32*B32 -> 66 | F32: =+C32*B32 -> 66 | G32: =+C32*B32*6 -> 396 | H32: =+C32*B32 -> 66 | I32: 51 | J32: =+I32*35 -> 1785 | K32: 210 | L32: =+K32*60 -> 12600 | M32: =+M31 -> 4 | N32: =+B32-80 -> -60 | O32: =IF((N32>0),(N32*M32*2),) -> 0 | P32: 60 | Q32: =+P32*8 -> 480 | R32: 44 | S32: =+R32*9 -> 396 | T32: =+T31 -> 6 | U32: =+IF(((B32-80)>0),((B32-80)*T32),0) -> 0 | V32: =+V31 -> 1.65 | W32: =+V32*2*B32*10 -> 660 | X32: 2 | AF32: =+A32 -> TATURA | AG32: =+Z95-B95 -> 890 | AH32: =+CEILING(AG32*1.36,10) -> 1220
A33: TONGALA | B33: 57 | C33: =+C32 -> 3.3 | D33: 80 | E33: =+C33*B33 -> 188.1 | F33: =+C33*B33 -> 188.1 | G33: =+C33*B33*6 -> 1128.6 | H33: =+C33*B33 -> 188.1 | I33: 65 | J33: =+I33*35 -> 2275 | K33: 230 | L33: =+K33*60 -> 13800 | M33: =+M32 -> 4 | N33: =+B33-80 -> -23 | O33: =IF((N33>0),(N33*M33*2),) -> 0 | P33: 85 | Q33: =+P33*8 -> 680 | R33: 52 | S33: =+R33*9 -> 468 | T33: =+T32 -> 6 | U33: =+IF(((B33-80)>0),((B33-80)*T33),0) -> 0 | V33: =+V32 -> 1.65 | W33: =+V33*2*B33*10 -> 1881 | X33: 2 | Y33: =+X33*B33 -> 114 | AF33: =+A33 -> TONGALA | AG33: =+AA95-B95 -> 7561.85 | AH33: =+CEILING(AG33*1.36,10) -> 10290
A34: TUNGAMAH | B34: 59 | C34: =+C33 -> 3.3 | D34: =+D10 -> 110 | E34: =+C34*B34 -> 194.7 | F34: =+C34*B34 -> 194.7 | G34: =+C34*B34*6 -> 1168.2 | H34: =+C34*B34 -> 194.7 | I34: 65 | J34: =+I34*35 -> 2275 | K34: 240 | L34: =+K34*60 -> 14400 | M34: =+M33 -> 4 | N34: =+B34-80 -> -21 | O34: =IF((N34>0),(N34*M34*2),) -> 0 | P34: 70 | Q34: =+P34*8 -> 560 | R34: 65 | S34: =+R34*9 -> 585 | T34: =+T33 -> 6 | U34: =+IF(((B34-80)>0),((B34-80)*T34),0) -> 0 | V34: =+V33 -> 1.65 | W34: =+V34*2*B34*10 -> 1947 | X34: 2 | Y34: =+X34*B34 -> 118 | AF34: =+A34 -> TUNGAMAH | AG34: =+AB95-B95 -> 11173.45 | AH34: =+CEILING(AG34*1.36,10) -> 15200
A35: YARRAWONGA | B35: 78 | C35: =+C34 -> 3.3 | D35: 80 | E35: =+C35*B35 -> 257.4 | F35: =+C35*B35 -> 257.4 | G35: =+C35*B35*6 -> 1544.4 | H35: =+C35*B35 -> 257.4 | I35: 65 | J35: =+I35*35 -> 2275 | K35: 220 | L35: =+K35*60 -> 13200 | M35: =+M34 -> 4 | N35: =+B35-80 -> -2 | O35: =IF((N35>0),(N35*M35*2),) -> 0 | P35: 65 | Q35: =+P35*8 -> 520 | R35: 54 | S35: =+R35*9 -> 486 | T35: =+T34 -> 6 | U35: =+IF(((B35-80)>0),((B35-80)*T35),0) -> 0 | V35: =+V34 -> 1.65 | W35: =+V35*2*B35*10 -> 2574 | X35: 2 | Y35: =+X35*B35 -> 156 | AF35: =+A35 -> YARRAWONGA | AG35: =+AC95-B95 -> 11539.15 | AH35: =+CEILING(AG35*1.36,10) -> 15700
A36: YEA | B36: 119 | C36: =+C35 -> 3.3 | D36: =+D22 -> 150 | E36: =+C36*B36 -> 392.7 | F36: =+C36*B36 -> 392.7 | G36: =(+VALUE(B36))*1.65 -> 196.35 | H36: =+C36*B36 -> 392.7 | I36: 85 | J36: =+I36*35 -> 2975 | K36: 295 | L36: =+K36*60 -> 17700 | M36: =+M35 -> 4 | N36: =+B36-80 -> 39 | O36: =IF((N36>0),(N36*M36*2),) -> 312 | P36: 80 | Q36: =+P36*8 -> 640 | R36: 80 | S36: =+R36*9 -> 720 | T36: =+T35 -> 6 | U36: =+IF(((B36-80)>0),((B36-80)*T36),0) -> 234 | V36: =+V35 -> 1.65 | W36: =+V36*2*B36*10 -> 3927 | X36: 2 | Y36: =+X36*B36 -> 238 | AF36: =+A36 -> YEA | AG36: =+AD95-B95 -> 28472.6 | AH36: =+CEILING(AG36*1.36,10) -> 38730
B38: 3630 | C38: 3714 | D38: 3664 | E38: 3671 | F38: 3644 | G38: 3568 | H38: 2710 | I38: 3564 | J38: 3666 | K38: 2713 | L38: 3634 | M38: 3580 | N38: 3620 | O38: 3722 | P38: 2710 | Q38: 3610 | R38: 3608 | S38: 3638 | T38: 3636 | U38: 3561 | V38: 3612 | W38: 3660 | X38: 3623 | Y38: 3641 | Z38: 3616 | AA38: 3621 | AB38: 3728 | AC38: 3730 | AD38: 3717
B39: SHEPPARTON | C39: ALEXANDRA | D39: AVENEL | E39: BENALLA | F39: COBRAM | G39: COHUNA | H39: DENILIQUIN | I39: ECHUCA | J39: EUROA | K39: FINLEY | L39: KATANDRA | M39: KOONDROOK | N39: KYABRAM | O39: MANSFIELD | P39: MATHOURA | Q39: MURCHISON | R39: NAGAMBIE | S39: NATHALIA | T39: NUMURKAH | U39: ROCHESTER | V39: RUSHWORTH | W39: SEYMOUR | X39: STANHOPE | Y39: STRATHMERTON | Z39: TATURA | AA39: TONGALA | AB39: TUNGAMAH | AC39: YARRAWONGA | AD39: YEA
A40: Km | C40: 120km | D40: 71km | E40: 62km | F40: 71km | G40: 135km | H40: 137KM | I40: 71km | J40: 49km | K40: 101km | L40: 29km | M40: 158km | N40: 37km | O40: 125km | P40: 103km | Q40: 43km | R40: 60km | S40: 40km | T40: 35km | U40: 70km | V40: 48km | W40: 86km | X40: 42km | Y40: 56km | Z40: 20km | AA40: 57km | AB40: 59km | AC40: 78km | AD40: 119km
A41: Bunnings delivery - (205, 350, 385, 395) Added extra delivery Load 5 on 545 Fix materials | B41: =+D8*5 -> 227.25 | C41: =+D9*5 -> 750 | D41: =+D10*5 -> 550 | E41: =+D11*5 -> 350 | F41: =+D12*5 -> 350 | G41: =+D13*5 -> 750 | H41: =+D14*5 -> 750 | I41: =+D15*5 -> 400 | J41: =+D16*5 -> 450 | K41: =+D17*5 -> 750 | L41: =+D18*5 -> 550 | M41: =+D19*5 -> 750 | N41: =+D20*5 -> 250 | O41: =+D21*5 -> 550 | P41: =+D22*5 -> 750 | Q41: =+D23*5 -> 450 | R41: =+D24*5 -> 350 | S41: =+D25*5 -> 350 | T41: =+D26*5 -> 300 | U41: =+D27*5 -> 450 | V41: =+D28*5 -> 450 | W41: =+D29*5 -> 550 | X41: =+D30*5 -> 300 | Y41: =+D31*5 -> 350 | Z41: =+D32*5 -> 227.25 | AA41: =+D33*5 -> 400 | AB41: =+D34*5 -> 550 | AC41: =+D35*5 -> 400 | AD41: =+D36*5 -> 750
A42: Bunting & pickets at Benalla | E42: 150
A43: Drafting Inspection travel | B43: =E8 -> 66 | C43: =E9 -> 396 | D43: =E10 -> 234.3 | E43: =E11 -> 204.6 | F43: =E12 -> 234.3 | G43: =E13 -> 445.5 | H43: =E14 -> 452.1 | I43: =E15 -> 234.3 | J43: =E16 -> 161.7 | K43: =E17 -> 333.3 | L43: =E18 -> 95.7 | M43: =E19 -> 521.4 | N43: =E20 -> 122.1 | O43: =E21 -> 412.5 | P43: =E22 -> 339.9 | Q43: =E23 -> 141.9 | R43: =E24 -> 198 | S43: =E25 -> 132 | T43: =E26 -> 115.5 | U43: =E27 -> 231 | V43: =E28 -> 158.4 | W43: =E29 -> 283.8 | X43: =E30 -> 138.6 | Y43: =E31 -> 184.8 | Z43: =E32 -> 66 | AA43: =E33 -> 188.1 | AB43: =E34 -> 194.7 | AC43: =E35 -> 257.4 | AD43: =E36 -> 392.7
A44: Soil test (020) | B44: 0 | C44: 340 | D44: 220 | E44: 220 | F44: 140 | G44: 220 | H44: 220 | I44: 0 | J44: 220 | K44: 220 | L44: 140 | M44: 220 | N44: 115 | O44: 340 | P44: 140 | Q44: 140 | R44: 220 | S44: 140 | T44: 140 | U44: 220 | V44: 140 | W44: 220 | X44: 140 | Y44: 220 | Z44: 140 | AA44: 220 | AB44: 220 | AC44: 0 | AD44: 340
A45: Water connection (050) | O45: 78
A46: Building Surveyour (080) | B46: 0 | C46: 400 | D46: 0 | E46: 0 | F46: 0 | G46: 0 | H46: 400 | I46: 0 | J46: 0 | K46: 400 | L46: 0 | M46: 400 | N46: 0 | O46: 400 | P46: 0 | Q46: 0 | R46: 0 | S46: 0 | T46: 0 | U46: 0 | V46: 0 | W46: 0 | X46: 0 | Y46: 0 | Z46: 0 | AA46: 0 | AB46: 0 | AC46: 0 | AD46: 400
A47: Council charges | D47: 1500 | W47: 1000
A48: Temp fencing travel (100) | B48: =F8 -> 66 | C48: =F9 -> 396 | D48: =+F10 -> 234.3 | E48: =F11 -> 204.6 | F48: =F12 -> 234.3 | G48: =F13 -> 445.5 | H48: =F14 -> 452.1 | I48: =F15 -> 234.3 | J48: =F16 -> 161.7 | K48: =F17 -> 333.3 | L48: =F18 -> 95.7 | M48: =F19 -> 521.4 | N48: =F20 -> 122.1 | O48: =F21 -> 412.5 | P48: =F22 -> 339.9 | Q48: =F23 -> 141.9 | R48: =F24 -> 198 | S48: =F25 -> 132 | T48: =F26 -> 115.5 | U48: =F27 -> 231 | V48: =F28 -> 158.4 | W48: =F29 -> 283.8 | X48: =F30 -> 138.6 | Y48: =F31 -> 184.8 | Z48: =F32 -> 66 | AA48: =F33 -> 188.1 | AB48: =F34 -> 194.7 | AC48: =F35 -> 257.4 | AD48: =F36 -> 392.7
A49: Toilet hire (105) | B49: 0 | C49: 50 | D49: 50 | E49: 50 | F49: 50 | G49: 50 | H49: 50 | I49: 50 | J49: 50 | K49: 50 | L49: 0 | M49: 50 | N49: 0 | O49: 50 | P49: 50 | Q49: 0 | R49: 50 | S49: 0 | T49: 0 | U49: 50 | V49: 50 | W49: 50 | X49: 0 | Y49: 50 | Z49: 0 | AA49: 50 | AB49: 50 | AC49: 50 | AD49: 50
A50: Forklift travel (105) | B50: 0 | C50: 290 | D50: 190 | E50: 190 | F50: 190 | G50: 350 | H50: 350 | I50: 190 | J50: 150 | K50: 290 | L50: 150 | M50: 350 | N50: 150 | O50: 270 | P50: 290 | Q50: 130 | R50: 150 | S50: 150 | T50: 90 | U50: 190 | V50: 150 | W50: 210 | X50: 150 | Y50: 190 | Z50: 90 | AA50: 150 | AB50: 190 | AC50: 190 | AD50: 290
A51: Skip truck travel (115) | B51: =G8 -> 396 | C51: =G9 -> 2376 | D51: =G10 -> 1405.8 | E51: =G11 -> 1227.6 | F51: =G12 -> 1405.8 | G51: =G13 -> 2673 | H51: =G14 -> 2712.6 | I51: =G15 -> 1405.8 | J51: =G16 -> 970.2 | K51: =G17 -> 1999.8 | L51: =G18 -> 574.2 | M51: =G19 -> 3128.4 | N51: =G20 -> 732.6 | O51: =G21 -> 2475 | P51: =G22 -> 2039.4 | Q51: =G23 -> 851.4 | R51: =G24 -> 1188 | S51: =G25 -> 792 | T51: =G26 -> 693 | U51: =G27 -> 1386 | V51: =G28 -> 950.4 | W51: =G29 -> 1702.8 | X51: =G30 -> 831.6 | Y51: =G31 -> 1108.8 | Z51: =G32 -> 396 | AA51: =G33 -> 1128.6 | AB51: =G34 -> 1168.2 | AC51: =G35 -> 1544.4 | AD51: =G36 -> 196.35
A52: Set out travel (125) | B52: =+B61 -> 66 | C52: =+C61 -> 396 | D52: =+D61 -> 234.3 | E52: =+E61 -> 204.6 | F52: =+F61 -> 234.3 | G52: =+G61 -> 445.5 | H52: =+H61 -> 452.1 | I52: =+I61 -> 234.3 | ... AD52: =+AD61 -> 392.7
A53: Drainer travel (135) | C53: 700 | D53: 700 | E53: 780 | F53: 700 | G53: 700 | H53: 700 | I53: 0 | J53: 700 | K53: 700 | L53: 700 | M53: 700 | N53: 700 | O53: 700 | P53: 700 | Q53: 700 | R53: 700 | S53: 700 | T53: 700 | U53: 700 | V53: 700 | W53: 700 | X53: 700 | Y53: 700 | Z53: 700 | AA53: 700 | AB53: 700 | AC53: 760 | AD53: 700
A54: Stormy travel
A55: Post Slab Inspection Travel (135) | C55: 165 | D55: 165 | E55: 165 | F55: 165 | G55: 165 | H55: 165 | J55: 165 | K55: 165 | L55: 165 | M55: 165 | N55: 165 | O55: 165 | P55: 165 | Q55: 165 | R55: 165 | S55: 165 | T55: 165 | U55: 165 | V55: 165 | W55: 165 | X55: 165 | Y55: 165 | AA55: 165 | AB55: 165 | AC55: 165 | AD55: 165
A56: Waffle pod delivery (145) | B56: 870 | C56: 800 | D56: 670 | E56: 1030 | F56: 1270 | G56: 1500 | H56: 1500 | I56: 1070 | J56: 770 | K56: 1500 | L56: 1200 | M56: 1500 | N56: 1030 | O56: 1030 | P56: 1500 | Q56: 780 | R56: 680 | S56: 1140 | T56: 1120 | U56: 1000 | V56: 750 | W56: 600 | X56: 950 | Y56: 1230 | Z56: 880 | AA56: 1050 | AB56: 1400 | AC56: 1400 | AD56: 650
A57: Crusher dust (allow 35 M3) | B57: =+J8 -> 1785 | C57: =+J9 -> 2975 | D57: =+J10 -> 2275 | E57: =+J11 -> 2275 | F57: =+J12 -> 2275 | G57: =+J13 -> 2975 | H57: =+J14 -> 2975 | I57: =+J15 -> 2205 | J57: =+J16 -> 2205 | K57: =+J17 -> 2975 | L57: =+J18 -> 2275 | M57: =+J19 -> 2975 | N57: =+J20 -> 2205 | O57: =+J21 -> 2975 | P57: =+J22 -> 2975 | Q57: =+J23 -> 2275 | R57: =+J24 -> 2275 | S57: =+J25 -> 2205 | T57: =+J26 -> 1785 | U57: =+J27 -> 2275 | V57: =+J28 -> 2275 | W57: =+J29 -> 2275 | X57: =+J30 -> 2205 | Y57: =+J31 -> 2275 | Z57: =+J32 -> 1785 | AA57: =+J33 -> 2275 | AB57: =+J34 -> 2275 | AC57: =+J35 -> 2275 | AD57: =+J36 -> 2975
A58: Concreter machine travel (150) | C58: 1800 | D58: 350 | E58: 350 | F58: 350 | G58: 1800 | H58: 1800 | I58: 350 | K58: 350 | M58: 1800 | O58: 1800 | P58: 1800 | U58: 350 | W58: 350 | AB58: 350 | AC58: 350 | AD58: 1800
A59: Concreter labour travel (150) | C59: 650 | D59: 650 | G59: 650 | H59: 650 | I59: 850 | K59: 650 | M59: 650 | O59: 650 | P59: 650 | AD59: 1000
A60: Concreter labour accommodation | C60: 2000 | G60: 2000 | H60: 2000 | K60: 2000 | M60: 2000 | O60: 2000 | P60: 2000 | AD60: 2000
A61: Site scrape travel | B61: =+H8 -> 66 | C61: =+H9 -> 396 | D61: =+H10 -> 234.3 | E61: =+H11 -> 204.6 | F61: =+H12 -> 234.3 | G61: =+H13 -> 445.5 | H61: =+H14 -> 452.1 | I61: =+H15 -> 234.3 | J61: =+H16 -> 161.7 | K61: =+H17 -> 333.3 | L61: =+H18 -> 95.7 | M61: =+H19 -> 521.4 | N61: =+H20 -> 122.1 | O61: =+H21 -> 412.5 | P61: =+H22 -> 339.9 | Q61: =+H23 -> 141.9 | R61: =+H24 -> 198 | S61: =+H25 -> 132 | T61: =+H26 -> 115.5 | U61: =+H27 -> 231 | V61: =+H28 -> 158.4 | W61: =+H29 -> 283.8 | X61: =+H30 -> 138.6 | Y61: =+H31 -> 184.8 | Z61: =+H32 -> 66 | AA61: =+H33 -> 188.1 | AB61: =+H34 -> 194.7 | AC61: =+H35 -> 257.4 | AD61: =+H36 -> 392.7
A62: Concrete supply - allow 60 m3 (155) | B62: =+L8 -> 12600 | C62: =+L9 -> 17220 | D62: =+L10 -> 12600 | E62: =+L11 -> 14100 | F62: =+L12 -> 13200 | G62: =+L13 -> 20700 | H62: =+L14 -> 21480 | I62: =+L15 -> 13800 | J62: =+L16 -> 15420 | K62: =+L17 -> 14820 | L62: =+L17 -> 14820 | M62: =+L19 -> 20700 | N62: =+L20 -> 13800 | O62: =+L21 -> 16740 | P62: =+L22 -> 21480 | Q62: =+L23 -> 13080 | R62: =+L24 -> 12600 | S62: =+L25 -> 13920 | T62: =+L26 -> 13200 | U62: =+L27 -> 15360 | V62: =+L28 -> 14520 | W62: =+L29 -> 13200 | X62: =+L30 -> 13920 | Y62: =+L31 -> 12960 | Z62: =+L32 -> 12600 | AA62: =+L33 -> 13800 | AB62: =+L34 -> 14400 | AC62: =+L35 -> 13200 | AD62: =+L36 -> 17700
A63: Concrete pump travel (160) | B63: =+O8 -> 0 | C63: =+O9 -> 320 | D63: =+O10 -> 0 | E63: =+O11 -> 0 | F63: =+O12 -> 0 | G63: =+O13 -> 440 | H63: =+O14 -> 456 | I63: =+O15 -> 0 | J63: =+O16 -> 0 | K63: =+O17 -> 168 | L63: =+O18 -> 0 | M63: =+O19 -> 624 | N63: =+O20 -> 0 | O63: =+O21 -> 360 | P63: =+O22 -> 184 | Q63: =+O23 -> 0 | R63: =+O24 -> 0 | S63: =+O25 -> 0 | T63: =+O26 -> 0 | U63: =+O27 -> 0 | V63: =+O28 -> 0 | W63: =+O29 -> 48 | X63: =+O30 -> 0 | Y63: =+O31 -> 0 | Z63: =+O32 -> 0 | AA63: =+O33 -> 0 | AB63: =+O34 -> 0 | AC63: =+O35 -> 0 | AD63: =+O36 -> 312
A64: Trusses (200) | B64: 710 | C64: 1030 | D64: 720 | E64: 1020 | F64: 1150 | G64: 730 | H64: 990 | I64: 710 | J64: 800 | K64: 1330 | L64: 880 | M64: 930 | N64: 620 | O64: 1230 | Q64: 620 | R64: 620 | S64: 820 | T64: 930 | U64: 520 | V64: 520 | W64: 620 | X64: 620 | Y64: 1050 | Z64: 620 | AA64: 620 | AB64: 1070 | AC64: 1200 | AD64: 840
A65: Framer travel (210) | C65: 800 | G65: 400 | H65: 400 | K65: 400 | M65: 400 | O65: 400 | P65: 400 | Q65: 400 | AC65: 400 | AD65: 800
A66: Framer accommodation | C66: 2000 | G66: 2000 | H66: 2000 | K66: 2000 | M66: 2000 | O66: 2000 | P66: 2000 | AD66: 2000
A67: Roofing delivery (315) | C67: 1125 | D67: 650 | E67: 650 | F67: 650 | G67: 1125 | H67: 1125 | I67: 650 | J67: 650 | K67: 890 | M67: 1125 | O67: 1125 | P67: 890 | Q67: 650 | R67: 650 | S67: 650 | U67: 650 | V67: 650 | W67: 890 | X67: 650 | Y67: 650 | AA67: 650 | AB67: 650 | AC67: 650 | AD67: 1125
A68: Plumber travel (330) | C68: 400 | G68: 400 | H68: 400 | I68: 400 | K68: 400 | M68: 400 | O68: 400 | P68: 400 | AD68: 400
A69: Electrician travel (335) | C69: 300 | G69: 300 | H69: 300 | I69: 300 | K69: 300 | M69: 300 | O69: 300 | P69: 300 | AD69: 300
A70: Soalr panel travel | C70: =+Y9 -> 240 | D70: =+Y10 -> 142 | E70: =+Y11 -> 124 | F70: =+Y12 -> 142 | G70: =+Y13 -> 270 | H70: =+Y14 -> 274 | I70: =+Y15 -> 142 | J70: =+Y16 -> 98 | K70: =+Y17 -> 202 | L70: =+Y18 -> 58 | M70: =+Y19 -> 316 | N70: =+Y20 -> 74 | O70: =+Y21 -> 250 | P70: =+Y22 -> 206 | Q70: =+Y23 -> 86 | R70: =+Y24 -> 120 | S70: =+Y25 -> 80 | T70: =+Y26 -> 70 | U70: =+Y27 -> 140 | V70: =+Y28 -> 96 | W70: =+Y29 -> 172 | X70: =+Y30 -> 84 | Y70: =+Y31 -> 112 | Z70: =+Y32 -> 0 | AA70: =+Y33 -> 114 | AB70: =+Y34 -> 118 | AC70: =+Y35 -> 156 | AD70: =+Y36 -> 238
A71: Inspection fee | B71: 0 | C71: 200 | D71: 80 | E71: 80 | F71: 80 | G71: 200 | H71: 200 | I71: 80 | J71: 50 | K71: 80 | M71: 200 | N71: 50 | O71: 200 | P71: 200 | Q71: 50 | R71: 80 | S71: 50 | T71: 50 | U71: 80 | V71: 50 | W71: 80 | X71: 50 | Y71: 50 | AA71: 50 | AB71: 50 | AC71: 80 | AD71: 200
A72: Brick delivery for 8000 (340) | B72: =+Q8 -> 440 | C72: =+Q9 -> 520 | D72: =+Q10 -> 440 | E72: =+Q11 -> 440 | F72: =+Q12 -> 560 | G72: =+Q13 -> 640 | H72: =+Q14 -> 640 | I72: =+Q15 -> 480 | J72: =+Q16 -> 440 | K72: =+Q17 -> 640 | L72: =+Q18 -> 520 | M72: =+Q19 -> 640 | N72: =+Q20 -> 600 | O72: =+Q21 -> 560 | P72: =+Q22 -> 640 | Q72: =+Q23 -> 440 | R72: =+Q24 -> 400 | S72: =+Q25 -> 520 | T72: =+Q26 -> 440 | U72: =+Q27 -> 600 | V72: =+Q28 -> 640 | W72: =+Q29 -> 440 | X72: =+Q30 -> 640 | Y72: =+Q31 -> 560 | Z72: =+Q32 -> 480 | AA72: =+Q33 -> 680 | AB72: =+Q34 -> 560 | AC72: =+Q35 -> 520 | AD72: =+Q36 -> 640
A73: Brick sand 9 m3 (345) | B73: =+S8 -> 396 | C73: =+S9 -> 720 | D73: =+S10 -> 504 | E73: =+S11 -> 486 | F73: =+S12 -> 486 | G73: =+S13 -> 720 | H73: =+S14 -> 720 | I73: =+S15 -> 495 | J73: =+S16 -> 468 | K73: =+S17 -> 720 | L73: =+S18 -> 540 | M73: =+S19 -> 720 | N73: =+S20 -> 468 | O73: =+S21 -> 720 | P73: =+S22 -> 720 | Q73: =+S23 -> 468 | R73: =+S24 -> 486 | S73: =+S25 -> 468 | T73: =+S26 -> 396 | U73: =+S27 -> 486 | V73: =+S28 -> 468 | W73: =+S29 -> 486 | X73: =+S30 -> 468 | Y73: =+S31 -> 468 | Z73: =+S32 -> 396 | AA73: =+S33 -> 468 | AB73: =+S34 -> 585 | AC73: =+S35 -> 486 | AD73: =+S36 -> 720
A74: Bricklayer labour extra for 8000 (360) | O74: =8000*0.2 -> 1600
A75: Bricklayer travel (360) | C75: 600 | G75: 600 | H75: 600 | K75: 600 | M75: 600 | O75: 600 | P75: 600 | AD75: 600
A76: Eaves carpenter travel (390) | C76: 200 | G76: 200 | H76: 200 | K76: 200 | M76: 200 | O76: 200 | P76: 200 | AD76: 200
A77: Lock up travel (405) | B77: =+B52 -> 66 | C77: =+C52 -> 396 | D77: =+D52 -> 234.3 | E77: =+E52 -> 204.6 | F77: =+F52 -> 234.3 | G77: =+G52 -> 445.5 | H77: =+H52 -> 452.1 | I77: =+I52 -> 234.3 | ... AD77: =+AD52 -> 392.7
A78: Insulation walls (445) | C78: 85 | D78: 65 | E78: 65 | F78: 65 | G78: 85 | H78: 85 | I78: 65 | K78: 65 | M78: 85 | O78: 85 | P78: 85 | R78: 65 | U78: 65 | W78: 65 | AB78: 65 | AC78: 65 | AD78: 85
A79: Brick cleaner (450) | C79: 110 | D79: 60 | E79: 60 | F79: 60 | G79: 110 | H79: 110 | I79: 60 | J79: 60 | K79: 60 | M79: 110 | O79: 110 | P79: 110 | Q79: 60 | R79: 60 | U79: 60 | V79: 60 | W79: 60 | X79: 60 | Y79: 60 | AA79: 60 | AB79: 60 | AC79: 60 | AD79: 110
A80: Plaster delivery - allow 800 m2 (500) | C80: =0.4*800 -> 320 | D80: =0.4*800 -> 320 | E80: =0.4*800 -> 320 | F80: =0.4*800 -> 320 | G80: =0.4*800 -> 320 | H80: =0.4*800 -> 320 | I80: =0.4*800 -> 320 | J80: =0.4*800 -> 320 | K80: =0.4*800 -> 320 | M80: =0.4*800 -> 320 | O80: =0.4*800 -> 320 | P80: =0.4*800 -> 320 | R80: =0.4*800 -> 320 | U80: =0.4*800 -> 320 | W80: =0.4*800 -> 320 | Y80: =0.4*800 -> 320 | AA80: =0.4*800 -> 320 | AB80: =0.4*800 -> 320 | AC80: =0.4*800 -> 320 | AD80: =0.4*800 -> 320
A81: Plasterer travel (505) | C81: 832 | D81: 832 | E81: 832 | F81: 832 | G81: 832 | H81: 832 | M81: 832 | O81: 832 | P81: 832 | R81: 832 | U81: 832 | W81: 832 | AB81: 832 | AC81: 832 | AD81: 832
A82: Water proofer travel (510) | C82: 230 | D82: 115 | E82: 115 | F82: 115 | G82: 230 | H82: 230 | I82: 115 | J82: 115 | K82: 230 | M82: 230 | O82: 230 | P82: 230 | Q82: 115 | R82: 115 | S82: 115 | U82: 115 | V82: 115 | W82: 230 | X82: 115 | Y82: 115 | AA82: 115 | AB82: 115 | AC82: 115 | AD82: 230
A83: Stone benchtop (530) | C83: =+U9 -> 240 | D83: =+U10 -> 0 | E83: =+U11 -> 0 | F83: =+U12 -> 0 | G83: =+U13 -> 330 | H83: =+U14 -> 342 | I83: =+U15 -> 0 | J83: =+U16 -> 0 | K83: =+U17 -> 126 | L83: =+U18 -> 0 | M83: =+U19 -> 468 | N83: =+U20 -> 0 | O83: =+U21 -> 270 | P83: =+U22 -> 138 | Q83: =+U23 -> 0 | R83: =+U24 -> 0 | S83: =+U25 -> 0 | T83: =+U26 -> 0 | U83: =+U27 -> 0 | V83: =+U28 -> 0 | W83: =+U29 -> 36 | X83: =+U30 -> 0 | Y83: =+U31 -> 0 | Z83: =+U32 -> 0 | AA83: =+U33 -> 0 | AB83: =+U34 -> 0 | AC83: =+U35 -> 0 | AD83: =+U36 -> 234
A84: Fix carpenter travel (555) | C84: 200 | G84: 200 | H84: 200 | K84: 200 | M84: 200 | O84: 200 | P84: 200 | AD84: 200
A85: Fit off travel (565) | C85: 200 | G85: 200 | H85: 200 | K85: 200 | M85: 200 | O85: 200 | P85: 200 | AD85: 200
A86: Tiler travel (605) | C86: 200 | D86: 200 | E86: 200 | F86: 200 | G86: 200 | H86: 200 | I86: 200 | K86: 200 | M86: 200 | O86: 200 | P86: 200 | R86: 200 | U86: 200 | W86: 200 | AB86: 200 | AC86: 200 | AD86: 200
A87: Painter travel (610) | C87: 500 | G87: 500 | H87: 500 | K87: 500 | M87: 500 | O87: 500 | P87: 500 | AD87: 500
A88: Shower screens (615) | C88: 231 | D88: 139 | E88: 139 | F88: 139 | G88: 139 | H88: 139 | I88: 139 | J88: 38 | K88: 231 | L88: 38 | M88: 139 | N88: 38 | O88: 231 | P88: 231 | Q88: 38 | R88: 139 | S88: 38 | T88: 38 | U88: 139 | V88: 38 | W88: 139 | X88: 38 | Y88: 139 | Z88: 0 | AA88: 139 | AB88: 139 | AC88: 139 | AD88: 139
A89: Garage door (625) | B89: 200 | C89: 200 | D89: 200 | E89: 200 | F89: 200 | G89: 300 | H89: 300 | I89: 300 | J89: 200 | K89: 200 | L89: 300 | M89: 200 | N89: 200 | O89: 200 | P89: 300 | Q89: 200 | R89: 200 | S89: 200 | T89: 200 | U89: 200 | V89: 200 | W89: 200 | X89: 200 | Y89: 200 | Z89: 200 | AA89: 200 | AB89: 200 | AC89: 300 | AD89: 200
A90: Paving machine travel (640) | C90: 270 | D90: 270 | E90: 270 | F90: 270 | G90: 270 | H90: 270 | I90: 270 | K90: 270 | M90: 270 | O90: 270 | P90: 270 | R90: 270 | U90: 270 | W90: 270 | AB90: 270 | AC90: 270 | AD90: 270
A91: Insulation ceilings (675) | C91: =+C78 -> 85 | D91: =+D78 -> 65 | E91: =+E78 -> 65 | F91: =+F78 -> 65 | G91: =+G78 -> 85 | H91: =+H78 -> 85 | I91: =+I78 -> 65 | J91: =+J78 -> 0 | ... AD91: =+AD78 -> 85
A92: Site clean travel (included above)
A93: House clean (705) | C93: 200 | D93: 100 | E93: 100 | F93: 100 | G93: 200 | H93: 200 | I93: 100 | K93: 100 | M93: 200 | O93: 200 | P93: 200 | R93: 100 | U93: 100 | W93: 100 | AB93: 100 | AC93: 100 | AD93: 200
A94: Supervisor travel (710) | B94: =+W8 -> 660 | C94: =+W9 -> 3960 | D94: =+W10 -> 2343 | E94: =+W11 -> 2046 | F94: =+W12 -> 2343 | G94: =+W13 -> 4455 | H94: =+W14 -> 4521 | I94: =+W15 -> 2343 | J94: =+W16 -> 1617 | K94: =+W17 -> 3333 | L94: =+W18 -> 957 | M94: =+W19 -> 5214 | N94: =+W20 -> 1221 | O94: =+W21 -> 4125 | P94: =+W22 -> 3399 | Q94: =+W23 -> 1419 | R94: =+W24 -> 1980 | S94: =+W25 -> 1320 | T94: =+W26 -> 1155 | U94: =+W27 -> 2310 | V94: =+W28 -> 1584 | W94: =+W29 -> 2838 | X94: =+W30 -> 1386 | Y94: =+W31 -> 1848 | Z94: =+W32 -> 660 | AA94: =+W33 -> 1881 | AB94: =+W34 -> 1947 | AC94: =+W35 -> 2574 | AD94: =+W36 -> 3927
B95: =SUM(B41:B94) -> 18614.25 | C95: =SUM(C41:C94) -> 48814 | D95: =SUM(D41:D94) -> 29742.3 | E95: =SUM(E41:E94) -> 29122.6 | F95: =SUM(F41:F94) -> 29044.3 | G95: =SUM(G41:G94) -> 53241.5 | H95: =SUM(H41:H94) -> 54852.1 | I95: =SUM(I41:I94) -> 28726.3 | ... AD95: =SUM(AD41:AD94) -> 47086.85
B96: SHEPPARTON | C96: ALEXANDRA | D96: AVENEL | E96: BENALLA | F96: COBRAM | G96: COHUNA | H96: DENILIQUIN | I96: ECHUCA | J96: EUROA | K96: FINLEY | L96: KATANDRA | M96: KOONDROOK | N96: KYABRAM | O96: MANSFIELD | P96: MATHOURA | Q96: MURCHISON | R96: NAGAMBIE | S96: NATHALIA | T96: NUMURKAH | U96: ROCHESTER | V96: RUSHWORTH | W96: SEYMOUR | X96: STANHOPE | Y96: STRATHMERTON | Z96: TATURA | AA96: TONGALA | AB96: TUNGAMAH | AC96: YARRAWONGA | AD96: YEA | AE96: NSW
A99: NSW charges
A100: DA fee | B100: 1500
A101: Insurance | B101: 3200
A102: Floor waste | B102: 350
A103: Hi-impact poly | B103: 20
...

Sheet Estimator
B2: Base House Plan | C2: Price per sqm | D2: Tiles | E2: Carpets | H2: Pick the closest floor plan and add the items | N2: This sheet is good for adding area, NOT deleting
B3: =+'Fast Key'!A13 -> Byron 19 | C3: =+'Fast Key'!BO13 -> 0 | D3: =+Shepparton!#REF! -> #REF! | E3: =+Shepparton!#REF! -> #REF!
B4: =+'Fast Key'!A14 -> Byron 22A | C4: =+'Fast Key'!BO14 -> 0 | D4: =+Shepparton!#REF! -> #REF! | E4: =+Shepparton!#REF! -> #REF!
B5: =+'Fast Key'!A15 -> Byron 22B | C5: =+'Fast Key'!BO15 -> 0 | D5: =+Shepparton!#REF! -> #REF! | E5: =+Shepparton!#REF! -> #REF!
B6: =+'Fast Key'!A16 -> Ashwood 17 | C6: =+'Fast Key'!BO16 -> 0 | D6: =+Shepparton!#REF! -> #REF! | E6: =+Shepparton!#REF! -> #REF!
B7: =+'Fast Key'!A17 -> Ashwood 20 | C7: =+'Fast Key'!BO17 -> 0 | D7: =+Shepparton!#REF! -> #REF! | E7: =+Shepparton!#REF! -> #REF!
B8: =+'Fast Key'!A18 -> Malvern 20 | C8: =+'Fast Key'!BO18 -> 0 | D8: =+Shepparton!#REF! -> #REF! | E8: =+Shepparton!#REF! -> #REF!
B9: =+'Fast Key'!A19 -> Malvern 23 | C9: =+'Fast Key'!BO19 -> 0 | D9: =+Shepparton!#REF! -> #REF! | E9: =+Shepparton!#REF! -> #REF!
B10: =+'Fast Key'!A21 -> 0 | C10: =+'Fast Key'!BO21 -> 0 | D10: =+Shepparton!#REF! -> #REF! | E10: =+Shepparton!#REF! -> #REF!
B11: =+'Fast Key'!A22 -> 0 | C11: =+'Fast Key'!BO22 -> 0 | D11: =+Shepparton!#REF! -> #REF! | E11: =+Shepparton!#REF! -> #REF!
B12: =+'Fast Key'!A24 -> 0 | C12: =+'Fast Key'!BO24 -> 0 | D12: =+Shepparton!#REF! -> #REF! | E12: =+Shepparton!#REF! -> #REF!
B13: =+'Fast Key'!A26 -> 0 | C13: =+'Fast Key'!BO26 -> 0 | D13: =+Shepparton!#REF! -> #REF! | E13: =+Shepparton!#REF! -> #REF!
B14: =+'Fast Key'!A27 -> 0 | C14: =+'Fast Key'!BO27 -> 0 | D14: =+Shepparton!#REF! -> #REF! | E14: =+Shepparton!#REF! -> #REF!
B15: =+'Fast Key'!A28 -> 0 | C15: =+'Fast Key'!BO28 -> 0 | D15: =+Shepparton!#REF! -> #REF! | E15: =+Shepparton!#REF! -> #REF!
B16: =+'Fast Key'!A29 -> 0 | C16: =+'Fast Key'!BO29 -> 0 | D16: =+Shepparton!#REF! -> #REF! | E16: =+Shepparton!#REF! -> #REF!
B17: =+'Fast Key'!A30 -> 0 | C17: =+'Fast Key'!BO30 -> 0 | D17: =+Shepparton!#REF! -> #REF! | E17: =+Shepparton!#REF! -> #REF!
B18: =+'Fast Key'!A31 -> 0 | C18: =+'Fast Key'!BO31 -> 0 | D18: =+Shepparton!#REF! -> #REF! | E18: =+Shepparton!#REF! -> #REF!
B19: =+'Fast Key'!A34 -> 0 | C19: =+'Fast Key'!BO34 -> 0 | D19: =+Shepparton!#REF! -> #REF! | E19: =+Shepparton!#REF! -> #REF!
B20: =+'Fast Key'!A41 -> 0 | C20: =+'Fast Key'!BO41 -> 0 | D20: =+Shepparton!#REF! -> #REF! | E20: =+Shepparton!#REF! -> #REF!
B21: =+'Fast Key'!A42 -> 0 | C21: =+'Fast Key'!BO42 -> 0 | D21: =+Shepparton!#REF! -> #REF! | E21: =+Shepparton!#REF! -> #REF!
B22: =+'Fast Key'!A43 -> 0 | C22: =+'Fast Key'!BO43 -> 0 | D22: =+Shepparton!#REF! -> #REF! | E22: =+Shepparton!#REF! -> #REF!
B23: =+'Fast Key'!A44 -> 0 | C23: =+'Fast Key'!BO44 -> 0 | D23: =+Shepparton!#REF! -> #REF! | E23: =+Shepparton!#REF! -> #REF!
B24: =+'Fast Key'!A45 -> 0 | C24: =+'Fast Key'!BO45 -> 0 | D24: =+Shepparton!#REF! -> #REF! | E24: =+Shepparton!#REF! -> #REF!
B25: =+'Fast Key'!A46 -> 0 | C25: =+'Fast Key'!BO46 -> 0 | D25: =+Shepparton!#REF! -> #REF! | E25: =+Shepparton!#REF! -> #REF!
B26: =+'Fast Key'!A47 -> 0 | C26: =+'Fast Key'!BO47 -> 0 | D26: =+Shepparton!#REF! -> #REF! | E26: =+Shepparton!#REF! -> #REF!
B27: =+'Fast Key'!A48 -> 0 | C27: =+'Fast Key'!BO48 -> 0 | D27: =+Shepparton!#REF! -> #REF! | E27: =+Shepparton!#REF! -> #REF!
B28: =+'Fast Key'!A49 -> 0 | C28: =+'Fast Key'!BO49 -> 0 | D28: =+Shepparton!#REF! -> #REF! | E28: =+Shepparton!#REF! -> #REF!
B29: =+'Fast Key'!A50 -> 0 | C29: =+'Fast Key'!BO50 -> 0 | D29: =+Shepparton!#REF! -> #REF! | E29: =+Shepparton!#REF! -> #REF!
B30: =+'Fast Key'!A51 -> 0 | C30: =+'Fast Key'!BO51 -> 0 | D30: =+Shepparton!#REF! -> #REF! | E30: =+Shepparton!#REF! -> #REF!
B31: =+'Fast Key'!A52 -> 0 | C31: =+'Fast Key'!BO52 -> 0 | D31: =+Shepparton!#REF! -> #REF! | E31: =+Shepparton!#REF! -> #REF!
... B43: =+'Fast Key'!A64 -> 0 | C43: =+'Fast Key'!BO64 -> 0 | D43: =+Shepparton!#REF! -> #REF! | E43: =+Shepparton!#REF! -> #REF!
B44: =+'Fast Key'!A70 -> 0 | C44: =+'Fast Key'!BO70 -> 0 | D44: =+Shepparton!#REF! -> #REF! | E44: =+Shepparton!#REF! -> #REF!
B45: =+'Fast Key'!A71 -> 0 | C45: =+'Fast Key'!BO71 -> 0 | D45: =+Shepparton!#REF! -> #REF! | E45: =+Shepparton!#REF! -> #REF!
B46: =+'Fast Key'!A72 -> 0 | C46: =+'Fast Key'!BO72 -> 0 | D46: =+Shepparton!#REF! -> #REF! | E46: =+Shepparton!#REF! -> #REF!
B47: =+'Fast Key'!A73 -> 0 | C47: =+'Fast Key'!BO73 -> 0 | D47: =+Shepparton!#REF! -> #REF! | E47: =+Shepparton!#REF! -> #REF!
B48: =+'Fast Key'!A74 -> 0 | C48: =+'Fast Key'!BO74 -> 0 | D48: =+Shepparton!#REF! -> #REF! | E48: =+Shepparton!#REF! -> #REF!
B49: =+'Fast Key'!A75 -> 0 | C49: =+'Fast Key'!BO75 -> 0 | D49: =+Shepparton!#REF! -> #REF! | E49: =+Shepparton!#REF! -> #REF!
B50: =+'Fast Key'!A76 -> 0 | C50: =+'Fast Key'!BO76 -> 0 | D50: =+Shepparton!#REF! -> #REF! | E50: =+Shepparton!#REF! -> #REF!
B51: =+'Fast Key'!A77 -> 0 | C51: =+'Fast Key'!BO77 -> 0 | D51: =+Shepparton!#REF! -> #REF! | E51: =+Shepparton!#REF! -> #REF!
B52: =+'Fast Key'!A78 -> 0 | C52: =+'Fast Key'!BO78 -> 0 | D52: =+Shepparton!#REF! -> #REF! | E52: =+Shepparton!#REF! -> #REF!
B53: =+'Fast Key'!A79 -> 0 | C53: =+'Fast Key'!BO79 -> 0 | D53: =+Shepparton!#REF! -> #REF! | E53: =+Shepparton!#REF! -> #REF!
B54: =+'Fast Key'!A80 -> 0 | C54: =+'Fast Key'!BO80 -> 0 | D54: =+Shepparton!#REF! -> #REF! | E54: =+Shepparton!#REF! -> #REF!
B55: =+'Fast Key'!A81 -> 0 | C55: =+'Fast Key'!BO81 -> 0 | D55: =+Shepparton!#REF! -> #REF! | E55: =+Shepparton!#REF! -> #REF!
... B62: =+'Fast Key'!A88 -> 0 | C62: =+'Fast Key'!BO88 -> 0 | D62: =+Shepparton!#REF! -> #REF! | E62: =+Shepparton!#REF! -> #REF!
B63: =+'Fast Key'!A93 -> 0 | C63: =+'Fast Key'!BO93 -> 0 | D63: =+Shepparton!#REF! -> #REF! | E63: =+Shepparton!#REF! -> #REF!
B64: =+'Fast Key'!A94 -> 0 | C64: =+'Fast Key'!BO94 -> 0 | D64: =+Shepparton!#REF! -> #REF! | E64: =+Shepparton!#REF! -> #REF!
B65: =+'Fast Key'!A95 -> 0 | C65: =+'Fast Key'!BO95 -> 0 | D65: =+Shepparton!#REF! -> #REF! | E65: =+Shepparton!#REF! -> #REF!
B66: =+'Fast Key'!A96 -> 0 | C66: =+'Fast Key'!BO96 -> 0 | D66: =+Shepparton!#REF! -> #REF! | E66: =+Shepparton!#REF! -> #REF!
B67: =+'Fast Key'!A97 -> 0 | C67: =+'Fast Key'!BO97 -> 0 | D67: =+Shepparton!#REF! -> #REF! | E67: =+Shepparton!#REF! -> #REF!
B68: =+'Fast Key'!A99 -> 0 | C68: =+'Fast Key'!BO99 -> 0 | D68: =+Shepparton!#REF! -> #REF! | E68: =+Shepparton!#REF! -> #REF!
B69: =+'Fast Key'!A101 -> 0 | C69: =+'Fast Key'!BO101 -> 0 | D69: =+Shepparton!#REF! -> #REF! | E69: =+Shepparton!#REF! -> #REF!
B70: =+'Fast Key'!A102 -> 0 | C70: =+'Fast Key'!BO102 -> 0 | D70: =+Shepparton!#REF! -> #REF! | E70: =+Shepparton!#REF! -> #REF!
B71: =+'Fast Key'!A103 -> 0 | C71: =+'Fast Key'!BO103 -> 0 | D71: =+Shepparton!#REF! -> #REF! | E71: =+Shepparton!#REF! -> #REF!
B72: =+'Fast Key'!A104 -> 0 | C72: =+'Fast Key'!BO104 -> 0 | D72: =+Shepparton!#REF! -> #REF! | E72: =+Shepparton!#REF! -> #REF!
B73: =+'Fast Key'!A105 -> 0 | C73: =+'Fast Key'!BO105 -> 0 | D73: =+Shepparton!#REF! -> #REF! | E73: =+Shepparton!#REF! -> #REF!
B74: =+'Fast Key'!A106 -> 0 | C74: =+'Fast Key'!BO106 -> 0 | D74: =+Shepparton!#REF! -> #REF! | E74: =+Shepparton!#REF! -> #REF!
B75: =+'Fast Key'!A110 -> 0 | C75: =+'Fast Key'!BO110 -> 0 | D75: =+Shepparton!#REF! -> #REF! | E75: =+Shepparton!#REF! -> #REF!
B76: =+'Fast Key'!A111 -> 0 | C76: =+'Fast Key'!BO111 -> 0 | D76: =+Shepparton!#REF! -> #REF! | E76: =+Shepparton!#REF! -> #REF!
B77: =+'Fast Key'!A112 -> 0 | C77: =+'Fast Key'!BO112 -> 0 | D77: =+Shepparton!#REF! -> #REF! | E77: =+Shepparton!#REF! -> #REF!
B78: =+'Fast Key'!A115 -> 0 | C78: =+'Fast Key'!BO115 -> 0 | D78: =+Shepparton!#REF! -> #REF! | E78: =+Shepparton!#REF! -> #REF!
B79: =+'Fast Key'!A116 -> 0 | C79: =+'Fast Key'!BO116 -> 0 | D79: =+Shepparton!#REF! -> #REF! | E79: =+Shepparton!#REF! -> #REF!
B80: =+'Fast Key'!A117 -> 0 | C80: =+'Fast Key'!BO117 -> 0 | D80: =+Shepparton!#REF! -> #REF! | E80: =+Shepparton!#REF! -> #REF!
B81: =+'Fast Key'!A118 -> 0 | C81: =+'Fast Key'!BO118 -> 0 | D81: =+Shepparton!#REF! -> #REF! | E81: =+Shepparton!#REF! -> #REF!
B82: =+'Fast Key'!A119 -> 0 | C82: =+'Fast Key'!BO119 -> 0 | D82: =+Shepparton!#REF! -> #REF! | E82: =+Shepparton!#REF! -> #REF!
B83: =+'Fast Key'!A120 -> 0 | C83: =+'Fast Key'!BO120 -> 0 | D83: =+Shepparton!#REF! -> #REF! | E83: =+Shepparton!#REF! -> #REF!
B84: =+'Fast Key'!A121 -> 0 | C84: =+'Fast Key'!BO121 -> 0 | D84: =+Shepparton!#REF! -> #REF! | E84: =+Shepparton!#REF! -> #REF!
B85: =+'Fast Key'!A122 -> 0 | C85: =+'Fast Key'!BO122 -> 0 | D85: =+Shepparton!#REF! -> #REF! | E85: =+Shepparton!#REF! -> #REF!
B86: =+'Fast Key'!A123 -> 0 | C86: =+'Fast Key'!BO123 -> 0 | D86: =+Shepparton!#REF! -> #REF! | E86: =+Shepparton!#REF! -> #REF!
B87: =+'Fast Key'!A124 -> 0 | C87: =+'Fast Key'!BO124 -> 0 | D87: =+Shepparton!#REF! -> #REF! | E87: =+Shepparton!#REF! -> #REF!
B88: =+'Fast Key'!A125 -> 0 | C88: =+'Fast Key'!BO125 -> 0 | D88: =+Shepparton!#REF! -> #REF! | E88: =+Shepparton!#REF! -> #REF!
B89: =+'Fast Key'!A126 -> 0 | C89: =+'Fast Key'!BO126 -> 0 | D89: =+Shepparton!#REF! -> #REF! | E89: =+Shepparton!#REF! -> #REF!
... B93: =+'Fast Key'!A130 -> 0 | C93: =+'Fast Key'!BO130 -> 0 | D93: =+Shepparton!#REF! -> #REF! | E93: =+Shepparton!#REF! -> #REF!
B94: =+'Fast Key'!A134 -> 0 | C94: =+'Fast Key'!BO134 -> 0 | D94: =+Shepparton!#REF! -> #REF! | E94: =+Shepparton!#REF! -> #REF!
B95: =+'Fast Key'!A135 -> 0 | C95: =+'Fast Key'!BO135 -> 0 | D95: =+Shepparton!#REF! -> #REF! | E95: =+Shepparton!#REF! -> #REF!
B96: =+'Fast Key'!A136 -> 0 | C96: =+'Fast Key'!BO136 -> 0 | D96: =+Shepparton!#REF! -> #REF! | E96: =+Shepparton!#REF! -> #REF!
B97: =+'Fast Key'!A137 -> 0 | C97: =+'Fast Key'!BO137 -> 0 | D97: =+Shepparton!#REF! -> #REF! | E97: =+Shepparton!#REF! -> #REF!
B99: Rate per sqm for the custom plan | D99: 1600 | G99: Tiles | H99: 6105 | I99: Carpets | J99: 4160 | L99: Enter the figures manually
C101: Unit | D101: Base | E101: Custom | G101: =+(D102+D103+D104+D105)*D99+H99+J99 -> 10265
A102: QGEN000_0040_DWELLING | B102: Dwelling area | C102: M2 | F102: =+E102-D102 -> 0 | G102: =+IF(F102>0,(F102*#REF!),0) -> 0
A103: QGEN000_0060_GARAGE | B103: Garage area | C103: M2 | F103: =+E103-D103 -> 0 | G103: =+IF(F103>0,(F103*#REF!),0) -> 0
A104: QGEN000_0070_PORCH | B104: Porch area | C104: M2 | F104: =+E104-D104 -> 0 | G104: =+IF(F104>0,(F104*#REF!),0) -> 0
A105: QGEN000_0080_OUTDOOR_LIVING | B105: Outdoor living area | C105: M2 | F105: =+E105-D105 -> 0 | G105: =+IF(F105>0,(F105*#REF!),0) -> 0
B106: Porch concrete footing | C106: LM | F106: =+E106-D106 -> 0 | G106: =+IF(F106>0,(F106*(#REF!+#REF!)),0) -> 0
B107: Outdoor living footing | C107: LM | F107: =+E107-D107 -> 0 | G107: =+IF(F107>0,(F107*(#REF!+#REF!)),0) -> 0
A108: QGEN340_0510_BRICK_PIER_QUANTITY | B108: Brick pier | C108: Each | F108: =+E108-D108 -> 0 | G108: =+IF(F108>0,(F108*#REF!),0) -> 0
B109: 90X90 Steel column | C109: Each | F109: =+E109-D109 -> 0 | G109: =+IF(F109>0,(F109*#REF!),0) -> 0
A111: QGEN385_0030_EAVE_TYPE_450_BRICKWORK | B111: Eaves | C111: LM | F111: =+E111-D111 -> 0 | G111: =+IF(F111>0,(F111*#REF!),0) -> 0
A112: QGEN200_1030_HIP | B112: Hip length | C112: LM | F112: =+E112-D112 -> 0 | G112: =+IF(F112>0,(F112*#REF!),0) -> 0
A113: QGEN200_1040_VALLEY_LENGTH | B113: Valley length | C113: LM | F113: =+E113-D113 -> 0 | G113: =+IF(F113>0,(F113*#REF!),0) -> 0
A114: QGEN200_1050_RIDGE | B114: Ridge length | C114: LM | F114: =+E114-D114 -> 0 | G114: =+IF(F114>0,(F114*#REF!),0) -> 0
A116: QGEN205_0210_EXT_PERIMETER_WALL_BV | B116: Perimeter walls | C116: LM | F116: =+E116-D116 -> 0 | G116: =+IF(F116>0,(F116*#REF!),0) -> 0
A117: QGEN205_0250_INT_WALL | B117: Internal walls | C117: LM | F117: =+E117-D117 -> 0 | G117: =+IF(F117>0,(F117*#REF!),0) -> 0
A118: QGEN500_1050_BULKHEAD_LENGTH | B118: Plaster bulkheads | C118: LM | F118: =+E118-D118 -> 0 | G118: =+IF(F118>0,(F118*#REF!),0) -> 0
A120: QGEN520_0030_KITCHEN_CABINET_LENGTH | B120: Kitchen wall bench | C120: LM | F120: =+E120-D120 -> 0 | G120: =+IF(F120>0,(F120*#REF!*10),(F120*#REF!*10*0.8)) -> #REF!
A121: QGEN520_0070_KITCHEN_OH_LENGTH | B121: Kitchen overhead cupboards | C121: LM | F121: =+E121-D121 -> 0 | G121: =+IF(F121>0,(F121*#REF!*10),(F121*#REF!*10*0.8)) -> #REF!
A122: QGEN520_0110_ISLAND_BENCH_WITH_OVERHANG | B122: Kitchen island bench | C122: LM | F122: =+E122-D122 -> 0 | G122: =+IF(F122>0,(F122*#REF!*10),(F122*#REF!*10*0.8)) -> #REF!
A124: QGEN520_0230_VANITY_GF_ENSUITE_WIDTH | B124: Ensuite vanity benches | C124: LM | F124: =+E124-D124 -> 0 | G124: =IF(F124>0,(F124*#REF!*10),((F124*#REF!*10*0.8))) -> #REF!
A125: QGEN520_0250_VANITY_GF_ENSUITE_BASIN | B125: Ensuite vanity basins | C125: Each | F125: =+E125-D125 -> 0 | G125: =+IF(F125>0,(F125*#REF!),((F125*#REF!*0.8))) -> #REF!
A126: QGEN520_0330_VANITY_GF_BATHROOM_WIDTH | B126: Bath vanity benches | C126: LM | F126: =+E126-D126 -> 0 | G126: =IF(F126>0,(F126*#REF!*10),((F126*#REF!*10*0.8))) -> #REF!
A127: QGEN520_0350_VANITY_GF_BATHROOM_BASIN | B127: Bath vanity basins | C127: Each | F127: =+E127-D127 -> 0 | G127: =+IF(F127>0,(F127*#REF!),((F127*#REF!*0.8))) -> #REF!
...

Sheet Facade Pricing
A2: Facade pricing July 2024
A5: Disclaimer: Façade costings only include porches, windows, cladding, gables etc. Does not include features like lights, upgraded front or garage door, feature or upgraded bricks etc.
A12: FAÇADE 1A (TRADITIONAL)
A13: Awning windows to façade | B13: =ROUNDUP((2*#REF!)-#REF!,10) -> #REF!
B14: =SUM(B13:B13) -> #REF!
A16: FAÇADE 1B (TEMPO)
A17: Awning windows to façade | B17: =+B13 -> #REF!
A18: Stria board gable to porch and bed 1 | B18: 5500
B19: =SUM(B17:B18) -> #REF!
A21: FAÇADE 1Ca (TEMPO A)
A22: Full length awning windows to façade | B22: =+ROUNDUP((#REF!*2)-#REF!,10) -> #REF!
A23: Stria board gables | B23: =+B18 -> 5500
A24: Perimeter moulding around gable panels with one vent | B24: 1300
A25: Linea board to bed 1 | B25: =+CEILING(((#REF!*30)+(#REF!*2)+(#REF!*2)+(#REF!*2)),10) -> #REF!
B26: =SUM(B22:B25) -> #REF!
A28: FAÇADE 1Cb (TEMPO B)
A29: Overlooking windows to façade | B29: =+#REF!-#REF! -> #REF!
A30: Render finish to brick piers | B30: =+#REF! -> #REF!
A31: Stria board gable to porch and bed 1 | B31: =+B23 -> 5500
A32: Perimeter moulding around gable panels with one vent | B32: =+B24 -> 1300
A33: Add engaged brick pier | B33: 520
B34: =SUM(B29:B33) -> #REF!
A37: =+A2 -> Facade pricing July 2024
A40: FAÇADE 2A (CLASSIC)
A41: Awning windows to façade | B41: =+ROUNDUP((#REF!-#REF!)+#REF!,10) -> #REF!
A42: Extend porch | B42: =+ROUNDUP(((#REF!*2.5)+2*#REF!+(2+1.5)*#REF!),10)+200 -> #REF!
B43: =SUM(B41:B42) -> #REF!
A45: FAÇADE 2B (RESORT)
A46: Full length awning windows to façade | B46: =+ROUNDUP((#REF!+#REF!-#REF!),10) -> #REF!
A47: Raised portico with stria infill or Newtechwood cladding | B47: 6500
A48: Extend porch | B48: =+B42 -> #REF!
B49: =SUM(B46:B48) -> #REF!
A51: FAÇADE 2C (MODERN)
A52: Overlooking windows to façade | B52: =+B41 -> #REF!
A53: 590 Brick pier with capped flashing | B53: 1110
A54: RHS pier to be engaged | B54: 530
A55: Raised portico with stria infill or Newtechwood cladding | B55: 6100
A56: Extend porch | B56: =+B48 -> #REF!
A57: Linea board to bed 1 | B57: =+ROUNDUP((#REF!*30+#REF!+#REF!+#REF!+#REF!),10) -> #REF!
B58: =SUM(B52:B57) -> #REF!
A60: =+A37 -> Facade pricing July 2024
A63: FAÇADE 3A (CLASSIC)
A64: Awning windows to façade | B64: =+B13 -> #REF!
A65: Extend porch | B65: =+B48 -> #REF!
A66: Eaves to porch and bed 1 | B66: Inc
B67: =SUM(B64:B66) -> #REF!
A69: FAÇADE 3B (HAMPTONS B)
A70: Full length awning windows to façade | B70: =+B64 -> #REF!
A71: 115 Square painted timber posts | B71: =+ROUNDUP(#REF!*6-#REF!-#REF!,10) -> #REF!
A72: Exposed painted timber beam unwrapped | B72: 1040
A73: Stria board Dutch gable | B73: 3700
A74: Linea board to façade | B74: =+B25 -> #REF!
A75: Extend porch | B75: =+B65 -> #REF!
B76: =SUM(B70:B75) -> #REF!
A78: FAÇADE 3C (HAMPTONS A)
A79: Overlooking windows to façade | B79: =+B70 -> #REF!
A80: 3/4 470 Brick piers with brick capping | B80: 610
A81: 180 Square posts | B81: =+B71 -> #REF!
A82: Exposed painted timber beam unwrapped | B82: =+B72 -> 1040
A83: Linea board to façade | B83: =+B74 -> #REF!
A84: Stria board Dutch gable with perimeter moulding and vent | B84: =+B73+B32 -> 5000
A85: Render to brick piers and bed 1 | B85: =+#REF! -> #REF!
B86: =SUM(B79:B85) -> #REF!
A89: =+A60 -> Facade pricing July 2024
A92: FAÇADE 4A (CLASSIC 4A)
A93: Sliding windows throughout | B93: Inc
A94: Eaves to porch and lounge | B94: Inc
B95: =SUM(B94:B94) -> 0
A97: FAÇADE 4B (RESORT 4B)
A98: Awning windows to façade | B98: 1650
A99: Raised prtico with stria bulkhead or Newtechwood cladding | B99: 6500
B100: =SUM(B98:B99) -> 8150
A102: FAÇADE 4Ca (MODERN)
A103: Overlooking windows to façade | B103: 610
A104: 590x470 Brick piers | B104: =470*2 -> 940
A105: Tile finish to RHS brick pier | B105: 1950
A106: Raised prtico with stria bulkhead or Newtechwood cladding | B106: =+B47 -> 6500
A107: Linea board to lounge | B107: =+(#REF!*30)+#REF!+#REF!*2+#REF! -> #REF!
A108: Render finish to lounge brick base | B108: 3300
B109: =SUM(B103:B108) -> #REF!
A111: FAÇADE 4Cb (GRANGE)
A112: Full length awning windows to façade | B112: 1650
A113: Raised masterwall bulkhead with render | B113: 9500
A114: Newington entrance door | B114: 175
A115: Linea board to lounge | B115: =+B107 -> #REF!
B116: =SUM(B112:B115) -> #REF!
A118: =+A89 -> Facade pricing July 2024
A121: FAÇADE 5A (CLASSIC)
A122: Awning windows to façade | B122: 1115
B123: =SUM(B122:B122) -> 1115
A125: FAÇADE 5B (RESORT)
A126: Full length awning windows to façade | B126: 2490
A127: 470 brick piers X3 with capped flashing | B127: 1470
A128: Raised porch with stria or newtechwod cladding infill | B128: 8200
A129: Extend porch | B129: 4250
B130: =SUM(B126:B129) -> 16410
A132: FACADE 5C (ASCENT)
A133: Full length awning windows to façade | B133: 2490
A134: Piers - sizes vary | B134: 1980
A135: Linea boards to ensuite | B135: =+B115 -> #REF!
...

Sheet 1.HOUSE PRICE
A2: Please pick in the following order. Then go to sheet 2.TRAVEL
A3: 1.Price list
A4: 2.House plan
A7: 2.House design | B7: Base price | C7: 1.Price list | D7: Tiles | E7: Carpets | F7: 7 Star Allowance
A8: =IF('Fast Key'!A13=0," ",'Fast Key'!A13) -> Byron 19 | B8: =+Shepparton!B4 -> 270995 | C8: Shepparton | D8: =+Shepparton!D4 -> 5900 | E8: =+Shepparton!E4 -> 3010 | F8: 5000
A9: =IF('Fast Key'!A14=0," ",'Fast Key'!A14) -> Byron 22A | B9: =+Shepparton!B5 -> 289755 | C9: Shepparton | D9: =+Shepparton!D5 -> 7005 | E9: =+Shepparton!E5 -> 3715 | F9: 5000
A10: =IF('Fast Key'!A15=0," ",'Fast Key'!A15) -> Byron 22B | B10: =+Shepparton!B6 -> 294955 | C10: Shepparton | D10: =+Shepparton!D6 -> 7410 | E10: =+Shepparton!E6 -> 3680 | F10: 5000
A11: =IF('Fast Key'!A16=0," ",'Fast Key'!A16) -> Ashwood 17 | B11: =+Shepparton!B7 -> 253005 | C11: Shepparton | D11: =+Shepparton!D7 -> 5470 | E11: =+Shepparton!E7 -> 2295 | F11: 5000
A12: =IF('Fast Key'!A17=0," ",'Fast Key'!A17) -> Ashwood 20 | B12: =+Shepparton!B8 -> 276490 | C12: Shepparton | D12: =+Shepparton!D8 -> 5865 | E12: =+Shepparton!E8 -> 3715 | F12: 5000
A13: =IF('Fast Key'!A18=0," ",'Fast Key'!A18) -> Malvern 20 | B13: =+Shepparton!B9 -> 282770 | C13: Shepparton | D13: =+Shepparton!D9 -> 5590 | E13: =+Shepparton!E9 -> 3875 | F13: 5000
A14: =IF('Fast Key'!A19=0," ",'Fast Key'!A19) -> Malvern 23 | B14: =+Shepparton!B10 -> 304150 | C14: Shepparton | D14: =+Shepparton!D10 -> 7320 | E14: =+Shepparton!E10 -> 4435 | F14: 5000
A15: =IF('Fast Key'!A20=0," ",'Fast Key'!A20) -> Malvern 25 | B15: =+Shepparton!B11 -> 332790 | C15: Shepparton | D15: =+Shepparton!D11 -> 7185 | E15: =+Shepparton!E11 -> 5395 | F15: 5000
A16: =IF('Fast Key'!A21=0," ",'Fast Key'!A21) | B16: =+Shepparton!B12 -> 0 | C16: Shepparton | D16: =+Shepparton!D12 -> 0 | E16: =+Shepparton!E12 -> 0
A17: =IF('Fast Key'!A22=0," ",'Fast Key'!A22) | B17: =+Shepparton!B13 -> 0 | C17: Shepparton | D17: =+Shepparton!D13 -> 0 | E17: =+Shepparton!E13 -> 0
A18: =IF('Fast Key'!A23=0," ",'Fast Key'!A23) | B18: =+Shepparton!B14 -> 0 | C18: Shepparton | D18: =+Shepparton!D14 -> 0 | E18: =+Shepparton!E14 -> 0
A19: =IF('Fast Key'!A24=0," ",'Fast Key'!A24) | B19: =+Shepparton!B15 -> 0 | C19: Shepparton | D19: =+Shepparton!D15 -> 0 | E19: =+Shepparton!E15 -> 0
A20: =IF('Fast Key'!A25=0," ",'Fast Key'!A25) | B20: =+Shepparton!B16 -> 0 | C20: Shepparton | D20: =+Shepparton!D16 -> 0 | E20: =+Shepparton!E16 -> 0
B23: =SUBTOTAL(9,B8:B20) -> 2304910
A24: =_xlfn.XLOOKUP(B23,B8:B20,A8:A20," ",0,1) | B24: =IF(A24=" ",0,SUBTOTAL(9,B8:B20)) -> 0 | D24: =IF($A$24=" ",0,+SUBTOTAL(9,D8:D20)) -> 0 | E24: =IF(A24=" ",0,+SUBTOTAL(9,E8:E20)) -> 0 | F24: =IF(A24=" ",0,+SUBTOTAL(9,F8:F20)) -> 0

Sheet 2.TRAVEL
A1: Please pick Travel area
A2: TRAVEL AREA | B2: Area | D2: Date | G2: Paving Rates | N2: Plain | O2: ='[1]Yard Items'!$D$9 -> 140
D3: 45497 | H3: Natural | I3: 50m2 paving | J3: Exp Aggregate
A4: BARHAM | B4: 58650 | G4: =+A4 -> BARHAM | H4: =+O2+15 -> 155 | I4: =+H4*50 -> 7750 | J4: =+H4+50 -> 205
A5: BAROOGA | B5: 22390 | G5: =+A5 -> BAROOGA | H5: =+O2 -> 140 | I5: =+H5*50 -> 7000 | J5: =+H5+50 -> 190
A6: DENILIQUIN | B6: 57490 | G6: =+A6 -> DENILIQUIN | H6: =+O2+15 -> 155 | I6: =+H6*50 -> 7750 | J6: =+H6+50+40 -> 245
A7: FINLEY | B7: 40780 | G7: =+A7 -> FINLEY | H7: =+O2+15 -> 155 | I7: =+H7*50 -> 7750 | J7: =+H7+50 -> 205
A8: MATHOURA | B8: 51270 | G8: =+A8 -> MATHOURA | H8: =+O2+15 -> 155 | I8: =+H8*50 -> 7750 | J8: =+H8+50+40 -> 245
A9: MOAMA | B9: 21960 | G9: =+A9 -> MOAMA | H9: 140 | I9: =+H9*50 -> 7000 | J9: =+H9+50 -> 190
A10: MULWALA | B10: 23900 | G10: =+A10 -> MULWALA | H10: =+O2+5 -> 145 | I10: =+H10*50 -> 7250 | J10: =+H10+50 -> 195
A11: TOCUMWAL | B11: 22390 | G11: =+A11 -> TOCUMWAL | H11: =+O2+15 -> 155 | I11: =+H11*50 -> 7750 | J11: =+H11+50 -> 205
A12: NOTE: All travel rates are applicable for jobs up to 20kms from the specified towns
A13: POA for any job outside 20km from town centre location as per google maps
B15: =+SUBTOTAL(9,(B4:B11)) -> 298830
A16: =_xlfn.XLOOKUP(B15,B4:B11,A4:A11," ",0,1) | B16: =IF(A16=" ",0,+SUBTOTAL(9,(B4:B11))) -> 0 | H16: =IF(A16=" ",0,+SUBTOTAL(9,(H4:H11))) -> 0 | I16: =IF(A16=" ",0,+SUBTOTAL(9,(I4:I11))) -> 0 | J16: =IF(A16=" ",0,+SUBTOTAL(9,(J4:J11))) -> 0

Sheet 3.SALES ESTIMATE
B4: ABN: 50 105 889 745
B5: 7961 Goulburn Valley Hwy | E5: Telephone 5823 1859
B6: P O BOX 922 | E6: Display Home 5832 6082
B7: SHEPPARTON VIC 3632 | E7: DB-U 9856
B9: Dear | C9: =+C47 -> 0
B11: RE: PRELIMINARY PRICING
B13: Thank you for your interest in building a new home with Cavalier Homes Goulburn Valley, we greatly
B14: appreciate the opportunity to work with you designing and building your new home.
B16: Please find attached the preliminary pricing to build a house on your land at
B17: =+C51 -> 0
B19: This preliminary pricing is provided as a guide and is subject to review after 60 days.
B21: If you are pleased with the preliminary price, we can then provide a firm price once you have paid an
B22: initial preliminary service fee of $2,000 - (this will secure the price as per the terms and conditions
B23: of the Cavalier Homes Goulburn Valley Ground Work document which we will discuss further should
B24: you wish to proceed to the next stage).
B26: Once the initial preliminary service fee is received, we will arrange to have working drawings drafted
B27: which will show you fully detailed plan of the interior and exterior of your home.
B28: We will also engage an independent, qualified engineer to provide a slab design based on your home
B29: design and the results of the soil test inspection carried out on your block.
B31: As discussed, we will provide you with a final fixed price once the following are completed:
B32: The colour selections
B33: Working drawings
... B54: PRE- CONSTRUCTION
B55: Soil test and site inspection of your block | D55: Included
B56: Independent qualified engineer designed slab | D56: Included
B57: Rescode investigation | D57: Included
B58: Building permit and associated fees (does not include planning permit) | D58: Included
B59: Builder's insurances | D59: Included
B60: Independent 7 star energy rating and whole of home assessment | D60: Included
B61: SERVICE CONNECTIONS
B62: Sewer run and connection fees to 700m2 block | D62: Included
B63: Water run and connection fees to 6m front setback | D63: Included
B64: Stormwater connection to 6m front setback | D64: Included
B65: Electricity run to 6m front setback (does not include connection fee) | D65: Included
B66: Gas service is to be supplied by the retailer (if applicable)
B67: FOUNDATIONS
B68: Site fall up to 300mm | D68: Included
B69: MD class concrete slab (floor height at least 250mm - there is no allowance for piers) | D69: Included
B70: Concrete pump | D70: Included
B71: TERMITE PROTECTION
B72: Termite resistant treated timber to all structural framing | D72: Included
B73: ROOFING
B74: Colorbond iron roof with sarking | D74: Included
B75: Colorbond slotted gutter, fascia and downpipes (downpipes 100mm x 50mm) | D75: Included
B76: 22.5 degree roof pitch | D76: Included
B77: 100mm PVC stormwater | D77: Included
B78: EXTERNAL FINISH
B79: Standard façade with 450mm eaves to front elevation as per brochure plans | D79: Included
B80: Builder's range of Austral bricks with natural mortar & raked joints | D80: Included
B81: Bricks over external swing and sliding doors (to openings up to 3.6m wide), windows and garage doors | D81: Included
B82: ENERGY EFFICIENT FEATURES
B83: R6.0 Insulation batts to ceiling (excludes garage ceiling) | D83: Included
B84: R2.5 Insulation batts plus sisalation paper to external walls (excludes garage external walls) | D84: Included
B85: EXTERNAL DOORS
B86: Front door - Hume Vaucluse solid core door with Lockwood Symmetry entry set | D86: Included
B87: External door jambs with perimeter draft seal (Glass sidelights are plan specific) | D87: Included
B88: Flydoors to glass sliding doors (except garage) | D88: Included
B89: WINDOWS
B90: Aluminium sliding windows with key locks | D90: Included
B91: Flyscreens to all opening windows (except garage) | D91: Included
B92: Obscure or clear glass to bathroom, ensuite & WC windows | D92: Included
B93: GARAGE
B94: External swing door | D94: Included
B95: Plaster lined walls & ceiling | D95: Included
B96: Sectional overhead garage door with wall mounted remote control and 2 transmitters | D96: Included
B97: Concrete slab floor | D97: Included
B98: INTERNAL FINISH
B99: 2400mm ceiling height | D99: Included
B100: Plaster ceilings are fixed to a metal batten system, suspended on clips and is laser levelled to the entire home | D100: Included
B101: 75mm Cove cornice | D101: Included
B102: 67mm x 18mm Bevelled edge architraves | D102: Included
B103: 67mm x 18mm Bevelled edge skirtings | D103: Included
B104: INTERNAL DOORS
B105: Internal doors - 2040mm high flush panel doors | D105: Included
B106: Whitco door furniture to hinged doors | D106: Included
B107: Privacy locks to bathroom, ensuite and WC hinged doors | D107: Included
B108: Door stops to all hinged doors | D108: Included
B109: KITCHEN
B110: 60cm stainless steel multifunction electric underbench oven | D110: Included
B111: 60cm stainless steel cooktop | D111: Included
B112: 60cm stainless steel canopy rangehood | D112: Included
B113: Joinery made base cabinet with laminate benchtop | D113: Included
B114: Soft close doors | D114: Included
B115: 1 & 3/4 bowl stainless steel sink with sink mixer | D115: Included
B116: Bank of four drawers with cutlery insert to top drawer | D116: Included
B117: Four white melamine shelves to pantry | D117: Included
B118: ENSUITE/BATHROOM/WC
B119: Joinery made cabinet with laminate benchtop | D119: Included
B120: Frameless mirror 900mm high x width of vanity | D120: Included
B121: Acrylic bath in white to bathroom | D121: Included
B122: Vanity basin in white | D122: Included
B123: Mixer tapware in chrome | D123: Included
B124: Semi framed pivot door shower screen in polished silver with clear glass | D124: Included
B125: Tiled shower base | D125: Included
B126: Goulburn glass shower shelf | D126: Included
B127: Double towel rail & toilet roll holder in chrome | D127: Included
B128: Back to wall toilet suites in white with soft close seat | D128: Included
B129: LAUNDRY
B130: Utility tub & cabinet in white with stainless steel bowl | D130: Included
B131: Sink mixer & 1/4 turn washing machine stops | D131: Included
...

Sheet Inglewood 42 Display
B4: ABN: 50 105 889 745
B5: 7961 Goulburn Valley Hwy | E5: Telephone 5823 1859
B6: P O BOX 922 | E6: Display Home 5832 6082
B7: SHEPPARTON VIC 3632 | E7: DB-U 9856
B9: Dear | C9: =+C48 -> 0
B11: RE: PRELIMINARY PRICING
B13: Thank you for your interest in building a new home with Cavalier Homes Goulburn Valley, we greatly
B14: appreciate the opportunity to work with you designing and building your new home.
B16: Please find attached the preliminary pricing to build a house on your land at
B17: =+C52 -> 0
B19: This preliminary pricing is provided as a guide and is subject to review after 30 days or before this
B20: time if a new price list is released in the interim.
B22: If you are pleased with the preliminary price, we can then provide a firm price once you have paid an
B23: initial preliminary service fee of $2,000 - (this will secure the price as per the terms and conditions
B24: of the Cavalier Homes Goulburn Valley Ground Work document which we will discuss further should
B25: you wish to proceed to the next stage).
B27: Once the initial preliminary service fee is received, we will arrange to have working drawings drafted
B28: which will show you fully detailed plan of the interior and exterior of your home.
B29: We will also engage an independent, qualified engineer to provide a slab design based on your home
B30: design and the results of the soil test inspection carried out on your block.
B32: As discussed, we will provide you with a final fixed price once the following are completed:
B33: The colour selections
... B55: PRE- CONSTRUCTION
B56: Soil test and site inspection of your block | D56: Included
B57: Independent qualified engineer designed slab | D57: Included
B58: Rescode investigation | D58: Included
B59: Building permit and associated fees (does not include planning permit) | D59: Included
B60: Development application for NSW jobs | D60: Included
B61: Builder's insurances | D61: Included
B62: Independent 6 star energy rating | D62: Included
B63: SERVICE CONNECTIONS
B64: Sewer run and connection fees to 700m2 block | D64: Included
B65: Water run and connection fees to 6m front setback | D65: Included
B66: Stormwater connection to 6m front setback | D66: Included
B67: Electricity run to 6m front setback (does not include connection fee) | D67: Included
B68: Gas service is to be supplied by the retailer
B69: FOUNDATIONS
B70: Site fall up to 200mm | D70: Included
B71: MD class concrete slab (floor height at least 250mm - there is no allowance for piers) | D71: Included
B72: Concrete pump | D72: Included
B73: TERMITE PROTECTION
B74: Termite resistant treated timber to all structural framing | D74: Included
B75: ROOFING
B76: Colorbond iron roof with sarking | D76: Included
B77: Colorbond slotted gutter, fascia and downpipes (downpipes 100mm x 50mm) | D77: Included
B78: 22.5 degree roof pitch | D78: Included
B79: FACADE
B80: Standard façade with 450mm eaves to front elevation as per brochure plans | D80: Included
B81: CEILING HEIGHT
B82: 2400mm ceiling height | D82: Included
B83: Plaster ceilings are fixed to a metal batten system, suspended on clips and is laser levelled to the entire home | D83: Included
B84: EXTERNAL FINISH
B85: Lifestyle range of PGH bricks with natural mortar | D85: Included
B86: Bricks over external swing and sliding doors (to openings up to 3.6m wide), windows and garage doors | D86: Included
B87: Outdoor living ceiling to be lined with plaster sheeting (brick piers or duragal steel columns are plan specific) | D87: Included
B88: ENERGY EFFICIENT FEATURES
B89: R3.5 Insulation batts to ceiling (excludes garage ceiling) | D89: Included
B90: R2.0 Insulation batts plus sisalation paper to external walls (excludes garage external walls) | D90: Included
B91: EXTERNAL DOORS
B92: Front door - Hume Newington solid core door with Lockwood Symmetry entry set | D92: Included
B93: External door jambs with perimeter draft seal (Glass sidelights are plan specific) | D93: Included
B94: Flydoors to glass sliding doors (except garage) | D94: Included
B95: WINDOWS
B96: Aluminium sliding windows with key locks | D96: Included
B97: Flyscreens to all opening windows (except garage) | D97: Included
B98: Obscure or clear glass to bathroom, ensuite & WC windows | D98: Included
B99: GARAGE
B100: Choice of external swing door or 2118 glass sliding door | D100: Included
B101: Plaster lined walls & ceiling | D101: Included
B102: Sectional overhead garage door with wall mounted remote control and 2 transmitters | D102: Included
B103: Concrete slab floor | D103: Included
B104: INTERNAL FINISH
B105: 75mm Cove cornice | D105: Included
B106: 67mm x 18mm Bevelled edge architraves | D106: Included
B107: 67mm x 18mm Bevelled edge skirtings | D107: Included
B108: INTERNAL DOORS
B109: Internal doors - 2040mm high flush panel doors | D109: Included
B110: Lockwood velocity door furniture to hinged doors | D110: Included
B111: Privacy locks to bathroom, ensuite and WC hinged doors | D111: Included
B112: Door stops to all hinged doors | D112: Included
B113: KITCHEN
B114: Westinghouse 60cm stainless steel multifunction electric underbench oven | D114: Included
B115: Westinghouse 60cm stainless steel gas cooktop | D115: Included
B116: Westinghouse 60cm stainless steel slideout rangehood | D116: Included
B117: Westinghouse 60cm freestanding dishwasher | D117: Included
B118: Joinery made base cabinet with laminate benchtop and overhead cupboards above cooktop section | D118: Included
B119: Soft close drawers & cupboard doors | D119: Included
B120: Underbench microwave cavity with one pot drawer | D120: Included
B121: 1 & 3/4 bowl stainless steel sink with sink mixer | D121: Included
B122: Bank of four drawers with cutlery insert to top drawer | D122: Included
B123: Four white melamine shelves to pantry | D123: Included
B124: ENSUITE/BATHROOM/WC
B125: Joinery made cabinet with laminate benchtop | D125: Included
B126: Frameless mirror 900mm high x width of vanity | D126: Included
B127: Acrylic bath in white to bathroom | D127: Included
B128: Choice of vanity basins in white | D128: Included
B129: Choice of mixer tapware in chrome | D129: Included
B130: Semi frameless pivot door shower screen in polished silver with clear glass | D130: Included
B131: Tiled shower base | D131: Included
B132: Goulburn glass shower shelf | D132: Included
...

Sheet ASHWOOD 17
C3: Floor Plan Extensions
C4: ='[2]UPGRADES - ASHWOOD RANGE'!$B$6 -> Extend garage by 500mm | D4: ='[2]UPGRADES - ASHWOOD RANGE'!$K$6 -> 2500
C5: ='[2]UPGRADES - ASHWOOD RANGE'!$B$7 -> Extend garage by 1000mm | D5: ='[2]UPGRADES - ASHWOOD RANGE'!$K$7 -> 5000
C6: ='[2]UPGRADES - ASHWOOD RANGE'!$B$8 -> Outdoor Living - addition 1 | D6: ='[2]UPGRADES - ASHWOOD RANGE'!$K$8 -> 4350
C7: ='[2]UPGRADES - ASHWOOD RANGE'!$B$9 -> Outdoor Living - brick pier in lieu of steel post | D7: ='[2]UPGRADES - ASHWOOD RANGE'!$K$9 -> 400
C8: ='[2]UPGRADES - ASHWOOD RANGE'!$B10 -> Additional concrete - outdoor living | D8: ='[2]UPGRADES - ASHWOOD RANGE'!$K$10 -> 1260
C9: ='[2]UPGRADES - ASHWOOD RANGE'!$B$11 -> Outdoor Living - addition 2 | D9: ='[2]UPGRADES - ASHWOOD RANGE'!$K$11 -> 7100
C10: ='[2]UPGRADES - ASHWOOD RANGE'!$B$12 -> Outdoor Living - brick pier in lieu of steel post | D10: ='[2]UPGRADES - ASHWOOD RANGE'!$K$12 -> 400
C11: ='[2]UPGRADES - ASHWOOD RANGE'!$B$13 -> Additional concrete- Outdoor living | D11: ='[2]UPGRADES - ASHWOOD RANGE'!$K$13 -> 1960
C12: ='[2]UPGRADES - ASHWOOD RANGE'!$B$14 -> Kitchen - Upgrade 1 - The Entertainers Kitchen | D12: ='[2]UPGRADES - ASHWOOD RANGE'!$K$14 -> 980
C13: ='[2]UPGRADES - ASHWOOD RANGE'!$B$15 -> Kitchen - Upgrade 2 - The Modern Chef Kitchen | D13: ='[2]UPGRADES - ASHWOOD RANGE'!$K$15 -> 2850
C14: ='[2]UPGRADES - ASHWOOD RANGE'!$B$16 -> Ensuite - Upgrade 1 - The Signature Ensuite | D14: ='[2]UPGRADES - ASHWOOD RANGE'!$K$16 -> 600
C15: ='[2]UPGRADES - ASHWOOD RANGE'!$B$17 -> Ensuite - Upgrade 2 - The Indulgence Ensuite | D15: ='[2]UPGRADES - ASHWOOD RANGE'!$K$17 -> 2780
C17: Façade
C18: Standard Façade | D18: Included
C19: ='[2]UPGRADES - ASHWOOD RANGE'!$B$19 -> 1 The Retreat Façade | D19: ='[2]UPGRADES - ASHWOOD RANGE'!$K$19 -> 3300
C20: ='[2]UPGRADES - ASHWOOD RANGE'!$B$20 -> 2 The Rise Façade | D20: ='[2]UPGRADES - ASHWOOD RANGE'!$K$20 -> 7300
C21: ='[2]UPGRADES - ASHWOOD RANGE'!$B$21 -> 3 The Escape Façade | D21: ='[2]UPGRADES - ASHWOOD RANGE'!$K$21 -> 8950
C22: ='[2]UPGRADES - ASHWOOD RANGE'!$B$22 -> 4 The Essence Façade | D22: ='[2]UPGRADES - ASHWOOD RANGE'!$K$22 -> 6500
C23: ='[2]UPGRADES - ASHWOOD RANGE'!$B$23 -> 5 The Sanctuary Façade | D23: ='[2]UPGRADES - ASHWOOD RANGE'!$K$23 -> 9050
C24: ='[2]UPGRADES - ASHWOOD RANGE'!$B$24 -> 6. The Summit Façade | D24: ='[2]UPGRADES - ASHWOOD RANGE'!$K$24 -> 8500
C25: ='[2]UPGRADES - ASHWOOD RANGE'!$B$25 -> 7. The Haven Facade | D25: ='[2]UPGRADES - ASHWOOD RANGE'!$K$25 -> 8500
C26: ='[2]UPGRADES - ASHWOOD RANGE'!$B$26 -> 9. The Horizon Façade | D26: ='[2]UPGRADES - ASHWOOD RANGE'!$K$26 -> 10500
C28: Add Ons
C29: Kitchen
C30: ='[2]UPGRADES - ASHWOOD RANGE'!$B29 -> 600mm overhead either side of rangehood | D30: ='[2]UPGRADES - ASHWOOD RANGE'!$K$29 -> 990
C31: ='[2]UPGRADES - ASHWOOD RANGE'!$B30 -> Overhead cupboards with integrated rangehood | D31: ='[2]UPGRADES - ASHWOOD RANGE'!$K$30 -> 2120
C32: ='[2]UPGRADES - ASHWOOD RANGE'!$B31 -> Fridge overhead cupboard | D32: ='[2]UPGRADES - ASHWOOD RANGE'!$K$31 -> 960
C33: 1 Bank of 3 pot drawers | D33: ='[2]UPGRADES - ASHWOOD RANGE'!$K$32 -> 330
C34: 2 Banks of 3 pot drawers | D34: ='[2]UPGRADES - ASHWOOD RANGE'!$K$32*2 -> 660
C35: 3 Banks of 3 pot drawers | D35: ='[2]UPGRADES - ASHWOOD RANGE'!$K$32*3 -> 990
C36: 4 Banks of 3 pot drawers | D36: ='[2]UPGRADES - ASHWOOD RANGE'!$K$32*4 -> 1320
C37: 5 Banks of 3 pot drawers | D37: ='[2]UPGRADES - ASHWOOD RANGE'!$K$32*5 -> 1650
C38: ='[2]UPGRADES - ASHWOOD RANGE'!$B$33 -> Microwave cavity with drawer below | D38: ='[2]UPGRADES - ASHWOOD RANGE'!$K$33 -> 415
C39: ='[2]UPGRADES - ASHWOOD RANGE'!$B$34 -> Twin bin with drawer below | D39: ='[2]UPGRADES - ASHWOOD RANGE'!$K$34 -> 250
C40: ='[2]UPGRADES - ASHWOOD RANGE'!$B$35 -> 1212 No Bottom Reveal Window | D40: ='[2]UPGRADES - ASHWOOD RANGE'!$K$35 -> 390
C42: Ensuite & Bathroom
C43: ='[2]UPGRADES - ASHWOOD RANGE'!$B$37 -> Bank of 3 drawers to vanities | D43: ='[2]UPGRADES - ASHWOOD RANGE'!$K$37 -> 660
C44: 2 drawers to vanity in lieu of doors - (2 Banks) | D44: ='[2]UPGRADES - ASHWOOD RANGE'!$K$38*2 -> 660
C45: 2 drawers to vanity in lieu of doors - (3 Banks) | D45: ='[2]UPGRADES - ASHWOOD RANGE'!$K$38*3 -> 990
C46: Rectangle with rounded edge mirrors - (2 Mirrors) | D46: ='[2]UPGRADES - ASHWOOD RANGE'!$K$39/2*2 -> 280
C47: Rectangle with rounded edge mirrors - (3 Mirrors) | D47: ='[2]UPGRADES - ASHWOOD RANGE'!$K$39/2*3 -> 420
C48: ='[2]UPGRADES - ASHWOOD RANGE'!$B$40 -> Tiled recess shelves | D48: ='[2]UPGRADES - ASHWOOD RANGE'!$K$40 -> 800
C49: ='[2]UPGRADES - ASHWOOD RANGE'!$B$41 -> Extend tiles to 2.1m high on vanity wall | D49: ='[2]UPGRADES - ASHWOOD RANGE'!$K$41 -> 500
C50: ='[2]UPGRADES - ASHWOOD RANGE'!$B$42 -> Extend tiles to 2.1m high on remaining three walls | D50: ='[2]UPGRADES - ASHWOOD RANGE'!$K$42 -> 1800
C52: Laundry
C53: ='[2]UPGRADES - ASHWOOD RANGE'!$B$44 -> 1200mm Laminate benchtop & cupboards | D53: ='[2]UPGRADES - ASHWOOD RANGE'!$K$44 -> 1680
C54: ='[2]UPGRADES - ASHWOOD RANGE'!$B$45 -> Extend laminate benchtop only by 900mm with powerpoint | D54: ='[2]UPGRADES - ASHWOOD RANGE'!$K$45 -> 580
C55: ='[2]UPGRADES - ASHWOOD RANGE'!$B$46 -> 1200mm Overhead cupboards | D55: ='[2]UPGRADES - ASHWOOD RANGE'!$K$46 -> 1040
C56: ='[2]UPGRADES - ASHWOOD RANGE'!$B$47 -> 900mm Overhead cupboards | D56: ='[2]UPGRADES - ASHWOOD RANGE'!$K$47 -> 765
C57: ='[2]UPGRADES - ASHWOOD RANGE'!$B$48 -> Hanging rail under overheads | D57: ='[2]UPGRADES - ASHWOOD RANGE'!$K$48 -> 300
C58: ='[2]UPGRADES - ASHWOOD RANGE'!$B$49 -> Pullout laundry basket with drawer | D58: ='[2]UPGRADES - ASHWOOD RANGE'!$K$49 -> 235
C60: Additional Add Ons
C61: ='[2]UPGRADES - ASHWOOD RANGE'!$B$51 -> Eaves to whole home | D61: ='[2]UPGRADES - ASHWOOD RANGE'!$K$51 -> 3700
C62: ='[2]UPGRADES - ASHWOOD RANGE'!$B$52 -> Add 2100h x 2400w roller door - (2550mm Cielings Required) | D62: ='[2]UPGRADES - ASHWOOD RANGE'!$K$52 -> 1670
C63: ='[2]UPGRADES - ASHWOOD RANGE'!$B$53 -> 2550mm ceiling | D63: ='[2]UPGRADES - ASHWOOD RANGE'!$K$53 -> 3100
C65: Personalised Selections
C66: External Finishes
C67: ='[2]UPGRADES - ASHWOOD RANGE'!$B$56 -> Double glazing to whole home (please note: all windows will be awning) | D67: ='[2]UPGRADES - ASHWOOD RANGE'!$K$56 -> 3200
C68: ='[2]UPGRADES - ASHWOOD RANGE'!$B$57 -> Sliding door in lieu of swing | D68: ='[2]UPGRADES - ASHWOOD RANGE'!$K$57 -> 200
C69: ='[2]UPGRADES - ASHWOOD RANGE'!$B$58 -> Wall mounted clothesline | D69: ='[2]UPGRADES - ASHWOOD RANGE'!$K$58 -> 400
C70: ='[2]UPGRADES - ASHWOOD RANGE'!$B$59 -> Letterbox | D70: ='[2]UPGRADES - ASHWOOD RANGE'!$K$59 -> 350
C71: ='[2]UPGRADES - ASHWOOD RANGE'!$B$60 -> Newington front door | D71: ='[2]UPGRADES - ASHWOOD RANGE'!$K$60 -> 300
C72: ='[2]UPGRADES - ASHWOOD RANGE'!$B$61 -> Nexion front door handle | D72: ='[2]UPGRADES - ASHWOOD RANGE'!$K$61 -> 175
C73: ='[2]UPGRADES - ASHWOOD RANGE'!$B$62 -> Brick Upgrade | D73: ='[2]UPGRADES - ASHWOOD RANGE'!$K$62 -> 720
C75: Internal Finishes
C76: ='[2]UPGRADES - ASHWOOD RANGE'!$B$64 -> Internal door pack - WIR & rear hallway | D76: ='[2]UPGRADES - ASHWOOD RANGE'!$K$64 -> 440
C77: ='[2]UPGRADES - ASHWOOD RANGE'!$B$65 -> 2340mm high internal doors & robe/linen doors - (2550mm Cielings Required) | D77: ='[2]UPGRADES - ASHWOOD RANGE'!$K$65 -> 1100 | F77: can we put proviso only to add if with 2550mm ceiling
C78: ='[2]UPGRADES - ASHWOOD RANGE'!$B$66 -> Single roller blinds | D78: ='[2]UPGRADES - ASHWOOD RANGE'!$K$66 -> 1770
C80: Robes
C81: Vinyl / Mirror sliding robe door Combination to 1 Robe | D81: ='[2]UPGRADES - ASHWOOD RANGE'!$K$68 -> 50
C82: Vinyl / Mirror sliding robe door Combination to 2 Robes | D82: ='[2]UPGRADES - ASHWOOD RANGE'!$K$68*2 -> 100
C83: Vinyl / Mirror sliding robe door Combination to 3 Robes | D83: ='[2]UPGRADES - ASHWOOD RANGE'!$K$68*3 -> 150
C84: Double Mirror sliding robe door Combination to 1 Robe | D84: ='[2]UPGRADES - ASHWOOD RANGE'!$K$68*2 -> 100
C85: Double Mirror sliding robe door Combination to 2 Robe | D85: ='[2]UPGRADES - ASHWOOD RANGE'!$K$68*4 -> 200
C86: Double Mirror sliding robe door Combination to 3 Robe | D86: ='[2]UPGRADES - ASHWOOD RANGE'!$K$68*6 -> 300
C87: 1 Bank of three shelves - (Shirt Stacker) | D87: ='[2]UPGRADES - ASHWOOD RANGE'!$K$69 -> 185
C88: 2 Bank of three shelves - (Shirt Stacker) | D88: ='[2]UPGRADES - ASHWOOD RANGE'!$K$69*2 -> 370
C89: 3 Bank of three shelves - (Shirt Stacker) | D89: ='[2]UPGRADES - ASHWOOD RANGE'!$K$69*3 -> 555
C90: 4 Bank of three shelves - (Shirt Stacker) | D90: ='[2]UPGRADES - ASHWOOD RANGE'!$K$69*4 -> 740
C91: 5 Bank of three shelves - (Shirt Stacker) | D91: ='[2]UPGRADES - ASHWOOD RANGE'!$K$69*5 -> 925
C92: 6 Bank of three shelves - (Shirt Stacker) | D92: ='[2]UPGRADES - ASHWOOD RANGE'!$K$69*6 -> 1110
C93: 1 Bank of two shelves & four drawers | D93: ='[2]UPGRADES - ASHWOOD RANGE'!$K$70 -> 510
C94: 2 Bank of two shelves & four drawers | D94: ='[2]UPGRADES - ASHWOOD RANGE'!$K$70*2 -> 1020
C95: 3 Bank of two shelves & four drawers | D95: ='[2]UPGRADES - ASHWOOD RANGE'!$K$70*3 -> 1530
C96: 4 Bank of two shelves & four drawers | D96: ='[2]UPGRADES - ASHWOOD RANGE'!$K$70*4 -> 2040
C97: 5 Bank of two shelves & four drawers | D97: ='[2]UPGRADES - ASHWOOD RANGE'!$K$70*5 -> 2550
C98: 6 Bank of two shelves & four drawers | D98: ='[2]UPGRADES - ASHWOOD RANGE'!$K$70*6 -> 3060
C100: Kitchen
C101: ='[2]UPGRADES - ASHWOOD RANGE'!$B$72 -> 600mm stainless steel oven & canopy rangehood and electric cooktop | D101: ='[2]UPGRADES - ASHWOOD RANGE'!$K$72 -> 365
C102: ='[2]UPGRADES - ASHWOOD RANGE'!$B$73 -> 900mm black inbuilt oven, cooktop & canopy rangehood | D102: ='[2]UPGRADES - ASHWOOD RANGE'!$K$73 -> 1870
C103: ='[2]UPGRADES - ASHWOOD RANGE'!$B$74 -> 900mm stainless steel inbuilt oven, cooktop & canopy rangehood | D103: ='[2]UPGRADES - ASHWOOD RANGE'!$K$74 -> 1860
C104: ='[2]UPGRADES - ASHWOOD RANGE'!$B$75 -> 900mm black undermount rangehood in lieu of canopy | D104: ='[2]UPGRADES - ASHWOOD RANGE'!$K$75 -> 800
C105: ='[2]UPGRADES - ASHWOOD RANGE'!$B$76 -> 900mm stainless steel undermount rangehood in lieu of canopy | D105: ='[2]UPGRADES - ASHWOOD RANGE'!$K$76 -> 770
C106: ='[2]UPGRADES - ASHWOOD RANGE'!$B$77 -> Stainless steel dishwasher | D106: ='[2]UPGRADES - ASHWOOD RANGE'!$K$77 -> 700
C107: ='[2]UPGRADES - ASHWOOD RANGE'!$B$78 -> Black dishwasher | D107: ='[2]UPGRADES - ASHWOOD RANGE'!$K$78 -> 750
C108: ='[2]UPGRADES - ASHWOOD RANGE'!$B$79 -> Cold water point for fridge | D108: ='[2]UPGRADES - ASHWOOD RANGE'!$K$79 -> 200
C109: Soft close drawers to 1 Bank of Draws | D109: ='[2]UPGRADES - ASHWOOD RANGE'!$K$80 -> 350
C110: Soft close drawers to 2 Bank of Draws | D110: ='[2]UPGRADES - ASHWOOD RANGE'!$K$80*2 -> 700
C111: Soft close drawers to 3 Bank of Draws | D111: ='[2]UPGRADES - ASHWOOD RANGE'!$K$80*3 -> 1050
...

Sheet ASHWOOD 20
C3: Floor Plan Extensions
C4: ='[2]UPGRADES - ASHWOOD RANGE'!$B$6 -> Extend garage by 500mm | D4: ='[2]UPGRADES - ASHWOOD RANGE'!$L$6 -> 2500
C5: ='[2]UPGRADES - ASHWOOD RANGE'!$B$7 -> Extend garage by 1000mm | D5: ='[2]UPGRADES - ASHWOOD RANGE'!$L$7 -> 5000
C6: ='[2]UPGRADES - ASHWOOD RANGE'!$B$8 -> Outdoor Living - addition 1 | D6: ='[2]UPGRADES - ASHWOOD RANGE'!$L$8 -> 4350
C7: ='[2]UPGRADES - ASHWOOD RANGE'!$B$9 -> Outdoor Living - brick pier in lieu of steel post | D7: ='[2]UPGRADES - ASHWOOD RANGE'!$L$9 -> 800
C8: ='[2]UPGRADES - ASHWOOD RANGE'!$B10 -> Additional concrete - outdoor living | D8: ='[2]UPGRADES - ASHWOOD RANGE'!$L$10 -> 1260
C9: ='[2]UPGRADES - ASHWOOD RANGE'!$B$11 -> Outdoor Living - addition 2 | D9: ='[2]UPGRADES - ASHWOOD RANGE'!$L$11 -> 7100
C10: ='[2]UPGRADES - ASHWOOD RANGE'!$B$12 -> Outdoor Living - brick pier in lieu of steel post | D10: ='[2]UPGRADES - ASHWOOD RANGE'!$L$12 -> 800
C11: ='[2]UPGRADES - ASHWOOD RANGE'!$B$13 -> Additional concrete- Outdoor living | D11: ='[2]UPGRADES - ASHWOOD RANGE'!$L$13 -> 1960
C12: ='[2]UPGRADES - ASHWOOD RANGE'!$B$14 -> Kitchen - Upgrade 1 - The Entertainers Kitchen | D12: ='[2]UPGRADES - ASHWOOD RANGE'!$L$14 -> 980
C13: ='[2]UPGRADES - ASHWOOD RANGE'!$B$15 -> Kitchen - Upgrade 2 - The Modern Chef Kitchen | D13: ='[2]UPGRADES - ASHWOOD RANGE'!$L$15 -> 2850
C14: ='[2]UPGRADES - ASHWOOD RANGE'!$B$16 -> Ensuite - Upgrade 1 - The Signature Ensuite | D14: ='[2]UPGRADES - ASHWOOD RANGE'!$L$16 -> 600
C15: ='[2]UPGRADES - ASHWOOD RANGE'!$B$17 -> Ensuite - Upgrade 2 - The Indulgence Ensuite | D15: ='[2]UPGRADES - ASHWOOD RANGE'!$L$17 -> 2780
C17: Façade
C18: Standard Façade | D18: Included
C19: ='[2]UPGRADES - ASHWOOD RANGE'!$B$19 -> 1 The Retreat Façade | D19: ='[2]UPGRADES - ASHWOOD RANGE'!$L$19 -> 3300
C20: ='[2]UPGRADES - ASHWOOD RANGE'!$B$20 -> 2 The Rise Façade | D20: ='[2]UPGRADES - ASHWOOD RANGE'!$L$20 -> 7300
C21: ='[2]UPGRADES - ASHWOOD RANGE'!$B$21 -> 3 The Escape Façade | D21: ='[2]UPGRADES - ASHWOOD RANGE'!$L$21 -> 8950
C22: ='[2]UPGRADES - ASHWOOD RANGE'!$B$22 -> 4 The Essence Façade | D22: ='[2]UPGRADES - ASHWOOD RANGE'!$L$22 -> 6500
C23: ='[2]UPGRADES - ASHWOOD RANGE'!$B$23 -> 5 The Sanctuary Façade | D23: ='[2]UPGRADES - ASHWOOD RANGE'!$L$23 -> 9050
C24: ='[2]UPGRADES - ASHWOOD RANGE'!$B$24 -> 6. The Summit Façade | D24: ='[2]UPGRADES - ASHWOOD RANGE'!$L$24 -> 8500
C25: ='[2]UPGRADES - ASHWOOD RANGE'!$B$25 -> 7. The Haven Facade | D25: ='[2]UPGRADES - ASHWOOD RANGE'!$L$25 -> 8500
C26: ='[2]UPGRADES - ASHWOOD RANGE'!$B$26 -> 9. The Horizon Façade | D26: ='[2]UPGRADES - ASHWOOD RANGE'!$L$26 -> 10500
C28: Add Ons
C29: Kitchen
C30: ='[2]UPGRADES - ASHWOOD RANGE'!$B29 -> 600mm overhead either side of rangehood | D30: ='[2]UPGRADES - ASHWOOD RANGE'!$L$29 -> 990
C31: ='[2]UPGRADES - ASHWOOD RANGE'!$B30 -> Overhead cupboards with integrated rangehood | D31: ='[2]UPGRADES - ASHWOOD RANGE'!$L$30 -> 2120
C32: ='[2]UPGRADES - ASHWOOD RANGE'!$B31 -> Fridge overhead cupboard | D32: ='[2]UPGRADES - ASHWOOD RANGE'!$L$31 -> 960
C33: 1 Bank of 3 pot drawers | D33: ='[2]UPGRADES - ASHWOOD RANGE'!$L$32 -> 330
C34: 2 Banks of 3 pot drawers | D34: ='[2]UPGRADES - ASHWOOD RANGE'!$L$32*2 -> 660
C35: 3 Banks of 3 pot drawers | D35: ='[2]UPGRADES - ASHWOOD RANGE'!$L$32*3 -> 990
C36: 4 Banks of 3 pot drawers | D36: ='[2]UPGRADES - ASHWOOD RANGE'!$L$32*4 -> 1320
C37: 5 Banks of 3 pot drawers | D37: ='[2]UPGRADES - ASHWOOD RANGE'!$L$32*5 -> 1650
C38: ='[2]UPGRADES - ASHWOOD RANGE'!$B$33 -> Microwave cavity with drawer below | D38: ='[2]UPGRADES - ASHWOOD RANGE'!$L$33 -> 415
C39: ='[2]UPGRADES - ASHWOOD RANGE'!$B$34 -> Twin bin with drawer below | D39: ='[2]UPGRADES - ASHWOOD RANGE'!$L$34 -> 250
C40: ='[2]UPGRADES - ASHWOOD RANGE'!$B$35 -> 1212 No Bottom Reveal Window | D40: ='[2]UPGRADES - ASHWOOD RANGE'!$L$35 -> 390
C42: Ensuite & Bathroom
C43: ='[2]UPGRADES - ASHWOOD RANGE'!$B$37 -> Bank of 3 drawers to vanities | D43: ='[2]UPGRADES - ASHWOOD RANGE'!$L$37 -> 660
C44: 2 drawers to vanity in lieu of doors - (2 Banks) | D44: ='[2]UPGRADES - ASHWOOD RANGE'!$L$38*2 -> 660
C45: 2 drawers to vanity in lieu of doors - (3 Banks) | D45: ='[2]UPGRADES - ASHWOOD RANGE'!$L$38*3 -> 990
C46: Rectangle with rounded edge mirrors - (2 Mirrors) | D46: ='[2]UPGRADES - ASHWOOD RANGE'!$L$39/2*2 -> 280
C47: Rectangle with rounded edge mirrors - (3 Mirrors) | D47: ='[2]UPGRADES - ASHWOOD RANGE'!$L$39/2*3 -> 420
C48: ='[2]UPGRADES - ASHWOOD RANGE'!$B$40 -> Tiled recess shelves | D48: ='[2]UPGRADES - ASHWOOD RANGE'!$L$40 -> 800
C49: ='[2]UPGRADES - ASHWOOD RANGE'!$B$41 -> Extend tiles to 2.1m high on vanity wall | D49: ='[2]UPGRADES - ASHWOOD RANGE'!$L$41 -> 500
C50: ='[2]UPGRADES - ASHWOOD RANGE'!$B$42 -> Extend tiles to 2.1m high on remaining three walls | D50: ='[2]UPGRADES - ASHWOOD RANGE'!$L$42 -> 1800
C52: Laundry
C53: ='[2]UPGRADES - ASHWOOD RANGE'!$B$44 -> 1200mm Laminate benchtop & cupboards | D53: ='[2]UPGRADES - ASHWOOD RANGE'!$L$44 -> 1680
C54: ='[2]UPGRADES - ASHWOOD RANGE'!$B$45 -> Extend laminate benchtop only by 900mm with powerpoint | D54: ='[2]UPGRADES - ASHWOOD RANGE'!$L$45 -> 580
C55: ='[2]UPGRADES - ASHWOOD RANGE'!$B$46 -> 1200mm Overhead cupboards | D55: ='[2]UPGRADES - ASHWOOD RANGE'!$L$46 -> 1040
C56: ='[2]UPGRADES - ASHWOOD RANGE'!$B$47 -> 900mm Overhead cupboards | D56: ='[2]UPGRADES - ASHWOOD RANGE'!$L$47 -> 765
C57: ='[2]UPGRADES - ASHWOOD RANGE'!$B$48 -> Hanging rail under overheads | D57: ='[2]UPGRADES - ASHWOOD RANGE'!$L$48 -> 300
C58: ='[2]UPGRADES - ASHWOOD RANGE'!$B$49 -> Pullout laundry basket with drawer | D58: ='[2]UPGRADES - ASHWOOD RANGE'!$L$49 -> 235
C60: Additional Add Ons
C61: ='[2]UPGRADES - ASHWOOD RANGE'!$B$51 -> Eaves to whole home | D61: ='[2]UPGRADES - ASHWOOD RANGE'!$L$51 -> 4210
C62: ='[2]UPGRADES - ASHWOOD RANGE'!$B$52 -> Add 2100h x 2400w roller door - (2550mm Cielings Required) | D62: ='[2]UPGRADES - ASHWOOD RANGE'!$L$52 -> 1670
C63: ='[2]UPGRADES - ASHWOOD RANGE'!$B$53 -> 2550mm ceiling | D63: ='[2]UPGRADES - ASHWOOD RANGE'!$L$53 -> 3700
C65: Personalised Selections
C66: External Finishes
C67: ='[2]UPGRADES - ASHWOOD RANGE'!$B$56 -> Double glazing to whole home (please note: all windows will be awning) | D67: ='[2]UPGRADES - ASHWOOD RANGE'!$L$56 -> 4200
C68: ='[2]UPGRADES - ASHWOOD RANGE'!$B$57 -> Sliding door in lieu of swing | D68: ='[2]UPGRADES - ASHWOOD RANGE'!$L$57 -> 200
C69: ='[2]UPGRADES - ASHWOOD RANGE'!$B$58 -> Wall mounted clothesline | D69: ='[2]UPGRADES - ASHWOOD RANGE'!$L$58 -> 400
C70: ='[2]UPGRADES - ASHWOOD RANGE'!$B$59 -> Letterbox | D70: ='[2]UPGRADES - ASHWOOD RANGE'!$L$59 -> 350
C71: ='[2]UPGRADES - ASHWOOD RANGE'!$B$60 -> Newington front door | D71: ='[2]UPGRADES - ASHWOOD RANGE'!$L$60 -> 300
C72: ='[2]UPGRADES - ASHWOOD RANGE'!$B$61 -> Nexion front door handle | D72: ='[2]UPGRADES - ASHWOOD RANGE'!$L$61 -> 175
C73: ='[2]UPGRADES - ASHWOOD RANGE'!$B$62 -> Brick Upgrade | D73: ='[2]UPGRADES - ASHWOOD RANGE'!$L$62 -> 720
C75: Internal Finishes
C76: ='[2]UPGRADES - ASHWOOD RANGE'!$B$64 -> Internal door pack - WIR & rear hallway | D76: ='[2]UPGRADES - ASHWOOD RANGE'!$L$64 -> 440
C77: ='[2]UPGRADES - ASHWOOD RANGE'!$B$65 -> 2340mm high internal doors & robe/linen doors - (2550mm Cielings Required) | D77: ='[2]UPGRADES - ASHWOOD RANGE'!$L$65 -> 1300 | F77: can we put proviso only to add if with 2550mm ceiling
C78: ='[2]UPGRADES - ASHWOOD RANGE'!$B$66 -> Single roller blinds | D78: ='[2]UPGRADES - ASHWOOD RANGE'!$L$66 -> 2500
C80: Robes
C81: Vinyl / Mirror sliding robe door Combination to 1 Robe | D81: ='[2]UPGRADES - ASHWOOD RANGE'!$L$68 -> 50
C82: Vinyl / Mirror sliding robe door Combination to 2 Robes | D82: ='[2]UPGRADES - ASHWOOD RANGE'!$L$68*2 -> 100
C83: Vinyl / Mirror sliding robe door Combination to 3 Robes | D83: ='[2]UPGRADES - ASHWOOD RANGE'!$L$68*3 -> 150
C84: Double Mirror sliding robe door Combination to 1 Robe | D84: ='[2]UPGRADES - ASHWOOD RANGE'!$L$68*2 -> 100
C85: Double Mirror sliding robe door Combination to 2 Robe | D85: ='[2]UPGRADES - ASHWOOD RANGE'!$L$68*4 -> 200
C86: Double Mirror sliding robe door Combination to 3 Robe | D86: ='[2]UPGRADES - ASHWOOD RANGE'!$L$68*6 -> 300
C87: 1 Bank of three shelves - (Shirt Stacker) | D87: ='[2]UPGRADES - ASHWOOD RANGE'!$L$69 -> 185
C88: 2 Bank of three shelves - (Shirt Stacker) | D88: ='[2]UPGRADES - ASHWOOD RANGE'!$L$69*2 -> 370
C89: 3 Bank of three shelves - (Shirt Stacker) | D89: ='[2]UPGRADES - ASHWOOD RANGE'!$L$69*3 -> 555
C90: 4 Bank of three shelves - (Shirt Stacker) | D90: ='[2]UPGRADES - ASHWOOD RANGE'!$L$69*4 -> 740
C91: 5 Bank of three shelves - (Shirt Stacker) | D91: ='[2]UPGRADES - ASHWOOD RANGE'!$L$69*5 -> 925
C92: 6 Bank of three shelves - (Shirt Stacker) | D92: ='[2]UPGRADES - ASHWOOD RANGE'!$L$69*6 -> 1110
C93: 1 Bank of two shelves & four drawers | D93: ='[2]UPGRADES - ASHWOOD RANGE'!$L$70 -> 510
C94: 2 Bank of two shelves & four drawers | D94: ='[2]UPGRADES - ASHWOOD RANGE'!$L$70*2 -> 1020
C95: 3 Bank of two shelves & four drawers | D95: ='[2]UPGRADES - ASHWOOD RANGE'!$L$70*3 -> 1530
C96: 4 Bank of two shelves & four drawers | D96: ='[2]UPGRADES - ASHWOOD RANGE'!$L$70*4 -> 2040
C97: 5 Bank of two shelves & four drawers | D97: ='[2]UPGRADES - ASHWOOD RANGE'!$L$70*5 -> 2550
C98: 6 Bank of two shelves & four drawers | D98: ='[2]UPGRADES - ASHWOOD RANGE'!$L$70*6 -> 3060
C100: Kitchen
C101: ='[2]UPGRADES - ASHWOOD RANGE'!$B$72 -> 600mm stainless steel oven & canopy rangehood and electric cooktop | D101: ='[2]UPGRADES - ASHWOOD RANGE'!$L$72 -> 365
C102: ='[2]UPGRADES - ASHWOOD RANGE'!$B$73 -> 900mm black inbuilt oven, cooktop & canopy rangehood | D102: ='[2]UPGRADES - ASHWOOD RANGE'!$L$73 -> 1870
C103: ='[2]UPGRADES - ASHWOOD RANGE'!$B$74 -> 900mm stainless steel inbuilt oven, cooktop & canopy rangehood | D103: ='[2]UPGRADES - ASHWOOD RANGE'!$L$74 -> 1860
C104: ='[2]UPGRADES - ASHWOOD RANGE'!$B$75 -> 900mm black undermount rangehood in lieu of canopy | D104: ='[2]UPGRADES - ASHWOOD RANGE'!$L$75 -> 800
C105: ='[2]UPGRADES - ASHWOOD RANGE'!$B$76 -> 900mm stainless steel undermount rangehood in lieu of canopy | D105: ='[2]UPGRADES - ASHWOOD RANGE'!$L$76 -> 770
C106: ='[2]UPGRADES - ASHWOOD RANGE'!$B$77 -> Stainless steel dishwasher | D106: ='[2]UPGRADES - ASHWOOD RANGE'!$L$77 -> 700
C107: ='[2]UPGRADES - ASHWOOD RANGE'!$B$78 -> Black dishwasher | D107: ='[2]UPGRADES - ASHWOOD RANGE'!$L$78 -> 750
C108: ='[2]UPGRADES - ASHWOOD RANGE'!$B$79 -> Cold water point for fridge | D108: ='[2]UPGRADES - ASHWOOD RANGE'!$L$79 -> 200
C109: Soft close drawers to 1 Bank of Draws | D109: ='[2]UPGRADES - ASHWOOD RANGE'!$L$80 -> 350
C110: Soft close drawers to 2 Bank of Draws | D110: ='[2]UPGRADES - ASHWOOD RANGE'!$L$80*2 -> 700
C111: Soft close drawers to 3 Bank of Draws | D111: ='[2]UPGRADES - ASHWOOD RANGE'!$L$80*3 -> 1050
...

Sheet BYRON 19
C3: Floor Plan Extensions
C4: ='[2]UPGRADES - BYRON RANGE'!$B$6 -> Extend garage by 500mm | D4: ='[2]UPGRADES - BYRON RANGE'!$L$6 -> 2500
C5: ='[2]UPGRADES - BYRON RANGE'!$B$7 -> Extend garage by 1000mm | D5: ='[2]UPGRADES - BYRON RANGE'!$L$7 -> 5000
C6: ='[2]UPGRADES - BYRON RANGE'!$B$8 -> Outdoor Living - addition 1 | D6: ='[2]UPGRADES - BYRON RANGE'!$L$8 -> 4580
C7: ='[2]UPGRADES - BYRON RANGE'!$B$9 -> Outdoor Living - brick pier in lieu of steel post | D7: ='[2]UPGRADES - BYRON RANGE'!$L$9 -> 400
C8: ='[2]UPGRADES - BYRON RANGE'!$B$10 -> Additional concrete - outdoor living | D8: ='[2]UPGRADES - BYRON RANGE'!$L$10 -> 1680
C9: ='[2]UPGRADES - BYRON RANGE'!$B$11 -> Outdoor Living - addition 2 | D9: ='[2]UPGRADES - BYRON RANGE'!$L$11 -> 7250
C10: ='[2]UPGRADES - BYRON RANGE'!$B$12 -> Outdoor Living - brick pier in lieu of steel post | D10: ='[2]UPGRADES - BYRON RANGE'!$L$12 -> 800
C11: ='[2]UPGRADES - BYRON RANGE'!$B$13 -> Additional concrete- Outdoor living | D11: ='[2]UPGRADES - BYRON RANGE'!$L$13 -> 2520
C12: ='[2]UPGRADES - BYRON RANGE'!$B$14 -> Kitchen - The Entertainers Kitchen | D12: ='[2]UPGRADES - BYRON RANGE'!$L$14 -> 900
C13: ='[2]UPGRADES - BYRON RANGE'!$B$15 -> Kitchen - The Modern Chef Kitchen | D13: ='[2]UPGRADES - BYRON RANGE'!$L$15 -> 4100
C14: ='[2]UPGRADES - BYRON RANGE'!$B$16 -> Ensuite - The Signature Ensuite | D14: ='[2]UPGRADES - BYRON RANGE'!$L$16 -> 750
C15: ='[2]UPGRADES - BYRON RANGE'!$B$17 -> Ensuite - The Indulgence Ensuite | D15: ='[2]UPGRADES - BYRON RANGE'!$L$17 -> 3280
C17: Façade
C18: Standard Façade | D18: Included
C19: ='[2]UPGRADES - BYRON RANGE'!$B$19 -> 1 The Retreat Façade | D19: ='[2]UPGRADES - BYRON RANGE'!$L$19 -> 3300
C20: ='[2]UPGRADES - BYRON RANGE'!$B$20 -> 2 The Rise Façade | D20: ='[2]UPGRADES - BYRON RANGE'!$L$20 -> 7300
C21: ='[2]UPGRADES - BYRON RANGE'!$B$21 -> 3 The Escape Façade | D21: ='[2]UPGRADES - BYRON RANGE'!$L$21 -> 8950
C22: ='[2]UPGRADES - BYRON RANGE'!$B$22 -> 4 The Essence Façade | D22: ='[2]UPGRADES - BYRON RANGE'!$L$22 -> 6500
C23: ='[2]UPGRADES - BYRON RANGE'!$B$23 -> 5 The Sanctuary Façade | D23: ='[2]UPGRADES - BYRON RANGE'!$L$23 -> 9050
C24: ='[2]UPGRADES - BYRON RANGE'!$B$24 -> 6. The Summit Façade | D24: ='[2]UPGRADES - BYRON RANGE'!$L$24 -> 8500
C25: ='[2]UPGRADES - BYRON RANGE'!$B$25 -> 7. The Haven Facade | D25: ='[2]UPGRADES - BYRON RANGE'!$L$25 -> 8500
C26: ='[2]UPGRADES - BYRON RANGE'!$B$26 -> 9. The Horizon Façade | D26: ='[2]UPGRADES - BYRON RANGE'!$L$26 -> 10500
C28: Add Ons
C29: Kitchen
C30: ='[2]UPGRADES - BYRON RANGE'!$B$29 -> 600mm overhead either side of rangehood | D30: ='[2]UPGRADES - BYRON RANGE'!$L$29 -> 990
C31: ='[2]UPGRADES - BYRON RANGE'!$B$30 -> Overhead cupboards with integrated rangehood | D31: ='[2]UPGRADES - BYRON RANGE'!$L$30 -> 1650
C32: ='[2]UPGRADES - BYRON RANGE'!$B$31 -> Fridge overhead cupboard | D32: ='[2]UPGRADES - BYRON RANGE'!$L$31 -> 960
C33: 1 Bank of 3 pot drawers | D33: ='[2]UPGRADES - BYRON RANGE'!$L$32 -> 330
C34: 2 Banks of 3 pot drawers | D34: ='[2]UPGRADES - BYRON RANGE'!$L$32*2 -> 660
C35: 3 Banks of 3 pot drawers | D35: ='[2]UPGRADES - BYRON RANGE'!$L$32*3 -> 990
C36: 4 Banks of 3 pot drawers | D36: ='[2]UPGRADES - BYRON RANGE'!$L$32*4 -> 1320
C37: 5 Banks of 3 pot drawers | D37: ='[2]UPGRADES - BYRON RANGE'!$L$32*5 -> 1650
C38: ='[2]UPGRADES - BYRON RANGE'!$B$33 -> Microwave cavity with drawer below | D38: ='[2]UPGRADES - BYRON RANGE'!$L$33 -> 415
C39: ='[2]UPGRADES - BYRON RANGE'!$B$34 -> Twin bin with drawer below | D39: ='[2]UPGRADES - BYRON RANGE'!$L$34 -> 250
C40: ='[2]UPGRADES - BYRON RANGE'!$B$35 -> 1212 No Bottom Reveal Window to Kitchen Upgrade 2 | D40: ='[2]UPGRADES - BYRON RANGE'!$L$35 -> 390
C42: Ensuite & Bathroom
C43: ='[2]UPGRADES - BYRON RANGE'!$B$37 -> Bank of 3 drawers to vanities | D43: ='[2]UPGRADES - BYRON RANGE'!$L$37 -> 660
C44: 2 drawers to vanity in lieu of doors - (2 Banks) | D44: ='[2]UPGRADES - BYRON RANGE'!$L$38*2 -> 660
C45: 2 drawers to vanity in lieu of doors - (3 Banks) | D45: ='[2]UPGRADES - BYRON RANGE'!$L$38*3 -> 990
C46: Rectangle with rounded edge mirrors - (2 Mirrors) | D46: ='[2]UPGRADES - BYRON RANGE'!$L$39/2*2 -> 280
C47: Rectangle with rounded edge mirrors - (3 Mirrors) | D47: ='[2]UPGRADES - BYRON RANGE'!$L$39/2*3 -> 420
C48: ='[2]UPGRADES - BYRON RANGE'!$B$40 -> Tiled recess shelves | D48: ='[2]UPGRADES - BYRON RANGE'!$L$40 -> 800
C49: ='[2]UPGRADES - BYRON RANGE'!$B$41 -> Extend tiles to 2.1m high on vanity wall | D49: ='[2]UPGRADES - BYRON RANGE'!$L$41 -> 300
C50: ='[2]UPGRADES - BYRON RANGE'!$B$42 -> Extend tiles to 2.1m high on remaining three walls | D50: ='[2]UPGRADES - BYRON RANGE'!$L$42 -> 1700
C52: Laundry
C53: ='[2]UPGRADES - BYRON RANGE'!$B$44 -> 1200mm Laminate benchtop & cupboards | D53: ='[2]UPGRADES - BYRON RANGE'!$L$44 -> 1680
C54: ='[2]UPGRADES - BYRON RANGE'!$B$45 -> Extend laminate benchtop only by 1350mm with powerpoint | D54: ='[2]UPGRADES - BYRON RANGE'!$L$45 -> 830
C55: ='[2]UPGRADES - BYRON RANGE'!$B$46 -> 1200mm Overhead cupboards | D55: ='[2]UPGRADES - BYRON RANGE'!$L$46 -> 1040
C56: ='[2]UPGRADES - BYRON RANGE'!$B$47 -> 1350mm Overhead cupboards | D56: ='[2]UPGRADES - BYRON RANGE'!$L$47 -> 1170
C57: ='[2]UPGRADES - BYRON RANGE'!$B$48 -> Hanging rail under overheads | D57: ='[2]UPGRADES - BYRON RANGE'!$L$48 -> 300
C58: ='[2]UPGRADES - BYRON RANGE'!$B$49 -> Pullout laundry basket with drawer | D58: ='[2]UPGRADES - BYRON RANGE'!$L$49 -> 235
C60: Additional Add Ons
C61: ='[2]UPGRADES - BYRON RANGE'!$B$51 -> Eaves to whole home | D61: ='[2]UPGRADES - BYRON RANGE'!$L$51 -> 4500
C62: ='[2]UPGRADES - BYRON RANGE'!$B$52 -> Add 2100h x 2400w roller door - (2550mm Cielings Required) | D62: ='[2]UPGRADES - BYRON RANGE'!$L$52 -> 1670
C63: ='[2]UPGRADES - BYRON RANGE'!$B$53 -> 2550mm ceiling | D63: ='[2]UPGRADES - BYRON RANGE'!$L$53 -> 3500
C65: Personalised Selections
C66: External Finishes
C67: ='[2]UPGRADES - BYRON RANGE'!$B$56 -> Double glazing to whole home (please note: all windows will be awning) | D67: ='[2]UPGRADES - BYRON RANGE'!$L$56 -> 4700
C68: ='[2]UPGRADES - BYRON RANGE'!$B$57 -> Sliding door in lieu of swing | D68: ='[2]UPGRADES - BYRON RANGE'!$L$57 -> 200
C69: ='[2]UPGRADES - BYRON RANGE'!$B$58 -> Wall mounted clothesline | D69: ='[2]UPGRADES - BYRON RANGE'!$L$58 -> 400
C70: ='[2]UPGRADES - BYRON RANGE'!$B$59 -> Letterbox | D70: ='[2]UPGRADES - BYRON RANGE'!$L$59 -> 350
C71: ='[2]UPGRADES - BYRON RANGE'!$B$60 -> Newington front door | D71: ='[2]UPGRADES - BYRON RANGE'!$L$60 -> 300
C72: ='[2]UPGRADES - BYRON RANGE'!$B$61 -> Nexion front door handle | D72: ='[2]UPGRADES - BYRON RANGE'!$L$61 -> 175
C73: ='[2]UPGRADES - BYRON RANGE'!$B$62 -> Brick Upgrade | D73: ='[2]UPGRADES - BYRON RANGE'!$L$62 -> 720
C75: Internal Finishes
C76: ='[2]UPGRADES - BYRON RANGE'!$B$64 -> Internal door pack - WIR, WIP & rear hallway | D76: ='[2]UPGRADES - BYRON RANGE'!$L$64 -> 660
C77: ='[2]UPGRADES - BYRON RANGE'!$B$65 -> 2340mm high internal doors & robe/linen doors - (2550mm Cielings Required) | D77: ='[2]UPGRADES - BYRON RANGE'!$L$65 -> 960
C78: ='[2]UPGRADES - BYRON RANGE'!$B$66 -> Single roller blinds | D78: ='[2]UPGRADES - BYRON RANGE'!$L$66 -> 2500
C80: Robes
C81: Vinyl / Mirror sliding robe door Combination to 1 Robe | D81: ='[2]UPGRADES - BYRON RANGE'!$L$68 -> 50
C82: Vinyl / Mirror sliding robe door Combination to 2 Robes | D82: ='[2]UPGRADES - BYRON RANGE'!$L$68*2 -> 100
C83: Vinyl / Mirror sliding robe door Combination to 3 Robes | D83: ='[2]UPGRADES - BYRON RANGE'!$L$68*3 -> 150
C84: Double Mirror sliding robe door Combination to 1 Robe | D84: ='[2]UPGRADES - BYRON RANGE'!$L$68*2 -> 100
C85: Double Mirror sliding robe door Combination to 2 Robe | D85: ='[2]UPGRADES - BYRON RANGE'!$L$68*4 -> 200
C86: Double Mirror sliding robe door Combination to 3 Robe | D86: ='[2]UPGRADES - BYRON RANGE'!$L$68*6 -> 300
C87: 1 Bank of three shelves - (Shirt Stacker) | D87: ='[2]UPGRADES - BYRON RANGE'!$L$69 -> 185
C88: 2 Banks of three shelves - (Shirt Stacker) | D88: ='[2]UPGRADES - BYRON RANGE'!$L$69*2 -> 370
C89: 3 Banks of three shelves - (Shirt Stacker) | D89: ='[2]UPGRADES - BYRON RANGE'!$L$69*3 -> 555
C90: 4 Banks of three shelves - (Shirt Stacker) | D90: ='[2]UPGRADES - BYRON RANGE'!$L$69*4 -> 740
C91: 5 Banks of three shelves - (Shirt Stacker) | D91: ='[2]UPGRADES - BYRON RANGE'!$L$69*5 -> 925
C92: 6 Banks of three shelves - (Shirt Stacker) | D92: ='[2]UPGRADES - BYRON RANGE'!$L$69*6 -> 1110
C93: 1 Bank of two shelves & four drawers | D93: ='[2]UPGRADES - BYRON RANGE'!$L$70 -> 510
C94: 2 Banks of two shelves & four drawers | D94: ='[2]UPGRADES - BYRON RANGE'!$L$70*2 -> 1020
C95: 3 Banks of two shelves & four drawers | D95: ='[2]UPGRADES - BYRON RANGE'!$L$70*3 -> 1530
C96: 4 Banks of two shelves & four drawers | D96: ='[2]UPGRADES - BYRON RANGE'!$L$70*4 -> 2040
C97: 5 Banks of two shelves & four drawers | D97: ='[2]UPGRADES - BYRON RANGE'!$L$70*5 -> 2550
C98: 6 Banks of two shelves & four drawers | D98: ='[2]UPGRADES - BYRON RANGE'!$L$70*6 -> 3060
C100: Kitchen
C101: ='[2]UPGRADES - BYRON RANGE'!$B$72 -> 600mm stainless steel oven & canopy rangehood and electric cooktop | D101: ='[2]UPGRADES - BYRON RANGE'!$L$72 -> 365
C102: ='[2]UPGRADES - BYRON RANGE'!$B$73 -> 900mm black inbuilt oven, cooktop & canopy rangehood | D102: ='[2]UPGRADES - BYRON RANGE'!$L$73 -> 1870
C103: ='[2]UPGRADES - BYRON RANGE'!$B$74 -> 900mm stainless steel inbuilt oven, cooktop & canopy rangehood | D103: ='[2]UPGRADES - BYRON RANGE'!$L$74 -> 1860
C104: ='[2]UPGRADES - BYRON RANGE'!$B$75 -> 900mm black undermount rangehood in lieu of canopy | D104: ='[2]UPGRADES - BYRON RANGE'!$L$75 -> 800
C105: ='[2]UPGRADES - BYRON RANGE'!$B$76 -> 900mm stainless steel undermount rangehood in lieu of canopy | D105: ='[2]UPGRADES - BYRON RANGE'!$L$76 -> 770
C106: ='[2]UPGRADES - BYRON RANGE'!$B$77 -> Stainless steel dishwasher | D106: ='[2]UPGRADES - BYRON RANGE'!$L$77 -> 700
C107: ='[2]UPGRADES - BYRON RANGE'!$B$78 -> Black dishwasher | D107: ='[2]UPGRADES - BYRON RANGE'!$L$78 -> 750
C108: ='[2]UPGRADES - BYRON RANGE'!$B$79 -> Cold water point for fridge | D108: ='[2]UPGRADES - BYRON RANGE'!$L$79 -> 200
C109: Soft close drawers to 1 Bank of Draws | D109: ='[2]UPGRADES - BYRON RANGE'!$L$80 -> 350
C110: Soft close drawers to 2 Bank of Draws | D110: ='[2]UPGRADES - BYRON RANGE'!$L$80*2 -> 700
C111: Soft close drawers to 3 Bank of Draws | D111: ='[2]UPGRADES - BYRON RANGE'!$L$80*3 -> 1050
...

Sheet BYRON 22A
C3: Floor Plan Extensions
C4: ='[2]UPGRADES - BYRON RANGE'!$B$6 -> Extend garage by 500mm | D4: ='[2]UPGRADES - BYRON RANGE'!$M$6 -> 2500
C5: ='[2]UPGRADES - BYRON RANGE'!$B$7 -> Extend garage by 1000mm | D5: ='[2]UPGRADES - BYRON RANGE'!$M$7 -> 5000
C6: ='[2]UPGRADES - BYRON RANGE'!$B$8 -> Outdoor Living - addition 1 | D6: ='[2]UPGRADES - BYRON RANGE'!$M$8 -> 5500
C7: ='[2]UPGRADES - BYRON RANGE'!$B$9 -> Outdoor Living - brick pier in lieu of steel post | D7: ='[2]UPGRADES - BYRON RANGE'!$M$9 -> 800
C8: ='[2]UPGRADES - BYRON RANGE'!$B$10 -> Additional concrete - outdoor living | D8: ='[2]UPGRADES - BYRON RANGE'!$M$10 -> 1960
C9: ='[2]UPGRADES - BYRON RANGE'!$B$11 -> Outdoor Living - addition 2 | D9: ='[2]UPGRADES - BYRON RANGE'!$M$11 -> 7250
C10: ='[2]UPGRADES - BYRON RANGE'!$B$12 -> Outdoor Living - brick pier in lieu of steel post | D10: ='[2]UPGRADES - BYRON RANGE'!$M$12 -> 800
C11: ='[2]UPGRADES - BYRON RANGE'!$B$13 -> Additional concrete- Outdoor living | D11: ='[2]UPGRADES - BYRON RANGE'!$M$13 -> 2520
C12: ='[2]UPGRADES - BYRON RANGE'!$B$14 -> Kitchen - The Entertainers Kitchen | D12: ='[2]UPGRADES - BYRON RANGE'!$M$14 -> 900
C13: ='[2]UPGRADES - BYRON RANGE'!$B$15 -> Kitchen - The Modern Chef Kitchen | D13: ='[2]UPGRADES - BYRON RANGE'!$M$15 -> 4100
C14: ='[2]UPGRADES - BYRON RANGE'!$B$16 -> Ensuite - The Signature Ensuite | D14: ='[2]UPGRADES - BYRON RANGE'!$M$16 -> 750
C15: ='[2]UPGRADES - BYRON RANGE'!$B$17 -> Ensuite - The Indulgence Ensuite | D15: ='[2]UPGRADES - BYRON RANGE'!$M$17 -> 3280
C17: Façade
C18: Standard Façade | D18: Included
C19: ='[2]UPGRADES - BYRON RANGE'!$B$19 -> 1 The Retreat Façade | D19: ='[2]UPGRADES - BYRON RANGE'!$M$19 -> 3300
C20: ='[2]UPGRADES - BYRON RANGE'!$B$20 -> 2 The Rise Façade | D20: ='[2]UPGRADES - BYRON RANGE'!$M$20 -> 7300
C21: ='[2]UPGRADES - BYRON RANGE'!$B$21 -> 3 The Escape Façade | D21: ='[2]UPGRADES - BYRON RANGE'!$M$21 -> 8950
C22: ='[2]UPGRADES - BYRON RANGE'!$B$22 -> 4 The Essence Façade | D22: ='[2]UPGRADES - BYRON RANGE'!$M$22 -> 6500
C23: ='[2]UPGRADES - BYRON RANGE'!$B$23 -> 5 The Sanctuary Façade | D23: ='[2]UPGRADES - BYRON RANGE'!$M$23 -> 9050
C24: ='[2]UPGRADES - BYRON RANGE'!$B$24 -> 6. The Summit Façade | D24: ='[2]UPGRADES - BYRON RANGE'!$M$24 -> 8500
C25: ='[2]UPGRADES - BYRON RANGE'!$B$25 -> 7. The Haven Facade | D25: ='[2]UPGRADES - BYRON RANGE'!$M$25 -> 8500
C26: ='[2]UPGRADES - BYRON RANGE'!$B$26 -> 9. The Horizon Façade | D26: ='[2]UPGRADES - BYRON RANGE'!$M$26 -> 10500
C28: Add Ons
C29: Kitchen
C30: ='[2]UPGRADES - BYRON RANGE'!$B$29 -> 600mm overhead either side of rangehood | D30: ='[2]UPGRADES - BYRON RANGE'!$M$29 -> 990
C31: ='[2]UPGRADES - BYRON RANGE'!$B$30 -> Overhead cupboards with integrated rangehood | D31: ='[2]UPGRADES - BYRON RANGE'!$M$30 -> 1650
C32: ='[2]UPGRADES - BYRON RANGE'!$B$31 -> Fridge overhead cupboard | D32: ='[2]UPGRADES - BYRON RANGE'!$M$31 -> 960
C33: 1 Bank of 3 pot drawers | D33: ='[2]UPGRADES - BYRON RANGE'!$M$32 -> 330
C34: 2 Banks of 3 pot drawers | D34: ='[2]UPGRADES - BYRON RANGE'!$M$32*2 -> 660
C35: 3 Banks of 3 pot drawers | D35: ='[2]UPGRADES - BYRON RANGE'!$M$32*3 -> 990
C36: 4 Banks of 3 pot drawers | D36: ='[2]UPGRADES - BYRON RANGE'!$M$32*4 -> 1320
C37: 5 Banks of 3 pot drawers | D37: ='[2]UPGRADES - BYRON RANGE'!$M$32*5 -> 1650
C38: ='[2]UPGRADES - BYRON RANGE'!$B$33 -> Microwave cavity with drawer below | D38: ='[2]UPGRADES - BYRON RANGE'!$M$33 -> 415
C39: ='[2]UPGRADES - BYRON RANGE'!$B$34 -> Twin bin with drawer below | D39: ='[2]UPGRADES - BYRON RANGE'!$M$34 -> 250
C40: ='[2]UPGRADES - BYRON RANGE'!$B$35 -> 1212 No Bottom Reveal Window to Kitchen Upgrade 2 | D40: ='[2]UPGRADES - BYRON RANGE'!$M$35 -> 390
C42: Ensuite & Bathroom
C43: ='[2]UPGRADES - BYRON RANGE'!$B$37 -> Bank of 3 drawers to vanities | D43: ='[2]UPGRADES - BYRON RANGE'!$M$37 -> 660
C44: 2 drawers to vanity in lieu of doors - (2 Banks) | D44: ='[2]UPGRADES - BYRON RANGE'!$M$38*2 -> 660
C45: 2 drawers to vanity in lieu of doors - (3 Banks) | D45: ='[2]UPGRADES - BYRON RANGE'!$M$38*3 -> 990
C46: Rectangle with rounded edge mirrors - (2 Mirrors) | D46: ='[2]UPGRADES - BYRON RANGE'!$M$39/2*2 -> 280
C47: Rectangle with rounded edge mirrors - (3 Mirrors) | D47: ='[2]UPGRADES - BYRON RANGE'!$M$39/2*3 -> 420
C48: ='[2]UPGRADES - BYRON RANGE'!$B$40 -> Tiled recess shelves | D48: ='[2]UPGRADES - BYRON RANGE'!$M$40 -> 800
C49: ='[2]UPGRADES - BYRON RANGE'!$B$41 -> Extend tiles to 2.1m high on vanity wall | D49: ='[2]UPGRADES - BYRON RANGE'!$M$41 -> 300
C50: ='[2]UPGRADES - BYRON RANGE'!$B$42 -> Extend tiles to 2.1m high on remaining three walls | D50: ='[2]UPGRADES - BYRON RANGE'!$M$42 -> 1700
C52: Laundry
C53: ='[2]UPGRADES - BYRON RANGE'!$B$44 -> 1200mm Laminate benchtop & cupboards | D53: ='[2]UPGRADES - BYRON RANGE'!$M$44 -> 1680
C54: ='[2]UPGRADES - BYRON RANGE'!$B$45 -> Extend laminate benchtop only by 1350mm with powerpoint | D54: ='[2]UPGRADES - BYRON RANGE'!$M$45 -> 830
C55: ='[2]UPGRADES - BYRON RANGE'!$B$46 -> 1200mm Overhead cupboards | D55: ='[2]UPGRADES - BYRON RANGE'!$M$46 -> 1040
C56: ='[2]UPGRADES - BYRON RANGE'!$B$47 -> 1350mm Overhead cupboards | D56: ='[2]UPGRADES - BYRON RANGE'!$M$47 -> 1170
C57: ='[2]UPGRADES - BYRON RANGE'!$B$48 -> Hanging rail under overheads | D57: ='[2]UPGRADES - BYRON RANGE'!$M$48 -> 300
C58: ='[2]UPGRADES - BYRON RANGE'!$B$49 -> Pullout laundry basket with drawer | D58: ='[2]UPGRADES - BYRON RANGE'!$M$49 -> 235
C60: Additional Add Ons
C61: ='[2]UPGRADES - BYRON RANGE'!$B$51 -> Eaves to whole home | D61: ='[2]UPGRADES - BYRON RANGE'!$M$51 -> 4900
C62: ='[2]UPGRADES - BYRON RANGE'!$B$52 -> Add 2100h x 2400w roller door - (2550mm Cielings Required) | D62: ='[2]UPGRADES - BYRON RANGE'!$M$52 -> 1670
C63: ='[2]UPGRADES - BYRON RANGE'!$B$53 -> 2550mm ceiling | D63: ='[2]UPGRADES - BYRON RANGE'!$M$53 -> 3900
C65: Personalised Selections
C66: External Finishes
C67: ='[2]UPGRADES - BYRON RANGE'!$B$56 -> Double glazing to whole home (please note: all windows will be awning) | D67: ='[2]UPGRADES - BYRON RANGE'!$M$56 -> 5100
C68: ='[2]UPGRADES - BYRON RANGE'!$B$57 -> Sliding door in lieu of swing | D68: ='[2]UPGRADES - BYRON RANGE'!$M$57 -> 200
C69: ='[2]UPGRADES - BYRON RANGE'!$B$58 -> Wall mounted clothesline | D69: ='[2]UPGRADES - BYRON RANGE'!$M$58 -> 400
C70: ='[2]UPGRADES - BYRON RANGE'!$B$59 -> Letterbox | D70: ='[2]UPGRADES - BYRON RANGE'!$M$59 -> 350
C71: ='[2]UPGRADES - BYRON RANGE'!$B$60 -> Newington front door | D71: ='[2]UPGRADES - BYRON RANGE'!$M$60 -> 300
C72: ='[2]UPGRADES - BYRON RANGE'!$B$61 -> Nexion front door handle | D72: ='[2]UPGRADES - BYRON RANGE'!$M$61 -> 175
C73: ='[2]UPGRADES - BYRON RANGE'!$B$62 -> Brick Upgrade | D73: ='[2]UPGRADES - BYRON RANGE'!$M$62 -> 720
C75: Internal Finishes
C76: ='[2]UPGRADES - BYRON RANGE'!$B$64 -> Internal door pack - WIR, WIP & rear hallway | D76: ='[2]UPGRADES - BYRON RANGE'!$M$64 -> 660
C77: ='[2]UPGRADES - BYRON RANGE'!$B$65 -> 2340mm high internal doors & robe/linen doors - (2550mm Cielings Required) | D77: ='[2]UPGRADES - BYRON RANGE'!$M$65 -> 1200
C78: ='[2]UPGRADES - BYRON RANGE'!$B$66 -> Single roller blinds | D78: ='[2]UPGRADES - BYRON RANGE'!$M$66 -> 2780
C80: Robes
C81: Vinyl / Mirror sliding robe door Combination to 1 Robe | D81: ='[2]UPGRADES - BYRON RANGE'!$M$68 -> 50
C82: Vinyl / Mirror sliding robe door Combination to 2 Robes | D82: ='[2]UPGRADES - BYRON RANGE'!$M$68*2 -> 100
C83: Vinyl / Mirror sliding robe door Combination to 3 Robes | D83: ='[2]UPGRADES - BYRON RANGE'!$M$68*3 -> 150
C84: Double Mirror sliding robe door Combination to 1 Robe | D84: ='[2]UPGRADES - BYRON RANGE'!$M$68*2 -> 100
C85: Double Mirror sliding robe door Combination to 2 Robe | D85: ='[2]UPGRADES - BYRON RANGE'!$M$68*4 -> 200
C86: Double Mirror sliding robe door Combination to 3 Robe | D86: ='[2]UPGRADES - BYRON RANGE'!$M$68*6 -> 300
C87: 1 Bank of three shelves - (Shirt Stacker) | D87: ='[2]UPGRADES - BYRON RANGE'!$M$69 -> 185
C88: 2 Banks of three shelves - (Shirt Stacker) | D88: ='[2]UPGRADES - BYRON RANGE'!$M$69*2 -> 370
C89: 3 Banks of three shelves - (Shirt Stacker) | D89: ='[2]UPGRADES - BYRON RANGE'!$M$69*3 -> 555
C90: 4 Banks of three shelves - (Shirt Stacker) | D90: ='[2]UPGRADES - BYRON RANGE'!$M$69*4 -> 740
C91: 5 Banks of three shelves - (Shirt Stacker) | D91: ='[2]UPGRADES - BYRON RANGE'!$M$69*5 -> 925
C92: 6 Banks of three shelves - (Shirt Stacker) | D92: ='[2]UPGRADES - BYRON RANGE'!$M$69*6 -> 1110
C93: 1 Bank of two shelves & four drawers | D93: ='[2]UPGRADES - BYRON RANGE'!$M$70 -> 510
C94: 2 Banks of two shelves & four drawers | D94: ='[2]UPGRADES - BYRON RANGE'!$M$70*2 -> 1020
C95: 3 Banks of two shelves & four drawers | D95: ='[2]UPGRADES - BYRON RANGE'!$M$70*3 -> 1530
C96: 4 Banks of two shelves & four drawers | D96: ='[2]UPGRADES - BYRON RANGE'!$M$70*4 -> 2040
C97: 5 Banks of two shelves & four drawers | D97: ='[2]UPGRADES - BYRON RANGE'!$M$70*5 -> 2550
C98: 6 Banks of two shelves & four drawers | D98: ='[2]UPGRADES - BYRON RANGE'!$M$70*6 -> 3060
C100: Kitchen
C101: ='[2]UPGRADES - BYRON RANGE'!$B$72 -> 600mm stainless steel oven & canopy rangehood and electric cooktop | D101: ='[2]UPGRADES - BYRON RANGE'!$M$72 -> 365
C102: ='[2]UPGRADES - BYRON RANGE'!$B$73 -> 900mm black inbuilt oven, cooktop & canopy rangehood | D102: ='[2]UPGRADES - BYRON RANGE'!$M$73 -> 1870
C103: ='[2]UPGRADES - BYRON RANGE'!$B$74 -> 900mm stainless steel inbuilt oven, cooktop & canopy rangehood | D103: ='[2]UPGRADES - BYRON RANGE'!$M$74 -> 1860
C104: ='[2]UPGRADES - BYRON RANGE'!$B$75 -> 900mm black undermount rangehood in lieu of canopy | D104: ='[2]UPGRADES - BYRON RANGE'!$M$75 -> 800
C105: ='[2]UPGRADES - BYRON RANGE'!$B$76 -> 900mm stainless steel undermount rangehood in lieu of canopy | D105: ='[2]UPGRADES - BYRON RANGE'!$M$76 -> 770
C106: ='[2]UPGRADES - BYRON RANGE'!$B$77 -> Stainless steel dishwasher | D106: ='[2]UPGRADES - BYRON RANGE'!$M$77 -> 700
C107: ='[2]UPGRADES - BYRON RANGE'!$B$78 -> Black dishwasher | D107: ='[2]UPGRADES - BYRON RANGE'!$M$78 -> 750
C108: ='[2]UPGRADES - BYRON RANGE'!$B$79 -> Cold water point for fridge | D108: ='[2]UPGRADES - BYRON RANGE'!$M$79 -> 200
C109: Soft close drawers to 1 Bank of Draws | D109: ='[2]UPGRADES - BYRON RANGE'!$M$80 -> 350
C110: Soft close drawers to 2 Bank of Draws | D110: ='[2]UPGRADES - BYRON RANGE'!$M$80*2 -> 700
C111: Soft close drawers to 3 Bank of Draws | D111: ='[2]UPGRADES - BYRON RANGE'!$M$80*3 -> 1050
...

Sheet BYRON 22B
C3: Floor Plan Extensions
C4: ='[2]UPGRADES - BYRON RANGE'!$B$6 -> Extend garage by 500mm | D4: ='[2]UPGRADES - BYRON RANGE'!$N$6 -> 2500
C5: ='[2]UPGRADES - BYRON RANGE'!$B$7 -> Extend garage by 1000mm | D5: ='[2]UPGRADES - BYRON RANGE'!$N$7 -> 5000
C6: ='[2]UPGRADES - BYRON RANGE'!$B$8 -> Outdoor Living - addition 1 | D6: ='[2]UPGRADES - BYRON RANGE'!$N$8 -> 4050
C7: ='[2]UPGRADES - BYRON RANGE'!$B$9 -> Outdoor Living - brick pier in lieu of steel post | D7: ='[2]UPGRADES - BYRON RANGE'!$N$9 -> 400
C8: ='[2]UPGRADES - BYRON RANGE'!$B$10 -> Additional concrete - outdoor living | D8: ='[2]UPGRADES - BYRON RANGE'!$N$10 -> 1400
C9: ='[2]UPGRADES - BYRON RANGE'!$B$11 -> Outdoor Living - addition 2 | D9: ='[2]UPGRADES - BYRON RANGE'!$N$11 -> 7250
C10: ='[2]UPGRADES - BYRON RANGE'!$B$12 -> Outdoor Living - brick pier in lieu of steel post | D10: ='[2]UPGRADES - BYRON RANGE'!$N$12 -> 800
C11: ='[2]UPGRADES - BYRON RANGE'!$B$13 -> Additional concrete- Outdoor living | D11: ='[2]UPGRADES - BYRON RANGE'!$N$13 -> 2520
C12: ='[2]UPGRADES - BYRON RANGE'!$B$14 -> Kitchen - The Entertainers Kitchen | D12: ='[2]UPGRADES - BYRON RANGE'!$N$14 -> 900
C13: ='[2]UPGRADES - BYRON RANGE'!$B$15 -> Kitchen - The Modern Chef Kitchen | D13: ='[2]UPGRADES - BYRON RANGE'!$N$15 -> 4100
C14: ='[2]UPGRADES - BYRON RANGE'!$B$16 -> Ensuite - The Signature Ensuite | D14: ='[2]UPGRADES - BYRON RANGE'!$N$16 -> 750
C15: ='[2]UPGRADES - BYRON RANGE'!$B$17 -> Ensuite - The Indulgence Ensuite | D15: ='[2]UPGRADES - BYRON RANGE'!$N$17 -> 3280
C17: Façade
C18: Standard Façade | D18: Included
C19: ='[2]UPGRADES - BYRON RANGE'!$B$19 -> 1 The Retreat Façade | D19: ='[2]UPGRADES - BYRON RANGE'!$N$19 -> 3300
C20: ='[2]UPGRADES - BYRON RANGE'!$B$20 -> 2 The Rise Façade | D20: ='[2]UPGRADES - BYRON RANGE'!$N$20 -> 7300
C21: ='[2]UPGRADES - BYRON RANGE'!$B$21 -> 3 The Escape Façade | D21: ='[2]UPGRADES - BYRON RANGE'!$N$21 -> 8950
C22: ='[2]UPGRADES - BYRON RANGE'!$B$22 -> 4 The Essence Façade | D22: ='[2]UPGRADES - BYRON RANGE'!$N$22 -> 6500
C23: ='[2]UPGRADES - BYRON RANGE'!$B$23 -> 5 The Sanctuary Façade | D23: ='[2]UPGRADES - BYRON RANGE'!$N$23 -> 9050
C24: ='[2]UPGRADES - BYRON RANGE'!$B$24 -> 6. The Summit Façade | D24: ='[2]UPGRADES - BYRON RANGE'!$N$24 -> 8500
C25: ='[2]UPGRADES - BYRON RANGE'!$B$25 -> 7. The Haven Facade | D25: ='[2]UPGRADES - BYRON RANGE'!$N$25 -> 8500
C26: ='[2]UPGRADES - BYRON RANGE'!$B$26 -> 9. The Horizon Façade | D26: ='[2]UPGRADES - BYRON RANGE'!$N$26 -> 10500
C28: Add Ons
C29: Kitchen
C30: ='[2]UPGRADES - BYRON RANGE'!$B$29 -> 600mm overhead either side of rangehood | D30: ='[2]UPGRADES - BYRON RANGE'!$N$29 -> 990
C31: ='[2]UPGRADES - BYRON RANGE'!$B$30 -> Overhead cupboards with integrated rangehood | D31: ='[2]UPGRADES - BYRON RANGE'!$N$30 -> 1650
C32: ='[2]UPGRADES - BYRON RANGE'!$B$31 -> Fridge overhead cupboard | D32: ='[2]UPGRADES - BYRON RANGE'!$N$31 -> 960
C33: 1 Bank of 3 pot drawers | D33: ='[2]UPGRADES - BYRON RANGE'!$N$32 -> 330
C34: 2 Banks of 3 pot drawers | D34: ='[2]UPGRADES - BYRON RANGE'!$N$32*2 -> 660
C35: 3 Banks of 3 pot drawers | D35: ='[2]UPGRADES - BYRON RANGE'!$N$32*3 -> 990
C36: 4 Banks of 3 pot drawers | D36: ='[2]UPGRADES - BYRON RANGE'!$N$32*4 -> 1320
C37: 5 Banks of 3 pot drawers | D37: ='[2]UPGRADES - BYRON RANGE'!$N$32*5 -> 1650
C38: ='[2]UPGRADES - BYRON RANGE'!$B$33 -> Microwave cavity with drawer below | D38: ='[2]UPGRADES - BYRON RANGE'!$N$33 -> 415
C39: ='[2]UPGRADES - BYRON RANGE'!$B$34 -> Twin bin with drawer below | D39: ='[2]UPGRADES - BYRON RANGE'!$N$34 -> 250
C40: ='[2]UPGRADES - BYRON RANGE'!$B$35 -> 1212 No Bottom Reveal Window to Kitchen Upgrade 2 | D40: ='[2]UPGRADES - BYRON RANGE'!$N$35 -> 390
C42: Ensuite & Bathroom
C43: ='[2]UPGRADES - BYRON RANGE'!$B$37 -> Bank of 3 drawers to vanities | D43: ='[2]UPGRADES - BYRON RANGE'!$N$37 -> 660
C44: 2 drawers to vanity in lieu of doors - (2 Banks) | D44: ='[2]UPGRADES - BYRON RANGE'!$N$38*2 -> 660
C45: 2 drawers to vanity in lieu of doors - (3 Banks) | D45: ='[2]UPGRADES - BYRON RANGE'!$N$38*3 -> 990
C46: Rectangle with rounded edge mirrors - (2 Mirrors) | D46: ='[2]UPGRADES - BYRON RANGE'!$N$39/2*2 -> 280
C47: Rectangle with rounded edge mirrors - (3 Mirrors) | D47: ='[2]UPGRADES - BYRON RANGE'!$N$39/2*3 -> 420
C48: ='[2]UPGRADES - BYRON RANGE'!$B$40 -> Tiled recess shelves | D48: ='[2]UPGRADES - BYRON RANGE'!$N$40 -> 800
C49: ='[2]UPGRADES - BYRON RANGE'!$B$41 -> Extend tiles to 2.1m high on vanity wall | D49: ='[2]UPGRADES - BYRON RANGE'!$N$41 -> 300
C50: ='[2]UPGRADES - BYRON RANGE'!$B$42 -> Extend tiles to 2.1m high on remaining three walls | D50: ='[2]UPGRADES - BYRON RANGE'!$N$42 -> 1700
C52: Laundry
C53: ='[2]UPGRADES - BYRON RANGE'!$B$44 -> 1200mm Laminate benchtop & cupboards | D53: ='[2]UPGRADES - BYRON RANGE'!$N$44 -> 1680
C54: ='[2]UPGRADES - BYRON RANGE'!$B$45 -> Extend laminate benchtop only by 1350mm with powerpoint | D54: ='[2]UPGRADES - BYRON RANGE'!$N$45 -> 830
C55: ='[2]UPGRADES - BYRON RANGE'!$B$46 -> 1200mm Overhead cupboards | D55: ='[2]UPGRADES - BYRON RANGE'!$N$46 -> 1040
C56: ='[2]UPGRADES - BYRON RANGE'!$B$47 -> 1350mm Overhead cupboards | D56: ='[2]UPGRADES - BYRON RANGE'!$N$47 -> 1170
C57: ='[2]UPGRADES - BYRON RANGE'!$B$48 -> Hanging rail under overheads | D57: ='[2]UPGRADES - BYRON RANGE'!$N$48 -> 300
C58: ='[2]UPGRADES - BYRON RANGE'!$B$49 -> Pullout laundry basket with drawer | D58: ='[2]UPGRADES - BYRON RANGE'!$N$49 -> 235
C60: Additional Add Ons
C61: ='[2]UPGRADES - BYRON RANGE'!$B$51 -> Eaves to whole home | D61: ='[2]UPGRADES - BYRON RANGE'!$N$51 -> 5100
C62: ='[2]UPGRADES - BYRON RANGE'!$B$52 -> Add 2100h x 2400w roller door - (2550mm Cielings Required) | D62: ='[2]UPGRADES - BYRON RANGE'!$N$52 -> 1670
C63: ='[2]UPGRADES - BYRON RANGE'!$B$53 -> 2550mm ceiling | D63: ='[2]UPGRADES - BYRON RANGE'!$N$53 -> 4000
C65: Personalised Selections
C66: External Finishes
C67: ='[2]UPGRADES - BYRON RANGE'!$B$56 -> Double glazing to whole home (please note: all windows will be awning) | D67: ='[2]UPGRADES - BYRON RANGE'!$N$56 -> 5500
C68: ='[2]UPGRADES - BYRON RANGE'!$B$57 -> Sliding door in lieu of swing | D68: ='[2]UPGRADES - BYRON RANGE'!$N$57 -> 200
C69: ='[2]UPGRADES - BYRON RANGE'!$B$58 -> Wall mounted clothesline | D69: ='[2]UPGRADES - BYRON RANGE'!$N$58 -> 400
C70: ='[2]UPGRADES - BYRON RANGE'!$B$59 -> Letterbox | D70: ='[2]UPGRADES - BYRON RANGE'!$N$59 -> 350
C71: ='[2]UPGRADES - BYRON RANGE'!$B$60 -> Newington front door | D71: ='[2]UPGRADES - BYRON RANGE'!$N$60 -> 300
C72: ='[2]UPGRADES - BYRON RANGE'!$B$61 -> Nexion front door handle | D72: ='[2]UPGRADES - BYRON RANGE'!$N$61 -> 175
C73: ='[2]UPGRADES - BYRON RANGE'!$B$62 -> Brick Upgrade | D73: ='[2]UPGRADES - BYRON RANGE'!$N$62 -> 720
C75: Internal Finishes
C76: ='[2]UPGRADES - BYRON RANGE'!$B$64 -> Internal door pack - WIR, WIP & rear hallway | D76: ='[2]UPGRADES - BYRON RANGE'!$N$64 -> 660
C77: ='[2]UPGRADES - BYRON RANGE'!$B$65 -> 2340mm high internal doors & robe/linen doors - (2550mm Cielings Required) | D77: ='[2]UPGRADES - BYRON RANGE'!$N$65 -> 1200
C78: ='[2]UPGRADES - BYRON RANGE'!$B$66 -> Single roller blinds | D78: ='[2]UPGRADES - BYRON RANGE'!$N$66 -> 2780
C80: Robes
C81: Vinyl / Mirror sliding robe door Combination to 1 Robe | D81: ='[2]UPGRADES - BYRON RANGE'!$N$68 -> 50
C82: Vinyl / Mirror sliding robe door Combination to 2 Robes | D82: ='[2]UPGRADES - BYRON RANGE'!$N$68*2 -> 100
C83: Vinyl / Mirror sliding robe door Combination to 3 Robes | D83: ='[2]UPGRADES - BYRON RANGE'!$N$68*3 -> 150
C84: Double Mirror sliding robe door Combination to 1 Robe | D84: ='[2]UPGRADES - BYRON RANGE'!$N$68*2 -> 100
C85: Double Mirror sliding robe door Combination to 2 Robe | D85: ='[2]UPGRADES - BYRON RANGE'!$N$68*4 -> 200
C86: Double Mirror sliding robe door Combination to 3 Robe | D86: ='[2]UPGRADES - BYRON RANGE'!$N$68*6 -> 300
C87: 1 Bank of three shelves - (Shirt Stacker) | D87: ='[2]UPGRADES - BYRON RANGE'!$N$69 -> 185
C88: 2 Banks of three shelves - (Shirt Stacker) | D88: ='[2]UPGRADES - BYRON RANGE'!$N$69*2 -> 370
C89: 3 Banks of three shelves - (Shirt Stacker) | D89: ='[2]UPGRADES - BYRON RANGE'!$N$69*3 -> 555
C90: 4 Banks of three shelves - (Shirt Stacker) | D90: ='[2]UPGRADES - BYRON RANGE'!$N$69*4 -> 740
C91: 5 Banks of three shelves - (Shirt Stacker) | D91: ='[2]UPGRADES - BYRON RANGE'!$N$69*5 -> 925
C92: 6 Banks of three shelves - (Shirt Stacker) | D92: ='[2]UPGRADES - BYRON RANGE'!$N$69*6 -> 1110
C93: 1 Bank of two shelves & four drawers | D93: ='[2]UPGRADES - BYRON RANGE'!$N$70 -> 510
C94: 2 Banks of two shelves & four drawers | D94: ='[2]UPGRADES - BYRON RANGE'!$N$70*2 -> 1020
C95: 3 Banks of two shelves & four drawers | D95: ='[2]UPGRADES - BYRON RANGE'!$N$70*3 -> 1530
C96: 4 Banks of two shelves & four drawers | D96: ='[2]UPGRADES - BYRON RANGE'!$N$70*4 -> 2040
C97: 5 Banks of two shelves & four drawers | D97: ='[2]UPGRADES - BYRON RANGE'!$N$70*5 -> 2550
C98: 6 Banks of two shelves & four drawers | D98: ='[2]UPGRADES - BYRON RANGE'!$N$70*6 -> 3060
C100: Kitchen
C101: ='[2]UPGRADES - BYRON RANGE'!$B$72 -> 600mm stainless steel oven & canopy rangehood and electric cooktop | D101: ='[2]UPGRADES - BYRON RANGE'!$N$72 -> 365
C102: ='[2]UPGRADES - BYRON RANGE'!$B$73 -> 900mm black inbuilt oven, cooktop & canopy rangehood | D102: ='[2]UPGRADES - BYRON RANGE'!$N$73 -> 1870
C103: ='[2]UPGRADES - BYRON RANGE'!$B$74 -> 900mm stainless steel inbuilt oven, cooktop & canopy rangehood | D103: ='[2]UPGRADES - BYRON RANGE'!$N$74 -> 1860
C104: ='[2]UPGRADES - BYRON RANGE'!$B$75 -> 900mm black undermount rangehood in lieu of canopy | D104: ='[2]UPGRADES - BYRON RANGE'!$N$75 -> 800
C105: ='[2]UPGRADES - BYRON RANGE'!$B$76 -> 900mm stainless steel undermount rangehood in lieu of canopy | D105: ='[2]UPGRADES - BYRON RANGE'!$N$76 -> 770
C106: ='[2]UPGRADES - BYRON RANGE'!$B$77 -> Stainless steel dishwasher | D106: ='[2]UPGRADES - BYRON RANGE'!$N$77 -> 700
C107: ='[2]UPGRADES - BYRON RANGE'!$B$78 -> Black dishwasher | D107: ='[2]UPGRADES - BYRON RANGE'!$N$78 -> 750
C108: ='[2]UPGRADES - BYRON RANGE'!$B$79 -> Cold water point for fridge | D108: ='[2]UPGRADES - BYRON RANGE'!$N$79 -> 200
C109: Soft close drawers to 1 Bank of Draws | D109: ='[2]UPGRADES - BYRON RANGE'!$N$80 -> 350
C110: Soft close drawers to 2 Bank of Draws | D110: ='[2]UPGRADES - BYRON RANGE'!$N$80*2 -> 700
C111: Soft close drawers to 3 Bank of Draws | D111: ='[2]UPGRADES - BYRON RANGE'!$N$80*3 -> 1050
...

Sheet MALVERN 20
C3: Floor Plan Extensions
C4: ='[2]UPGRADES - MALVERN RANGE'!$B$6 -> Extend garage by 500mm | D4: ='[2]UPGRADES - MALVERN RANGE'!$L$6 -> 2500
C5: ='[2]UPGRADES - MALVERN RANGE'!$B$7 -> Extend garage by 1000mm | D5: ='[2]UPGRADES - MALVERN RANGE'!$L$7 -> 5000
C6: ='[2]UPGRADES - MALVERN RANGE'!$B$8 -> Outdoor Living - addition 1 | D6: ='[2]UPGRADES - MALVERN RANGE'!$L$8 -> 5900
C7: ='[2]UPGRADES - MALVERN RANGE'!$B$9 -> Outdoor Living - brick pier in lieu of steel post | D7: ='[2]UPGRADES - MALVERN RANGE'!$L$9 -> 800
C8: ='[2]UPGRADES - MALVERN RANGE'!$B$10 -> Additional concrete - outdoor living | D8: ='[2]UPGRADES - MALVERN RANGE'!$L$10 -> 1260
C9: ='[2]UPGRADES - MALVERN RANGE'!$B$11 -> Outdoor Living - addition 2 | D9: ='[2]UPGRADES - MALVERN RANGE'!$L$11 -> 8100
C10: ='[2]UPGRADES - MALVERN RANGE'!$B$12 -> Outdoor Living - brick pier in lieu of steel post | D10: ='[2]UPGRADES - MALVERN RANGE'!$L$12 -> 800
C11: ='[2]UPGRADES - MALVERN RANGE'!$B$13 -> Additional concrete- Outdoor living | D11: ='[2]UPGRADES - MALVERN RANGE'!$L$13 -> 2100
C12: ='[2]UPGRADES - MALVERN RANGE'!$B$14 -> Kitchen - The Everyday Kitchen | D12: ='[2]UPGRADES - MALVERN RANGE'!$L$14 -> 2400
C13: ='[2]UPGRADES - MALVERN RANGE'!$B$15 -> Kitchen - The Modern Chef Kitchen | D13: ='[2]UPGRADES - MALVERN RANGE'!$L$15 -> 5400
C14: ='[2]UPGRADES - MALVERN RANGE'!$B$16 -> Ensuite - The Signature Ensuite | D14: ='[2]UPGRADES - MALVERN RANGE'!$L$16 -> 650
C15: ='[2]UPGRADES - MALVERN RANGE'!$B$17 -> Ensuite - The Indulgence Ensuite | D15: ='[2]UPGRADES - MALVERN RANGE'!$L$17 -> 3500
C16: ='[2]UPGRADES - MALVERN RANGE'!$B$18 -> The Premier Meals | D16: ='[2]UPGRADES - MALVERN RANGE'!$L$18 -> 12120
C18: Façade
C19: Standard Façade | D19: Included
C20: ='[2]UPGRADES - MALVERN RANGE'!$B$24 -> The Rise Façade | D20: ='[2]UPGRADES - MALVERN RANGE'!$L$24 -> 6270
C21: ='[2]UPGRADES - MALVERN RANGE'!$B$25 -> The Crest Façade | D21: ='[2]UPGRADES - MALVERN RANGE'!$L$25 -> 9200
C22: ='[2]UPGRADES - MALVERN RANGE'!$B$26 -> The Sanctuary Façade | D22: ='[2]UPGRADES - MALVERN RANGE'!$L$26 -> 9950
C23: ='[2]UPGRADES - MALVERN RANGE'!$B$27 -> The Meadow Façade | D23: ='[2]UPGRADES - MALVERN RANGE'!$L$27 -> 12980
C24: ='[2]UPGRADES - MALVERN RANGE'!$B$28 -> Double Posts | D24: ='[2]UPGRADES - MALVERN RANGE'!$L$28 -> 2430
C25: ='[2]UPGRADES - MALVERN RANGE'!$B$29 -> Double Posts & 1/2 Bricks Piers | D25: ='[2]UPGRADES - MALVERN RANGE'!$L$29 -> 7460
C27: Add Ons
C28: Kitchen
C29: ='[2]UPGRADES - MALVERN RANGE'!$B$32 -> 600mm overhead either side of rangehood | D29: ='[2]UPGRADES - MALVERN RANGE'!$L$32 -> 990
C30: ='[2]UPGRADES - MALVERN RANGE'!$B$33 -> Overhead cupboards with integrated rangehood | D30: ='[2]UPGRADES - MALVERN RANGE'!$L$33 -> 1860
C31: ='[2]UPGRADES - MALVERN RANGE'!$B$34 -> Fridge overhead cupboard | D31: ='[2]UPGRADES - MALVERN RANGE'!$L$34 -> 960
C32: 1 Bank of 3 pot drawers | D32: ='[2]UPGRADES - MALVERN RANGE'!$L$35 -> 330
C33: 2 Banks of 3 pot drawers | D33: ='[2]UPGRADES - MALVERN RANGE'!$L$35*2 -> 660
C34: 3 Banks of 3 pot drawers | D34: ='[2]UPGRADES - MALVERN RANGE'!$L$35*3 -> 990
C35: 4 Banks of 3 pot drawers | D35: ='[2]UPGRADES - MALVERN RANGE'!$L$35*4 -> 1320
C36: 5 Banks of 3 pot drawers | D36: ='[2]UPGRADES - MALVERN RANGE'!$L$35*5 -> 1650
C37: ='[2]UPGRADES - MALVERN RANGE'!$B$36 -> Microwave cavity with drawer below | D37: ='[2]UPGRADES - MALVERN RANGE'!$L$36 -> 415
C38: ='[2]UPGRADES - MALVERN RANGE'!$B$37 -> Twin bin with drawer below | D38: ='[2]UPGRADES - MALVERN RANGE'!$L$37 -> 250
C39: ='[2]UPGRADES - MALVERN RANGE'!$B$38 -> 1212 No Bottom Reveal Window | D39: ='[2]UPGRADES - MALVERN RANGE'!$L$38 -> 390
C41: Ensuite & Bathroom
C42: ='[2]UPGRADES - MALVERN RANGE'!$B$40 -> Bank of 3 drawers to vanities | D42: ='[2]UPGRADES - MALVERN RANGE'!$L$40 -> 660
C43: 2 drawers to vanity in lieu of doors - (2 Banks) | D43: ='[2]UPGRADES - MALVERN RANGE'!$L$41*2 -> 660
C44: 2 drawers to vanity in lieu of doors - (3 Banks) | D44: ='[2]UPGRADES - MALVERN RANGE'!$L$41*3 -> 990
C45: Rectangle with rounded edge mirrors - (2 Mirrors) | D45: ='[2]UPGRADES - MALVERN RANGE'!$L$42/2*2 -> 280
C46: Rectangle with rounded edge mirrors - (3 Mirrors) | D46: ='[2]UPGRADES - MALVERN RANGE'!$L$42/2*3 -> 420
C47: ='[2]UPGRADES - MALVERN RANGE'!$B$43 -> Tiled recess shelves | D47: ='[2]UPGRADES - MALVERN RANGE'!$L$43 -> 800
C48: ='[2]UPGRADES - MALVERN RANGE'!$B$44 -> Extend tiles to 2m high on vanity wall | D48: ='[2]UPGRADES - MALVERN RANGE'!$L$44 -> 500
C49: ='[2]UPGRADES - MALVERN RANGE'!$B$45 -> Extend tiles to 2m high on remaining three walls | D49: ='[2]UPGRADES - MALVERN RANGE'!$L$45 -> 2000
C51: Laundry
C52: ='[2]UPGRADES - MALVERN RANGE'!$B$47 -> 1200mm Laminate benchtop & cupboards | D52: ='[2]UPGRADES - MALVERN RANGE'!$L$47 -> 1680
C53: ='[2]UPGRADES - MALVERN RANGE'!$B$48 -> Extend laminate benchtop only by 750mm with powerpoint | D53: ='[2]UPGRADES - MALVERN RANGE'!$L$48 -> 525
C54: ='[2]UPGRADES - MALVERN RANGE'!$B$49 -> 1200mm Overhead cupboards | D54: ='[2]UPGRADES - MALVERN RANGE'!$L$49 -> 1040
C55: ='[2]UPGRADES - MALVERN RANGE'!$B$50 -> 750mm Overhead cupboards | D55: ='[2]UPGRADES - MALVERN RANGE'!$L$50 -> 765
C56: ='[2]UPGRADES - MALVERN RANGE'!$B$51 -> Hanging rail under overheads | D56: ='[2]UPGRADES - MALVERN RANGE'!$L$51 -> 300
C57: ='[2]UPGRADES - MALVERN RANGE'!$B$52 -> Pullout laundry basket with drawer | D57: ='[2]UPGRADES - MALVERN RANGE'!$L$52 -> 235
C59: Additional Add Ons
C60: ='[2]UPGRADES - MALVERN RANGE'!$B$54 -> Eaves to whole home | D60: ='[2]UPGRADES - MALVERN RANGE'!$L$54 -> 5100
C61: ='[2]UPGRADES - MALVERN RANGE'!$B$55 -> 2550mm ceiling | D61: ='[2]UPGRADES - MALVERN RANGE'!$L$55 -> 3700
C62: ='[2]UPGRADES - MALVERN RANGE'!$B$56 -> Add 2100h x 2400w roller door | D62: ='[2]UPGRADES - MALVERN RANGE'!$L$56 -> 1670
C64: Personalised Selections
C65: External Finishes
C66: ='[2]UPGRADES - MALVERN RANGE'!$B$59 -> Double glazing to whole home (please note: all windows will be awning) | D66: ='[2]UPGRADES - MALVERN RANGE'!$L$59 -> 4500
C67: ='[2]UPGRADES - MALVERN RANGE'!$B$60 -> Sliding door in lieu of swing | D67: ='[2]UPGRADES - MALVERN RANGE'!$L$60 -> 200
C68: ='[2]UPGRADES - MALVERN RANGE'!$B$61 -> Wall mounted clothesline | D68: ='[2]UPGRADES - MALVERN RANGE'!$L$61 -> 400
C69: ='[2]UPGRADES - MALVERN RANGE'!$B$62 -> Letterbox | D69: ='[2]UPGRADES - MALVERN RANGE'!$L$62 -> 350
C70: ='[2]UPGRADES - MALVERN RANGE'!$B$63 -> Newington front door | D70: ='[2]UPGRADES - MALVERN RANGE'!$L$63 -> 300
C71: ='[2]UPGRADES - MALVERN RANGE'!$B$64 -> Nexion front door handle | D71: ='[2]UPGRADES - MALVERN RANGE'!$L$64 -> 175
C72: ='[2]UPGRADES - MALVERN RANGE'!$B$65 -> Brick Upgrade | D72: ='[2]UPGRADES - MALVERN RANGE'!$L$65 -> 720
C74: Internal Finishes
C75: ='[2]UPGRADES - MALVERN RANGE'!$B$67 -> Internal door - single doors each | D75: ='[2]UPGRADES - MALVERN RANGE'!$L$67 -> 475
C76: ='[2]UPGRADES - MALVERN RANGE'!$B$68 -> Internal door - double doors each | D76: ='[2]UPGRADES - MALVERN RANGE'!$L$68 -> 1480
C77: ='[2]UPGRADES - MALVERN RANGE'!$B$69 -> 2340mm high internal doors & robe/linen doors | D77: ='[2]UPGRADES - MALVERN RANGE'!$L$69 -> 1450
C78: ='[2]UPGRADES - MALVERN RANGE'!$B$70 -> Single roller blinds | D78: ='[2]UPGRADES - MALVERN RANGE'!$L$70 -> 2700
C80: Robes
C81: Vinyl / Mirror sliding robe door Combination to 1 Robe | D81: ='[2]UPGRADES - MALVERN RANGE'!$L$72 -> 50
C82: Vinyl / Mirror sliding robe door Combination to 2 Robes | D82: ='[2]UPGRADES - MALVERN RANGE'!$L$72*2 -> 100
C83: Vinyl / Mirror sliding robe door Combination to 3 Robes | D83: ='[2]UPGRADES - MALVERN RANGE'!$L$72*3 -> 150
C84: Double Mirror sliding robe door Combination to 1 Robe | D84: ='[2]UPGRADES - MALVERN RANGE'!$L$72*2 -> 100
C85: Double Mirror sliding robe door Combination to 2 Robe | D85: ='[2]UPGRADES - MALVERN RANGE'!$L$72*4 -> 200
C86: Double Mirror sliding robe door Combination to 3 Robe | D86: ='[2]UPGRADES - MALVERN RANGE'!$L$72*6 -> 300
C87: 1 Bank of three shelves - (Shirt Stacker) | D87: ='[2]UPGRADES - MALVERN RANGE'!$L$73 -> 185
C88: 2 Banks of three shelves - (Shirt Stacker) | D88: ='[2]UPGRADES - MALVERN RANGE'!$L$73*2 -> 370
C89: 3 Banks of three shelves - (Shirt Stacker) | D89: ='[2]UPGRADES - MALVERN RANGE'!$L$73*3 -> 555
C90: 4 Banks of three shelves - (Shirt Stacker) | D90: ='[2]UPGRADES - MALVERN RANGE'!$L$73*4 -> 740
C91: 5 Banks of three shelves - (Shirt Stacker) | D91: ='[2]UPGRADES - MALVERN RANGE'!$L$73*5 -> 925
C92: 6 Banks of three shelves - (Shirt Stacker) | D92: ='[2]UPGRADES - MALVERN RANGE'!$L$73*6 -> 1110
C93: 1 Bank of two shelves & four drawers | D93: ='[2]UPGRADES - MALVERN RANGE'!$L$74 -> 510
C94: 2 Banks of two shelves & four drawers | D94: ='[2]UPGRADES - MALVERN RANGE'!$L$74*2 -> 1020
C95: 3 Banks of two shelves & four drawers | D95: ='[2]UPGRADES - MALVERN RANGE'!$L$74*3 -> 1530
C96: 4 Banks of two shelves & four drawers | D96: ='[2]UPGRADES - MALVERN RANGE'!$L$74*4 -> 2040
C97: 5 Banks of two shelves & four drawers | D97: ='[2]UPGRADES - MALVERN RANGE'!$L$74*5 -> 2550
C98: 6 Banks of two shelves & four drawers | D98: ='[2]UPGRADES - MALVERN RANGE'!$L$74*6 -> 3060
C100: Kitchen
C101: ='[2]UPGRADES - MALVERN RANGE'!$B$76 -> 600mm stainless steel oven & canopy rangehood and electric cooktop | D101: ='[2]UPGRADES - MALVERN RANGE'!$L$76 -> 365
C102: ='[2]UPGRADES - MALVERN RANGE'!$B$77 -> 900mm stainless steel inbuilt oven, cooktop & canopy rangehood | D102: ='[2]UPGRADES - MALVERN RANGE'!$L$77 -> 1860
C103: ='[2]UPGRADES - MALVERN RANGE'!$B$78 -> 900mm black inbuilt oven, cooktop & canopy rangehood | D103: ='[2]UPGRADES - MALVERN RANGE'!$L$78 -> 1870
C104: ='[2]UPGRADES - MALVERN RANGE'!$B$79 -> 900mm black undermount rangehood in lieu of canopy | D104: ='[2]UPGRADES - MALVERN RANGE'!$L$79 -> 800
C105: ='[2]UPGRADES - MALVERN RANGE'!$B$80 -> 900mm stainless steel undermount rangehood in lieu of canopy | D105: ='[2]UPGRADES - MALVERN RANGE'!$L$80 -> 770
C106: ='[2]UPGRADES - MALVERN RANGE'!$B$81 -> Stainless steel dishwasher | D106: ='[2]UPGRADES - MALVERN RANGE'!$L$81 -> 700
C107: ='[2]UPGRADES - MALVERN RANGE'!$B$82 -> Black dishwasher | D107: ='[2]UPGRADES - MALVERN RANGE'!$L$82 -> 750
C108: ='[2]UPGRADES - MALVERN RANGE'!$B$83 -> 20mm Stone benchtops- Standard | D108: ='[2]UPGRADES - MALVERN RANGE'!$L$83 -> 3100
C109: ='[2]UPGRADES - MALVERN RANGE'!$B$84 -> 20mm Stone benchtops - The Everyday Kitchen | D109: ='[2]UPGRADES - MALVERN RANGE'!$L$84 -> 2980
C110: ='[2]UPGRADES - MALVERN RANGE'!$B$85 -> 20mm Stone benchtops - The Modern Chef Kitchen | D110: ='[2]UPGRADES - MALVERN RANGE'!$L$85 -> 4780
C111: ='[2]UPGRADES - MALVERN RANGE'!$B$86 -> 20mm Stone benchtops - The Premier Meals | D111: ='[2]UPGRADES - MALVERN RANGE'!$L$86 -> 3325
...

Sheet MALVERN 23
C3: Floor Plan Extensions
C4: ='[2]UPGRADES - MALVERN RANGE'!$B$6 -> Extend garage by 500mm | D4: ='[2]UPGRADES - MALVERN RANGE'!$M$6 -> 2500
C5: ='[2]UPGRADES - MALVERN RANGE'!$B$7 -> Extend garage by 1000mm | D5: ='[2]UPGRADES - MALVERN RANGE'!$M$7 -> 5000
C6: ='[2]UPGRADES - MALVERN RANGE'!$B$8 -> Outdoor Living - addition 1 | D6: ='[2]UPGRADES - MALVERN RANGE'!$M$8 -> 5900
C7: ='[2]UPGRADES - MALVERN RANGE'!$B$9 -> Outdoor Living - brick pier in lieu of steel post | D7: ='[2]UPGRADES - MALVERN RANGE'!$M$9 -> 800
C8: ='[2]UPGRADES - MALVERN RANGE'!$B$10 -> Additional concrete - outdoor living | D8: ='[2]UPGRADES - MALVERN RANGE'!$M$10 -> 1260
C9: ='[2]UPGRADES - MALVERN RANGE'!$B$11 -> Outdoor Living - addition 2 | D9: ='[2]UPGRADES - MALVERN RANGE'!$M$11 -> 8100
C10: ='[2]UPGRADES - MALVERN RANGE'!$B$12 -> Outdoor Living - brick pier in lieu of steel post | D10: ='[2]UPGRADES - MALVERN RANGE'!$M$12 -> 800
C11: ='[2]UPGRADES - MALVERN RANGE'!$B$13 -> Additional concrete- Outdoor living | D11: ='[2]UPGRADES - MALVERN RANGE'!$M$13 -> 2100
C12: ='[2]UPGRADES - MALVERN RANGE'!$B$14 -> Kitchen - The Everyday Kitchen | D12: ='[2]UPGRADES - MALVERN RANGE'!$M$14 -> 2400
C13: ='[2]UPGRADES - MALVERN RANGE'!$B$15 -> Kitchen - The Modern Chef Kitchen | D13: ='[2]UPGRADES - MALVERN RANGE'!$M$15 -> 5400
C14: ='[2]UPGRADES - MALVERN RANGE'!$B$16 -> Ensuite - The Signature Ensuite | D14: ='[2]UPGRADES - MALVERN RANGE'!$M$16 -> 650
C15: ='[2]UPGRADES - MALVERN RANGE'!$B$17 -> Ensuite - The Indulgence Ensuite | D15: ='[2]UPGRADES - MALVERN RANGE'!$M$17 -> 3500
C16: ='[2]UPGRADES - MALVERN RANGE'!$B$18 -> The Premier Meals | D16: ='[2]UPGRADES - MALVERN RANGE'!$M$18 -> 12120
C18: Façade
C19: Standard Façade | D19: Included
C20: ='[2]UPGRADES - MALVERN RANGE'!$B$24 -> The Rise Façade | D20: ='[2]UPGRADES - MALVERN RANGE'!$M$24 -> 6270
C21: ='[2]UPGRADES - MALVERN RANGE'!$B$25 -> The Crest Façade | D21: ='[2]UPGRADES - MALVERN RANGE'!$M$25 -> 9200
C22: ='[2]UPGRADES - MALVERN RANGE'!$B$26 -> The Sanctuary Façade | D22: ='[2]UPGRADES - MALVERN RANGE'!$M$26 -> 9950
C23: ='[2]UPGRADES - MALVERN RANGE'!$B$27 -> The Meadow Façade | D23: ='[2]UPGRADES - MALVERN RANGE'!$M$27 -> 15370
C24: ='[2]UPGRADES - MALVERN RANGE'!$B$28 -> Double Posts | D24: ='[2]UPGRADES - MALVERN RANGE'!$M$28 -> 2835
C25: ='[2]UPGRADES - MALVERN RANGE'!$B$29 -> Double Posts & 1/2 Bricks Piers | D25: ='[2]UPGRADES - MALVERN RANGE'!$M$29 -> 8660
C27: Add Ons
C28: Kitchen
C29: ='[2]UPGRADES - MALVERN RANGE'!$B$32 -> 600mm overhead either side of rangehood | D29: ='[2]UPGRADES - MALVERN RANGE'!$M$32 -> 990
C30: ='[2]UPGRADES - MALVERN RANGE'!$B$33 -> Overhead cupboards with integrated rangehood | D30: ='[2]UPGRADES - MALVERN RANGE'!$M$33 -> 1860
C31: ='[2]UPGRADES - MALVERN RANGE'!$B$34 -> Fridge overhead cupboard | D31: ='[2]UPGRADES - MALVERN RANGE'!$M$34 -> 960
C32: 1 Bank of 3 pot drawers | D32: ='[2]UPGRADES - MALVERN RANGE'!$M$35 -> 330
C33: 2 Banks of 3 pot drawers | D33: ='[2]UPGRADES - MALVERN RANGE'!$M$35*2 -> 660
C34: 3 Banks of 3 pot drawers | D34: ='[2]UPGRADES - MALVERN RANGE'!$M$35*3 -> 990
C35: 4 Banks of 3 pot drawers | D35: ='[2]UPGRADES - MALVERN RANGE'!$M$35*4 -> 1320
C36: 5 Banks of 3 pot drawers | D36: ='[2]UPGRADES - MALVERN RANGE'!$M$35*5 -> 1650
C37: ='[2]UPGRADES - MALVERN RANGE'!$B$36 -> Microwave cavity with drawer below | D37: ='[2]UPGRADES - MALVERN RANGE'!$M$36 -> 415
C38: ='[2]UPGRADES - MALVERN RANGE'!$B$37 -> Twin bin with drawer below | D38: ='[2]UPGRADES - MALVERN RANGE'!$M$37 -> 250
C39: ='[2]UPGRADES - MALVERN RANGE'!$B$38 -> 1212 No Bottom Reveal Window | D39: ='[2]UPGRADES - MALVERN RANGE'!$M$38 -> 390
C41: Ensuite & Bathroom
C42: ='[2]UPGRADES - MALVERN RANGE'!$B$40 -> Bank of 3 drawers to vanities | D42: ='[2]UPGRADES - MALVERN RANGE'!$M$40 -> 660
C43: 2 drawers to vanity in lieu of doors - (2 Banks) | D43: ='[2]UPGRADES - MALVERN RANGE'!$M$41*2 -> 660
C44: 2 drawers to vanity in lieu of doors - (3 Banks) | D44: ='[2]UPGRADES - MALVERN RANGE'!$M$41*3 -> 990
C45: Rectangle with rounded edge mirrors - (2 Mirrors) | D45: ='[2]UPGRADES - MALVERN RANGE'!$M$42/2*2 -> 280
C46: Rectangle with rounded edge mirrors - (3 Mirrors) | D46: ='[2]UPGRADES - MALVERN RANGE'!$M$42/2*3 -> 420
C47: ='[2]UPGRADES - MALVERN RANGE'!$B$43 -> Tiled recess shelves | D47: ='[2]UPGRADES - MALVERN RANGE'!$M$43 -> 800
C48: ='[2]UPGRADES - MALVERN RANGE'!$B$44 -> Extend tiles to 2m high on vanity wall | D48: ='[2]UPGRADES - MALVERN RANGE'!$M$44 -> 500
C49: ='[2]UPGRADES - MALVERN RANGE'!$B$45 -> Extend tiles to 2m high on remaining three walls | D49: ='[2]UPGRADES - MALVERN RANGE'!$M$45 -> 2000
C51: Laundry
C52: ='[2]UPGRADES - MALVERN RANGE'!$B$47 -> 1200mm Laminate benchtop & cupboards | D52: ='[2]UPGRADES - MALVERN RANGE'!$M$47 -> 1680
C53: ='[2]UPGRADES - MALVERN RANGE'!$B$48 -> Extend laminate benchtop only by 750mm with powerpoint | D53: ='[2]UPGRADES - MALVERN RANGE'!$M$48 -> 525
C54: ='[2]UPGRADES - MALVERN RANGE'!$B$49 -> 1200mm Overhead cupboards | D54: ='[2]UPGRADES - MALVERN RANGE'!$M$49 -> 1040
C55: ='[2]UPGRADES - MALVERN RANGE'!$B$50 -> 750mm Overhead cupboards | D55: ='[2]UPGRADES - MALVERN RANGE'!$M$50 -> 765
C56: ='[2]UPGRADES - MALVERN RANGE'!$B$51 -> Hanging rail under overheads | D56: ='[2]UPGRADES - MALVERN RANGE'!$M$51 -> 300
C57: ='[2]UPGRADES - MALVERN RANGE'!$B$52 -> Pullout laundry basket with drawer | D57: ='[2]UPGRADES - MALVERN RANGE'!$M$52 -> 235
C59: Additional Add Ons
C60: ='[2]UPGRADES - MALVERN RANGE'!$B$54 -> Eaves to whole home | D60: ='[2]UPGRADES - MALVERN RANGE'!$M$54 -> 5600
C61: ='[2]UPGRADES - MALVERN RANGE'!$B$55 -> 2550mm ceiling | D61: ='[2]UPGRADES - MALVERN RANGE'!$M$55 -> 4200
C62: ='[2]UPGRADES - MALVERN RANGE'!$B$56 -> Add 2100h x 2400w roller door | D62: ='[2]UPGRADES - MALVERN RANGE'!$M$56 -> 1670
C64: Personalised Selections
C65: External Finishes
C66: ='[2]UPGRADES - MALVERN RANGE'!$B$59 -> Double glazing to whole home (please note: all windows will be awning) | D66: ='[2]UPGRADES - MALVERN RANGE'!$M$59 -> 4950
C67: ='[2]UPGRADES - MALVERN RANGE'!$B$60 -> Sliding door in lieu of swing | D67: ='[2]UPGRADES - MALVERN RANGE'!$M$60 -> 200
C68: ='[2]UPGRADES - MALVERN RANGE'!$B$61 -> Wall mounted clothesline | D68: ='[2]UPGRADES - MALVERN RANGE'!$M$61 -> 400
C69: ='[2]UPGRADES - MALVERN RANGE'!$B$62 -> Letterbox | D69: ='[2]UPGRADES - MALVERN RANGE'!$M$62 -> 350
C70: ='[2]UPGRADES - MALVERN RANGE'!$B$63 -> Newington front door | D70: ='[2]UPGRADES - MALVERN RANGE'!$M$63 -> 300
C71: ='[2]UPGRADES - MALVERN RANGE'!$B$64 -> Nexion front door handle | D71: ='[2]UPGRADES - MALVERN RANGE'!$M$64 -> 175
C72: ='[2]UPGRADES - MALVERN RANGE'!$B$65 -> Brick Upgrade | D72: ='[2]UPGRADES - MALVERN RANGE'!$M$65 -> 720
C74: Internal Finishes
C75: ='[2]UPGRADES - MALVERN RANGE'!$B$67 -> Internal door - single doors each | D75: ='[2]UPGRADES - MALVERN RANGE'!$M$67 -> 475
C76: ='[2]UPGRADES - MALVERN RANGE'!$B$68 -> Internal door - double doors each | D76: ='[2]UPGRADES - MALVERN RANGE'!$M$68 -> 1480
C77: ='[2]UPGRADES - MALVERN RANGE'!$B$69 -> 2340mm high internal doors & robe/linen doors | D77: ='[2]UPGRADES - MALVERN RANGE'!$M$69 -> 1470
C78: ='[2]UPGRADES - MALVERN RANGE'!$B$70 -> Single roller blinds | D78: ='[2]UPGRADES - MALVERN RANGE'!$M$70 -> 3000
C80: Robes
C81: Vinyl / Mirror sliding robe door Combination to 1 Robe | D81: ='[2]UPGRADES - MALVERN RANGE'!$M$72 -> 50
C82: Vinyl / Mirror sliding robe door Combination to 2 Robes | D82: ='[2]UPGRADES - MALVERN RANGE'!$M$72*2 -> 100
C83: Vinyl / Mirror sliding robe door Combination to 3 Robes | D83: ='[2]UPGRADES - MALVERN RANGE'!$M$72*3 -> 150
C84: Double Mirror sliding robe door Combination to 1 Robe | D84: ='[2]UPGRADES - MALVERN RANGE'!$M$72*2 -> 100
C85: Double Mirror sliding robe door Combination to 2 Robe | D85: ='[2]UPGRADES - MALVERN RANGE'!$M$72*4 -> 200
C86: Double Mirror sliding robe door Combination to 3 Robe | D86: ='[2]UPGRADES - MALVERN RANGE'!$M$72*6 -> 300
C87: 1 Bank of three shelves - (Shirt Stacker) | D87: ='[2]UPGRADES - MALVERN RANGE'!$M$73 -> 185
C88: 2 Banks of three shelves - (Shirt Stacker) | D88: ='[2]UPGRADES - MALVERN RANGE'!$M$73*2 -> 370
C89: 3 Banks of three shelves - (Shirt Stacker) | D89: ='[2]UPGRADES - MALVERN RANGE'!$M$73*3 -> 555
C90: 4 Banks of three shelves - (Shirt Stacker) | D90: ='[2]UPGRADES - MALVERN RANGE'!$M$73*4 -> 740
C91: 5 Banks of three shelves - (Shirt Stacker) | D91: ='[2]UPGRADES - MALVERN RANGE'!$M$73*5 -> 925
C92: 6 Banks of three shelves - (Shirt Stacker) | D92: ='[2]UPGRADES - MALVERN RANGE'!$M$73*6 -> 1110
C93: 1 Bank of two shelves & four drawers | D93: ='[2]UPGRADES - MALVERN RANGE'!$M$74 -> 510
C94: 2 Banks of two shelves & four drawers | D94: ='[2]UPGRADES - MALVERN RANGE'!$M$74*2 -> 1020
C95: 3 Banks of two shelves & four drawers | D95: ='[2]UPGRADES - MALVERN RANGE'!$M$74*3 -> 1530
C96: 4 Banks of two shelves & four drawers | D96: ='[2]UPGRADES - MALVERN RANGE'!$M$74*4 -> 2040
C97: 5 Banks of two shelves & four drawers | D97: ='[2]UPGRADES - MALVERN RANGE'!$M$74*5 -> 2550
C98: 6 Banks of two shelves & four drawers | D98: ='[2]UPGRADES - MALVERN RANGE'!$M$74*6 -> 3060
C100: Kitchen
C101: ='[2]UPGRADES - MALVERN RANGE'!$B$76 -> 600mm stainless steel oven & canopy rangehood and electric cooktop | D101: ='[2]UPGRADES - MALVERN RANGE'!$M$76 -> 365
